Radix-32-approx-ABM-M2/radix4approx.v
`timescale 10ms / 1ms

module radix4approx(p,x,y);                 //M2

parameter N = 32;   //size of muliplicant and multiplier
parameter K = N/2;  //

input   [N-1 : 0]   x,y;
output  [N+N-1:0]   p;

reg [2:0]   bits    [K:0];
reg   neg     [K:0];
reg   two     [K:0];
reg   zero     [K:0];

wire [N+1:0] x_shift;
reg [N+1:0]       PP      [K:0]; //riyaj 
reg [N+N-1:0]   ACC     [K:0];
reg [N+N-1:0]   ANS;
reg mux;

integer i , j, t;

integer  m = 24;        //number of bits to approximate
localparam d = 24;

integer sum_check = 0;

assign x_shift = {2'b0,x};

reg [N+1:0] x_new = 0;


always@(*)
begin

    bits[0] = {y[1],y[0],1'b0};             //setting last bit -1 as 0

    for(i=1; i<K+1; i=i+1) begin
            if(i == K)
                bits[i] = {2'b0,y[2*i-1]};
            else
                bits[i] = {y[2*i+1], y[2*i], y[2*i-1]};
            //$display("%b", bits[i]);
            
        end

    //M2 approximation
    x_new = x_shift;

    for(i=0; i<m; i++) begin
        sum_check = sum_check + x_shift[i];
    end

    if(sum_check > m/2) begin
        x_new[d-1] = {1'b1};
    end

    else
        x_new[d-1] = {1'b0};

    for(i = 0; i<m-1; i++) begin
        x_new[i] = {1'b0};
    end

    //

    for(i=0; i<K+1; i=i+1)
        begin                               //approximated 2A as A introduced error
            case(bits[i])

            
            3'b001, 3'b010:         
            begin
                neg[i] = 1'b0;
                two[i] = 1'b0;
                zero[i] = 1'b0;
            end

            3'b011:
            begin
                neg[i] = 1'b0;
                two[i] = 1'b1;
                zero[i] = 1'b0;
            end

            3'b101, 3'b110:         
            begin 
               neg[i] = 1'b1;
                two[i] = 1'b0;
                zero[i] = 1'b0;
            end

            3'b100:
            begin
                neg[i] = 1'b1;
                two[i] = 1'b1;
                zero[i] = 1'b0;
            end
         
            default: 
            begin
                neg[i] = 1'b0;
                two[i] = 1'b0;
                zero[i] = 1'b1;
            end

            endcase

            PP[i] = 0;
            PP[i][N+1] = neg[i];           //sign conservation

            for(t=0; t<N+1; t=t+1) begin
                if(t>=m) 
                begin
                    mux = (x_new[t] & ~two[i]) | (x_new[t-1] & two[i]);             
                    PP[i][t] = ~zero[i] & (neg[i] ^ mux);
                end

                else 
                begin
                    PP[i][t] = (~x_new[t] & neg[i]) | (x_new[t] & ~neg[i] & ~zero[i]);
                end
            end

            PP[i][0] = PP[i][0] | neg[i];

            ACC[i] = $signed(PP[i]);        //sign extension
            
            for(j=0; j<i; j=j+1)
                ACC[i] = {ACC[i],2'b00};        //shifting

        
        end

    ANS = ACC[0];

    for(i=1; i<K+1; i=i+1)
        ANS = ANS+ACC[i];
        
end


assign p = ANS;

endmodule

Radix-32-approx-ABM-M2/radix4approx_tb.v
`timescale 10ms / 1ms
`include "radix4approx.v"

module radix4approx_tb();               //M2

reg unsigned [31:0] A,B;
wire unsigned [63:0] P;
integer i, out, seed=7;


radix4approx uut(P,A,B);


initial begin
    $dumpfile("radix4approx.vcd");
    $dumpvars(0, radix4approx_tb);
    out = $fopen("radix4approxoutput.csv");
    
    for(i=0; i<50; i=i+1)
    begin
        A = $urandom(seed) %4294967295;
        B = $urandom(seed) %4294967295;
        #1;
        $fwrite(out, "%d, %d, %d\n", A,B,P);
        #4;
    end
    $finish;
end

endmodule

Radix-32-approx-ABM-M2/radix4approx.vcd
$date
	Thu Sep  2 20:24:26 2021
$end
$version
	Icarus Verilog
$end
$timescale
	1ms
$end
$scope module radix4approx_tb $end
$var wire 64 ! P [63:0] $end
$var reg 32 " A [31:0] $end
$var reg 32 # B [31:0] $end
$var integer 32 $ i [31:0] $end
$var integer 32 % out [31:0] $end
$var integer 32 & seed [31:0] $end
$scope module uut $end
$var wire 64 ' p [63:0] $end
$var wire 32 ( x [31:0] $end
$var wire 32 ) y [31:0] $end
$var wire 34 * x_shift [33:0] $end
$var reg 64 + ANS [63:0] $end
$var reg 1 , mux $end
$var reg 34 - x_new [33:0] $end
$var integer 32 . i [31:0] $end
$var integer 32 / j [31:0] $end
$var integer 32 0 m [31:0] $end
$var integer 32 1 sum_check [31:0] $end
$var integer 32 2 t [31:0] $end
$upscope $end
$upscope $end
$enddefinitions $end
#0
$dumpvars
b100001 2
b110 1
b11000 0
b10000 /
b10001 .
b0 -
0,
b1111111111111111111111111111111110111110111010111111101110111100 +
b1110110001000000000 *
b11000110011011000100101110001100 )
b1110110001000000000 (
b1111111111111111111111111111111110111110111010111111101110111100 '
b11000110011011000100100011101101 &
b10 %
b0 $
b11000110011011000100101110001100 #
b1110110001000000000 "
b1111111111111111111111111111111110111110111010111111101110111100 !
$end
#50
b111011000110111001010100101101010010000111010111111101011111100 !
b111011000110111001010100101101010010000111010111111101011111100 '
b111011000110111001010100101101010010000111010111111101011111100 +
b10000 /
0,
b100001 2
b10011 1
b10101101100000000000000000000000 -
b10001 .
b10101110011011011111101101011100 #
b10101110011011011111101101011100 )
b10101101010101110111000101011010 *
b10101101010101110111000101011010 "
b10101101010101110111000101011010 (
b10101110011011011111100111000011 &
b1 $
#100
b11000111101010000011101000011001011010001111111110111110111111 !
b11000111101010000011101000011001011010001111111110111110111111 '
b11000111101010000011101000011001011010001111111110111110111111 +
b10000 /
0,
b100001 2
b100000 1
b111101100000000000000000000000 -
b10001 .
b11001111110001011111001110011111 #
b11001111110001011111001110011111 )
b111101100000101110101001111011 *
b111101100000101110101001111011 "
b111101100000101110101001111011 (
b11001111110001011111000000001001 &
b10 $
#150
b11100110001101010100000111111000111011111010111100000000 !
b11100110001101010100000111111000111011111010111100000000 '
b11100110001101010100000111111000111011111010111100000000 +
b10000 /
0,
b100001 2
b110000 1
b1011110100000000000000000000000 -
b10001 .
b10011100001010011000000100 #
b10011100001010011000000100 )
b1011110101110101010111010111101 *
b1011110101110101010111010111101 "
b1011110101110101010111010111101 (
b10011100001010010100111111 &
b11 $
#200
b10011000111000101011100011110100001111101011111111111111 !
b10011000111000101011100011110100001111101011111111111111 '
b10011000111000101011100011110100001111101011111111111111 +
b10000 /
0,
b100001 2
b111100 1
b1010001100000000000000000000000 -
b10001 .
b1110111101001000000000011 #
b1110111101001000000000011 )
b1010001110101111000100010100011 *
b1010001110101111000100010100011 "
b1010001110101111000100010100011 (
b1110111101000111011100101 &
b100 $
#250
b10010111010110001000010100101001110011110111011111111111011 !
b10010111010110001000010100101001110011110111011111111111011 '
b10010111010110001000010100101001110011110111011111111111011 +
b10000 /
0,
b100001 2
b1001000 1
b1011011100000000000000000000000 -
b10001 .
b1101001110111000000000011010 #
b1101001110111000000000011010 )
b1011011010111110001000010110110 *
b1011011010111110001000010110110 "
b1011011010111110001000010110110 (
b1101001110110111111001111011 &
b101 $
#300
b110110011001110000101101001111101100011110111111111011101111 !
b110110011001110000101101001111101100011110111111111011101111 '
b110110011001110000101101001111101100011110111111111011101111 +
b10000 /
0,
b100001 2
b1010010 1
b11100100000000000000000000000 -
b10001 .
b1111001000111010000001011110010 #
b1111001000111010000001011110010 )
b11100100010111000100000111001 *
b11100100010111000100000111001 "
b11100100010111000100000111001 (
b1111001000111010000000110000001 &
b110 $
#350
b10111010110011010110111010100111111000001011111011111010111100 !
b10111010110011010110111010100111111000001011111011111010111100 '
b10111010110011010110111010100111111000001011111011111010111100 +
b10000 /
0,
b100001 2
b1100000 1
b1110110100000000000000000000000 -
b10001 .
b1100100101011111100001011001001 #
b1100100101011111100001011001001 )
b1110110110011101100001011101101 *
b1110110110011101100001011101101 "
b1110110110011101100001011101101 (
b1100100101011111100000101110111 &
b111 $
#400
b11010000111100100110011010111000000011111110111111000000000000 !
b11010000111100100110011010111000000011111110111111000000000000 '
b11010000111100100110011010111000000011111110111111000000000000 +
b10000 /
0,
b100001 2
b1101101 1
b1001111100000000000000000000000 -
b10001 .
b10101000001110111110010101010000 #
b10101000001110111110010101010000 )
b1001111000001111111100010011110 *
b1001111000001111111100010011110 "
b1001111000001111111100010011110 (
b10101000001110111110001111011101 &
b1000 $
#450
b100000110001000010000110111001000100001110111110101111111100 !
b100000110001000010000110111001000100001110111110101111111100 '
b100000110001000010000110111001000100001110111110101111111100 +
b10000 /
0,
b100001 2
b1111000 1
b10100110100000000000000000000000 -
b10001 .
b1100100110000110110000011001 #
b1100100110000110110000011001 )
b10100110011001001011001101001100 *
b10100110011001001011001101001100 "
b10100110011001001011001101001100 (
b1100100110000110101000110011 &
b1001 $
#500
b1010111011110000111110001111001110110011011111011111010110000 !
b1010111011110000111110001111001110110011011111011111010110000 '
b1010111011110000111110001111001110110011011111011111010110000 +
b10000 /
0,
b100001 2
b10000100 1
b111101100000000000000000000000 -
b10001 .
b1011010111001011001001010110101 #
b1011010111001011001001010110101 )
b111101101001001010001001111011 *
b111101101001001010001001111011 "
b111101101001001010001001111011 (
b1011010111001011001000111111001 &
b1010 $
#550
b1110001001111001010111101110110001001011101110111110111111 !
b1110001001111001010111101110110001001011101110111110111111 '
b1110001001111001010111101110110001001011101110111110111111 +
b10000 /
0,
b100001 2
b10001011 1
b100100000000000000000000000 -
b10001 .
b11001001101001100011011110010011 #
b11001001101001100011011110010011 )
b100001110001000101000001000 *
b100001110001000101000001000 "
b100001110001000101000001000 (
b11001001101001100011010010101111 &
b1011 $
#600
b10011101011111111001111001111000011111111111110110000000000 !
b10011101011111111001111001111000011111111111110110000000000 '
b10011101011111111001111001111000011111111111110110000000000 +
b10000 /
0,
b100001 2
b10010110 1
b11111100000000000000000000000 -
b10001 .
b101000000100000010100001010000 #
b101000000100000010100001010000 )
b11111011101000001010000111110 *
b11111011101000001010000111110 "
b11111011101000001010000111110 (
b101000000100000010011111010101 &
b1100 $
#650
b110001100010111110000111001101101100111010111011111110110000 !
b110001100010111110000111001101101100111010111011111110110000 '
b110001100010111110000111001101101100111010111011111110110000 +
b10000 /
0,
b100001 2
b10100010 1
b1110100000000000000000000000 -
b10001 .
b11011010001010111001111110110100 #
b11011010001010111001111110110100 )
b1110110010101011100000011101 *
b1110110010101011100000011101 "
b1110110010101011100000011101 (
b11011010001010111001110011101011 &
b1101 $
#700
b101110111100101101000001110110001110111111110111011111011110000 !
b101110111100101101000001110110001110111111110111011111011110000 '
b101110111100101101000001110110001110111111110111011111011110000 +
b10000 /
0,
b100001 2
b10101110 1
b10001000100000000000000000000000 -
b10001 .
b10110000000110011000001101100000 #
b10110000000110011000001101100000 )
b10001000110011111001100100010001 *
b10001000110011111001100100010001 "
b10001000110011111001100100010001 (
b10110000000110011000000101110001 &
b1110 $
#750
b1010101010110101000000101001110101111001001110111110111110110000 !
b1010101010110101000000101001110101111001001110111110111110110000 '
b1010101010110101000000101001110101111001001110111110111110110000 +
b10000 /
0,
b100001 2
b10111001 1
b11010001100000000000000000000000 -
b10001 .
b11010000100110001110000110100001 #
b11010000100110001110000110100001 )
b11010001011100000110011110100010 *
b11010001011100000110011110100010 "
b11010001011100000110011110100010 (
b11010000100110001101111011100111 &
b1111 $
#800
b1000001100100110111101101111010000111101001011101111101111000000 !
b1000001100100110111101101111010000111101001011101111101111000000 '
b1000001100100110111101101111010000111101001011101111101111000000 +
b10000 /
0,
b100001 2
b11000110 1
b10101100100000000000000000000000 -
b10001 .
b11000010101000110011110110000101 #
b11000010101000110011110110000101 )
b10101100101000110011101101011001 *
b10101100101000110011101101011001 "
b10101100101000110011101101011001 (
b11000010101000110011101011001101 &
b10000 $
#850
b10001110110100100101111101011000000001011111111101111111111 !
b10001110110100100101111101011000000001011111111101111111111 '
b10001110110100100101111101011000000001011111111101111111111 +
b10000 /
0,
b100001 2
b11010001 1
b1100001100000000000000000000000 -
b10001 .
b1011101101111111100000010111 #
b1011101101111111100000010111 )
b1100001011111111000000011000010 *
b1100001011111111000000011000010 "
b1100001011111111000000011000010 (
b1011101101111111011010100011 &
b10001 $
#900
b11000111000010001100001011101100100011111011101010111111000000 !
b11000111000010001100001011101100100011111011101010111111000000 '
b11000111000010001100001011101100100011111011101010111111000000 +
b10000 /
0,
b100001 2
b11011100 1
b10110000100000000000000000000000 -
b10001 .
b1001000001011101011000010010000 #
b1001000001011101011000010010000 )
b10110000011110011100100101100000 *
b10110000011110011100100101100000 "
b10110000011110011100100101100000 (
b1001000001011101010111111101001 &
b10010 $
#950
b11101110011001111011000111100100000001010111010111100000000 !
b11101110011001111011000111100100000001010111010111100000000 '
b11101110011001111011000111100100000001010111010111100000000 +
b10000 /
0,
b100001 2
b11101001 1
b11011100100000000000000000000000 -
b10001 .
b1000101010001010001000010001 #
b1000101010001010001000010001 )
b11011100001110101011010110111000 *
b11011100001110101011010110111000 "
b11011100001110101011010110111000 (
b1000101010001010000000011111 &
b10011 $
#1000
b1000100001001100000010110001011110001011110111111111011111111 !
b1000100001001100000010110001011110001011110111111111011111111 '
b1000100001001100000010110001011110001011110111111111011111111 +
b10000 /
0,
b100001 2
b11110100 1
b11111100000000000000000000000 -
b10001 .
b10001011011110001111111100010110 #
b10001011011110001111111100010110 )
b11111010010001100110000111110 *
b11111010010001100110000111110 "
b11111010010001100110000111110 (
b10001011011110001111110011000101 &
b10100 $
#1050
b111000101001110110110101110110001101010001110111111110000000000 !
b111000101001110110110101110110001101010001110111111110000000000 '
b111000101001110110110101110110001101010001110111111110000000000 +
b10000 /
0,
b100001 2
b100000010 1
b11010001100000000000000000000000 -
b10001 .
b10001010100111000101100100010101 #
b10001010100111000101100100010101 )
b11010001011111010110110110100010 *
b11010001011111010110110110100010 "
b11010001011111010110110110100010 (
b10001010100111000101011101011011 &
b10101 $
#1100
b1000100111100011101110001010100001011001111101111111011111100 !
b1000100111100011101110001010100001011001111101111111011111100 '
b1000100111100011101110001010100001011001111101111111011111100 +
b10000 /
0,
b100001 2
b100001111 1
b1000110100000000000000000000000 -
b10001 .
b111110100101101111111001111101 #
b111110100101101111111001111101 )
b1000110111111001001010010001101 *
b1000110111111001001010010001101 "
b1000110111111001001010010001101 (
b111110100101101111110101100001 &
b10110 $
#1150
b100000110110110001011010010110111101001111111101111101010101100 !
b100000110110110001011010010110111101001111111101111101010101100 '
b100000110110110001011010010110111101001111111101111101010101100 +
b10000 /
0,
b100001 2
b100011100 1
b11000111100000000000000000000000 -
b10001 .
b1010100010100100101101010101000 #
b1010100010100100101101010101000 )
b11000111001001111101010110001110 *
b11000111001001111101010110001110 "
b11000111001001111101010110001110 (
b1010100010100100101100001010111 &
b10111 $
#1200
b10001001011101110000101011110001011001111111111111010101111 !
b10001001011101110000101011110001011001111111111111010101111 '
b10001001011101110000101011110001011001111111111111010101111 +
b10000 /
0,
b100001 2
b100100101 1
b1100100000000000000000000000 -
b10001 .
b1010111110100010100111010101111 #
b1010111110100010100111010101111 )
b1100110001000010101000011001 *
b1100110001000010101000011001 "
b1100110001000010101000011001 (
b1010111110100010100110110111101 &
b11000 $
#1250
b11110100111011111001011110001011000011011111111010111110111111 !
b11110100111011111001011110001011000011011111111010111110111111 '
b11110100111011111001011110001011000011011111111010111110111111 +
b10000 /
0,
b100001 2
b100101111 1
b1000001100000000000000000000000 -
b10001 .
b11101111010100111010000111011110 #
b11101111010100111010000111011110 )
b1000001010010101101101010000010 *
b1000001010010101101101010000010 "
b1000001010010101101101010000010 (
b11101111010100111001111100010011 &
b11001 $
#1300
b101001111110001110001101111010001100000111111111111101100000000 !
b101001111110001110001101111010001100000111111111111101100000000 '
b101001111110001110001101111010001100000111111111111101100000000 +
b10000 /
0,
b100001 2
b100111001 1
b10000100100000000000000000000000 -
b10001 .
b10100010010000000100101101000100 #
b10100010010000000100101101000100 )
b10000100000111010101101100001000 *
b10000100000111010101101100001000 "
b10000100000111010101101100001000 (
b10100010010000000100100111011001 &
b11010 $
#1350
b101101100100101010000011001111110111001011011101110101111111100 !
b101101100100101010000011001111110111001011011101110101111111100 '
b101101100100101010000011001111110111001011011101110101111111100 +
b10000 /
0,
b100001 2
b101000011 1
b1111011100000000000000000000000 -
b10001 .
b10111100111011101110100101111001 #
b10111100111011101110100101111001 )
b1111011000101000010100011110110 *
b1111011000101000010100011110110 "
b1111011000101000010100011110110 (
b10111100111011101110011110001111 &
b11011 $
#1400
b11010000011011101101110000011100001100111010111111111011111100 !
b11010000011011101101110000011100001100111010111111111011111100 '
b11010000011011101101110000011100001100111010111111111011111100 +
b10000 /
0,
b100001 2
b101001101 1
b1010100100000000000000000000000 -
b10001 .
b10011110001010000000111100111100 #
b10011110001010000000111100111100 )
b1010100101000001011001010101001 *
b1010100101000001011001010101001 "
b1010100101000001011001010101001 (
b10011110001010000000110110110101 &
b11100 $
#1450
b11100010101010001010101000111110001010011011111010111010111100 !
b11100010101010001010101000111110001010011011111010111010111100 '
b11100010101010001010101000111110001010011011111010111010111100 +
b10000 /
0,
b100001 2
b101011010 1
b10111100100000000000000000000000 -
b10001 .
b1001100111101001010111010011001 #
b1001100111101001010111010011001 )
b10111100011110100010110101111000 *
b10111100011110100010110101111000 "
b10111100011110100010110101111000 (
b1001100111101001010110111001011 &
b11101 $
#1500
b100110000111011010000010101101110100011111111110111011111011 !
b100110000111011010000010101101110100011111111110111011111011 '
b100110000111011010000010101101110100011111111110111011111011 +
b10000 /
0,
b100001 2
b101101001 1
b10111010100000000000000000000000 -
b10001 .
b1101000101000111011000011010 #
b1101000101000111011000011010 )
b10111010100011010111110101110101 *
b10111010100011010111110101110101 "
b10111010100011010111110101110101 (
b1101000101000111010101010001 &
b11110 $
#1550
b1011000011011110001011111000100000100100111011101110111011101100 !
b1011000011011110001011111000100000100100111011101110111011101100 '
b1011000011011110001011111000100000100100111011101110111011101100 +
b10000 /
0,
b100001 2
b101110011 1
b11111000100000000000000000000000 -
b10001 .
b10110110001100110010111101101100 #
b10110110001100110010111101101100 )
b11111000101010000001000111110001 *
b11111000101010000001000111110001 "
b11111000101010000001000111110001 (
b10110110001100110010110111000111 &
b11111 $
#1600
b10111110000100011101010101100110011111001011111111111010111011 !
b10111110000100011101010101100110011111001011111111111010111011 '
b10111110000100011101010101100110011111001011111111111010111011 +
b10000 /
0,
b100001 2
b101111110 1
b10101110100000000000000000000000 -
b10001 .
b1000101101101010001111010001011 #
b1000101101101010001111010001011 )
b10101110000101011100010101011100 *
b10101110000101011100010101011100 "
b10101110000101011100010101011100 (
b1000101101101010001110010101101 &
b100000 $
#1650
b111001011001010101111100101001010111001011101110111110111100 !
b111001011001010101111100101001010111001011101110111110111100 '
b111001011001010101111100101001010111001011101110111110111100 +
b10000 /
0,
b100001 2
b110000101 1
b100001100000000000000000000000 -
b10001 .
b1101100101100100110010011011001 #
b1101100101100100110010011011001 )
b100001001010011100000001000010 *
b100001001010011100000001000010 "
b100001001010011100000001000010 (
b1101100101100100110001110000011 &
b100001 $
#1700
b1010101010000000111101101001000010101011110111110111111111111 !
b1010101010000000111101101001000010101011110111110111111111111 '
b1010101010000000111101101001000010101011110111110111111111111 +
b10000 /
0,
b100001 2
b110010010 1
b1111101100000000000000000000000 -
b10001 .
b101011011110010110000001010110 #
b101011011110010110000001010110 )
b1111101011010100101100011111010 *
b1111101011010100101100011111010 "
b1111101011010100101100011111010 (
b101011011110010101111111001001 &
b100010 $
#1750
b100100101001111100011001100010010110100001011111111101110101111 !
b100100101001111100011001100010010110100001011111111101110101111 '
b100100101001111100011001100010010110100001011111111101110101111 +
b10000 /
0,
b100001 2
b110100010 1
b1011001100000000000000000000000 -
b10001 .
b11010001101100000000110110100011 #
b11010001101100000000110110100011 )
b1011001110101111110101010110011 *
b1011001110101111110101010110011 "
b1011001110101111110101010110011 (
b11010001101100000000101011111111 &
b100011 $
#1800
b101101101110111111001010011011111101100011010111111101110111011 !
b101101101110111111001010011011111101100011010111111101110111011 '
b101101101110111111001010011011111101100011010111111101110111011 +
b10000 /
0,
b100001 2
b110101110 1
b11100101100000000000000000000000 -
b10001 .
b1100101111011000101110011001011 #
b1100101111011000101110011001011 )
b11100101100001101100001111001011 *
b11100101100001101100001111001011 "
b11100101100001101100001111001011 (
b1100101111011000101101010100101 &
b100100 $
#1850
b111011001100100110101110100011011010110011110111010111011101111 !
b111011001100100110101110100011011010110011110111010111011101111 '
b111011001100100110101110100011011010110011110111010111011101111 +
b10000 /
0,
b100001 2
b110111101 1
b11111001100000000000000000000000 -
b10001 .
b1111001010110111010001011110010 #
b1111001010110111010001011110010 )
b11111001100000111111100111110011 *
b11111001100000111111100111110011 "
b11111001100000111111100111110011 (
b1111001010110111010000000111011 &
b100101 $
#1900
b1011111001000011000111001010111010000001111111110101011101111 !
b1011111001000011000111001010111010000001111111110101011101111 '
b1011111001000011000111001010111010000001111111110101011101111 +
b10000 /
0,
b100001 2
b111001011 1
b1110101100000000000000000000000 -
b10001 .
b110011110100001110101001100111 #
b110011110100001110101001100111 )
b1110101101111010101000011101011 *
b1110101101111010101000011101011 "
b1110101101111010101000011101011 (
b110011110100001110100101000001 &
b100110 $
#1950
b1100001111100111111110111010011100111111101110111111000000 !
b1100001111100111111110111010011100111111101110111111000000 '
b1100001111100111111110111010011100111111101110111111000000 +
b10000 /
0,
b100001 2
b111010010 1
b11100000000000000000000000 -
b10001 .
b11100010010100100110000111000100 #
b11100010010100100110000111000100 )
b11011001000001100000000110 *
b11011001000001100000000110 "
b11011001000001100000000110 (
b11100010010100100101111100110111 &
b100111 $
#2000
b1100001010010101101001110110011011010011011110111010101111101011 !
b1100001010010101101001110110011011010011011110111010101111101011 '
b1100001010010101101001110110011011010011011110111010101111101011 +
b10000 /
0,
b100001 2
b111011010 1
b11001010100000000000000000000000 -
b10001 .
b11110101111111011010100111101011 #
b11110101111111011010100111101011 )
b11001010000000110000110110010100 *
b11001010000000110000110110010100 "
b11001010000000110000110110010100 (
b11110101111111011010011110011101 &
b101000 $
#2050
b111000001001011000000001000110011110001110101111111111110000 !
b111000001001011000000001000110011110001110101111111111110000 '
b111000001001011000000001000110011110001110101111111111110000 +
b10000 /
0,
b100001 2
b111100110 1
b10000101100000000000000000000000 -
b10001 .
b11010110110110100010000110101 #
b11010110110110100010000110101 )
b10000101001111110011001100001010 *
b10000101001111110011001100001010 "
b10000101001111110011001100001010 (
b11010110110110100001111110011 &
b101001 $
#2100
b100011010000011000111010110001100001110011110111110111010111011 !
b100011010000011000111010110001100001110011110111110111010111011 '
b100011010000011000111010110001100001110011110111110111010111011 +
b10000 /
0,
b100001 2
b111110111 1
b11100111100000000000000000000000 -
b10001 .
b1001101111110001111001010011011 #
b1001101111110001111001010011011 )
b11100111111110111100001111001111 *
b11100111111110111100001111001111 "
b11100111111110111100001111001111 (
b1001101111110001111000110111001 &
b101010 $
#2150
b1110000111001110111101010100010001011011101111101111111111 !
b1110000111001110111101010100010001011011101111101111111111 '
b1110000111001110111101010100010001011011101111101111111111 +
b10000 /
0,
b100001 2
b1000000001 1
b110100000000000000000000000 -
b10001 .
b10001111111000110000110100011111 #
b10001111111000110000110100011111 )
b110010110001111100000001100 *
b110010110001111100000001100 "
b110010110001111100000001100 (
b10001111111000110000101001101111 &
b101011 $
#2200
b101010111010001001001101111110011001101111111111110111110111100 !
b101010111010001001001101111110011001101111111111110111110111100 '
b101010111010001001001101111110011001101111111111110111110111100 +
b10000 /
0,
b100001 2
b1000010001 1
b11001010100000000000000000000000 -
b10001 .
b1101100010101001110010011011000 #
b1101100010101001110010011011000 )
b11001010110001011111111110010101 *
b11001010110001011111111110010101 "
b11001010110001011111111110010101 (
b1101100010101001110001110010101 &
b101100 $
#2250
b110100011001011111010101011011010001110111110111111111111 !
b110100011001011111010101011011010001110111110111111111111 '
b110100011001011111010101011011010001110111110111111111111 +
b10000 /
0,
b100001 2
b1000011110 1
b11110011100000000000000000000000 -
b10001 .
b1101110000011000000000011 #
b1101110000011000000000011 )
b11110011000111011101000111100110 *
b11110011000111011101000111100110 "
b11110011000111011101000111100110 (
b1101110000010111010101011 &
b101101 $
#2300
b1101011000101000011111000100101010110010001110101111101111000000 !
b1101011000101000011111000100101010110010001110101111101111000000 '
b1101011000101000011111000100101010110010001110101111101111000000 +
b10000 /
0,
b100001 2
b1000101011 1
b11101001100000000000000000000000 -
b10001 .
b11101010110010110101101111010101 #
b11101010110010110101101111010101 )
b11101001100001110000111111010011 *
b11101001100001110000111111010011 "
b11101001100001110000111111010011 (
b11101010110010110101100100110001 &
b101110 $
#2350
b11111011001100011100001000001001111010001111101110111010110000 !
b11111011001100011100001000001001111010001111101110111010110000 '
b11111011001100011100001000001001111010001111101110111010110000 +
b10000 /
0,
b100001 2
b1000111001 1
b10110001100000000000000000000000 -
b10001 .
b1011010100001101110111010110101 #
b1011010100001101110111010110101 )
b10110001100011101110101101100011 *
b10110001100011101110101101100011 "
b10110001100011101110101101100011 (
b1011010100001101110110010100111 &
b101111 $
#2400
b1010011100101011101110110000110100100111110111110111110111100 !
b1010011100101011101110110000110100100111110111110111110111100 '
b1010011100101011101110110000110100100111110111110111110111100 +
b10000 /
0,
b100001 2
b1001001000 1
b1000100100000000000000000000000 -
b10001 .
b1001110000110011111000010011100 #
b1001110000110011111000010011100 )
b1000100101101101111111010001001 *
b1000100101101101111111010001001 "
b1000100101101101111111010001001 (
b1001110000110011110111010001101 &
b110000 $
#2450
b1011001100110010111100100001101101000011001111111111111111000000 !
b1011001100110010111100100001101101000011001111111111111111000000 '
b1011001100110010111100100001101101000011001111111111111111000000 +
b10000 /
0,
b100001 2
b1001010011 1
b11001010100000000000000000000000 -
b10001 .
b11100010100101010100001111000101 #
b11100010100101010100001111000101 )
b11001010011011100011000110010100 *
b11001010011011100011000110010100 "
b11001010011011100011000110010100 (
b11100010100101010100000001100011 &
b110001 $
#2500
b110010 $
