Radix-32-approx-ABM-M2/radix4approx.v
`timescale 10ms / 1ms

module radix4approx(p,x,y);                 //M2

parameter N = 32;   //size of muliplicant and multiplier
parameter K = N/2;  //

input   [N-1 : 0]   x,y;
output  [N+N-1:0]   p;

reg [2:0]   bits    [K:0];
reg   neg     [K:0];
reg   two     [K:0];
reg   zero     [K:0];

wire [N+1:0] x_shift;
reg [N+1:0]       PP      [K:0]; //riyaj 
reg [N+N-1:0]   ACC     [K:0];
reg [N+N-1:0]   ANS;
reg mux;

integer i , j, t,z;

integer  m = 16;        //number of bits to approximate
localparam d = 16;

integer sum_check = 0;

assign x_shift = {2'b0,x};

reg [N+1:0] x_new = 0;


always@(*)
begin

    bits[0] = {y[1],y[0],1'b0};             //setting last bit -1 as 0

    for(i=1; i<K+1; i=i+1) begin
            if(i == K)
                bits[i] = {2'b0,y[2*i-1]};
            else
                bits[i] = {y[2*i+1], y[2*i], y[2*i-1]};
            //$display("%b", bits[i]);
            
        end

    //M2 approximation
    x_new = x_shift;

    for(z=0; z<m; z=z+1) begin
        sum_check = sum_check + x_shift[z];
    end

    if(sum_check > m/2) begin
        x_new[d-1] = {1'b1};
    end

    else
        x_new[d-1] = {1'b0};

    for(z = 0; z<m-1; z=z+1) begin
        x_new[z] = {1'b0};
    end

    //

    for(i=0; i<K+1; i=i+1)
        begin                               //approximated 2A as A introduced error
            case(bits[i])

            
            3'b001, 3'b010:         
            begin
                neg[i] = 1'b0;
                two[i] = 1'b0;
                zero[i] = 1'b0;
            end

            3'b011:
            begin
                neg[i] = 1'b0;
                two[i] = 1'b1;
                zero[i] = 1'b0;
            end

            3'b101, 3'b110:         
            begin 
               neg[i] = 1'b1;
                two[i] = 1'b0;
                zero[i] = 1'b0;
            end

            3'b100:
            begin
                neg[i] = 1'b1;
                two[i] = 1'b1;
                zero[i] = 1'b0;
            end
         
            default: 
            begin
                neg[i] = 1'b0;
                two[i] = 1'b0;
                zero[i] = 1'b1;
            end

            endcase

            PP[i] = 0;
            PP[i][N+1] = neg[i];           //sign conservation

            for(t=0; t<N+1; t=t+1) begin
                if(t>=m) 
                begin
                    mux = (x_new[t] & ~two[i]) | (x_new[t-1] & two[i]);             
                    PP[i][t] = ~zero[i] & (neg[i] ^ mux);
                end

                else 
                begin
                    PP[i][t] = (~x_new[t] & neg[i]) | (x_new[t] & ~neg[i] & ~zero[i]);
                end
            end

            PP[i][0] = PP[i][0] | neg[i];

            ACC[i] = $signed(PP[i]);        //sign extension
            
            for(j=0; j<i; j=j+1)
                ACC[i] = {ACC[i],2'b00};        //shifting

        
        end

    ANS = ACC[0];

    for(i=1; i<K+1; i=i+1)
        ANS = ANS+ACC[i];
        
end


assign p = ANS;

endmodule

Radix-32-approx-ABM-M2/radix4approx_tb.v
`timescale 10ms / 1ms
`include "radix4approx.v"

module radix4approx_tb();               //M2

reg unsigned [31:0] A,B;
wire unsigned [63:0] P;
integer i, out, seed=7;


radix4approx uut(P,A,B);


initial begin
    $dumpfile("radix4approx.vcd");
    $dumpvars(0, radix4approx_tb);
    out = $fopen("radix4approxoutput.csv");
    
    for(i=0; i<500; i=i+1)
    begin
        A = $urandom(seed) %4294967295;
        B = $urandom(seed) %4294967295;
        #1;
        $fwrite(out, "%d, %d, %d\n", A,B,P);
        #4;
    end
    $finish;
end

endmodule

Radix-32-approx-ABM-M2/radix4approx.vcd
$date
	Fri Sep  3 01:26:06 2021
$end
$version
	Icarus Verilog
$end
$timescale
	1ms
$end
$scope module radix4approx_tb $end
$var wire 64 ! P [63:0] $end
$var reg 32 " A [31:0] $end
$var reg 32 # B [31:0] $end
$var integer 32 $ i [31:0] $end
$var integer 32 % out [31:0] $end
$var integer 32 & seed [31:0] $end
$scope module uut $end
$var wire 64 ' p [63:0] $end
$var wire 32 ( x [31:0] $end
$var wire 32 ) y [31:0] $end
$var wire 34 * x_shift [33:0] $end
$var reg 64 + ANS [63:0] $end
$var reg 1 , mux $end
$var reg 34 - x_new [33:0] $end
$var integer 32 . i [31:0] $end
$var integer 32 / j [31:0] $end
$var integer 32 0 m [31:0] $end
$var integer 32 1 sum_check [31:0] $end
$var integer 32 2 t [31:0] $end
$var integer 32 3 z [31:0] $end
$upscope $end
$upscope $end
$enddefinitions $end
#0
$dumpvars
b1111 3
b100001 2
b11 1
b10000 0
b10000 /
b10001 .
b1110000000000000000 -
0,
b101011011001111010111001111101111111111101110111100 +
b1110110001000000000 *
b11000110011011000100101110001100 )
b1110110001000000000 (
b101011011001111010111001111101111111111101110111100 '
b11000110011011000100100011101101 &
b10 %
b0 $
b11000110011011000100101110001100 #
b1110110001000000000 "
b101011011001111010111001111101111111111101110111100 !
$end
#50
b111011000011011111100010001010011000100111001011111101011111100 !
b111011000011011111100010001010011000100111001011111101011111100 '
b111011000011011111100010001010011000100111001011111101011111100 +
b10000 /
0,
b100001 2
b1011 1
b1111 3
b10101101010101111000000000000000 -
b10001 .
b10101110011011011111101101011100 #
b10101110011011011111101101011100 )
b10101101010101110111000101011010 *
b10101101010101110111000101011010 "
b10101101010101110111000101011010 (
b10101110011011011111100111000011 &
b1 $
#100
b11000111101100000101010111010111010011001101010110111110111111 !
b11000111101100000101010111010111010011001101010110111110111111 '
b11000111101100000101010111010111010011001101010110111110111111 +
b10000 /
0,
b100001 2
b10110 1
b1111 3
b111101100000101000000000000000 -
b10001 .
b11001111110001011111001110011111 #
b11001111110001011111001110011111 )
b111101100000101110101001111011 *
b111101100000101110101001111011 "
b111101100000101110101001111011 (
b11001111110001011111000000001001 &
b10 $
#150
b11100111001000111010011001100010010110011010111100000000 !
b11100111001000111010011001100010010110011010111100000000 '
b11100111001000111010011001100010010110011010111100000000 +
b10000 /
0,
b100001 2
b100001 1
b1111 3
b1011110101110101000000000000000 -
b10001 .
b10011100001010011000000100 #
b10011100001010011000000100 )
b1011110101110101010111010111101 *
b1011110101110101010111010111101 "
b1011110101110101010111010111101 (
b10011100001010010100111111 &
b11 $
#200
b10011000111111101111001100001101010001010011111111111111 !
b10011000111111101111001100001101010001010011111111111111 '
b10011000111111101111001100001101010001010011111111111111 +
b10000 /
0,
b100001 2
b100111 1
b1111 3
b1010001110101111000000000000000 -
b10001 .
b1110111101001000000000011 #
b1110111101001000000000011 )
b1010001110101111000100010100011 *
b1010001110101111000100010100011 "
b1010001110101111000100010100011 (
b1110111101000111011100101 &
b100 $
#250
b10010111001000101100011101101100011101101100011111111111011 !
b10010111001000101100011101101100011101101100011111111111011 '
b10010111001000101100011101101100011101101100011111111111011 +
b10000 /
0,
b100001 2
b101101 1
b1111 3
b1011011010111111000000000000000 -
b10001 .
b1101001110111000000000011010 #
b1101001110111000000000011010 )
b1011011010111110001000010110110 *
b1011011010111110001000010110110 "
b1011011010111110001000010110110 (
b1101001110110111111001111011 &
b101 $
#300
b110110000001010010011010100110001110110110100111111011101111 !
b110110000001010010011010100110001110110110100111111011101111 '
b110110000001010010011010100110001110110110100111111011101111 +
b10000 /
0,
b100001 2
b110011 1
b1111 3
b11100100010111000000000000000 -
b10001 .
b1111001000111010000001011110010 #
b1111001000111010000001011110010 )
b11100100010111000100000111001 *
b11100100010111000100000111001 "
b11100100010111000100000111001 (
b1111001000111010000000110000001 &
b110 $
#350
b10111010111010010100111000111100110100110100000011111010111100 !
b10111010111010010100111000111100110100110100000011111010111100 '
b10111010111010010100111000111100110100110100000011111010111100 +
b10000 /
0,
b100001 2
b111100 1
b1111 3
b1110110110011101000000000000000 -
b10001 .
b1100100101011111100001011001001 #
b1100100101011111100001011001001 )
b1110110110011101100001011101101 *
b1110110110011101100001011101101 "
b1110110110011101100001011101101 (
b1100100101011111100000101110111 &
b111 $
#400
b11001111101111011001111000010010001011110100111111000000000000 !
b11001111101111011001111000010010001011110100111111000000000000 '
b11001111101111011001111000010010001011110100111111000000000000 +
b10000 /
0,
b100001 2
b1000110 1
b1111 3
b1001111000001111000000000000000 -
b10001 .
b10101000001110111110010101010000 #
b10101000001110111110010101010000 )
b1001111000001111111100010011110 *
b1001111000001111111100010011110 "
b1001111000001111111100010011110 (
b10101000001110111110001111011101 &
b1000 $
#450
b100000101111110001111101010011000001100100100110101111111100 !
b100000101111110001111101010011000001100100100110101111111100 '
b100000101111110001111101010011000001100100100110101111111100 +
b10000 /
0,
b100001 2
b1001110 1
b1111 3
b10100110011001001000000000000000 -
b10001 .
b1100100110000110110000011001 #
b1100100110000110110000011001 )
b10100110011001001011001101001100 *
b10100110011001001011001101001100 "
b10100110011001001011001101001100 (
b1100100110000110101000110011 &
b1001 $
#500
b1010111100011001001000111001001000001001111100011111010110000 !
b1010111100011001001000111001001000001001111100011111010110000 '
b1010111100011001001000111001001000001001111100011111010110000 +
b10000 /
0,
b100001 2
b1010111 1
b1111 3
b111101101001001000000000000000 -
b10001 .
b1011010111001011001001010110101 #
b1011010111001011001001010110101 )
b111101101001001010001001111011 *
b111101101001001010001001111011 "
b111101101001001010001001111011 (
b1011010111001011001000111111001 &
b1010 $
#550
b1101010011000110001000011011001101100000000110111110111111 !
b1101010011000110001000011011001101100000000110111110111111 '
b1101010011000110001000011011001101100000000110111110111111 +
b10000 /
0,
b100001 2
b1011011 1
b1111 3
b100001110001000000000000000 -
b10001 .
b11001001101001100011011110010011 #
b11001001101001100011011110010011 )
b100001110001000101000001000 *
b100001110001000101000001000 "
b100001110001000101000001000 (
b11001001101001100011010010101111 &
b1011 $
#600
b10011101100001011100011101111110010011001111110110000000000 !
b10011101100001011100011101111110010011001111110110000000000 '
b10011101100001011100011101111110010011001111110110000000000 +
b10000 /
0,
b100001 2
b1100010 1
b1111 3
b11111011101001000000000000000 -
b10001 .
b101000000100000010100001010000 #
b101000000100000010100001010000 )
b11111011101000001010000111110 *
b11111011101000001010000111110 "
b11111011101000001010000111110 (
b101000000100000010011111010101 &
b1100 $
#650
b110010011010111111011011110101001110110011011011111110110000 !
b110010011010111111011011110101001110110011011011111110110000 '
b110010011010111111011011110101001110110011011011111110110000 +
b10000 /
0,
b100001 2
b1101010 1
b1111 3
b1110110010101000000000000000 -
b10001 .
b11011010001010111001111110110100 #
b11011010001010111001111110110100 )
b1110110010101011100000011101 *
b1110110010101011100000011101 "
b1110110010101011100000011101 (
b11011010001010111001110011101011 &
b1101 $
#700
b101111000011100010010100111111100001100011000111011111011110000 !
b101111000011100010010100111111100001100011000111011111011110000 '
b101111000011100010010100111111100001100011000111011111011110000 +
b10000 /
0,
b100001 2
b1110000 1
b1111 3
b10001000110011111000000000000000 -
b10001 .
b10110000000110011000001101100000 #
b10110000000110011000001101100000 )
b10001000110011111001100100010001 *
b10001000110011111001100100010001 "
b10001000110011111001100100010001 (
b10110000000110011000000101110001 &
b1110 $
#750
b1010101010101000011110110100100101010000011101000110111110110000 !
b1010101010101000011110110100100101010000011101000110111110110000 '
b1010101010101000011110110100100101010000011101000110111110110000 +
b10000 /
0,
b100001 2
b1111000 1
b1111 3
b11010001011100001000000000000000 -
b10001 .
b11010000100110001110000110100001 #
b11010000100110001110000110100001 )
b11010001011100000110011110100010 *
b11010001011100000110011110100010 "
b11010001011100000110011110100010 (
b11010000100110001101111011100111 &
b1111 $
#800
b1000001101000001111111001000111011100101100000000111101111000000 !
b1000001101000001111111001000111011100101100000000111101111000000 '
b1000001101000001111111001000111011100101100000000111101111000000 +
b10000 /
0,
b100001 2
b10000001 1
b1111 3
b10101100101000111000000000000000 -
b10001 .
b11000010101000110011110110000101 #
b11000010101000110011110110000101 )
b10101100101000110011101101011001 *
b10101100101000110011101101011001 "
b10101100101000110011101101011001 (
b11000010101000110011101011001101 &
b10000 $
#850
b10001110110100010110010001011000000001001100111101111111111 !
b10001110110100010110010001011000000001001100111101111111111 '
b10001110110100010110010001011000000001001100111101111111111 +
b10000 /
0,
b100001 2
b10000101 1
b1111 3
b1100001011111111000000000000000 -
b10001 .
b1011101101111111100000010111 #
b1011101101111111100000010111 )
b1100001011111111000000011000010 *
b1100001011111111000000011000010 "
b1100001011111111000000011000010 (
b1011101101111111011010100011 &
b10001 $
#900
b11000111000010010110011000101111001000001001101010111111000000 !
b11000111000010010110011000101111001000001001101010111111000000 '
b11000111000010010110011000101111001000001001101010111111000000 +
b10000 /
0,
b100001 2
b10001011 1
b1111 3
b10110000011110011000000000000000 -
b10001 .
b1001000001011101011000010010000 #
b1001000001011101011000010010000 )
b10110000011110011100100101100000 *
b10110000011110011100100101100000 "
b10110000011110011100100101100000 (
b1001000001011101010111111101001 &
b10010 $
#950
b11101110010111000111100110110011000000011100010111100000000 !
b11101110010111000111100110110011000000011100010111100000000 '
b11101110010111000111100110110011000000011100010111100000000 +
b10000 /
0,
b100001 2
b10010100 1
b1111 3
b11011100001110101000000000000000 -
b10001 .
b1000101010001010001000010001 #
b1000101010001010001000010001 )
b11011100001110101011010110111000 *
b11011100001110101011010110111000 "
b11011100001110101011010110111000 (
b1000101010001010000000011111 &
b10011 $
#1000
b1000100001011000001101100010110100010101110000111111011111111 !
b1000100001011000001101100010110100010101110000111111011111111 '
b1000100001011000001101100010110100010101110000111111011111111 +
b10000 /
0,
b100001 2
b10011101 1
b1111 3
b11111010010001000000000000000 -
b10001 .
b10001011011110001111111100010110 #
b10001011011110001111111100010110 )
b11111010010001100110000111110 *
b11111010010001100110000111110 "
b11111010010001100110000111110 (
b10001011011110001111110011000101 &
b10100 $
#1050
b111000101101101011110000100011110010001100001110111110000000000 !
b111000101101101011110000100011110010001100001110111110000000000 '
b111000101101101011110000100011110010001100001110111110000000000 +
b10000 /
0,
b100001 2
b10100101 1
b1111 3
b11010001011111011000000000000000 -
b10001 .
b10001010100111000101100100010101 #
b10001010100111000101100100010101 )
b11010001011111010110110110100010 *
b11010001011111010110110110100010 "
b11010001011111010110110110100010 (
b10001010100111000101011101011011 &
b10101 $
#1100
b1000101011011000001010110011000101110101010010111111011111100 !
b1000101011011000001010110011000101110101010010111111011111100 '
b1000101011011000001010110011000101110101010010111111011111100 +
b10000 /
0,
b100001 2
b10101100 1
b1111 3
b1000110111111001000000000000000 -
b10001 .
b111110100101101111111001111101 #
b111110100101101111111001111101 )
b1000110111111001001010010001101 *
b1000110111111001001010010001101 "
b1000110111111001001010010001101 (
b111110100101101111110101100001 &
b10110 $
#1150
b100000110011001000001110010110100011100111010001111101010101100 !
b100000110011001000001110010110100011100111010001111101010101100 '
b100000110011001000001110010110100011100111010001111101010101100 +
b10000 /
0,
b100001 2
b10110101 1
b1111 3
b11000111001001111000000000000000 -
b10001 .
b1010100010100100101101010101000 #
b1010100010100100101101010101000 )
b11000111001001111101010110001110 *
b11000111001001111101010110001110 "
b11000111001001111101010110001110 (
b1010100010100100101100001010111 &
b10111 $
#1200
b10001100001001110011101100100011001000100110111111010101111 !
b10001100001001110011101100100011001000100110111111010101111 '
b10001100001001110011101100100011001000100110111111010101111 +
b10000 /
0,
b100001 2
b10111011 1
b1111 3
b1100110001001000000000000000 -
b10001 .
b1010111110100010100111010101111 #
b1010111110100010100111010101111 )
b1100110001000010101000011001 *
b1100110001000010101000011001 "
b1100110001000010101000011001 (
b1010111110100010100110110111101 &
b11000 $
#1250
b11110100001001111000011110111111100000101000100010111110111111 !
b11110100001001111000011110111111100000101000100010111110111111 '
b11110100001001111000011110111111100000101000100010111110111111 +
b10000 /
0,
b100001 2
b11000010 1
b1111 3
b1000001010010101000000000000000 -
b10001 .
b11101111010100111010000111011110 #
b11101111010100111010000111011110 )
b1000001010010101101101010000010 *
b1000001010010101101101010000010 "
b1000001010010101101101010000010 (
b11101111010100111001111100010011 &
b11001 $
#1300
b101001110111011110100001011011101101011010101011111101100000000 !
b101001110111011110100001011011101101011010101011111101100000000 '
b101001110111011110100001011011101101011010101011111101100000000 +
b10000 /
0,
b100001 2
b11001000 1
b1111 3
b10000100000111011000000000000000 -
b10001 .
b10100010010000000100101101000100 #
b10100010010000000100101101000100 )
b10000100000111010101101100001000 *
b10000100000111010101101100001000 "
b10000100000111010101101100001000 (
b10100010010000000100100111011001 &
b11010 $
#1350
b101101011010101111010110100111010001111001111010110101111111100 !
b101101011010101111010110100111010001111001111010110101111111100 '
b101101011010101111010110100111010001111001111010110101111111100 +
b10000 /
0,
b100001 2
b11010000 1
b1111 3
b1111011000101001000000000000000 -
b10001 .
b10111100111011101110100101111001 #
b10111100111011101110100101111001 )
b1111011000101000010100011110110 *
b1111011000101000010100011110110 "
b1111011000101000010100011110110 (
b10111100111011101110011110001111 &
b11011 $
#1400
b11010001001000001101001001101011111100000010011111111011111100 !
b11010001001000001101001001101011111100000010011111111011111100 '
b11010001001000001101001001101011111100000010011111111011111100 +
b10000 /
0,
b100001 2
b11011000 1
b1111 3
b1010100101000001000000000000000 -
b10001 .
b10011110001010000000111100111100 #
b10011110001010000000111100111100 )
b1010100101000001011001010101001 *
b1010100101000001011001010101001 "
b1010100101000001011001010101001 (
b10011110001010000000110110110101 &
b11100 $
#1450
b11100010101000100000110100110111100100000011000010111010111100 !
b11100010101000100000110100110111100100000011000010111010111100 '
b11100010101000100000110100110111100100000011000010111010111100 +
b10000 /
0,
b100001 2
b11100000 1
b1111 3
b10111100011110101000000000000000 -
b10001 .
b1001100111101001010111010011001 #
b1001100111101001010111010011001 )
b10111100011110100010110101111000 *
b10111100011110100010110101111000 "
b10111100011110100010110101111000 (
b1001100111101001010110111001011 &
b11101 $
#1500
b100110001000000110001001111001001000111001100110111011111011 !
b100110001000000110001001111001001000111001100110111011111011 '
b100110001000000110001001111001001000111001100110111011111011 +
b10000 /
0,
b100001 2
b11101011 1
b1111 3
b10111010100011011000000000000000 -
b10001 .
b1101000101000111011000011010 #
b1101000101000111011000011010 )
b10111010100011010111110101110101 *
b10111010100011010111110101110101 "
b10111010100011010111110101110101 (
b1101000101000111010101010001 &
b11110 $
#1550
b1011000011111001100001000010000100000101101001001110111011101100 !
b1011000011111001100001000010000100000101101001001110111011101100 '
b1011000011111001100001000010000100000101101001001110111011101100 +
b10000 /
0,
b100001 2
b11110010 1
b1111 3
b11111000101010001000000000000000 -
b10001 .
b10110110001100110010111101101100 #
b10110110001100110010111101101100 )
b11111000101010000001000111110001 *
b11111000101010000001000111110001 "
b11111000101010000001000111110001 (
b10110110001100110010110111000111 &
b11111 $
#1600
b10111101100110111101011111100010010010001111000111111010111011 !
b10111101100110111101011111100010010010001111000111111010111011 '
b10111101100110111101011111100010010010001111000111111010111011 +
b10000 /
0,
b100001 2
b11111010 1
b1111 3
b10101110000101011000000000000000 -
b10001 .
b1000101101101010001111010001011 #
b1000101101101010001111010001011 )
b10101110000101011100010101011100 *
b10101110000101011100010101011100 "
b10101110000101011100010101011100 (
b1000101101101010001110010101101 &
b100000 $
#1650
b111000010100101111011110101011010101111000100110111110111100 !
b111000010100101111011110101011010101111000100110111110111100 '
b111000010100101111011110101011010101111000100110111110111100 +
b10000 /
0,
b100001 2
b11111110 1
b1111 3
b100001001010011000000000000000 -
b10001 .
b1101100101100100110010011011001 #
b1101100101100100110010011011001 )
b100001001010011100000001000010 *
b100001001010011100000001000010 "
b100001001010011100000001000010 (
b1101100101100100110001110000011 &
b100001 $
#1700
b1010101001100010110100010011010010100110001000110111111111111 !
b1010101001100010110100010011010010100110001000110111111111111 '
b1010101001100010110100010011010010100110001000110111111111111 +
b10000 /
0,
b100001 2
b100000111 1
b1111 3
b1111101011010101000000000000000 -
b10001 .
b101011011110010110000001010110 #
b101011011110010110000001010110 )
b1111101011010100101100011111010 *
b1111101011010100101100011111010 "
b1111101011010100101100011111010 (
b101011011110010101111111001001 &
b100010 $
#1750
b100100110010110101110001111000011100101110111100111101110101111 !
b100100110010110101110001111000011100101110111100111101110101111 '
b100100110010110101110001111000011100101110111100111101110101111 +
b10000 /
0,
b100001 2
b100010001 1
b1111 3
b1011001110101111000000000000000 -
b10001 .
b11010001101100000000110110100011 #
b11010001101100000000110110100011 )
b1011001110101111110101010110011 *
b1011001110101111110101010110011 "
b1011001110101111110101010110011 (
b11010001101100000000101011111111 &
b100011 $
#1800
b101101101100010000101000011000001001111100100110111101110111011 !
b101101101100010000101000011000001001111100100110111101110111011 '
b101101101100010000101000011000001001111100100110111101110111011 +
b10000 /
0,
b100001 2
b100011010 1
b1111 3
b11100101100001101000000000000000 -
b10001 .
b1100101111011000101110011001011 #
b1100101111011000101110011001011 )
b11100101100001101100001111001011 *
b11100101100001101100001111001011 "
b11100101100001101100001111001011 (
b1100101111011000101101010100101 &
b100100 $
#1850
b111011001001000100101100001011110001001010010100010111011101111 !
b111011001001000100101100001011110001001010010100010111011101111 '
b111011001001000100101100001011110001001010010100010111011101111 +
b10000 /
0,
b100001 2
b100100110 1
b1111 3
b11111001100000111000000000000000 -
b10001 .
b1111001010110111010001011110010 #
b1111001010110111010001011110010 )
b11111001100000111111100111110011 *
b11111001100000111111100111110011 "
b11111001100000111111100111110011 (
b1111001010110111010000000111011 &
b100101 $
#1900
b1011111010100110101100100011010000101100110000110101011101111 !
b1011111010100110101100100011010000101100110000110101011101111 '
b1011111010100110101100100011010000101100110000110101011101111 +
b10000 /
0,
b100001 2
b100101110 1
b1111 3
b1110101101111011000000000000000 -
b10001 .
b110011110100001110101001100111 #
b110011110100001110101001100111 )
b1110101101111010101000011101011 *
b1110101101111010101000011101011 "
b1110101101111010101000011101011 (
b110011110100001110100101000001 &
b100110 $
#1950
b1011111111110001111111110000110100111100001110111111000000 !
b1011111111110001111111110000110100111100001110111111000000 '
b1011111111110001111111110000110100111100001110111111000000 +
b10000 /
0,
b100001 2
b100110010 1
b1111 3
b11011001001000000000000000 -
b10001 .
b11100010010100100110000111000100 #
b11100010010100100110000111000100 )
b11011001000001100000000110 *
b11011001000001100000000110 "
b11011001000001100000000110 (
b11100010010100100101111100110111 &
b100111 $
#2000
b1100001000011101100001011000101110101111001100100010101111101011 !
b1100001000011101100001011000101110101111001100100010101111101011 '
b1100001000011101100001011000101110101111001100100010101111101011 +
b10000 /
0,
b100001 2
b100111000 1
b1111 3
b11001010000000111000000000000000 -
b10001 .
b11110101111111011010100111101011 #
b11110101111111011010100111101011 )
b11001010000000110000110110010100 *
b11001010000000110000110110010100 "
b11001010000000110000110110010100 (
b11110101111111011010011110011101 &
b101000 $
#2050
b110111111010100110111101101011101110111000000111111111110000 !
b110111111010100110111101101011101110111000000111111111110000 '
b110111111010100110111101101011101110111000000111111111110000 +
b10000 /
0,
b100001 2
b100111110 1
b1111 3
b10000101001111111000000000000000 -
b10001 .
b11010110110110100010000110101 #
b11010110110110100010000110101 )
b10000101001111110011001100001010 *
b10000101001111110011001100001010 "
b10000101001111110011001100001010 (
b11010110110110100001111110011 &
b101001 $
#2100
b100011010101000001111010111101000110000001010100110111010111011 !
b100011010101000001111010111101000110000001010100110111010111011 '
b100011010101000001111010111101000110000001010100110111010111011 +
b10000 /
0,
b100001 2
b101001000 1
b1111 3
b11100111111110111000000000000000 -
b10001 .
b1001101111110001111001010011011 #
b1001101111110001111001010011011 )
b11100111111110111100001111001111 *
b11100111111110111100001111001111 "
b11100111111110111100001111001111 (
b1001101111110001111000110111001 &
b101010 $
#2150
b1110010000111100000100010010000011001011100111101111111111 !
b1110010000111100000100010010000011001011100111101111111111 '
b1110010000111100000100010010000011001011100111101111111111 +
b10000 /
0,
b100001 2
b101001111 1
b1111 3
b110010110001000000000000000 -
b10001 .
b10001111111000110000110100011111 #
b10001111111000110000110100011111 )
b110010110001111100000001100 *
b110010110001111100000001100 "
b110010110001111100000001100 (
b10001111111000110000101001101111 &
b101011 $
#2200
b101010111001110101100000001000011100000101010011110111110111100 !
b101010111001110101100000001000011100000101010011110111110111100 '
b101010111001110101100000001000011100000101010011110111110111100 +
b10000 /
0,
b100001 2
b101011011 1
b1111 3
b11001010110001011000000000000000 -
b10001 .
b1101100010101001110010011011000 #
b1101100010101001110010011011000 )
b11001010110001011111111110010101 *
b11001010110001011111111110010101 "
b11001010110001011111111110010101 (
b1101100010101001110001110010101 &
b101100 $
#2250
b110100010000010001100101001100001000101000110111111111111 !
b110100010000010001100101001100001000101000110111111111111 '
b110100010000010001100101001100001000101000110111111111111 +
b10000 /
0,
b100001 2
b101100100 1
b1111 3
b11110011000111011000000000000000 -
b10001 .
b1101110000011000000000011 #
b1101110000011000000000011 )
b11110011000111011101000111100110 *
b11110011000111011101000111100110 "
b11110011000111011101000111100110 (
b1101110000010111010101011 &
b101101 $
#2300
b1101011000101111010111010011011111101010111110000111101111000000 !
b1101011000101111010111010011011111101010111110000111101111000000 '
b1101011000101111010111010011011111101010111110000111101111000000 +
b10000 /
0,
b100001 2
b101101101 1
b1111 3
b11101001100001111000000000000000 -
b10001 .
b11101010110010110101101111010101 #
b11101010110010110101101111010101 )
b11101001100001110000111111010011 *
b11101001100001110000111111010011 "
b11101001100001110000111111010011 (
b11101010110010110101100100110001 &
b101110 $
#2350
b11111011001001101101110000100011111111011111110110111010110000 !
b11111011001001101101110000100011111111011111110110111010110000 '
b11111011001001101101110000100011111111011111110110111010110000 +
b10000 /
0,
b100001 2
b101110111 1
b1111 3
b10110001100011101000000000000000 -
b10001 .
b1011010100001101110111010110101 #
b1011010100001101110111010110101 )
b10110001100011101110101101100011 *
b10110001100011101110101101100011 "
b10110001100011101110101101100011 (
b1011010100001101110110010100111 &
b101111 $
#2400
b1010011110110100100001110110111110110000110011110111110111100 !
b1010011110110100100001110110111110110000110011110111110111100 '
b1010011110110100100001110110111110110000110011110111110111100 +
b10000 /
0,
b100001 2
b110000001 1
b1111 3
b1000100101101101000000000000000 -
b10001 .
b1001110000110011111000010011100 #
b1001110000110011111000010011100 )
b1000100101101101111111010001001 *
b1000100101101101111111010001001 "
b1000100101101101111111010001001 (
b1001110000110011110111010001101 &
b110000 $
#2450
b1011001100101011100011001100011100100001010010000111111111000000 !
b1011001100101011100011001100011100100001010010000111111111000000 '
b1011001100101011100011001100011100100001010010000111111111000000 +
b10000 /
0,
b100001 2
b110000111 1
b1111 3
b11001010011011101000000000000000 -
b10001 .
b11100010100101010100001111000101 #
b11100010100101010100001111000101 )
b11001010011011100011000110010100 *
b11001010011011100011000110010100 "
b11001010011011100011000110010100 (
b11100010100101010100000001100011 &
b110001 $
#2500
b110010 $
