ABM-M1-Karatsuba-bitwise-32/radix4approx.v
`timescale 10ms / 1ms

module radix4approx(p,x,y);         //8 bit multiplier to give 16 bit product

parameter N = 16;   //size of muliplicant and multiplier
parameter K = N/2;  //

input   [N-1 : 0]   x,y;
output  [N+N-1:0]   p;

reg [2:0]   bits    [K:0];
reg   neg     [K:0];
reg   two     [K:0];
reg   zero     [K:0];

wire [N+1:0] x_new;
reg [N+1:0]       PP      [K:0]; //riyaj 
reg [N+N-1:0]   ACC     [K:0];
reg [N+N-1:0]   ANS;
reg mux;

integer i , j, t;
integer  m = 12;        //number of bits to approximate

assign x_new = {2'b0,x};

always@(*)

begin
    bits[0] = {y[1],y[0],1'b0};             //setting last bit -1 as 0

    for(i=1; i<K+1; i=i+1) begin
            if(i == K)
                bits[i] = {2'b0,y[2*i-1]};
            else
                bits[i] = {y[2*i+1], y[2*i], y[2*i-1]};
            //$display("%b", bits[i]);
            
        end


    for(i=0; i<K+1; i=i+1)
        begin                               //approximated 2A as A introduced error
            case(bits[i])

            
            3'b001, 3'b010:         
            begin
                neg[i] = 1'b0;
                two[i] = 1'b0;
                zero[i] = 1'b0;
            end

            3'b011:
            begin
                neg[i] = 1'b0;
                two[i] = 1'b1;
                zero[i] = 1'b0;
            end

            3'b101, 3'b110:         
            begin 
               neg[i] = 1'b1;
                two[i] = 1'b0;
                zero[i] = 1'b0;
            end

            3'b100:
            begin
                neg[i] = 1'b1;
                two[i] = 1'b1;
                zero[i] = 1'b0;
            end
         
            default: 
            begin
                neg[i] = 1'b0;
                two[i] = 1'b0;
                zero[i] = 1'b1;
            end

            endcase

            PP[i] = 0;
            PP[i][N+1] = neg[i];           //sign conservation

            for(t=0; t<N+1; t=t+1) begin
                if(t>=m) 
                begin
                    mux = (x_new[t] & ~two[i]) | (x_new[t-1] & two[i]);             
                    PP[i][t] = ~zero[i] & (neg[i] ^ mux);
                end

                else 
                begin
                    PP[i][t] = (~x_new[t] & neg[i]) | (x_new[t] & ~neg[i] & ~zero[i]);
                end
            end

            PP[i][0] = PP[i][0] | neg[i];

            ACC[i] = $signed(PP[i]);        //sign extension
            
            for(j=0; j<i; j=j+1)
                ACC[i] = {ACC[i],2'b00};        //shifting

        
        end

    ANS = ACC[0];

    for(i=1; i<K+1; i=i+1)
        ANS = ANS+ACC[i];
        
end


assign p = ANS;

endmodule

ABM-M1-WT-bitwise-64/radix4acc.v
`timescale 10ms / 1ms

module radix4acc(p,x,y);        

parameter N = 32;   //size of muliplicant and multiplier
parameter K = N/2;  //

input [N-1 : 0]   x,y;
output [N+N-1:0]   p;

reg [2:0]   bits    [K:0];
reg   neg     [K:0];
reg   two     [K:0];
reg   zero     [K:0];

wire [N+1:0] x_new;
reg [N+1:0]       PP      [K:0]; 
reg [N+N-1:0]   ACC     [K:0];
reg [N+N-1:0]   ANS;
reg mux;

integer i , j, t;

assign x_new = {2'b0,x};

always@(*)

begin
    bits[0] = {y[1],y[0],1'b0};             //setting last bit -1 as 0
    //$display("%b", bits[0]);
    for(i=1; i<K+1; i=i+1) begin
        if(i == K)
            bits[i] = {2'b0,y[2*i-1]};
        else
            bits[i] = {y[2*i+1], y[2*i], y[2*i-1]};
        //$display("%b", bits[i]);
        
    end

    for(i=0; i<K+1; i=i+1)
        begin                                      //accurate cases
            case(bits[i])

            
            3'b001, 3'b010:         
            begin
                neg[i] = 1'b0;
                two[i] = 1'b0;
                zero[i] = 1'b0;
            end

            3'b011:
            begin
                neg[i] = 1'b0;
                two[i] = 1'b1;
                zero[i] = 1'b0;
            end

            3'b101, 3'b110:         
            begin 
               neg[i] = 1'b1;
                two[i] = 1'b0;
                zero[i] = 1'b0;
            end

            3'b100:
            begin
                neg[i] = 1'b1;
                two[i] = 1'b1;
                zero[i] = 1'b0;
            end
         
            default: 
            begin
                neg[i] = 1'b0;
                two[i] = 1'b0;
                zero[i] = 1'b1;
            end

            endcase
            
            //$display("%b %b %b", neg[i], two[i], zero[i]);
            
            PP[i] = 0;
            PP[i][N+1] = neg[i];           //sign conservation

            for(t=0; t<N+1; t=t+1) begin
                if(t==0) 
                    mux = (x_new[t] & ~two[i]) | (1'b0 & two[i]);
                
                else
                    mux = (x_new[t] & ~two[i]) | (x_new[t-1] & two[i]);

                
                PP[i][t] = ~zero[i] & (neg[i] ^ mux);       
            end

            PP[i] = PP[i] + neg[i];             //correction term added
            
            //$display("%b", PP[i]);

            ACC[i] = $signed(PP[i]);        //sign extension
            //$display("%b", ACC[i]);

            for(j=0; j<i; j=j+1)
                ACC[i] = {ACC[i],2'b00};        //shifting

        
        end

    ANS = ACC[0];

    for(i=1; i<K+1; i=i+1)
        ANS = ANS+ACC[i];
        
    
end


assign p = ANS;

endmodule

ABM-M1-WT-bitwise-64/WT64.v
`timescale 10ms/1ms
`include "radix4acc.v"
`include "radix4approx.v"

module WT64(P,A,B);


parameter N = 64;   //size of muliplicant and multiplier
parameter K = N/2;  //

input   [N-1 : 0]   A,B;
output  [N+N-1:0]   P;

wire [K-1:0] AH, AL, BH, BL;

wire reg [N-1:0] M1, M2, M3, M4;

reg     [N:0]   A1, A2, A3;

reg [N+N-1:0]   ACC     [2:0];
reg [N+N-1:0] ANS;
integer i;


assign AH = A[N-1:K];
assign AL = A[K-1:0];

assign BH = B[N-1:K];
assign BL = B[K-1:0];

radix4approx APP1(.p(M1), .x(AL), .y(BL));

radix4acc ACC1(.p(M2), .x(AH), .y(BH));

radix4approx APP2(.p(M3), .x(AH), .y(BL));
radix4approx APP3(.p(M4), .x(AL), .y(BH));


always@(*)
begin

    A1 =  M3+M4;
    ACC[0] = $signed(A1);
    ACC[0] = {ACC[0], {32{1'b0}}};

    A2 = M1;
    ACC[1] = $signed(A2);
    
    A3 = M2;
    ACC[2] = $signed(A3);
    ACC[2] = {ACC[2], {64{1'b0}}};

    ANS = ACC[0];
    for(i=1; i<3; i=i+1)
        ANS = ANS+ACC[i];

    
end

assign P = ANS;

endmodule

ABM-M1-WT-bitwise-64/WT64_tb.v
`timescale 10ms / 1ms
`include "WT64.v"

module WT64_tb();

reg unsigned [63:0] A,B;
wire unsigned [127:0] P;
integer i, out, seed=7;


WT64 uut(P,A,B);


initial begin
    $dumpfile("WT64.vcd");
    $dumpvars(0, WT64_tb);
    out = $fopen("WT64output.csv");
    
    for(i=0; i<500; i=i+1)
    begin
        A = {2{$urandom(seed)}};
        B = {2{$urandom(seed)}};
        #1;
        $fwrite(out, "%d, %d, %d\n", A,B,P);
        #4;
    end
    $finish;
end

endmodule

ABM-M1-WT-bitwise-64/WT64.vcd
$date
	Fri Jul  9 13:39:42 2021
$end
$version
	Icarus Verilog
$end
$timescale
	1ms
$end
$scope module WT64_tb $end
$var wire 128 ! P [127:0] $end
$var reg 64 " A [63:0] $end
$var reg 64 # B [63:0] $end
$var integer 32 $ i [31:0] $end
$var integer 32 % out [31:0] $end
$var integer 32 & seed [31:0] $end
$scope module uut $end
$var wire 64 ' A [63:0] $end
$var wire 64 ( B [63:0] $end
$var wire 128 ) P [127:0] $end
$var wire 64 * M4 [63:0] $end
$var wire 64 + M3 [63:0] $end
$var wire 64 , M2 [63:0] $end
$var wire 64 - M1 [63:0] $end
$var wire 32 . BL [31:0] $end
$var wire 32 / BH [31:0] $end
$var wire 32 0 AL [31:0] $end
$var wire 32 1 AH [31:0] $end
$var reg 65 2 A1 [64:0] $end
$var reg 65 3 A2 [64:0] $end
$var reg 65 4 A3 [64:0] $end
$var reg 128 5 ANS [127:0] $end
$var integer 32 6 i [31:0] $end
$scope module ACC1 $end
$var wire 64 7 p [63:0] $end
$var wire 32 8 x [31:0] $end
$var wire 32 9 y [31:0] $end
$var wire 34 : x_new [33:0] $end
$var reg 64 ; ANS [63:0] $end
$var reg 1 < mux $end
$var integer 32 = i [31:0] $end
$var integer 32 > j [31:0] $end
$var integer 32 ? t [31:0] $end
$upscope $end
$scope module APP1 $end
$var wire 64 @ p [63:0] $end
$var wire 32 A x [31:0] $end
$var wire 32 B y [31:0] $end
$var wire 34 C x_new [33:0] $end
$var reg 64 D ANS [63:0] $end
$var reg 1 E mux $end
$var integer 32 F i [31:0] $end
$var integer 32 G j [31:0] $end
$var integer 32 H m [31:0] $end
$var integer 32 I t [31:0] $end
$upscope $end
$scope module APP2 $end
$var wire 64 J p [63:0] $end
$var wire 32 K x [31:0] $end
$var wire 32 L y [31:0] $end
$var wire 34 M x_new [33:0] $end
$var reg 64 N ANS [63:0] $end
$var reg 1 O mux $end
$var integer 32 P i [31:0] $end
$var integer 32 Q j [31:0] $end
$var integer 32 R m [31:0] $end
$var integer 32 S t [31:0] $end
$upscope $end
$scope module APP3 $end
$var wire 64 T p [63:0] $end
$var wire 32 U x [31:0] $end
$var wire 32 V y [31:0] $end
$var wire 34 W x_new [33:0] $end
$var reg 64 X ANS [63:0] $end
$var reg 1 Y mux $end
$var integer 32 Z i [31:0] $end
$var integer 32 [ j [31:0] $end
$var integer 32 \ m [31:0] $end
$var integer 32 ] t [31:0] $end
$upscope $end
$upscope $end
$upscope $end
$enddefinitions $end
#0
$dumpvars
b100001 ]
b11000 \
b10000 [
b10001 Z
0Y
b101101000001110110011000110100001000001001110111100 X
b1110110001000000000 W
b11000110011011000100101110001100 V
b1110110001000000000 U
b101101000001110110011000110100001000001001110111100 T
b100001 S
b11000 R
b10000 Q
b10001 P
0O
b101101000001110110011000110100001000001001110111100 N
b1110110001000000000 M
b11000110011011000100101110001100 L
b1110110001000000000 K
b101101000001110110011000110100001000001001110111100 J
b100001 I
b11000 H
b10000 G
b10001 F
0E
b101101000001110110011000110100001000001001110111100 D
b1110110001000000000 C
b11000110011011000100101110001100 B
b1110110001000000000 A
b101101000001110110011000110100001000001001110111100 @
b100001 ?
b10000 >
b10001 =
0<
b101101110001110101110000101101111111001100000000000 ;
b1110110001000000000 :
b11000110011011000100101110001100 9
b1110110001000000000 8
b101101110001110101110000101101111111001100000000000 7
b11 6
b1011011100011101011100001011100101011011001110110011000110100001101110010000110010011000110100001000001001110111100 5
b101101110001110101110000101101111111001100000000000 4
b101101000001110110011000110100001000001001110111100 3
b1011010000011101100110001101000010000010011101111000 2
b1110110001000000000 1
b1110110001000000000 0
b11000110011011000100101110001100 /
b11000110011011000100101110001100 .
b101101000001110110011000110100001000001001110111100 -
b101101110001110101110000101101111111001100000000000 ,
b101101000001110110011000110100001000001001110111100 +
b101101000001110110011000110100001000001001110111100 *
b1011011100011101011100001011100101011011001110110011000110100001101110010000110010011000110100001000001001110111100 )
b1100011001101100010010111000110011000110011011000100101110001100 (
b111011000100000000000000000000001110110001000000000 '
b11000110011011000100100011101101 &
b10 %
b0 $
b1100011001101100010010111000110011000110011011000100101110001100 #
b111011000100000000000000000000001110110001000000000 "
b1011011100011101011100001011100101011011001110110011000110100001101110010000110010011000110100001000001001110111100 !
$end
#50
b11 6
b1110110000110111110011101111010011000110001101001001011110001011101101100010101111010000001111010110010011111001101111110110100 !
b1110110000110111110011101111010011000110001101001001011110001011101101100010101111010000001111010110010011111001101111110110100 )
b1110110000110111110011101111010011000110001101001001011110001011101101100010101111010000001111010110010011111001101111110110100 5
b111011000011011111001110111100101110110111000011111101001011000 4
b111011000011100001010001011011010110010011111001101111110110100 3
b1110110000111000010100010110110101100100111110011011111101101000 2
b111011000011011111001110111100101110110111000011111101001011000 ,
b111011000011011111001110111100101110110111000011111101001011000 7
b111011000011011111001110111100101110110111000011111101001011000 ;
b10000 >
0<
b100001 ?
b10001 =
b111011000011100001010001011011010110010011111001101111110110100 +
b111011000011100001010001011011010110010011111001101111110110100 J
b111011000011100001010001011011010110010011111001101111110110100 N
b10000 Q
0O
b100001 S
b10001 P
b111011000011100001010001011011010110010011111001101111110110100 -
b111011000011100001010001011011010110010011111001101111110110100 @
b111011000011100001010001011011010110010011111001101111110110100 D
b10000 G
0E
b100001 I
b10001 F
b111011000011100001010001011011010110010011111001101111110110100 *
b111011000011100001010001011011010110010011111001101111110110100 T
b111011000011100001010001011011010110010011111001101111110110100 X
b10000 [
0Y
b100001 ]
b10001 Z
b10101110011011011111101101011100 /
b10101110011011011111101101011100 9
b10101110011011011111101101011100 V
b10101110011011011111101101011100 .
b10101110011011011111101101011100 B
b10101110011011011111101101011100 L
b10101101010101110111000101011010 :
b10101101010101110111000101011010 M
b10101101010101110111000101011010 1
b10101101010101110111000101011010 8
b10101101010101110111000101011010 K
b10101101010101110111000101011010 C
b10101101010101110111000101011010 W
b10101101010101110111000101011010 0
b10101101010101110111000101011010 A
b10101101010101110111000101011010 U
b1010111001101101111110110101110010101110011011011111101101011100 #
b1010111001101101111110110101110010101110011011011111101101011100 (
b1010110101010111011100010101101010101101010101110111000101011010 "
b1010110101010111011100010101101010101101010101110111000101011010 '
b10101110011011011111100111000011 &
b1 $
#100
b11 6
b110001111011000110101111100001110000100110001000111100001000011110101100100001001000010100100001011100100110100101101001110101 !
b110001111011000110101111100001110000100110001000111100001000011110101100100001001000010100100001011100100110100101101001110101 )
b110001111011000110101111100001110000100110001000111100001000011110101100100001001000010100100001011100100110100101101001110101 5
b11000111101100011010111110000101011110100010010110001101100101 4
b11000111101100011011000101111001011100100110100101101001110101 3
b110001111011000110110001011110010111001001101001011010011101010 2
b11000111101100011010111110000101011110100010010110001101100101 ,
b11000111101100011010111110000101011110100010010110001101100101 7
b11000111101100011010111110000101011110100010010110001101100101 ;
b10000 >
0<
b100001 ?
b10001 =
b11000111101100011011000101111001011100100110100101101001110101 +
b11000111101100011011000101111001011100100110100101101001110101 J
b11000111101100011011000101111001011100100110100101101001110101 N
b10000 Q
0O
b100001 S
b10001 P
b11000111101100011011000101111001011100100110100101101001110101 -
b11000111101100011011000101111001011100100110100101101001110101 @
b11000111101100011011000101111001011100100110100101101001110101 D
b10000 G
0E
b100001 I
b10001 F
b11000111101100011011000101111001011100100110100101101001110101 *
b11000111101100011011000101111001011100100110100101101001110101 T
b11000111101100011011000101111001011100100110100101101001110101 X
b10000 [
0Y
b100001 ]
b10001 Z
b11001111110001011111001110011111 /
b11001111110001011111001110011111 9
b11001111110001011111001110011111 V
b11001111110001011111001110011111 .
b11001111110001011111001110011111 B
b11001111110001011111001110011111 L
b111101100000101110101001111011 :
b111101100000101110101001111011 M
b111101100000101110101001111011 1
b111101100000101110101001111011 8
b111101100000101110101001111011 K
b111101100000101110101001111011 C
b111101100000101110101001111011 W
b111101100000101110101001111011 0
b111101100000101110101001111011 A
b111101100000101110101001111011 U
b1100111111000101111100111001111111001111110001011111001110011111 #
b1100111111000101111100111001111111001111110001011111001110011111 (
b11110110000010111010100111101100111101100000101110101001111011 "
b11110110000010111010100111101100111101100000101110101001111011 '
b11001111110001011111000000001001 &
b10 $
#150
b11 6
b111001110010010001111000011101101011011100101001111000111111101111111000101101000101111111111101100010001110000111110100 !
b111001110010010001111000011101101011011100101001111000111111101111111000101101000101111111111101100010001110000111110100 )
b111001110010010001111000011101101011011100101001111000111111101111111000101101000101111111111101100010001110000111110100 5
b11100111001001000111100001110100111010010100100011110100 4
b11100110111100000111011111111101100010001110000111110100 3
b111001101111000001110111111111011000100011100001111101000 2
b11100111001001000111100001110100111010010100100011110100 ,
b11100111001001000111100001110100111010010100100011110100 7
b11100111001001000111100001110100111010010100100011110100 ;
b10000 >
0<
b100001 ?
b10001 =
b11100110111100000111011111111101100010001110000111110100 +
b11100110111100000111011111111101100010001110000111110100 J
b11100110111100000111011111111101100010001110000111110100 N
b10000 Q
0O
b100001 S
b10001 P
b11100110111100000111011111111101100010001110000111110100 -
b11100110111100000111011111111101100010001110000111110100 @
b11100110111100000111011111111101100010001110000111110100 D
b10000 G
0E
b100001 I
b10001 F
b11100110111100000111011111111101100010001110000111110100 *
b11100110111100000111011111111101100010001110000111110100 T
b11100110111100000111011111111101100010001110000111110100 X
b10000 [
0Y
b100001 ]
b10001 Z
b10011100001010011000000100 /
b10011100001010011000000100 9
b10011100001010011000000100 V
b10011100001010011000000100 .
b10011100001010011000000100 B
b10011100001010011000000100 L
b1011110101110101010111010111101 :
b1011110101110101010111010111101 M
b1011110101110101010111010111101 1
b1011110101110101010111010111101 8
b1011110101110101010111010111101 K
b1011110101110101010111010111101 C
b1011110101110101010111010111101 W
b1011110101110101010111010111101 0
b1011110101110101010111010111101 A
b1011110101110101010111010111101 U
b1001110000101001100000010000000010011100001010011000000100 #
b1001110000101001100000010000000010011100001010011000000100 (
b101111010111010101011101011110101011110101110101010111010111101 "
b101111010111010101011101011110101011110101110101010111010111101 '
b10011100001010010100111111 &
b11 $
#200
b11 6
b100110001111111001111011010100111110111010011100110010010001000000000011001111010100001000000111101101010000100111101001 !
b100110001111111001111011010100111110111010011100110010010001000000000011001111010100001000000111101101010000100111101001 )
b100110001111111001111011010100111110111010011100110010010001000000000011001111010100001000000111101101010000100111101001 5
b10011000111111100111101101010010101111000100100111101001 4
b10011001001010010111000000000111101101010000100111101001 3
b100110010010100101110000000001111011010100001001111010010 2
b10011000111111100111101101010010101111000100100111101001 ,
b10011000111111100111101101010010101111000100100111101001 7
b10011000111111100111101101010010101111000100100111101001 ;
b10000 >
0<
b100001 ?
b10001 =
b10011001001010010111000000000111101101010000100111101001 +
b10011001001010010111000000000111101101010000100111101001 J
b10011001001010010111000000000111101101010000100111101001 N
b10000 Q
0O
b100001 S
b10001 P
b10011001001010010111000000000111101101010000100111101001 -
b10011001001010010111000000000111101101010000100111101001 @
b10011001001010010111000000000111101101010000100111101001 D
b10000 G
0E
b100001 I
b10001 F
b10011001001010010111000000000111101101010000100111101001 *
b10011001001010010111000000000111101101010000100111101001 T
b10011001001010010111000000000111101101010000100111101001 X
b10000 [
0Y
b100001 ]
b10001 Z
b1110111101001000000000011 /
b1110111101001000000000011 9
b1110111101001000000000011 V
b1110111101001000000000011 .
b1110111101001000000000011 B
b1110111101001000000000011 L
b1010001110101111000100010100011 :
b1010001110101111000100010100011 M
b1010001110101111000100010100011 1
b1010001110101111000100010100011 8
b1010001110101111000100010100011 K
b1010001110101111000100010100011 C
b1010001110101111000100010100011 W
b1010001110101111000100010100011 0
b1010001110101111000100010100011 A
b1010001110101111000100010100011 U
b111011110100100000000001100000001110111101001000000000011 #
b111011110100100000000001100000001110111101001000000000011 (
b101000111010111100010001010001101010001110101111000100010100011 "
b101000111010111100010001010001101010001110101111000100010100011 '
b1110111101000111011100101 &
b100 $
#250
b11 6
b100101110010001000001111010111100010110011011010011101000010100100111010001000000000010110010100010100010111111011111001101 !
b100101110010001000001111010111100010110011011010011101000010100100111010001000000000010110010100010100010111111011111001101 )
b100101110010001000001111010111100010110011011010011101000010100100111010001000000000010110010100010100010111111011111001101 5
b10010111001000100000111101011100111111101001011001001111100 4
b10010111001000100001001001010100010100010111111011111001101 3
b100101110010001000010010010101000101000101111110111110011010 2
b10010111001000100000111101011100111111101001011001001111100 ,
b10010111001000100000111101011100111111101001011001001111100 7
b10010111001000100000111101011100111111101001011001001111100 ;
b10000 >
0<
b100001 ?
b10001 =
b10010111001000100001001001010100010100010111111011111001101 +
b10010111001000100001001001010100010100010111111011111001101 J
b10010111001000100001001001010100010100010111111011111001101 N
b10000 Q
0O
b100001 S
b10001 P
b10010111001000100001001001010100010100010111111011111001101 -
b10010111001000100001001001010100010100010111111011111001101 @
b10010111001000100001001001010100010100010111111011111001101 D
b10000 G
0E
b100001 I
b10001 F
b10010111001000100001001001010100010100010111111011111001101 *
b10010111001000100001001001010100010100010111111011111001101 T
b10010111001000100001001001010100010100010111111011111001101 X
b10000 [
0Y
b100001 ]
b10001 Z
b1101001110111000000000011010 /
b1101001110111000000000011010 9
b1101001110111000000000011010 V
b1101001110111000000000011010 .
b1101001110111000000000011010 B
b1101001110111000000000011010 L
b1011011010111110001000010110110 :
b1011011010111110001000010110110 M
b1011011010111110001000010110110 1
b1011011010111110001000010110110 8
b1011011010111110001000010110110 K
b1011011010111110001000010110110 C
b1011011010111110001000010110110 W
b1011011010111110001000010110110 0
b1011011010111110001000010110110 A
b1011011010111110001000010110110 U
b110100111011100000000001101000001101001110111000000000011010 #
b110100111011100000000001101000001101001110111000000000011010 (
b101101101011111000100001011011001011011010111110001000010110110 "
b101101101011111000100001011011001011011010111110001000010110110 '
b1101001110110111111001111011 &
b101 $
#300
b11 6
b1101100000010010111110000101100011011010010100111101101000010011001001101100000000110001010110010010011001111100000000011011 !
b1101100000010010111110000101100011011010010100111101101000010011001001101100000000110001010110010010011001111100000000011011 )
b1101100000010010111110000101100011011010010100111101101000010011001001101100000000110001010110010010011001111100000000011011 5
b110110000001001011111000010101110010011011000011011111100010 4
b110110011100100000101101111110010010011001111100000000011011 3
b1101100111001000001011011111100100100110011111000000000110110 2
b110110000001001011111000010101110010011011000011011111100010 ,
b110110000001001011111000010101110010011011000011011111100010 7
b110110000001001011111000010101110010011011000011011111100010 ;
b10000 >
0<
b100001 ?
b10001 =
b110110011100100000101101111110010010011001111100000000011011 +
b110110011100100000101101111110010010011001111100000000011011 J
b110110011100100000101101111110010010011001111100000000011011 N
b10000 Q
0O
b100001 S
b10001 P
b110110011100100000101101111110010010011001111100000000011011 -
b110110011100100000101101111110010010011001111100000000011011 @
b110110011100100000101101111110010010011001111100000000011011 D
b10000 G
0E
b100001 I
b10001 F
b110110011100100000101101111110010010011001111100000000011011 *
b110110011100100000101101111110010010011001111100000000011011 T
b110110011100100000101101111110010010011001111100000000011011 X
b10000 [
0Y
b100001 ]
b10001 Z
b1111001000111010000001011110010 /
b1111001000111010000001011110010 9
b1111001000111010000001011110010 V
b1111001000111010000001011110010 .
b1111001000111010000001011110010 B
b1111001000111010000001011110010 L
b11100100010111000100000111001 :
b11100100010111000100000111001 M
b11100100010111000100000111001 1
b11100100010111000100000111001 8
b11100100010111000100000111001 K
b11100100010111000100000111001 C
b11100100010111000100000111001 W
b11100100010111000100000111001 0
b11100100010111000100000111001 A
b11100100010111000100000111001 U
b111100100011101000000101111001001111001000111010000001011110010 #
b111100100011101000000101111001001111001000111010000001011110010 (
b1110010001011100010000011100100011100100010111000100000111001 "
b1110010001011100010000011100100011100100010111000100000111001 '
b1111001000111010000000110000001 &
b110 $
#350
b11 6
b101110101110100101010111100010001010011001100011001000101111111110010101011100111101001110011101011011010011001011000111001001 !
b101110101110100101010111100010001010011001100011001000101111111110010101011100111101001110011101011011010011001011000111001001 )
b101110101110100101010111100010001010011001100011001000101111111110010101011100111101001110011101011011010011001011000111001001 5
b10111010111010010101011110000111001100000100011010011000010101 4
b10111011000011100100010101010101011011010011001011000111001001 3
b101110110000111001000101010101010110110100110010110001110010010 2
b10111010111010010101011110000111001100000100011010011000010101 ,
b10111010111010010101011110000111001100000100011010011000010101 7
b10111010111010010101011110000111001100000100011010011000010101 ;
b10000 >
0<
b100001 ?
b10001 =
b10111011000011100100010101010101011011010011001011000111001001 +
b10111011000011100100010101010101011011010011001011000111001001 J
b10111011000011100100010101010101011011010011001011000111001001 N
b10000 Q
0O
b100001 S
b10001 P
b10111011000011100100010101010101011011010011001011000111001001 -
b10111011000011100100010101010101011011010011001011000111001001 @
b10111011000011100100010101010101011011010011001011000111001001 D
b10000 G
0E
b100001 I
b10001 F
b10111011000011100100010101010101011011010011001011000111001001 *
b10111011000011100100010101010101011011010011001011000111001001 T
b10111011000011100100010101010101011011010011001011000111001001 X
b10000 [
0Y
b100001 ]
b10001 Z
b1100100101011111100001011001001 /
b1100100101011111100001011001001 9
b1100100101011111100001011001001 V
b1100100101011111100001011001001 .
b1100100101011111100001011001001 B
b1100100101011111100001011001001 L
b1110110110011101100001011101101 :
b1110110110011101100001011101101 M
b1110110110011101100001011101101 1
b1110110110011101100001011101101 8
b1110110110011101100001011101101 K
b1110110110011101100001011101101 C
b1110110110011101100001011101101 W
b1110110110011101100001011101101 0
b1110110110011101100001011101101 A
b1110110110011101100001011101101 U
b110010010101111110000101100100101100100101011111100001011001001 #
b110010010101111110000101100100101100100101011111100001011001001 (
b111011011001110110000101110110101110110110011101100001011101101 "
b111011011001110110000101110110101110110110011101100001011101101 '
b1100100101011111100000101110111 &
b111 $
#400
b11 6
b110011111011111011100011001001001110000010110010111000101101110001101110010101100001110110101101110011110100101101011101100000 !
b110011111011111011100011001001001110000010110010111000101101110001101110010101100001110110101101110011110100101101011101100000 )
b110011111011111011100011001001001110000010110010111000101101110001101110010101100001110110101101110011110100101101011101100000 5
b11001111101111101110001100100011010000010011010000011101100000 4
b11001111101111110110001010101101110011110100101101011101100000 3
b110011111011111101100010101011011100111101001011010111011000000 2
b11001111101111101110001100100011010000010011010000011101100000 ,
b11001111101111101110001100100011010000010011010000011101100000 7
b11001111101111101110001100100011010000010011010000011101100000 ;
b10000 >
0<
b100001 ?
b10001 =
b11001111101111110110001010101101110011110100101101011101100000 +
b11001111101111110110001010101101110011110100101101011101100000 J
b11001111101111110110001010101101110011110100101101011101100000 N
b10000 Q
0O
b100001 S
b10001 P
b11001111101111110110001010101101110011110100101101011101100000 -
b11001111101111110110001010101101110011110100101101011101100000 @
b11001111101111110110001010101101110011110100101101011101100000 D
b10000 G
0E
b100001 I
b10001 F
b11001111101111110110001010101101110011110100101101011101100000 *
b11001111101111110110001010101101110011110100101101011101100000 T
b11001111101111110110001010101101110011110100101101011101100000 X
b10000 [
0Y
b100001 ]
b10001 Z
b10101000001110111110010101010000 /
b10101000001110111110010101010000 9
b10101000001110111110010101010000 V
b10101000001110111110010101010000 .
b10101000001110111110010101010000 B
b10101000001110111110010101010000 L
b1001111000001111111100010011110 :
b1001111000001111111100010011110 M
b1001111000001111111100010011110 1
b1001111000001111111100010011110 8
b1001111000001111111100010011110 K
b1001111000001111111100010011110 C
b1001111000001111111100010011110 W
b1001111000001111111100010011110 0
b1001111000001111111100010011110 A
b1001111000001111111100010011110 U
b1010100000111011111001010101000010101000001110111110010101010000 #
b1010100000111011111001010101000010101000001110111110010101010000 (
b100111100000111111110001001111001001111000001111111100010011110 "
b100111100000111111110001001111001001111000001111111100010011110 '
b10101000001110111110001111011101 &
b1000 $
#450
b11 6
b1000001011111100101001110100110100001111100101010000000010111111010010100100000011000111111111110110001110100001011011011000 !
b1000001011111100101001110100110100001111100101010000000010111111010010100100000011000111111111110110001110100001011011011000 )
b1000001011111100101001110100110100001111100101010000000010111111010010100100000011000111111111110110001110100001011011011000 5
b100000101111110010100111010011000000100110011001001001101100 4
b100000101111110111101100111111110110001110100001011011011000 3
b1000001011111101111011001111111101100011101000010110110110000 2
b100000101111110010100111010011000000100110011001001001101100 ,
b100000101111110010100111010011000000100110011001001001101100 7
b100000101111110010100111010011000000100110011001001001101100 ;
b10000 >
0<
b100001 ?
b10001 =
b100000101111110111101100111111110110001110100001011011011000 +
b100000101111110111101100111111110110001110100001011011011000 J
b100000101111110111101100111111110110001110100001011011011000 N
b10000 Q
0O
b100001 S
b10001 P
b100000101111110111101100111111110110001110100001011011011000 -
b100000101111110111101100111111110110001110100001011011011000 @
b100000101111110111101100111111110110001110100001011011011000 D
b10000 G
0E
b100001 I
b10001 F
b100000101111110111101100111111110110001110100001011011011000 *
b100000101111110111101100111111110110001110100001011011011000 T
b100000101111110111101100111111110110001110100001011011011000 X
b10000 [
0Y
b100001 ]
b10001 Z
b1100100110000110110000011001 /
b1100100110000110110000011001 9
b1100100110000110110000011001 V
b1100100110000110110000011001 .
b1100100110000110110000011001 B
b1100100110000110110000011001 L
b10100110011001001011001101001100 :
b10100110011001001011001101001100 M
b10100110011001001011001101001100 1
b10100110011001001011001101001100 8
b10100110011001001011001101001100 K
b10100110011001001011001101001100 C
b10100110011001001011001101001100 W
b10100110011001001011001101001100 0
b10100110011001001011001101001100 A
b10100110011001001011001101001100 U
b110010011000011011000001100100001100100110000110110000011001 #
b110010011000011011000001100100001100100110000110110000011001 (
b1010011001100100101100110100110010100110011001001011001101001100 "
b1010011001100100101100110100110010100110011001001011001101001100 '
b1100100110000110101000110011 &
b1001 $
#500
b11 6
b10101111000110010100010111000001110111110100110111001001101010011000111000000011001110000110100001101111010111100011011110111 !
b10101111000110010100010111000001110111110100110111001001101010011000111000000011001110000110100001101111010111100011011110111 )
b10101111000110010100010111000001110111110100110111001001101010011000111000000011001110000110100001101111010111100011011110111 5
b1010111100011001010001011100000010000000110000000011011110111 4
b1010111101000110110010001111100001101111010111100011011110111 3
b10101111010001101100100011111000011011110101111000110111101110 2
b1010111100011001010001011100000010000000110000000011011110111 ,
b1010111100011001010001011100000010000000110000000011011110111 7
b1010111100011001010001011100000010000000110000000011011110111 ;
b10000 >
0<
b100001 ?
b10001 =
b1010111101000110110010001111100001101111010111100011011110111 +
b1010111101000110110010001111100001101111010111100011011110111 J
b1010111101000110110010001111100001101111010111100011011110111 N
b10000 Q
0O
b100001 S
b10001 P
b1010111101000110110010001111100001101111010111100011011110111 -
b1010111101000110110010001111100001101111010111100011011110111 @
b1010111101000110110010001111100001101111010111100011011110111 D
b10000 G
0E
b100001 I
b10001 F
b1010111101000110110010001111100001101111010111100011011110111 *
b1010111101000110110010001111100001101111010111100011011110111 T
b1010111101000110110010001111100001101111010111100011011110111 X
b10000 [
0Y
b100001 ]
b10001 Z
b1011010111001011001001010110101 /
b1011010111001011001001010110101 9
b1011010111001011001001010110101 V
b1011010111001011001001010110101 .
b1011010111001011001001010110101 B
b1011010111001011001001010110101 L
b111101101001001010001001111011 :
b111101101001001010001001111011 M
b111101101001001010001001111011 1
b111101101001001010001001111011 8
b111101101001001010001001111011 K
b111101101001001010001001111011 C
b111101101001001010001001111011 W
b111101101001001010001001111011 0
b111101101001001010001001111011 A
b111101101001001010001001111011 U
b101101011100101100100101011010101011010111001011001001010110101 #
b101101011100101100100101011010101011010111001011001001010110101 (
b11110110100100101000100111101100111101101001001010001001111011 "
b11110110100100101000100111101100111101101001001010001001111011 '
b1011010111001011001000111111001 &
b1010 $
