ABM-M1-Karatsuba-overall-16/radix4approx10bit.v
`timescale 10ms / 1ms

module radix4approx10bit(p,x,y);         //8 bit multiplier to give 32 bit product

parameter N = 10;   //size of muliplicant and multiplier
parameter K = N/2;  //

input   [N-1 : 0]   x,y;
output  [N+N-1:0]   p;

reg [2:0]   bits    [K-1:0];
//reg [2:0]   MBE     [K-1:0];


reg [N:0]       PP      [K-1:0];
reg [N+N-1:0]   ACC     [K-1:0];
reg [N+N-1:0]   ANS;

integer i , j;

wire [N:0] xbar;
assign xbar = {~x[N-1], ~x} + 1'b1;         //2's complement retaining the sign bit

always@(*)

begin
    bits[0] = {y[1],y[0],1'b0};             //setting last bit -1 as 0

    for(i=1; i<K; i=i+1)
        bits[i] = {y[2*i+1], y[2*i], y[2*i-1]};


    for(i=0; i<K; i=i+1)
        begin
            case(bits[i])

            //3'b000, 3'b111: MBE[i] = 3'b001;

            3'b001, 3'b010, 3'b011:         //adding the case of +2A 
            begin
                //MBE[i] = 3'b000; 
                PP[i] = {x[N-1], x};
            end

            
            3'b101, 3'b110, 3'b100:         //adding the case of -2A
            begin 
                //MBE[i] = 3'b100;
                PP[i] = xbar;
            end
         
            default: 
            begin
                //MBE[i] = 3'b001;
                PP[i]  = 0;
            end

            endcase

            ACC[i] = $signed(PP[i]);        //sign extension

            for(j=0; j<i; j=j+1)
                ACC[i] = {ACC[i],2'b00};        //shifting

            
        end

    ANS = ACC[0];

    for(i=1; i<K; i=i+1)
        ANS = ANS+ACC[i];

    ANS[9:2] = 1'b1;            //hybrid approximation          //doesnt make much difference
    //ANS = {ANS[N+N-1],ANS[N+N-3:0],1'b0};
    
end


assign p = ANS;

endmodule

unsigned/karatsuba/adder8.v
`timescale 10ms / 1ms

module adder8(s,a,b);

input [7:0] a,b;

output [8:0] s;


assign s = a+b;

endmodule

ABM-M1-WT-overall/radix4approx.v
`timescale 10ms / 1ms

module radix4approx(p,x,y);         //16 bit multiplier to give 32 bit product

parameter N = 8;   //size of muliplicant and multiplier
parameter K = N/2;  //

input   [N-1 : 0]   x,y;
output  [N+N-1:0]   p;

reg [2:0]   bits    [K-1:0];
//reg [2:0]   MBE     [K-1:0];


reg [N:0]       PP      [K-1:0];
reg [N+N-1:0]   ACC     [K-1:0];
reg [N+N-1:0]   ANS;

integer i , j;

wire [N:0] xbar;
assign xbar = {~x[N-1], ~x} + 1'b1;         //2's complement retaining the sign bit

always@(*)

begin
    bits[0] = {y[1],y[0],1'b0};             //setting last bit -1 as 0

    for(i=1; i<K; i=i+1)
        bits[i] = {y[2*i+1], y[2*i], y[2*i-1]};


    for(i=0; i<K; i=i+1)
        begin
            case(bits[i])

            //3'b000, 3'b111: MBE[i] = 3'b001;

            3'b001, 3'b010, 3'b011:         //adding the case of +2A 
            begin
                //MBE[i] = 3'b000; 
                PP[i] = {x[N-1], x};
            end

            
            3'b101, 3'b110, 3'b100:         //adding the case of -2A
            begin 
                //MBE[i] = 3'b100;
                PP[i] = xbar;
            end
         
            default: 
            begin
                //MBE[i] = 3'b001;
                PP[i]  = 0;
            end

            endcase

            ACC[i] = $signed(PP[i]);        //sign extension

            for(j=0; j<i; j=j+1)
                ACC[i] = {ACC[i],2'b00};        //shifting

        
        end

    ANS = ACC[0];

    for(i=1; i<K; i=i+1)
        ANS = ANS+ACC[i];

    ANS[7:2] = 1'b1;            //hybrid approximation
    //ANS = {ANS[N+N-1],ANS[N+N-3:0],1'b0};
        
end


assign p = ANS;

endmodule

ABM-M1-Karatsuba-overall/radix4acc.v
`timescale 10ms / 1ms

module radix4acc (p,x,y);           //8 bit multiplier to give 32 bit product

parameter N = 8;   //size of muliplicant and multiplier
parameter K = N/2;  //

input   [N-1 : 0]   x,y;
output  [N+N-1:0]   p;

reg [2:0]   bits    [K-1:0];
//reg [2:0]   MBE     [K-1:0];


reg [N:0]       PP      [K-1:0];
reg [N+N-1:0]   ACC     [K-1:0];
reg [N+N-1:0]   ANS;

integer i , j;

wire [N:0] xbar;
assign xbar = {~x[N-1], ~x} + 1'b1;         //2's complement retaining the sign bit

always@(*)

begin
    bits[0] = {y[1],y[0],1'b0};             //setting last bit -1 as 0

    for(i=1; i<K; i=i+1)
        bits[i] = {y[2*i+1], y[2*i], y[2*i-1]};


    //MBE encoding in terms of {neg, two, zero}

    for(i=0; i<K; i=i+1)
        begin
            case(bits[i])

            //3'b000, 3'b111: MBE[i] = 3'b001;

            3'b001, 3'b010: 
            begin
                //MBE[i] = 3'b000; 
                PP[i] = {x[N-1], x};
            end

            
            3'b101, 3'b110: 
            begin 
                //MBE[i] = 3'b100;
                PP[i] = xbar;
            end

            3'b011: 
            begin
                //MBE[i] = 3'b010;
                PP[i] = {x,1'b0};
            end 

            3'b100: 
            begin 
                //MBE[i] = 3'b110;
                PP[i] = {xbar[N-1:0],1'b0};
            end


            default: 
            begin
                //MBE[i] = 3'b001;
                PP[i]  = 0;
            end

            endcase

            ACC[i] = $signed(PP[i]);        //sign extension

            for(j=0; j<i; j=j+1)
                ACC[i] = {ACC[i],2'b00};        //shifting

        
        end

    ANS = ACC[0];

    for(i=1; i<K; i=i+1)
        ANS = ANS+ACC[i];
end


assign p = ANS;

endmodule

ABM-M1-Karatsuba-overall-16/karatsuba16.v
`timescale 10ms/1ms
`include "radix4acc.v"
`include "radix4approx.v"
`include "radix4approx10bit.v"
`include "adder8.v"

module karatsuba16(P,A,B);


parameter N = 16;   //size of muliplicant and multiplier
parameter K = N/2;  //

input   [N-1 : 0]   A,B;
output  [N+N-1:0]   P;

wire [K-1:0] AH, AL, BH, BL;

wire reg    [N-1:0]     M1, M2;
wire reg    [K:0]       S1, S2;
wire reg    [9:0]       c,d;
wire reg    [19:0]      M3;

reg [19:0] M4, M5, M6;

reg     [19:0]   A1, A2, A3;


reg [N+N-1:0]   ACC     [2:0];
reg [N+N-1:0] ANS;
integer i;


assign AH = A[N-1:K];
assign AL = A[K-1:0];

assign BH = B[N-1:K];
assign BL = B[K-1:0];



radix4acc ACC1(.p(M1), .x(AH), .y(BH));
radix4approx APP1(.p(M2), .x(AL), .y(BL));


adder8 ADD1(.s(S1), .a(AH), .b(AL));
adder8 ADD2(.s(S2), .a(BH), .b(BL));

assign c = $signed(S1);
assign d = $signed(S2);

radix4approx10bit APP2(.p(M3), .x(c), .y(d));


always@(*)
begin
    
    M4 = $signed(M1);
    M5 = $signed(M2);
    
    M6 = M3 - M4 - M5;

    ACC[0] = $signed(M6);
    ACC[0] = {ACC[0], {8{1'b0}}};

    ACC[1] = $signed(M2);
    
    ACC[2] = $signed(M1);
    ACC[2] = {ACC[2], {16{1'b0}}};

    ANS = ACC[0];
    for(i=1; i<3; i=i+1)
        ANS = ANS+ACC[i];
end

assign P = ANS;

endmodule

ABM-M1-Karatsuba-bitwise-16/karatsuba16_tb.v
`timescale 10ms / 1ms
`include "karatsuba16.v"

module karatsuba16_tb();

reg unsigned [15:0] A,B;
wire unsigned [31:0] P;
integer i, out, seed=7;


karatsuba16 uut(P,A,B);


initial begin
    $dumpfile("karatsuba16.vcd");
    $dumpvars(0, karatsuba16_tb);
    out = $fopen("karatsuba_output.csv");
    
    for(i=0; i<500; i=i+1)
    begin
        A = $urandom(seed) %65535;
        B = $urandom(seed) %65535;
        #1;
        $fwrite(out, "%d, %d, %d\n", A,B,P);
        #4;
    end
    
    $finish;
end




endmodule

ABM-M1-Karatsuba-overall/karatsuba16.vcd
$date
	Tue Jun 22 19:09:11 2021
$end
$version
	Icarus Verilog
$end
$timescale
	1ms
$end
$scope module karatsuba16_tb $end
$var wire 32 ! P [31:0] $end
$var reg 16 " A [15:0] $end
$var reg 16 # B [15:0] $end
$var integer 32 $ i [31:0] $end
$var integer 32 % out [31:0] $end
$var integer 32 & seed [31:0] $end
$scope module uut $end
$var wire 16 ' A [15:0] $end
$var wire 16 ( B [15:0] $end
$var wire 32 ) P [31:0] $end
$var wire 10 * d [9:0] $end
$var wire 10 + c [9:0] $end
$var wire 9 , S2 [8:0] $end
$var wire 9 - S1 [8:0] $end
$var wire 20 . M3 [19:0] $end
$var wire 16 / M2 [15:0] $end
$var wire 16 0 M1 [15:0] $end
$var wire 8 1 BL [7:0] $end
$var wire 8 2 BH [7:0] $end
$var wire 8 3 AL [7:0] $end
$var wire 8 4 AH [7:0] $end
$var reg 32 5 ANS [31:0] $end
$var reg 20 6 M4 [19:0] $end
$var reg 20 7 M5 [19:0] $end
$var reg 20 8 M6 [19:0] $end
$var integer 32 9 i [31:0] $end
$scope module ACC1 $end
$var wire 16 : p [15:0] $end
$var wire 8 ; x [7:0] $end
$var wire 8 < y [7:0] $end
$var wire 9 = xbar [8:0] $end
$var reg 16 > ANS [15:0] $end
$var integer 32 ? i [31:0] $end
$var integer 32 @ j [31:0] $end
$upscope $end
$scope module ADD1 $end
$var wire 8 A a [7:0] $end
$var wire 8 B b [7:0] $end
$var wire 9 C s [8:0] $end
$upscope $end
$scope module ADD2 $end
$var wire 8 D a [7:0] $end
$var wire 8 E b [7:0] $end
$var wire 9 F s [8:0] $end
$upscope $end
$scope module APP1 $end
$var wire 16 G p [15:0] $end
$var wire 8 H x [7:0] $end
$var wire 8 I y [7:0] $end
$var wire 9 J xbar [8:0] $end
$var reg 16 K ANS [15:0] $end
$var integer 32 L i [31:0] $end
$var integer 32 M j [31:0] $end
$upscope $end
$scope module APP2 $end
$var wire 20 N p [19:0] $end
$var wire 10 O x [9:0] $end
$var wire 10 P y [9:0] $end
$var wire 11 Q xbar [10:0] $end
$var reg 20 R ANS [19:0] $end
$var integer 32 S i [31:0] $end
$var integer 32 T j [31:0] $end
$upscope $end
$upscope $end
$upscope $end
$enddefinitions $end
#0
$dumpvars
b100 T
b101 S
b1001000000000101 R
b11100101011 Q
b10110001 P
b11010101 O
b1001000000000101 N
b11 M
b100 L
b1111110000000100 K
b111110001 J
b10000000 I
b1111 H
b1111110000000100 G
b10110001 F
b10000000 E
b110001 D
b11010101 C
b1111 B
b11000110 A
b11 @
b100 ?
b1111010011100110 >
b111010 =
b110001 <
b11000110 ;
b1111010011100110 :
b11 9
b1001111100011011 8
b11111111110000000100 7
b11111111010011100110 6
b11110101100001010001011100000100 5
b11000110 4
b1111 3
b110001 2
b10000000 1
b1111010011100110 0
b1111110000000100 /
b1001000000000101 .
b11010101 -
b10110001 ,
b11010101 +
b10110001 *
b11110101100001010001011100000100 )
b11000110000000 (
b1100011000001111 '
b10001101101110110101110010011011 &
b10 %
b0 $
b11000110000000 #
b1100011000001111 "
b11110101100001010001011100000100 !
$end
#50
b11 9
b11100110111011111001010000000111 !
b11100110111011111001010000000111 )
b11100110111011111001010000000111 5
b111101110001010 8
b101000000111 7
b11111110011001110100 6
b111100 =
b1110011001110100 0
b1110011001110100 :
b1110011001110100 >
b11 @
b100 ?
b1110001 Q
b110110000000101 .
b110110000000101 N
b110110000000101 R
b100 T
b101 S
b110101 J
b101000000111 /
b101000000111 G
b101000000111 K
b11 M
b100 L
b1101101 2
b1101101 <
b1101101 D
b1100000110 *
b1100000110 P
b100000110 ,
b100000110 F
b10011001 1
b10011001 E
b10011001 I
b11000100 4
b11000100 ;
b11000100 A
b1110001111 +
b1110001111 O
b110001111 -
b110001111 C
b11001011 3
b11001011 B
b11001011 H
b110110110011001 #
b110110110011001 (
b1100010011001011 "
b1100010011001011 '
b11011000111110100101010010100001 &
b1 $
#100
b11 9
b10010101000011010010000000111 !
b10010101000011010010000000111 )
b10010101000011010010000000111 5
b11110100101110100111 8
b11111111110100000111 7
b1001101010110 6
b111001001 =
b1001101010110 0
b1001101010110 :
b1001101010110 >
b11 @
b100 ?
b11011000 Q
b11110101110000000100 .
b11110101110000000100 N
b11110101110000000100 R
b100 T
b101 S
b1111 J
b1111110100000111 /
b1111110100000111 G
b1111110100000111 K
b11 M
b100 L
b1011010 2
b1011010 <
b1011010 D
b11000001 *
b11000001 P
b11000001 ,
b11000001 F
b1100111 1
b1100111 E
b1100111 I
b110111 4
b110111 ;
b110111 A
b1100101000 +
b1100101000 O
b100101000 -
b100101000 C
b11110001 3
b11110001 B
b11110001 H
b101101001100111 #
b101101001100111 (
b11011111110001 "
b11011111110001 '
b11010110011100101101000110010111 &
b10 $
#150
b11 9
b11110010010111111000101100000110 !
b11110010010111111000101100000110 )
b11110010010111111000101100000110 5
b11111111010010010110 8
b11111111010100000110 7
b11111111001001101011 6
b111101 =
b1111001001101011 0
b1111001001101011 :
b1111001001101011 >
b11 @
b100 ?
b1101111 Q
b11111101110000000111 .
b11111101110000000111 N
b11111101110000000111 R
b100 T
b101 S
b110010 J
b1111010100000110 /
b1111010100000110 G
b1111010100000110 K
b11 M
b100 L
b111001 2
b111001 <
b111001 D
b1011110 *
b1011110 P
b1011110 ,
b1011110 F
b100101 1
b100101 E
b100101 I
b11000011 4
b11000011 ;
b11000011 A
b1110010001 +
b1110010001 O
b110010001 -
b110010001 C
b11001110 3
b11001110 B
b11001110 H
b11100100100101 #
b11100100100101 (
b1100001111001110 "
b1100001111001110 '
b11010100111010000011100011111101 &
b11 $
#200
b11 9
b11111101100011110101101100000100 !
b11111101100011110101101100000100 )
b11111101100011110101101100000100 5
b11111110011101011000 8
b1100000100 7
b11111111110110101000 6
b111111000 =
b1111110110101000 0
b1111110110101000 :
b1111110110101000 >
b11 @
b100 ?
b11111101000 Q
b11111110100000000100 .
b11111110100000000100 N
b11111110100000000100 R
b100 T
b101 S
b111110000 J
b1100000100 /
b1100000100 G
b1100000100 K
b11 M
b100 L
b10110101 2
b10110101 <
b10110101 D
b1100011000 *
b1100011000 P
b100011000 ,
b100011000 F
b1100011 1
b1100011 E
b1100011 I
b1000 4
b1000 ;
b1000 A
b11000 +
b11000 O
b11000 -
b11000 C
b10000 3
b10000 B
b10000 H
b1011010101100011 #
b1011010101100011 (
b100000010000 "
b100000010000 '
b1100110011011101100110001010011 &
b100 $
#250
b11 9
b11011110111000011110100100000100 !
b11011110111000011110100100000100 )
b11011110111000011110100100000100 5
b1011001111010011 8
b1011000000100 7
b11111101111000101110 6
b1110101 =
b1101111000101110 0
b1101111000101110 :
b1101111000101110 >
b11 @
b100 ?
b11100000001 Q
b1010100000000101 .
b1010100000000101 N
b1010100000000101 R
b100 T
b101 S
b110001100 J
b1011000000100 /
b1011000000100 G
b1011000000100 K
b11 M
b100 L
b1001010 2
b1001010 <
b1001010 D
b10101011 *
b10101011 P
b10101011 ,
b10101011 F
b1100001 1
b1100001 E
b1100001 I
b10001011 4
b10001011 ;
b10001011 A
b11111111 +
b11111111 O
b11111111 -
b11111111 C
b1110100 3
b1110100 B
b1110100 H
b100101001100001 #
b100101001100001 (
b1000101101110100 "
b1000101101110100 '
b11001010011101100000100100011001 &
b101 $
#300
b11 9
b11100100111110001000101000000110 !
b11100100111110001000101000000110 )
b11100100111110001000101000000110 5
b11110111100010000000 8
b101000000110 7
b11111110010110000000 6
b10000000 =
b1110010110000000 0
b1110010110000000 :
b1110010110000000 >
b11 @
b100 ?
b10111110 Q
b11110110100000000110 .
b11110110100000000110 N
b11110110100000000110 R
b100 T
b101 S
b111110 J
b101000000110 /
b101000000110 G
b101000000110 K
b11 M
b100 L
b110101 2
b110101 <
b110101 D
b11001010 *
b11001010 P
b11001010 ,
b11001010 F
b10010101 1
b10010101 E
b10010101 I
b10000000 4
b10000000 ;
b10000000 A
b1101000010 +
b1101000010 O
b101000010 -
b101000010 C
b11000010 3
b11000010 B
b11000010 H
b11010110010101 #
b11010110010101 (
b1000000011000010 "
b1000000011000010 '
b10110001101100100000100011001111 &
b110 $
#350
b11 9
b11001011101111101001100000100 !
b11001011101111101001100000100 )
b11001011101111101001100000100 5
b11010110111110 8
b1010100000100 7
b1100101000010 6
b110101 =
b1100101000010 0
b1100101000010 :
b1100101000010 >
b11 @
b100 ?
b10001100 Q
b110010000000100 .
b110010000000100 N
b110010000000100 R
b100 T
b101 S
b1010111 J
b1010100000100 /
b1010100000100 G
b1010100000100 K
b11 M
b100 L
b10000110 2
b10000110 <
b10000110 D
b1101000110 *
b1101000110 P
b101000110 ,
b101000110 F
b11000000 1
b11000000 E
b11000000 I
b11001011 4
b11001011 ;
b11001011 A
b1101110100 +
b1101110100 O
b101110100 -
b101110100 C
b10101001 3
b10101001 B
b10101001 H
b1000011011000000 #
b1000011011000000 (
b1100101110101001 "
b1100101110101001 '
b110000101110111110000011110101 &
b111 $
#400
b11 9
b11110010111001010000011100000110 !
b11110010111001010000011100000110 )
b11110010111001010000011100000110 5
b11111111000000001010 8
b11111111110100000110 7
b11111111001011110101 6
b111111 =
b1111001011110101 0
b1111001011110101 :
b1111001011110101 >
b11 @
b100 ?
b1100001 Q
b11111110000000000101 .
b11111110000000000101 N
b11111110000000000101 R
b100 T
b101 S
b100010 J
b1111110100000110 /
b1111110100000110 G
b1111110100000110 K
b11 M
b100 L
b110101 2
b110101 <
b110101 D
b1001011 *
b1001011 P
b1001011 ,
b1001011 F
b10110 1
b10110 E
b10110 I
b11000001 4
b11000001 ;
b11000001 A
b1110011111 +
b1110011111 O
b110011111 -
b110011111 C
b11011110 3
b11011110 B
b11011110 H
b11010100010110 #
b11010100010110 (
b1100000111011110 "
b1100000111011110 '
b10001000000000010000001100001011 &
b1000 $
#450
b11 9
b11011101101011101011011000000111 !
b11011101101011101011011000000111 )
b11011101101011101011011000000111 5
b110011010110110 8
b111 7
b11111101110101001000 6
b110101000 =
b1101110101001000 0
b1101110101001000 :
b1101110101001000 >
b11 @
b100 ?
b11110011011 Q
b100010000000101 .
b100010000000101 N
b100010000000101 R
b100 T
b101 S
b111110011 J
b111 /
b111 G
b111 K
b11 M
b100 L
b10011011 2
b10011011 <
b10011011 D
b10110101 *
b10110101 P
b10110101 ,
b10110101 F
b11010 1
b11010 E
b11010 I
b1011000 4
b1011000 ;
b1011000 A
b1100101 +
b1100101 O
b1100101 -
b1100101 C
b1101 3
b1101 B
b1101 H
b1001101100011010 #
b1001101100011010 (
b101100000001101 "
b101100000001101 '
b1111111010110011001110010010001 &
b1001 $
#500
b1010 $
