Radix-32-approx-ABM-M1/radix4approx.v
`timescale 10ms / 1ms

module radix4approx(p,x,y);         

parameter N = 32;   //size of muliplicant and multiplier
parameter K = N/2;  //

input   [N-1 : 0]   x,y;
output  [N+N-1:0]   p;

reg [2:0]   bits    [K:0];
reg   neg     [K:0];
reg   two     [K:0];
reg   zero     [K:0];

wire [N+1:0] x_new;
reg [N+1:0]       PP      [K:0]; //riyaj 
reg [N+N-1:0]   ACC     [K:0];
reg [N+N-1:0]   ANS;
reg mux;

integer i , j, t;
integer  m = 48;        //number of bits to approximate

assign x_new = {2'b0,x};

always@(*)

begin
    bits[0] = {y[1],y[0],1'b0};             //setting last bit -1 as 0

    for(i=1; i<K+1; i=i+1) begin
            if(i == K)
                bits[i] = {2'b0,y[2*i-1]};
            else
                bits[i] = {y[2*i+1], y[2*i], y[2*i-1]};
            //$display("%b", bits[i]);
            
        end


    for(i=0; i<K+1; i=i+1)
        begin                               //approximated 2A as A introduced error
            case(bits[i])

            
            3'b001, 3'b010:         
            begin
                neg[i] = 1'b0;
                two[i] = 1'b0;
                zero[i] = 1'b0;
            end

            3'b011:
            begin
                neg[i] = 1'b0;
                two[i] = 1'b1;
                zero[i] = 1'b0;
            end

            3'b101, 3'b110:         
            begin 
               neg[i] = 1'b1;
                two[i] = 1'b0;
                zero[i] = 1'b0;
            end

            3'b100:
            begin
                neg[i] = 1'b1;
                two[i] = 1'b1;
                zero[i] = 1'b0;
            end
         
            default: 
            begin
                neg[i] = 1'b0;
                two[i] = 1'b0;
                zero[i] = 1'b1;
            end

            endcase

            PP[i] = 0;
            PP[i][N+1] = neg[i];           //sign conservation

            for(t=0; t<N+1; t=t+1) begin
                if(t>=m) 
                begin
                    mux = (x_new[t] & ~two[i]) | (x_new[t-1] & two[i]);             
                    PP[i][t] = ~zero[i] & (neg[i] ^ mux);
                end

                else 
                begin
                    PP[i][t] = (~x_new[t] & neg[i]) | (x_new[t] & ~neg[i] & ~zero[i]);
                end
            end

            PP[i][0] = PP[i][0] | neg[i];

            ACC[i] = $signed(PP[i]);        //sign extension
            
            for(j=0; j<i; j=j+1)
                ACC[i] = {ACC[i],2'b00};        //shifting

        
        end

    ANS = ACC[0];

    for(i=1; i<K+1; i=i+1)
        ANS = ANS+ACC[i];
        
end


assign p = ANS;

endmodule

ABM-M1-Karatsuba-bitwise-32- double approx/radix4approx_tb.v
`timescale 10ms / 1ms
`include "radix4approx.v"

module radix4approx_tb();


reg  unsigned [15 : 0]   x,y;

wire unsigned [31:0]   p;

integer i, out, seed=7;

radix4approx uut(p,x,y);

initial begin
    $dumpfile("radix4approx.vcd");
    $dumpvars(0, radix4approx_tb);
    out = $fopen("radix4-approx-mult-result.csv");
    

    for(i=0; i<50; i=i+1)
        begin
        x = $urandom(seed) %65535;
        y = $urandom(seed) %65535;
        #1;
        $fwrite(out, "%d, %d, %d\n", x,y,p);
        #4;
    end
    $finish;
end
endmodule

ABM-M2-Karatsuba-bitwise-32-double approx/radix4approx.vcd
$date
	Fri Jul  9 12:56:03 2021
$end
$version
	Icarus Verilog
$end
$timescale
	1ms
$end
$scope module radix4approx_tb $end
$var wire 32 ! p [31:0] $end
$var reg 16 " x [15:0] $end
$var reg 16 # y [15:0] $end
$var integer 32 $ i [31:0] $end
$var integer 32 % out [31:0] $end
$var integer 32 & seed [31:0] $end
$scope module uut $end
$var wire 32 ' p [31:0] $end
$var wire 16 ( x [15:0] $end
$var wire 16 ) y [15:0] $end
$var wire 18 * x_new [17:0] $end
$var reg 32 + ANS [31:0] $end
$var reg 1 , mux $end
$var integer 32 - i [31:0] $end
$var integer 32 . j [31:0] $end
$var integer 32 / m [31:0] $end
$var integer 32 0 t [31:0] $end
$upscope $end
$upscope $end
$enddefinitions $end
#0
$dumpvars
b10001 0
b1100 /
b1000 .
b1001 -
0,
b110110111111101000011101011 +
b110001000000111 *
b1000111111001 )
b110001000000111 (
b110110111111101000011101011 '
b11000110011011000100100011101101 &
b10 %
b0 $
b1000111111001 #
b110001000000111 "
b110110111111101000011101011 !
$end
#50
b10100010101110111101011100001 !
b10100010101110111101011100001 '
b10100010101110111101011100001 +
b1000 .
0,
b10001 0
b1001 -
b1010100111001010 #
b1010100111001010 )
b1111010110010 *
b1111010110010 "
b1111010110010 (
b10101110011011011111100111000011 &
b1 $
#100
b11110100001001000000010000110 !
b11110100001001000000010000110 '
b11110100001001000000010000110 +
b1000 .
0,
b10001 0
b1001 -
b1100001101100101 #
b1100001101100101 )
b10011111111110 *
b10011111111110 "
b10011111111110 (
b11001111110001011111000000001001 &
b10 $
#150
b1000110100110000100001010000 !
b1000110100110000100001010000 '
b1000110100110000100001010000 +
0,
b1000 .
b10001 0
b1001 -
b1010100001110100 #
b1010100001110100 )
b110101111000 *
b110101111000 "
b110101111000 (
b10011100001010010100111111 &
b11 $
#200
b1111011001000101000110011001010 !
b1111011001000101000110011001010 '
b1111011001000101000110011001010 +
b1000 .
0,
b10001 0
b1001 -
b1001000111100001 #
b1001000111100001 )
b1101101001111010 *
b1101101001111010 "
b1101101001111010 (
b1110111101000111011100101 &
b100 $
#250
b111010101100001011001111111001 !
b111010101100001011001111111001 '
b111010101100001011001111111001 +
b1000 .
0,
b10001 0
b1001 -
b1000110101010101 #
b1000110101010101 )
b110110000010101 *
b110110000010101 "
b110110000010101 (
b1101001110110111111001111011 &
b101 $
#300
b1001110101001111001001101111011 !
b1001110101001111001001101111011 '
b1001110101001111001001101111011 +
b1000 .
0,
b10001 0
b1001 -
b111110000001111 #
b111110000001111 )
b1010010011000100 *
b1010010011000100 "
b1010010011000100 (
b1111001000111010000000110000001 &
b110 $
#350
b1000100111010010010011001000 !
b1000100111010010010011001000 '
b1000100111010010010011001000 +
b1000 .
0,
b10001 0
b1001 -
b10011101111001 #
b10011101111001 )
b11100110111100 *
b11100110111100 "
b11100110111100 (
b1100100101011111100000101110111 &
b111 $
#400
b101001100000010001110000000100 !
b101001100000010001110000000100 '
b101001100000010001110000000100 +
b1000 .
0,
b10001 0
b1001 -
b1000110110001100 #
b1000110110001100 )
b100011110100110 *
b100011110100110 "
b100011110100110 (
b10101000001110111110001111011101 &
b1000 $
#450
b101011110000110111111101100001 !
b101011110000110111111101100001 '
b101011110000110111111101100001 +
b1000 .
0,
b10001 0
b1001 -
b111100010110001 #
b111100010110001 )
b101100110110001 *
b101100110110001 "
b101100110110001 (
b1100100110000110101000110011 &
b1001 $
#500
b11010000000000110110110010010101 !
b11010000000000110110110010010101 '
b11010000000000110110110010010101 +
b1000 .
0,
b10001 0
b1001 -
b1110110110011010 #
b1110110110011010 )
b1110000000011111 *
b1110000000011111 "
b1110000000011111 (
b1011010111001011001000111111001 &
b1010 $
#550
b101011100111100010111011 !
b101011100111100010111011 '
b101011100111100010111011 +
b1000 .
0,
b10001 0
b1001 -
b100111010 #
b100111010 )
b1000111001000000 *
b1000111001000000 "
b1000111001000000 (
b11001001101001100011010010101111 &
b1011 $
#600
b10000001110100101000101010000 !
b10000001110100101000101010000 '
b10000001110100101000101010000 +
b1000 .
0,
b10001 0
b1001 -
b101000001100000 #
b101000001100000 )
b11001110110010 *
b11001110110010 "
b11001110110010 (
b101000000100000010011111010101 &
b1100 $
#650
b1011101000011001001110010010000 !
b1011101000011001001110010010000 '
b1011101000011001001110010010000 +
b1000 .
0,
b10001 0
b1001 -
b111100111100000 #
b111100111100000 )
b1100011011100111 *
b1100011011100111 "
b1100011011100111 (
b11011010001010111001110011101011 &
b1101 $
#700
b110110011111000000111011011 !
b110110011111000000111011011 '
b110110011111000000111011011 +
b1000 .
0,
b10001 0
b1001 -
b11001101111010 #
b11001101111010 )
b10000111100001 *
b10000111100001 "
b10000111100001 (
b10110000000110011000000101110001 &
b1110 $
#750
b100111101101010011000001100001 !
b100111101101010011000001100001 '
b100111101101010011000001100001 +
b1000 .
0,
b10001 0
b1001 -
b1011001000111010 #
b1011001000111010 )
b11100100010011 *
b11100100010011 "
b11100100010011 (
b11010000100110001101111011100111 &
b1111 $
#800
b1001010100011100111000 !
b1001010100011100111000 '
b1001010100011100111000 +
b1000 .
0,
b10001 0
b1001 -
b101001 #
b101001 )
b1110011111111100 *
b1110011111111100 "
b1110011111111100 (
b11000010101000110011101011001101 &
b10000 $
#850
b11010111011011010110001111 !
b11010111011011010110001111 '
b11010111011011010110001111 +
b1000 .
0,
b10001 0
b1001 -
b1111001111 #
b1111001111 )
b1110001001000001 *
b1110001001000001 "
b1110001001000001 (
b1011101101111111011010100011 &
b10001 $
#900
b1110110010011001111110101100101 !
b1110110010011001111110101100101 '
b1110110010011001111110101100101 +
b1000 .
0,
b10001 0
b1001 -
b1111100010111110 #
b1111100010111110 )
b111100111011010 *
b111100111011010 "
b111100111011010 (
b1001000001011101010111111101001 &
b10010 $
#950
b1100001010101001101111001100111 !
b1100001010101001101111001100111 '
b1100001010101001101111001100111 +
b1000 .
0,
b10001 0
b1001 -
b1010101010111001 #
b1010101010111001 )
b1001000111110011 *
b1001000111110011 "
b1001000111110011 (
b1000101010001010000000011111 &
b10011 $
#1000
b1111110010110011110100000011001 !
b1111110010110011110100000011001 '
b1111110010110011110100000011001 +
b1000 .
0,
b10001 0
b1001 -
b1000101010001111 #
b1000101010001111 )
b1110101110000110 *
b1110101110000110 "
b1110101110000110 (
b10001011011110001111110011000101 &
b10100 $
#1050
b111000000101101111010011010000 !
b111000000101101111010011010000 '
b111000000101101111010011010000 +
b1000 .
0,
b10001 0
b1001 -
b1110001110110001 #
b1110001110110001 )
b11111100100000 *
b11111100100000 "
b11111100100000 (
b10001010100111000101011101011011 &
b10101 $
#1100
b110100011000001100101110110100 !
b110100011000001100101110110100 '
b110100011000001100101110110100 +
b1000 .
0,
b10001 0
b1001 -
b11110100010100 #
b11110100010100 )
b1101101110001001 *
b1101101110001001 "
b1101101110001001 (
b111110100101101111110101100001 &
b10110 $
#1150
b1101011000111000110100101101101 !
b1101011000111000110100101101101 '
b1101011000111000110100101101101 +
b1000 .
0,
b10001 0
b1001 -
b1010111011111010 #
b1010111011111010 )
b1001110010110110 *
b1001110010110110 "
b1001110010110110 (
b1010100010100100101100001010111 &
b10111 $
#1200
b100100000000101100111111000000 !
b100100000000101100111111000000 '
b100100000000101100111111000000 +
b1000 .
0,
b10001 0
b1001 -
b1010011010000000 #
b1010011010000000 )
b11011011011101 *
b11011011011101 "
b11011011011101 (
b1010111110100010100110110111101 &
b11000 $
#1250
b1110101101111100011011010111 !
b1110101101111100011011010111 '
b1110101101111100011011010111 +
b1000 .
0,
b10001 0
b1001 -
b1001000100110010 #
b1001000100110010 )
b1101111001101 *
b1101111001101 "
b1101111001101 (
b11101111010100111001111100010011 &
b11001 $
#1300
b11001111000010001111010001010100 !
b11001111000010001111010001010100 '
b11001111000010001111010001010100 +
b1000 .
0,
b10001 0
b1001 -
b1110110110000100 #
b1110110110000100 )
b1101111100100101 *
b1101111100100101 "
b1101111100100101 (
b10100010010000000100100111011001 &
b11010 $
#1350
b1101010110101000101111010100100 !
b1101010110101000101111010100100 '
b1101010110101000101111010100100 +
b1000 .
0,
b10001 0
b1001 -
b1010011001101000 #
b1010011001101000 )
b1010010000001010 *
b1010010000001010 "
b1010010000001010 (
b10111100111011101110011110001111 &
b11011 $
#1400
b100111011100010100011111000 !
b100111011100010100011111000 '
b100111011100010100011111000 +
b1000 .
b10001 0
b1001 -
b1010110101100100 #
b1010110101100100 )
b11101001010 *
b11101001010 "
b11101001010 (
b10011110001010000000110110110101 &
b11100 $
#1450
b11100101110111111001100010000110 !
b11100101110111111001100010000110 '
b11100101110111111001100010000110 +
b1000 .
0,
b10001 0
b1001 -
b1111101110001101 #
b1111101110001101 )
b1110100111110010 *
b1110100111110010 "
b1110100111110010 (
b1001100111101001010110111001011 &
b11101 $
#1500
b11010101101000101000110001101 !
b11010101101000101000110001101 '
b11010101101000101000110001101 +
b1000 .
0,
b10001 0
b1001 -
b1000001100101110 #
b1000001100101110 )
b11100000000011 *
b11100000000011 "
b11100000000011 (
b1101000101000111010101010001 &
b11110 $
#1550
b1001001100000100101001000101 !
b1001001100000100101001000101 '
b1001001100000100101001000101 +
0,
b1000 .
b10001 0
b1001 -
b1110010110011111 #
b1110010110011111 )
b101010011010 *
b101010011010 "
b101010011010 (
b10110110001100110010110111000111 &
b11111 $
#1600
b101100100011111111010010000000 !
b101100100011111111010010000000 '
b101100100011111111010010000000 +
b1000 .
0,
b10001 0
b1001 -
b110010001000000 #
b110010001000000 )
b111001101110010 *
b111001101110010 "
b111001101110010 (
b1000101101101010001110010101101 &
b100000 $
#1650
b10111000100000011010111111011001 !
b10111000100000011010111111011001 '
b10111000100000011010111111011001 +
b1000 .
0,
b10001 0
b1001 -
b1101000110001011 #
b1101000110001011 )
b1110000101101011 *
b1110000101101011 "
b1110000101101011 (
b1101100101100100110001110000011 &
b100001 $
#1700
b1110110101011100110001010011011 !
b1110110101011100110001010011011 '
b1110110101011100110001010011011 +
b1000 .
0,
b10001 0
b1001 -
b1000101111001111 #
b1000101111001111 )
b1101011001100100 *
b1101011001100100 "
b1101011001100100 (
b101011011110010101111111001001 &
b100010 $
#1750
b111011100000101001111000010001 !
b111011100000101001111000010001 '
b111011100000101001111000010001 +
b1000 .
0,
b10001 0
b1001 -
b1101111101010011 #
b1101111101010011 )
b100010010001011 *
b100010010001011 "
b100010010001011 (
b11010001101100000000101011111111 &
b100011 $
#1800
b10000000110010010000011100000101 !
b10000000110010010000011100000101 '
b10000000110010010000011100000101 +
b1000 .
0,
b10001 0
b1001 -
b1100001010110111 #
b1100001010110111 )
b1010100101010010 *
b1010100101010010 "
b1010100101010010 (
b1100101111011000101101010100101 &
b100100 $
#1850
b11010101100111100010110111001 !
b11010101100111100010110111001 '
b11010101100111100010110111001 +
b1000 .
0,
b10001 0
b1001 -
b1110001001110 #
b1110001001110 )
b1111001101110111 *
b1111001101110111 "
b1111001101110111 (
b1111001010110111010000000111011 &
b100101 $
#1900
b10111000011110110011001011100 !
b10111000011110110011001011100 '
b10111000011110110011001011100 +
b1000 .
0,
b10001 0
b1001 -
b1111000111000 #
b1111000111000 )
b1100011010101000 *
b1100011010101000 "
b1100011010101000 (
b110011110100001110100101000001 &
b100110 $
#1950
b111010010101011000011011101 !
b111010010101011000011011101 '
b111010010101011000011011101 +
b1000 .
0,
b10001 0
b1001 -
b100010000010111 #
b100010000010111 )
b1101101101010 *
b1101101101010 "
b1101101101010 (
b11100010010100100101111100110111 &
b100111 $
#2000
b10001000000101110110111111001011 !
b10001000000101110110111111001011 '
b10001000000101110110111111001011 +
b1000 .
0,
b10001 0
b1001 -
b1001111111101001 #
b1001111111101001 )
b1101011110010111 *
b1101011110010111 "
b1101011110010111 (
b11110101111111011010011110011101 &
b101000 $
#2050
b1000100111010100000101110010000 !
b1000100111010100000101110010000 '
b1000100111010100000101110010000 +
b1000 .
0,
b10001 0
b1001 -
b101111100010000 #
b101111100010000 )
b1011100001001001 *
b1011100001001001 "
b1011100001001001 (
b11010110110110100001111110011 &
b101001 $
#2100
b101011010101010000010000011100 !
b101011010101010000010000011100 '
b101011010101010000010000011100 +
b1000 .
0,
b10001 0
b1001 -
b100000010010100 #
b100000010010100 )
b1010101111001011 *
b1010101111001011 "
b1010101111001011 (
b1001101111110001111000110111001 &
b101010 $
#2150
b10011011101101111100101100101011 !
b10011011101101111100101100101011 '
b10011011101101111100101100101011 +
b1000 .
0,
b10001 0
b1001 -
b1001110100000010 #
b1001110100000010 )
b1111111001100100 *
b1111111001100100 "
b1111111001100100 (
b10001111111000110000101001101111 &
b101011 $
#2200
b1000000001010100101110011111111 !
b1000000001010100101110011111111 '
b1000000001010100101110011111111 +
b1000 .
0,
b10001 0
b1001 -
b101000100101101 #
b101000100101101 )
b1100101001011011 *
b1100101001011011 "
b1100101001011011 (
b1101100010101001110001110010101 &
b101100 $
#2250
b100110010000001001100110100111 !
b100110010000001001100110100111 '
b100110010000001001100110100111 +
b1000 .
0,
b10001 0
b1001 -
b11000110111011 #
b11000110111011 )
b1100010100000100 *
b1100010100000100 "
b1100010100000100 (
b1101110000010111010101011 &
b101101 $
#2300
b1000100111001011001100111101010 !
b1000100111001011001100111101010 '
b1000100111001011001100111101010 +
b1000 .
0,
b10001 0
b1001 -
b100011010100001 #
b100011010100001 )
b1111100101011010 *
b1111100101011010 "
b1111100101011010 (
b11101010110010110101100100110001 &
b101110 $
#2350
b101100110110011000111010110100 !
b101100110110011000111010110100 '
b101100110110011000111010110100 +
b1000 .
0,
b10001 0
b1001 -
b100100100111100 #
b100100100111100 )
b1001110011110010 *
b1001110011110010 "
b1001110011110010 (
b1011010100001101110110010100111 &
b101111 $
#2400
b10000011110010100010001101111 !
b10000011110010100010001101111 '
b10000011110010100010001101111 +
b1000 .
0,
b10001 0
b1001 -
b11111010110110 #
b11111010110110 )
b100001101000000 *
b100001101000000 "
b100001101000000 (
b1001110000110011110111010001101 &
b110000 $
#2450
b100101100011100010100110010001 !
b100101100011100010100110010001 '
b100101100011100010100110010001 +
b1000 .
0,
b10001 0
b1001 -
b10011001011011 #
b10011001011011 )
b1111110000000010 *
b1111110000000010 "
b1111110000000010 (
b11100010100101010100000001100011 &
b110001 $
#2500
b110010 $
