ABM-M1-Karatsuba-bitwise/radix4approx10bit.v
`timescale 10ms / 1ms

module radix4approx10bit(p,x,y);         //8 bit multiplier to give 16 bit product

parameter N = 10;   //size of muliplicant and multiplier
parameter K = N/2;  //

input   [N-1 : 0]   x,y;
output  [N+N-1:0]   p;

reg [2:0]   bits    [K:0];
reg   neg     [K:0];
reg   two     [K:0];
reg   zero     [K:0];

wire [N+1:0] x_new;
reg [N+1:0]       PP      [K:0]; //riyaj 
reg [N+N-1:0]   ACC     [K:0];
reg [N+N-1:0]   ANS;
reg mux;

integer i , j, t;
integer  m = 6;        //number of bits to approximate

assign x_new = {2'b0,x};

always@(*)

begin
    bits[0] = {y[1],y[0],1'b0};             //setting last bit -1 as 0

    for(i=1; i<K+1; i=i+1) begin
            if(i == K)
                bits[i] = {2'b0,y[2*i-1]};
            else
                bits[i] = {y[2*i+1], y[2*i], y[2*i-1]};
            //$display("%b", bits[i]);
            
        end


    for(i=0; i<K+1; i=i+1)
        begin                               //approximated 2A as A introduced error
            case(bits[i])

            
            3'b001, 3'b010:         
            begin
                neg[i] = 1'b0;
                two[i] = 1'b0;
                zero[i] = 1'b0;
            end

            3'b011:
            begin
                neg[i] = 1'b0;
                two[i] = 1'b1;
                zero[i] = 1'b0;
            end

            3'b101, 3'b110:         
            begin 
               neg[i] = 1'b1;
                two[i] = 1'b0;
                zero[i] = 1'b0;
            end

            3'b100:
            begin
                neg[i] = 1'b1;
                two[i] = 1'b1;
                zero[i] = 1'b0;
            end
         
            default: 
            begin
                neg[i] = 1'b0;
                two[i] = 1'b0;
                zero[i] = 1'b1;
            end

            endcase

            PP[i] = 0;
            PP[i][N+1] = neg[i];           //sign conservation

            for(t=0; t<N+1; t=t+1) begin
                if(t>=m) 
                begin
                    mux = (x_new[t] & ~two[i]) | (x_new[t-1] & two[i]);             
                    PP[i][t] = ~zero[i] & (neg[i] ^ mux);
                end

                else 
                begin
                    PP[i][t] = (~x_new[t] & neg[i]) | (x_new[t] & ~neg[i] & ~zero[i]);
                end
            end

            PP[i][0] = PP[i][0] | neg[i];

            ACC[i] = $signed(PP[i]);        //sign extension
            
            for(j=0; j<i; j=j+1)
                ACC[i] = {ACC[i],2'b00};        //shifting

        
        end

    ANS = ACC[0];

    for(i=1; i<K+1; i=i+1)
        ANS = ANS+ACC[i];
        
end


assign p = ANS;

endmodule

unsigned/karatsuba/adder8.v
`timescale 10ms / 1ms

module adder8(s,a,b);

input [7:0] a,b;

output [8:0] s;


assign s = a+b;

endmodule

ABM-M1-WT-bitwise/radix4approx.v
`timescale 10ms / 1ms

module radix4approx(p,x,y);         //8 bit multiplier to give 16 bit product

parameter N = 8;   //size of muliplicant and multiplier
parameter K = N/2;  //

input   [N-1 : 0]   x,y;
output  [N+N-1:0]   p;

reg [2:0]   bits    [K:0];
reg   neg     [K:0];
reg   two     [K:0];
reg   zero     [K:0];

wire [N+1:0] x_new;
reg [N+1:0]       PP      [K:0]; //riyaj 
reg [N+N-1:0]   ACC     [K:0];
reg [N+N-1:0]   ANS;
reg mux;

integer i , j, t;
integer  m = 6;        //number of bits to approximate

assign x_new = {2'b0,x};

always@(*)

begin
    bits[0] = {y[1],y[0],1'b0};             //setting last bit -1 as 0

    for(i=1; i<K+1; i=i+1) begin
            if(i == K)
                bits[i] = {2'b0,y[2*i-1]};
            else
                bits[i] = {y[2*i+1], y[2*i], y[2*i-1]};
            //$display("%b", bits[i]);
            
        end


    for(i=0; i<K+1; i=i+1)
        begin                               //approximated 2A as A introduced error
            case(bits[i])

            
            3'b001, 3'b010:         
            begin
                neg[i] = 1'b0;
                two[i] = 1'b0;
                zero[i] = 1'b0;
            end

            3'b011:
            begin
                neg[i] = 1'b0;
                two[i] = 1'b1;
                zero[i] = 1'b0;
            end

            3'b101, 3'b110:         
            begin 
               neg[i] = 1'b1;
                two[i] = 1'b0;
                zero[i] = 1'b0;
            end

            3'b100:
            begin
                neg[i] = 1'b1;
                two[i] = 1'b1;
                zero[i] = 1'b0;
            end
         
            default: 
            begin
                neg[i] = 1'b0;
                two[i] = 1'b0;
                zero[i] = 1'b1;
            end

            endcase

            PP[i] = 0;
            PP[i][N+1] = neg[i];           //sign conservation

            for(t=0; t<N+1; t=t+1) begin
                if(t>=m) 
                begin
                    mux = (x_new[t] & ~two[i]) | (x_new[t-1] & two[i]);             
                    PP[i][t] = ~zero[i] & (neg[i] ^ mux);
                end

                else 
                begin
                    PP[i][t] = (~x_new[t] & neg[i]) | (x_new[t] & ~neg[i] & ~zero[i]);
                end
            end

            PP[i][0] = PP[i][0] | neg[i];

            ACC[i] = $signed(PP[i]);        //sign extension
            
            for(j=0; j<i; j=j+1)
                ACC[i] = {ACC[i],2'b00};        //shifting

        
        end

    ANS = ACC[0];

    for(i=1; i<K+1; i=i+1)
        ANS = ANS+ACC[i];
        
end


assign p = ANS;

endmodule

ABM-M1-Karatsuba-bitwise/radix4acc.v
`timescale 10ms / 1ms

module radix4acc(p,x,y);         //8 bit multiplier to give 16 bit product

parameter N = 8;   //size of muliplicant and multiplier
parameter K = N/2;  //

input [N-1 : 0]   x,y;
output [N+N-1:0]   p;

reg [2:0]   bits    [K:0];
reg   neg     [K:0];
reg   two     [K:0];
reg   zero     [K:0];

wire [N+1:0] x_new;
reg [N+1:0]       PP      [K:0]; //riyaj 
reg [N+N-1:0]   ACC     [K:0];
reg [N+N-1:0]   ANS;
reg mux;

integer i , j, t;

assign x_new = {2'b0,x};

always@(*)

begin
    bits[0] = {y[1],y[0],1'b0};             //setting last bit -1 as 0
    //$display("%b", bits[0]);
    for(i=1; i<K+1; i=i+1) begin
        if(i == K)
            bits[i] = {2'b0,y[2*i-1]};
        else
            bits[i] = {y[2*i+1], y[2*i], y[2*i-1]};
        //$display("%b", bits[i]);
        
    end

    for(i=0; i<K+1; i=i+1)
        begin                                      //accurate cases
            case(bits[i])

            
            3'b001, 3'b010:         
            begin
                neg[i] = 1'b0;
                two[i] = 1'b0;
                zero[i] = 1'b0;
            end

            3'b011:
            begin
                neg[i] = 1'b0;
                two[i] = 1'b1;
                zero[i] = 1'b0;
            end

            3'b101, 3'b110:         
            begin 
               neg[i] = 1'b1;
                two[i] = 1'b0;
                zero[i] = 1'b0;
            end

            3'b100:
            begin
                neg[i] = 1'b1;
                two[i] = 1'b1;
                zero[i] = 1'b0;
            end
         
            default: 
            begin
                neg[i] = 1'b0;
                two[i] = 1'b0;
                zero[i] = 1'b1;
            end

            endcase
            
            //$display("%b %b %b", neg[i], two[i], zero[i]);
            
            PP[i] = 0;
            PP[i][N+1] = neg[i];           //sign conservation

            for(t=0; t<N+1; t=t+1) begin
                if(t==0) 
                    mux = (x_new[t] & ~two[i]) | (1'b0 & two[i]);
                
                else
                    mux = (x_new[t] & ~two[i]) | (x_new[t-1] & two[i]);

                
                PP[i][t] = ~zero[i] & (neg[i] ^ mux);       
            end

            PP[i] = PP[i] + neg[i];             //correction term added
            
            //$display("%b", PP[i]);

            ACC[i] = $signed(PP[i]);        //sign extension
            //$display("%b", ACC[i]);

            for(j=0; j<i; j=j+1)
                ACC[i] = {ACC[i],2'b00};        //shifting

        
        end

    ANS = ACC[0];

    for(i=1; i<K+1; i=i+1)
        ANS = ANS+ACC[i];
        
    
end


assign p = ANS;

endmodule

ABM-M1-Karatsuba-bitwise/karatsuba16.v
`timescale 10ms/1ms
`include "radix4acc.v"
`include "radix4approx.v"
`include "radix4approx10bit.v"
`include "adder8.v"

module karatsuba16(P,A,B);


parameter N = 16;   //size of muliplicant and multiplier
parameter K = N/2;  //

input   [N-1 : 0]   A,B;
output  [N+N-1:0]   P;

wire [K-1:0] AH, AL, BH, BL;

wire reg    [N-1:0]     M1, M2;
wire reg    [K:0]       S1, S2;
wire reg    [9:0]       c,d;
wire reg    [19:0]      M3;

reg [19:0] M4, M5, M6;

reg     [19:0]   A1, A2, A3;


reg [N+N-1:0]   ACC     [2:0];
reg [N+N-1:0] ANS;
integer i;


assign AH = A[N-1:K];
assign AL = A[K-1:0];

assign BH = B[N-1:K];
assign BL = B[K-1:0];



radix4acc ACC1(.p(M1), .x(AH), .y(BH));
radix4approx APP1(.p(M2), .x(AL), .y(BL));


adder8 ADD1(.s(S1), .a(AH), .b(AL));
adder8 ADD2(.s(S2), .a(BH), .b(BL));

assign c = (S1);
assign d = (S2);

radix4approx10bit APP2(.p(M3), .x(c), .y(d));


always@(*)
begin
    
    M4 = $signed(M1);
    M5 = $signed(M2);
    
    M6 = M3 - M4 - M5;

    ACC[0] = $signed(M6);
    ACC[0] = {ACC[0], {8{1'b0}}};

    ACC[1] = $signed(M2);
    
    ACC[2] = $signed(M1);
    ACC[2] = {ACC[2], {16{1'b0}}};

    ANS = ACC[0];
    for(i=1; i<3; i=i+1)
        ANS = ANS+ACC[i];
end

assign P = ANS;

endmodule

ABM-M1-Karatsuba-bitwise-16/karatsuba16_tb.v
`timescale 10ms / 1ms
`include "karatsuba16.v"

module karatsuba16_tb();

reg unsigned [15:0] A,B;
wire unsigned [31:0] P;
integer i, out, seed=7;


karatsuba16 uut(P,A,B);


initial begin
    $dumpfile("karatsuba16.vcd");
    $dumpvars(0, karatsuba16_tb);
    out = $fopen("karatsuba_output.csv");
    
    for(i=0; i<500; i=i+1)
    begin
        A = $urandom(seed) %65535;
        B = $urandom(seed) %65535;
        #1;
        $fwrite(out, "%d, %d, %d\n", A,B,P);
        #4;
    end
    
    $finish;
end




endmodule

ABM-M1-Karatsuba-bitwise/karatsuba16.vcd
$date
	Wed Jun 30 16:37:39 2021
$end
$version
	Icarus Verilog
$end
$timescale
	1ms
$end
$scope module karatsuba16_tb $end
$var wire 32 ! P [31:0] $end
$var reg 16 " A [15:0] $end
$var reg 16 # B [15:0] $end
$var integer 32 $ i [31:0] $end
$var integer 32 % out [31:0] $end
$var integer 32 & seed [31:0] $end
$scope module uut $end
$var wire 16 ' A [15:0] $end
$var wire 16 ( B [15:0] $end
$var wire 32 ) P [31:0] $end
$var wire 10 * d [9:0] $end
$var wire 10 + c [9:0] $end
$var wire 9 , S2 [8:0] $end
$var wire 9 - S1 [8:0] $end
$var wire 20 . M3 [19:0] $end
$var wire 16 / M2 [15:0] $end
$var wire 16 0 M1 [15:0] $end
$var wire 8 1 BL [7:0] $end
$var wire 8 2 BH [7:0] $end
$var wire 8 3 AL [7:0] $end
$var wire 8 4 AH [7:0] $end
$var reg 32 5 ANS [31:0] $end
$var reg 20 6 M4 [19:0] $end
$var reg 20 7 M5 [19:0] $end
$var reg 20 8 M6 [19:0] $end
$var integer 32 9 i [31:0] $end
$scope module ACC1 $end
$var wire 16 : p [15:0] $end
$var wire 8 ; x [7:0] $end
$var wire 8 < y [7:0] $end
$var wire 10 = x_new [9:0] $end
$var reg 16 > ANS [15:0] $end
$var reg 1 ? mux $end
$var integer 32 @ i [31:0] $end
$var integer 32 A j [31:0] $end
$var integer 32 B t [31:0] $end
$upscope $end
$scope module ADD1 $end
$var wire 8 C a [7:0] $end
$var wire 8 D b [7:0] $end
$var wire 9 E s [8:0] $end
$upscope $end
$scope module ADD2 $end
$var wire 8 F a [7:0] $end
$var wire 8 G b [7:0] $end
$var wire 9 H s [8:0] $end
$upscope $end
$scope module APP1 $end
$var wire 16 I p [15:0] $end
$var wire 8 J x [7:0] $end
$var wire 8 K y [7:0] $end
$var wire 10 L x_new [9:0] $end
$var reg 16 M ANS [15:0] $end
$var reg 1 N mux $end
$var integer 32 O i [31:0] $end
$var integer 32 P j [31:0] $end
$var integer 32 Q m [31:0] $end
$var integer 32 R t [31:0] $end
$upscope $end
$scope module APP2 $end
$var wire 20 S p [19:0] $end
$var wire 10 T x [9:0] $end
$var wire 10 U y [9:0] $end
$var wire 12 V x_new [11:0] $end
$var reg 20 W ANS [19:0] $end
$var reg 1 X mux $end
$var integer 32 Y i [31:0] $end
$var integer 32 Z j [31:0] $end
$var integer 32 [ m [31:0] $end
$var integer 32 \ t [31:0] $end
$upscope $end
$upscope $end
$upscope $end
$enddefinitions $end
#0
$dumpvars
b1011 \
b110 [
b101 Z
b110 Y
0X
b10011111100000011 W
b1101001 V
b1100001010 U
b1101001 T
b10011111100000011 S
b1001 R
b110 Q
b100 P
b101 O
0N
b11011101011 M
b111 L
b11111001 K
b111 J
b11011101011 I
b100001010 H
b11111001 G
b10001 F
b1101001 E
b111 D
b1100010 C
b1001 B
b100 A
b101 @
0?
b11010000010 >
b1100010 =
b10001 <
b1100010 ;
b11010000010 :
b11 9
b10011000110010110 8
b11011101011 7
b11010000010 6
b111101100111001110011101011 5
b1100010 4
b111 3
b10001 2
b11111001 1
b11010000010 0
b11011101011 /
b10011111100000011 .
b1101001 -
b100001010 ,
b1101001 +
b1100001010 *
b111101100111001110011101011 )
b1000111111001 (
b110001000000111 '
b11000110011011000100100011101101 &
b10 %
b0 $
b1000111111001 #
b110001000000111 "
b111101100111001110011101011 !
$end
#50
b11 9
b10110111101011111110000100001 !
b10110111101011111110000100001 )
b10110111101011111110000100001 5
b110010100001110000 8
b11111000110000100001 7
b1001111001110 6
b1001111001110 0
b1001111001110 :
b1001111001110 >
b100 A
0?
b1001 B
b101 @
b101100100001011111 .
b101100100001011111 S
b101100100001011111 W
b101 Z
0X
b1011 \
b110 Y
b1000110000100001 /
b1000110000100001 I
b1000110000100001 M
b100 P
0N
b1001 R
b101 O
b10101001 2
b10101001 <
b10101001 F
b1101110011 *
b1101110011 U
b101110011 ,
b101110011 H
b11001010 1
b11001010 G
b11001010 K
b11110 =
b11110 4
b11110 ;
b11110 C
b11010000 V
b11010000 +
b11010000 T
b11010000 -
b11010000 E
b10110010 L
b10110010 3
b10110010 D
b10110010 J
b1010100111001010 #
b1010100111001010 (
b1111010110010 "
b1111010110010 '
b10101110011011011111100111000011 &
b1 $
#100
b11 9
b10111000111111000010110000110 !
b10111000111111000010110000110 )
b10111000111111000010110000110 5
b10010110101000100001 8
b110010010000110 7
b1110110110101 6
b1110110110101 0
b1110110110101 :
b1110110110101 >
b100 A
0?
b1001 B
b101 @
b10011110110001011100 .
b10011110110001011100 S
b10011110110001011100 W
b101 Z
0X
b1011 \
b110 Y
b110010010000110 /
b110010010000110 I
b110010010000110 M
b100 P
0N
b1001 R
b101 O
b11000011 2
b11000011 <
b11000011 F
b1100101000 *
b1100101000 U
b100101000 ,
b100101000 H
b1100101 1
b1100101 G
b1100101 K
b100111 =
b100111 4
b100111 ;
b100111 C
b1100100101 V
b1100100101 +
b1100100101 T
b100100101 -
b100100101 E
b11111110 L
b11111110 3
b11111110 D
b11111110 J
b1100001101100101 #
b1100001101100101 (
b10011111111110 "
b10011111111110 '
b11001111110001011111000000001001 &
b10 $
#150
b11 9
b1001111001001001110001010000 !
b1001111001001001110001010000 )
b1001111001001001110001010000 5
b10101110001100100 8
b11100001010000 7
b100010001000 6
b100010001000 0
b100010001000 :
b100010001000 >
b100 A
0?
b1001 B
b101 @
b11001110100111100 .
b11001110100111100 S
b11001110100111100 W
b101 Z
0X
b1011 \
b110 Y
b11100001010000 /
b11100001010000 I
b11100001010000 M
b100 P
0N
b1001 R
b101 O
b10101000 2
b10101000 <
b10101000 F
b1100011100 *
b1100011100 U
b100011100 ,
b100011100 H
b1110100 1
b1110100 G
b1110100 K
b1101 =
b1101 4
b1101 ;
b1101 C
b10000101 V
b10000101 +
b10000101 T
b10000101 -
b10000101 E
b1111000 L
b1111000 3
b1111000 D
b1111000 J
b1010100001110100 #
b1010100001110100 (
b110101111000 "
b110101111000 '
b10011100001010010100111111 &
b11 $
#200
b11 9
b1110110000001011001000111001010 !
b1110110000001011001000111001010 )
b1110110000001011001000111001010 5
b10101000101100100111 8
b110101011001010 7
b111101101111010 6
b111101101111010 0
b111101101111010 :
b111101101111010 >
b100 A
0?
b1001 B
b101 @
b10110111000101101011 .
b10110111000101101011 S
b10110111000101101011 W
b101 Z
0X
b1011 \
b110 Y
b110101011001010 /
b110101011001010 I
b110101011001010 M
b100 P
0N
b1001 R
b101 O
b10010001 2
b10010001 <
b10010001 F
b1101110010 *
b1101110010 U
b101110010 ,
b101110010 H
b11100001 1
b11100001 G
b11100001 K
b11011010 =
b11011010 4
b11011010 ;
b11011010 C
b1101010100 V
b1101010100 +
b1101010100 T
b101010100 -
b101010100 E
b1111010 L
b1111010 3
b1111010 D
b1111010 J
b1001000111100001 #
b1001000111100001 (
b1101101001111010 "
b1101101001111010 '
b1110111101000111011100101 &
b100 $
#250
b11 9
b111011101010111000010011111001 !
b111011101010111000010011111001 )
b111011101010111000010011111001 5
b10111101111110 8
b11011111001 7
b11101101111100 6
b11101101111100 0
b11101101111100 :
b11101101111100 >
b100 A
0?
b1001 B
b101 @
b111000111110011 .
b111000111110011 S
b111000111110011 W
b101 Z
0X
b1011 \
b110 Y
b11011111001 /
b11011111001 I
b11011111001 M
b100 P
b1001 R
b101 O
b10001101 2
b10001101 <
b10001101 F
b11100010 *
b11100010 U
b11100010 ,
b11100010 H
b1010101 1
b1010101 G
b1010101 K
b1101100 =
b1101100 4
b1101100 ;
b1101100 C
b10000001 V
b10000001 +
b10000001 T
b10000001 -
b10000001 E
b10101 L
b10101 3
b10101 D
b10101 J
b1000110101010101 #
b1000110101010101 (
b110110000010101 "
b110110000010101 '
b1101001110110111111001111011 &
b101 $
#300
b11 9
b1010000111010000101001101111011 !
b1010000111010000101001101111011 )
b1010000111010000101001101111011 5
b10111100001001000 8
b101101111011 7
b100111101110000 6
b100111101110000 0
b100111101110000 :
b100111101110000 >
b100 A
0?
b1001 B
b101 @
b11101001100110011 .
b11101001100110011 S
b11101001100110011 W
b101 Z
0X
b1011 \
b110 Y
b101101111011 /
b101101111011 I
b101101111011 M
b100 P
0N
b1001 R
b101 O
b1111100 2
b1111100 <
b1111100 F
b10001011 *
b10001011 U
b10001011 ,
b10001011 H
b1111 1
b1111 G
b1111 K
b10100100 =
b10100100 4
b10100100 ;
b10100100 C
b1101101000 V
b1101101000 +
b1101101000 T
b101101000 -
b101101000 E
b11000100 L
b11000100 3
b11000100 D
b11000100 J
b111110000001111 #
b111110000001111 (
b1010010011000100 "
b1010010011000100 '
b1111001000111010000000110000001 &
b110 $
#350
b11 9
b1000111001010101001011001000 !
b1000111001010101001011001000 )
b1000111001010101001011001000 5
b11010111111001 8
b101100111001000 7
b100010101111 6
b100010101111 0
b100010101111 :
b100010101111 >
b100 A
0?
b1001 B
b101 @
b1001100001110000 .
b1001100001110000 S
b1001100001110000 W
b101 Z
0X
b1011 \
b110 Y
b101100111001000 /
b101100111001000 I
b101100111001000 M
b100 P
0N
b1001 R
b101 O
b100111 2
b100111 <
b100111 F
b10100000 *
b10100000 U
b10100000 ,
b10100000 H
b1111001 1
b1111001 G
b1111001 K
b111001 =
b111001 4
b111001 ;
b111001 C
b11110101 V
b11110101 +
b11110101 T
b11110101 -
b11110101 E
b10111100 L
b10111100 3
b10111100 D
b10111100 J
b10011101111001 #
b10011101111001 (
b11100110111100 "
b11100110111100 '
b1100100101011111100000101110111 &
b111 $
#400
b11 9
b101001011111110011111000000100 !
b101001011111110011111000000100 )
b101001011111110011111000000100 5
b100110001111101010 8
b101010000000100 7
b10011100011011 6
b10011100011011 0
b10011100011011 :
b10011100011011 >
b100 A
0?
b1001 B
b101 @
b101101111100001001 .
b101101111100001001 S
b101101111100001001 W
b101 Z
0X
b1011 \
b110 Y
b101010000000100 /
b101010000000100 I
b101010000000100 M
b100 P
0N
b1001 R
b101 O
b10001101 2
b10001101 <
b10001101 F
b1100011001 *
b1100011001 U
b100011001 ,
b100011001 H
b10001100 1
b10001100 G
b10001100 K
b1000111 =
b1000111 4
b1000111 ;
b1000111 C
b11101101 V
b11101101 +
b11101101 T
b11101101 -
b11101101 E
b10100110 L
b10100110 3
b10100110 D
b10100110 J
b1000110110001100 #
b1000110110001100 (
b100011110100110 "
b100011110100110 '
b10101000001110111110001111011101 &
b1000 $
#450
b11 9
b100010101011100000111101100001 !
b100010101011100000111101100001 )
b100010101011100000111101100001 5
b10001111010110010101 8
b111101001100001 7
b10100110111000 6
b10100110111000 0
b10100110111000 :
b10100110111000 >
b100 A
0?
b1001 B
b101 @
b10011001100110101110 .
b10011001100110101110 S
b10011001100110101110 W
b101 Z
0X
b1011 \
b110 Y
b111101001100001 /
b111101001100001 I
b111101001100001 M
b100 P
0N
b1001 R
b101 O
b1111000 2
b1111000 <
b1111000 F
b1100101001 *
b1100101001 U
b100101001 ,
b100101001 H
b10110001 1
b10110001 G
b10110001 K
b1011001 =
b1011001 4
b1011001 ;
b1011001 C
b1100001010 V
b1100001010 +
b1100001010 T
b100001010 -
b100001010 E
b10110001 L
b10110001 3
b10110001 D
b10110001 J
b111100010110001 #
b111100010110001 (
b101100110110001 "
b101100110110001 '
b1100100110000110101000110011 &
b1001 $
#500
b11 9
b11010010111110110110000010010101 !
b11010010111110110110000010010101 )
b11010010111110110110000010010101 5
b111001101101001000 8
b1100010010101 7
b11111100111101100000 6
b1100111101100000 0
b1100111101100000 :
b1100111101100000 >
b100 A
0?
b1001 B
b101 @
b111000001100111101 .
b111000001100111101 S
b111000001100111101 W
b101 Z
0X
b1011 \
b110 Y
b1100010010101 /
b1100010010101 I
b1100010010101 M
b100 P
b1001 R
b101 O
b11101101 2
b11101101 <
b11101101 F
b1110000111 *
b1110000111 U
b110000111 ,
b110000111 H
b10011010 1
b10011010 G
b10011010 K
b11100000 =
b11100000 4
b11100000 ;
b11100000 C
b11111111 V
b11111111 +
b11111111 T
b11111111 -
b11111111 E
b11111 L
b11111 3
b11111 D
b11111 J
b1110110110011010 #
b1110110110011010 (
b1110000000011111 "
b1110000000011111 '
b1011010111001011001000111111001 &
b1010 $
#550
b11 9
b101011100111101001111011 !
b101011100111101001111011 )
b101011100111101001111011 5
b10000001101100 8
b111001111011 7
b10001110 6
b10001110 0
b10001110 :
b10001110 >
b100 A
0?
b1001 B
b101 @
b10111101110101 .
b10111101110101 S
b10111101110101 W
b101 Z
0X
b1011 \
b110 Y
b111001111011 /
b111001111011 I
b111001111011 M
b100 P
0N
b1001 R
b101 O
b1 2
b1 <
b1 F
b111011 *
b111011 U
b111011 ,
b111011 H
b111010 1
b111010 G
b111010 K
b10001110 =
b10001110 4
b10001110 ;
b10001110 C
b11001110 V
b11001110 +
b11001110 T
b11001110 -
b11001110 E
b1000000 L
b1000000 3
b1000000 D
b1000000 J
b100111010 #
b100111010 (
b1000111001000000 "
b1000111001000000 '
b11001001101001100011010010101111 &
b1011 $
#600
b11 9
b10000001110000111010101010000 !
b10000001110000111010101010000 )
b10000001110000111010101010000 5
b100100000110000 8
b100010101010000 7
b111111110000 6
b111111110000 0
b111111110000 :
b111111110000 >
b100 A
0?
b1001 B
b101 @
b1001110101110000 .
b1001110101110000 S
b1001110101110000 W
b101 Z
0X
b1011 \
b110 Y
b100010101010000 /
b100010101010000 I
b100010101010000 M
b100 P
0N
b1001 R
b101 O
b1010000 2
b1010000 <
b1010000 F
b10110000 *
b10110000 U
b10110000 ,
b10110000 H
b1100000 1
b1100000 G
b1100000 K
b110011 =
b110011 4
b110011 ;
b110011 C
b11100101 V
b11100101 +
b11100101 T
b11100101 -
b11100101 E
b10110010 L
b10110010 3
b10110010 D
b10110010 J
b101000001100000 #
b101000001100000 (
b11001110110010 "
b11001110110010 '
b101000000100000010011111010101 &
b1100 $
#650
b11 9
b1011001101111101010101110010000 !
b1011001101111101010101110010000 )
b1011001101111101010101110010000 5
b11000010100011100011 8
b11111100100010010000 7
b101110110010110 6
b101110110010110 0
b101110110010110 :
b101110110010110 >
b100 A
0?
b1001 B
b101 @
b11000100111100001001 .
b11000100111100001001 S
b11000100111100001001 W
b101 Z
0X
b1011 \
b110 Y
b1100100010010000 /
b1100100010010000 I
b1100100010010000 M
b100 P
0N
b1001 R
b101 O
b1111001 2
b1111001 <
b1111001 F
b1101011001 *
b1101011001 U
b101011001 ,
b101011001 H
b11100000 1
b11100000 G
b11100000 K
b11000110 =
b11000110 4
b11000110 ;
b11000110 C
b1110101101 V
b1110101101 +
b1110101101 T
b110101101 -
b110101101 E
b11100111 L
b11100111 3
b11100111 D
b11100111 J
b111100111100000 #
b111100111100000 (
b1100011011100111 "
b1100011011100111 '
b11011010001010111001110011101011 &
b1101 $
#700
b11 9
b1000001000100000101011011011 !
b1000001000100000101011011011 )
b1000001000100000101011011011 5
b11000111010011000 8
b111001011011011 7
b11010010011 6
b11010010011 0
b11010010011 :
b11010010011 >
b100 A
0?
b1001 B
b101 @
b100000100000000110 .
b100000100000000110 S
b100000100000000110 W
b101 Z
0X
b1011 \
b110 Y
b111001011011011 /
b111001011011011 I
b111001011011011 M
b100 P
0N
b1001 R
b101 O
b110011 2
b110011 <
b110011 F
b10101101 *
b10101101 U
b10101101 ,
b10101101 H
b1111010 1
b1111010 G
b1111010 K
b100001 =
b100001 4
b100001 ;
b100001 C
b1100000010 V
b1100000010 +
b1100000010 T
b100000010 -
b100000010 E
b11100001 L
b11100001 3
b11100001 D
b11100001 J
b11001101111010 #
b11001101111010 (
b10000111100001 "
b10000111100001 '
b10110000000110011000000101110001 &
b1110 $
#750
b11 9
b100111101110111111110101100001 !
b100111101110111111110101100001 )
b100111101110111111110101100001 5
b1100111111001 8
b10001100001 7
b10011110100010 6
b10011110100010 0
b10011110100010 :
b10011110100010 >
b100 A
0?
b1001 B
b101 @
b100010111111100 .
b100010111111100 S
b100010111111100 W
b101 Z
0X
b1011 \
b110 Y
b10001100001 /
b10001100001 I
b10001100001 M
b100 P
b1001 R
b101 O
b10110010 2
b10110010 <
b10110010 F
b11101100 *
b11101100 U
b11101100 ,
b11101100 H
b111010 1
b111010 G
b111010 K
b111001 =
b111001 4
b111001 ;
b111001 C
b1001100 V
b1001100 +
b1001100 T
b1001100 -
b1001100 E
b10011 L
b10011 3
b10011 D
b10011 J
b1011001000111010 #
b1011001000111010 (
b11100100010011 "
b11100100010011 '
b11010000100110001101111011100111 &
b1111 $
#800
b11 9
b11101101101011100111000 !
b11101101101011100111000 )
b11101101101011100111000 5
b111011010101111 8
b10100000111000 7
b0 6
b0 0
b0 :
b0 >
b100 A
0?
b1001 B
b101 @
b1001111011100111 .
b1001111011100111 S
b1001111011100111 W
b101 Z
0X
b1011 \
b110 Y
b10100000111000 /
b10100000111000 I
b10100000111000 M
b100 P
0N
b1001 R
b101 O
b0 2
b0 <
b0 F
b101001 *
b101001 U
b101001 ,
b101001 H
b101001 1
b101001 G
b101001 K
b11100111 =
b11100111 4
b11100111 ;
b11100111 C
b1111100011 V
b1111100011 +
b1111100011 T
b111100011 -
b111100011 E
b11111100 L
b11111100 3
b11111100 D
b11111100 J
b101001 #
b101001 (
b1110011111111100 "
b1110011111111100 '
b11000010101000110011101011001101 &
b10000 $
#850
b11 9
b101000000011001100010001111 !
b101000000011001100010001111 )
b101000000011001100010001111 5
b100101101101100100 8
b11010010001111 7
b1010100110 6
b1010100110 0
b1010100110 :
b1010100110 >
b100 A
0?
b1001 B
b101 @
b101001001010011001 .
b101001001010011001 S
b101001001010011001 W
b101 Z
0X
b1011 \
b110 Y
b11010010001111 /
b11010010001111 I
b11010010001111 M
b100 P
0N
b1001 R
b101 O
b11 2
b11 <
b11 F
b11010010 *
b11010010 U
b11010010 ,
b11010010 H
b11001111 1
b11001111 G
b11001111 K
b11100010 =
b11100010 4
b11100010 ;
b11100010 C
b1100100011 V
b1100100011 +
b1100100011 T
b100100011 -
b100100011 E
b1000001 L
b1000001 3
b1000001 D
b1000001 J
b1111001111 #
b1111001111 (
b1110001001000001 "
b1110001001000001 '
b1011101101111111011010100011 &
b10001 $
#900
b11 9
b1110001011101101000110110100101 !
b1110001011101101000110110100101 )
b1110001011101101000110110100101 5
b11000011111011101100 8
b11111010000110100101 7
b111010100111000 6
b111010100111000 0
b111010100111000 :
b111010100111000 >
b100 A
0?
b1001 B
b101 @
b11000101010111001001 .
b11000101010111001001 S
b11000101010111001001 W
b101 Z
0X
b1011 \
b110 Y
b1010000110100101 /
b1010000110100101 I
b1010000110100101 M
b100 P
0N
b1001 R
b101 O
b11111000 2
b11111000 <
b11111000 F
b1110110110 *
b1110110110 U
b110110110 ,
b110110110 H
b10111110 1
b10111110 G
b10111110 K
b1111001 =
b1111001 4
b1111001 ;
b1111001 C
b1101010011 V
b1101010011 +
b1101010011 T
b101010011 -
b101010011 E
b11011010 L
b11011010 3
b11011010 D
b11011010 J
b1111100010111110 #
b1111100010111110 (
b111100111011010 "
b111100111011010 '
b1001000001011101010111111101001 &
b10010 $
#950
b11 9
b1011100001000000011100101100111 !
b1011100001000000011100101100111 )
b1011100001000000011100101100111 5
b10111101011010001010 8
b11111010111101100111 7
b110000001001010 6
b110000001001010 0
b110000001001010 :
b110000001001010 >
b100 A
0?
b1001 B
b101 @
b10111110011000111011 .
b10111110011000111011 S
b10111110011000111011 W
b101 Z
0X
b1011 \
b110 Y
b1010111101100111 /
b1010111101100111 I
b1010111101100111 M
b100 P
0N
b1001 R
b101 O
b10101010 2
b10101010 <
b10101010 F
b1101100011 *
b1101100011 U
b101100011 ,
b101100011 H
b10111001 1
b10111001 G
b10111001 K
b10010001 =
b10010001 4
b10010001 ;
b10010001 C
b1110000100 V
b1110000100 +
b1110000100 T
b110000100 -
b110000100 E
b11110011 L
b11110011 3
b11110011 D
b11110011 J
b1010101010111001 #
b1010101010111001 (
b1001000111110011 "
b1001000111110011 '
b1000101010001010000000011111 &
b10011 $
