ABM-M1-Karatsuba-bitwise-32/radix4approx.v
`timescale 10ms / 1ms

module radix4approx(p,x,y);         //8 bit multiplier to give 16 bit product

parameter N = 16;   //size of muliplicant and multiplier
parameter K = N/2;  //

input   [N-1 : 0]   x,y;
output  [N+N-1:0]   p;

reg [2:0]   bits    [K:0];
reg   neg     [K:0];
reg   two     [K:0];
reg   zero     [K:0];

wire [N+1:0] x_new;
reg [N+1:0]       PP      [K:0]; //riyaj 
reg [N+N-1:0]   ACC     [K:0];
reg [N+N-1:0]   ANS;
reg mux;

integer i , j, t;
integer  m = 12;        //number of bits to approximate

assign x_new = {2'b0,x};

always@(*)

begin
    bits[0] = {y[1],y[0],1'b0};             //setting last bit -1 as 0

    for(i=1; i<K+1; i=i+1) begin
            if(i == K)
                bits[i] = {2'b0,y[2*i-1]};
            else
                bits[i] = {y[2*i+1], y[2*i], y[2*i-1]};
            //$display("%b", bits[i]);
            
        end


    for(i=0; i<K+1; i=i+1)
        begin                               //approximated 2A as A introduced error
            case(bits[i])

            
            3'b001, 3'b010:         
            begin
                neg[i] = 1'b0;
                two[i] = 1'b0;
                zero[i] = 1'b0;
            end

            3'b011:
            begin
                neg[i] = 1'b0;
                two[i] = 1'b1;
                zero[i] = 1'b0;
            end

            3'b101, 3'b110:         
            begin 
               neg[i] = 1'b1;
                two[i] = 1'b0;
                zero[i] = 1'b0;
            end

            3'b100:
            begin
                neg[i] = 1'b1;
                two[i] = 1'b1;
                zero[i] = 1'b0;
            end
         
            default: 
            begin
                neg[i] = 1'b0;
                two[i] = 1'b0;
                zero[i] = 1'b1;
            end

            endcase

            PP[i] = 0;
            PP[i][N+1] = neg[i];           //sign conservation

            for(t=0; t<N+1; t=t+1) begin
                if(t>=m) 
                begin
                    mux = (x_new[t] & ~two[i]) | (x_new[t-1] & two[i]);             
                    PP[i][t] = ~zero[i] & (neg[i] ^ mux);
                end

                else 
                begin
                    PP[i][t] = (~x_new[t] & neg[i]) | (x_new[t] & ~neg[i] & ~zero[i]);
                end
            end

            PP[i][0] = PP[i][0] | neg[i];

            ACC[i] = $signed(PP[i]);        //sign extension
            
            for(j=0; j<i; j=j+1)
                ACC[i] = {ACC[i],2'b00};        //shifting

        
        end

    ANS = ACC[0];

    for(i=1; i<K+1; i=i+1)
        ANS = ANS+ACC[i];
        
end


assign p = ANS;

endmodule

ABM-M1-WT-bitwise-32/radix4acc.v
`timescale 10ms / 1ms

module radix4acc(p,x,y);        

parameter N = 16;   //size of muliplicant and multiplier
parameter K = N/2;  //

input [N-1 : 0]   x,y;
output [N+N-1:0]   p;

reg [2:0]   bits    [K:0];
reg   neg     [K:0];
reg   two     [K:0];
reg   zero     [K:0];

wire [N+1:0] x_new;
reg [N+1:0]       PP      [K:0]; 
reg [N+N-1:0]   ACC     [K:0];
reg [N+N-1:0]   ANS;
reg mux;

integer i , j, t;

assign x_new = {2'b0,x};

always@(*)

begin
    bits[0] = {y[1],y[0],1'b0};             //setting last bit -1 as 0
    //$display("%b", bits[0]);
    for(i=1; i<K+1; i=i+1) begin
        if(i == K)
            bits[i] = {2'b0,y[2*i-1]};
        else
            bits[i] = {y[2*i+1], y[2*i], y[2*i-1]};
        //$display("%b", bits[i]);
        
    end

    for(i=0; i<K+1; i=i+1)
        begin                                      //accurate cases
            case(bits[i])

            
            3'b001, 3'b010:         
            begin
                neg[i] = 1'b0;
                two[i] = 1'b0;
                zero[i] = 1'b0;
            end

            3'b011:
            begin
                neg[i] = 1'b0;
                two[i] = 1'b1;
                zero[i] = 1'b0;
            end

            3'b101, 3'b110:         
            begin 
               neg[i] = 1'b1;
                two[i] = 1'b0;
                zero[i] = 1'b0;
            end

            3'b100:
            begin
                neg[i] = 1'b1;
                two[i] = 1'b1;
                zero[i] = 1'b0;
            end
         
            default: 
            begin
                neg[i] = 1'b0;
                two[i] = 1'b0;
                zero[i] = 1'b1;
            end

            endcase
            
            //$display("%b %b %b", neg[i], two[i], zero[i]);
            
            PP[i] = 0;
            PP[i][N+1] = neg[i];           //sign conservation

            for(t=0; t<N+1; t=t+1) begin
                if(t==0) 
                    mux = (x_new[t] & ~two[i]) | (1'b0 & two[i]);
                
                else
                    mux = (x_new[t] & ~two[i]) | (x_new[t-1] & two[i]);

                
                PP[i][t] = ~zero[i] & (neg[i] ^ mux);       
            end

            PP[i] = PP[i] + neg[i];             //correction term added
            
            //$display("%b", PP[i]);

            ACC[i] = $signed(PP[i]);        //sign extension
            //$display("%b", ACC[i]);

            for(j=0; j<i; j=j+1)
                ACC[i] = {ACC[i],2'b00};        //shifting

        
        end

    ANS = ACC[0];

    for(i=1; i<K+1; i=i+1)
        ANS = ANS+ACC[i];
        
    
end


assign p = ANS;

endmodule

ABM-M1-WT-bitwise-32/WT32.v
`timescale 10ms/1ms
`include "radix4acc.v"
`include "radix4approx.v"

module WT32(P,A,B);


parameter N = 32;   //size of muliplicant and multiplier
parameter K = N/2;  //

input   [N-1 : 0]   A,B;
output  [N+N-1:0]   P;

wire [K-1:0] AH, AL, BH, BL;

wire reg [N-1:0] M1, M2, M3, M4;

reg     [N:0]   A1, A2, A3;

reg [N+N-1:0]   ACC     [2:0];
reg [N+N-1:0] ANS;
integer i;


assign AH = A[N-1:K];
assign AL = A[K-1:0];

assign BH = B[N-1:K];
assign BL = B[K-1:0];

radix4approx APP1(.p(M1), .x(AL), .y(BL));

radix4acc ACC1(.p(M2), .x(AH), .y(BH));

radix4approx APP2(.p(M3), .x(AH), .y(BL));
radix4approx APP3(.p(M4), .x(AL), .y(BH));


always@(*)
begin

    A1 =  M3+M4;
    ACC[0] = $signed(A1);
    ACC[0] = {ACC[0], {16{1'b0}}};

    A2 = M1;
    ACC[1] = $signed(A2);
    
    A3 = M2;
    ACC[2] = $signed(A3);
    ACC[2] = {ACC[2], {32{1'b0}}};

    ANS = ACC[0];
    for(i=1; i<3; i=i+1)
        ANS = ANS+ACC[i];

    
end

assign P = ANS;

endmodule

ABM-M1-WT-bitwise-32/WT32_tb.v
`timescale 10ms / 1ms
`include "WT32.v"

module WT32_tb();

reg unsigned [31:0] A,B;
wire unsigned [63:0] P;
integer i, out, seed=7;


WT32 uut(P,A,B);


initial begin
    $dumpfile("WT32.vcd");
    $dumpvars(0, WT32_tb);
    out = $fopen("WT32output.csv");
    
    for(i=0; i<500; i=i+1)
    begin
        A = $urandom(seed) %4294967295;
        B = $urandom(seed) %4294967295;
        #1;
        $fwrite(out, "%d, %d, %d\n", A,B,P);
        #4;
    end
    $finish;
end

endmodule

ABM-M1-WT-bitwise-32/WT32.vcd
$date
	Fri Jul  9 13:24:24 2021
$end
$version
	Icarus Verilog
$end
$timescale
	1ms
$end
$scope module WT32_tb $end
$var wire 64 ! P [63:0] $end
$var reg 32 " A [31:0] $end
$var reg 32 # B [31:0] $end
$var integer 32 $ i [31:0] $end
$var integer 32 % out [31:0] $end
$var integer 32 & seed [31:0] $end
$scope module uut $end
$var wire 32 ' A [31:0] $end
$var wire 32 ( B [31:0] $end
$var wire 64 ) P [63:0] $end
$var wire 32 * M4 [31:0] $end
$var wire 32 + M3 [31:0] $end
$var wire 32 , M2 [31:0] $end
$var wire 32 - M1 [31:0] $end
$var wire 16 . BL [15:0] $end
$var wire 16 / BH [15:0] $end
$var wire 16 0 AL [15:0] $end
$var wire 16 1 AH [15:0] $end
$var reg 33 2 A1 [32:0] $end
$var reg 33 3 A2 [32:0] $end
$var reg 33 4 A3 [32:0] $end
$var reg 64 5 ANS [63:0] $end
$var integer 32 6 i [31:0] $end
$scope module ACC1 $end
$var wire 32 7 p [31:0] $end
$var wire 16 8 x [15:0] $end
$var wire 16 9 y [15:0] $end
$var wire 18 : x_new [17:0] $end
$var reg 32 ; ANS [31:0] $end
$var reg 1 < mux $end
$var integer 32 = i [31:0] $end
$var integer 32 > j [31:0] $end
$var integer 32 ? t [31:0] $end
$upscope $end
$scope module APP1 $end
$var wire 32 @ p [31:0] $end
$var wire 16 A x [15:0] $end
$var wire 16 B y [15:0] $end
$var wire 18 C x_new [17:0] $end
$var reg 32 D ANS [31:0] $end
$var reg 1 E mux $end
$var integer 32 F i [31:0] $end
$var integer 32 G j [31:0] $end
$var integer 32 H m [31:0] $end
$var integer 32 I t [31:0] $end
$upscope $end
$scope module APP2 $end
$var wire 32 J p [31:0] $end
$var wire 16 K x [15:0] $end
$var wire 16 L y [15:0] $end
$var wire 18 M x_new [17:0] $end
$var reg 32 N ANS [31:0] $end
$var reg 1 O mux $end
$var integer 32 P i [31:0] $end
$var integer 32 Q j [31:0] $end
$var integer 32 R m [31:0] $end
$var integer 32 S t [31:0] $end
$upscope $end
$scope module APP3 $end
$var wire 32 T p [31:0] $end
$var wire 16 U x [15:0] $end
$var wire 16 V y [15:0] $end
$var wire 18 W x_new [17:0] $end
$var reg 32 X ANS [31:0] $end
$var reg 1 Y mux $end
$var integer 32 Z i [31:0] $end
$var integer 32 [ j [31:0] $end
$var integer 32 \ m [31:0] $end
$var integer 32 ] t [31:0] $end
$upscope $end
$upscope $end
$upscope $end
$enddefinitions $end
#0
$dumpvars
b10001 ]
b1100 \
b1000 [
b1001 Z
0Y
b1001011111011101001011011101100 X
b110001000000000 W
b1100011001101100 V
b110001000000000 U
b1001011111011101001011011101100 T
b10001 S
b1100 R
b1000 Q
b1001 P
0O
b100001001010010100 N
b111 M
b100101110001100 L
b111 K
b100001001010010100 J
b10001 I
b1100 H
b1000 G
b1001 F
0E
b11100111011000001001110111100 D
b110001000000000 C
b100101110001100 B
b110001000000000 A
b11100111011000001001110111100 @
b10001 ?
b1000 >
b1001 =
0<
b1010110110011110100 ;
b111 :
b1100011001101100 9
b111 8
b1010110110011110100 7
b11 6
b101101110001110010011000110011011000001001110111100 5
b1010110110011110100 4
b11100111011000001001110111100 3
b1001011111100001010100110000000 2
b111 1
b110001000000000 0
b1100011001101100 /
b100101110001100 .
b11100111011000001001110111100 -
b1010110110011110100 ,
b100001001010010100 +
b1001011111011101001011011101100 *
b101101110001110010011000110011011000001001110111100 )
b11000110011011000100101110001100 (
b1110110001000000000 '
b11000110011011000100100011101101 &
b10 %
b0 $
b11000110011011000100101110001100 #
b1110110001000000000 "
b101101110001110010011000110011011000001001110111100 !
$end
#50
b11 6
b111011000011011111001110111101001010011110111011101111110110100 !
b111011000011011111001110111101001010011110111011101111110110100 )
b111011000011011111001110111101001010011110111011101111110110100 5
b1110110000110101111000000001011 4
b1101111010010111101111110110100 3
b11110111011011101110010010010010 2
b1110110000110101111000000001011 ,
b1110110000110101111000000001011 7
b1110110000110101111000000001011 ;
b1000 >
0<
b10001 ?
b1001 =
b10101010001100101100001011010100 +
b10101010001100101100001011010100 J
b10101010001100101100001011010100 N
b1000 Q
0O
b10001 S
b1001 P
b1101111010010111101111110110100 -
b1101111010010111101111110110100 @
b1101111010010111101111110110100 D
b1000 G
0E
b10001 I
b1001 F
b1001101001111000010000110111110 *
b1001101001111000010000110111110 T
b1001101001111000010000110111110 X
b1000 [
0Y
b10001 ]
b1001 Z
b1010111001101101 /
b1010111001101101 9
b1010111001101101 V
b1111101101011100 .
b1111101101011100 B
b1111101101011100 L
b1010110101010111 :
b1010110101010111 M
b1010110101010111 1
b1010110101010111 8
b1010110101010111 K
b111000101011010 C
b111000101011010 W
b111000101011010 0
b111000101011010 A
b111000101011010 U
b10101110011011011111101101011100 #
b10101110011011011111101101011100 (
b10101101010101110111000101011010 "
b10101101010101110111000101011010 '
b10101110011011011111100111000011 &
b1 $
#100
b11 6
b11000111101100011010111110000011010110101001110101101001110101 !
b11000111101100011010111110000011010110101001110101101001110101 )
b11000111101100011010111110000011010110101001110101101001110101 5
b110001111010110111001100001010 4
b11011111001000110101101001110101 3
b11111000110101011111011110000100 2
b110001111010110111001100001010 ,
b110001111010110111001100001010 7
b110001111010110111001100001010 ;
b1000 >
0<
b10001 ?
b1001 =
b111010100010000001000111011101 +
b111010100010000001000111011101 J
b111010100010000001000111011101 N
b1000 Q
0O
b10001 S
b1001 P
b11011111001000110101101001110101 -
b11011111001000110101101001110101 @
b11011111001000110101101001110101 D
b1000 G
0E
b10001 I
b1001 F
b10111110010011011110010110100111 *
b10111110010011011110010110100111 T
b10111110010011011110010110100111 X
b1000 [
0Y
b10001 ]
b1001 Z
b1100111111000101 /
b1100111111000101 9
b1100111111000101 V
b1111001110011111 .
b1111001110011111 B
b1111001110011111 L
b11110110000010 :
b11110110000010 M
b11110110000010 1
b11110110000010 8
b11110110000010 K
b1110101001111011 C
b1110101001111011 W
b1110101001111011 0
b1110101001111011 A
b1110101001111011 U
b11001111110001011111001110011111 #
b11001111110001011111001110011111 (
b111101100000101110101001111011 "
b111101100000101110101001111011 '
b11001111110001011111000000001001 &
b10 $
#150
b11 6
b11100111001001000110011010100011100110001110000111110100 !
b11100111001001000110011010100011100110001110000111110100 )
b11100111001001000110011010100011100110001110000111110100 5
b111001101110010101100000 4
b1110001010000001110000111110100 3
b111111000001100011001001011000 2
b111001101110010101100000 ,
b111001101110010101100000 7
b111001101110010101100000 ;
b1000 >
0<
b10001 ?
b1001 =
b111101010111010011011111101000 +
b111101010111010011011111101000 J
b111101010111010011011111101000 N
b1000 Q
0O
b10001 S
b1001 P
b1110001010000001110000111110100 -
b1110001010000001110000111110100 @
b1110001010000001110000111110100 D
b1000 G
0E
b10001 I
b1001 F
b1101010001111101001110000 *
b1101010001111101001110000 T
b1101010001111101001110000 X
b1000 [
0Y
b10001 ]
b1001 Z
b1001110000 /
b1001110000 9
b1001110000 V
b1010011000000100 .
b1010011000000100 B
b1010011000000100 L
b101111010111010 :
b101111010111010 M
b101111010111010 1
b101111010111010 8
b101111010111010 K
b1010111010111101 C
b1010111010111101 W
b1010111010111101 0
b1010111010111101 A
b1010111010111101 U
b10011100001010011000000100 #
b10011100001010011000000100 (
b1011110101110101010111010111101 "
b1011110101110101010111010111101 '
b10011100001010010100111111 &
b11 $
#200
b11 6
b10011000111111101111100011011100010110000000100111101001 !
b10011000111111101111100011011100010110000000100111101001 )
b10011000111111101111100011011100010110000000100111101001 5
b100110001100111101110010 4
b1001011000001100000100111101001 3
b101111100001101001000101010010 2
b100110001100111101110010 ,
b100110001100111101110010 7
b100110001100111101110010 ;
b1000 >
0<
b10001 ?
b1001 =
b101110011111111010010110000101 +
b101110011111111010010110000101 J
b101110011111111010010110000101 N
b1000 Q
0O
b10001 S
b1001 P
b1001011000001100000100111101001 -
b1001011000001100000100111101001 @
b1001011000001100000100111101001 D
b1000 G
0E
b10001 I
b1001 F
b1000001101110101111001101 *
b1000001101110101111001101 T
b1000001101110101111001101 X
b1000 [
0Y
b10001 ]
b1001 Z
b111011110 /
b111011110 9
b111011110 V
b1001000000000011 .
b1001000000000011 B
b1001000000000011 L
b101000111010111 :
b101000111010111 M
b101000111010111 1
b101000111010111 8
b101000111010111 K
b1000100010100011 C
b1000100010100011 W
b1000100010100011 0
b1000100010100011 A
b1000100010100011 U
b1110111101001000000000011 #
b1110111101001000000000011 (
b1010001110101111000100010100011 "
b1010001110101111000100010100011 '
b1110111101000111011100101 &
b100 $
#250
b11 6
b10010111001000011110101001011101001100010111110011111001101 !
b10010111001000011110101001011101001100010111110011111001101 )
b10010111001000011110101001011101001100010111110011111001101 5
b100101110001110000111100101 4
b1000100010011110011111001101 3
b101101011011011110000100000010 2
b100101110001110000111100101 ,
b100101110001110000111100101 7
b100101110001110000111100101 ;
b1000 >
0<
b10001 ?
b1001 =
b101100100100001100110100010101 +
b101100100100001100110100010101 J
b101100100100001100110100010101 N
b1000 Q
0O
b10001 S
b1001 P
b1000100010011110011111001101 -
b1000100010011110011111001101 @
b1000100010011110011111001101 D
b1000 G
0E
b10001 I
b1001 F
b110111010001001111101101 *
b110111010001001111101101 T
b110111010001001111101101 X
b1000 [
0Y
b10001 ]
b1001 Z
b110100111011 /
b110100111011 9
b110100111011 V
b1000000000011010 .
b1000000000011010 B
b1000000000011010 L
b101101101011111 :
b101101101011111 M
b101101101011111 1
b101101101011111 8
b101101101011111 K
b1000010110110 C
b1000010110110 W
b1000010110110 0
b1000010110110 A
b1000010110110 U
b1101001110111000000000011010 #
b1101001110111000000000011010 (
b1011011010111110001000010110110 "
b1011011010111110001000010110110 '
b1101001110110111111001111011 &
b101 $
#300
b11 6
b110110000001001100010101100010001111011001110011000000011011 !
b110110000001001100010101100010001111011001110011000000011011 )
b110110000001001100010101100010001111011001110011000000011011 5
b1101100000001110111010111111 4
b1100100010011000000011011 3
b1000010100110011000110111010110 2
b1101100000001110111010111111 ,
b1101100000001110111010111111 7
b1101100000001110111010111111 ;
b1000 >
0<
b10001 ?
b1001 =
b10101000000110111110001 +
b10101000000110111110001 J
b10101000000110111110001 N
b1000 Q
0O
b10001 S
b1001 P
b1100100010011000000011011 -
b1100100010011000000011011 @
b1100100010011000000011011 D
b1000 G
0E
b10001 I
b1001 F
b1000010010001010111111111100101 *
b1000010010001010111111111100101 T
b1000010010001010111111111100101 X
b1000 [
0Y
b10001 ]
b1001 Z
b111100100011101 /
b111100100011101 9
b111100100011101 V
b1011110010 .
b1011110010 B
b1011110010 L
b1110010001011 :
b1110010001011 M
b1110010001011 1
b1110010001011 8
b1110010001011 K
b1000100000111001 C
b1000100000111001 W
b1000100000111001 0
b1000100000111001 A
b1000100000111001 U
b1111001000111010000001011110010 #
b1111001000111010000001011110010 (
b11100100010111000100000111001 "
b11100100010111000100000111001 '
b1111001000111010000000110000001 &
b110 $
#350
b11 6
b10111010111010010101010101010100110110000001011011000111001001 !
b10111010111010010101010101010100110110000001011011000111001001 )
b10111010111010010101010101010100110110000001011011000111001001 5
b101110101110011010111011010010 4
b10010100010100001011000111001001 3
b10100110100000101010000110110101 2
b101110101110011010111011010010 ,
b101110101110011010111011010010 7
b101110101110011010111011010010 ;
b1000 >
0<
b10001 ?
b1001 =
b1011010011001010011110110110010 +
b1011010011001010011110110110010 J
b1011010011001010011110110110010 N
b1000 Q
0O
b10001 S
b1001 P
b10010100010100001011000111001001 -
b10010100010100001011000111001001 @
b10010100010100001011000111001001 D
b1000 G
0E
b10001 I
b1001 F
b1001100000111010110010000000011 *
b1001100000111010110010000000011 T
b1001100000111010110010000000011 X
b1000 [
0Y
b10001 ]
b1001 Z
b110010010101111 /
b110010010101111 9
b110010010101111 V
b1100001011001001 .
b1100001011001001 B
b1100001011001001 L
b111011011001110 :
b111011011001110 M
b111011011001110 1
b111011011001110 8
b111011011001110 K
b1100001011101101 C
b1100001011101101 W
b1100001011101101 0
b1100001011101101 A
b1100001011101101 U
b1100100101011111100001011001001 #
b1100100101011111100001011001001 (
b1110110110011101100001011101101 "
b1110110110011101100001011101101 '
b1100100101011111100000101110111 &
b111 $
#400
b11 6
b11001111101111101110001001101101100011110100011101011101100000 !
b11001111101111101110001001101101100011110100011101011101100000 )
b11001111101111101110001001101101100011110100011101011101100000 5
b110011111011101100111010011101 4
b11011110001111001101011101100000 3
b11101001111111011000010110010101 2
b110011111011101100111010011101 ,
b110011111011101100111010011101 7
b110011111011101100111010011101 ;
b1000 >
0<
b10001 ?
b1001 =
b1000110101110100110010100110000 +
b1000110101110100110010100110000 J
b1000110101110100110010100110000 N
b1000 Q
0O
b10001 S
b1001 P
b11011110001111001101011101100000 -
b11011110001111001101011101100000 @
b11011110001111001101011101100000 D
b1000 G
0E
b10001 I
b1001 F
b10100011010000110010000001100101 *
b10100011010000110010000001100101 T
b10100011010000110010000001100101 X
b1000 [
0Y
b10001 ]
b1001 Z
b1010100000111011 /
b1010100000111011 9
b1010100000111011 V
b1110010101010000 .
b1110010101010000 B
b1110010101010000 L
b100111100000111 :
b100111100000111 M
b100111100000111 1
b100111100000111 8
b100111100000111 K
b1111100010011110 C
b1111100010011110 W
b1111100010011110 0
b1111100010011110 A
b1111100010011110 U
b10101000001110111110010101010000 #
b10101000001110111110010101010000 (
b1001111000001111111100010011110 "
b1001111000001111111100010011110 '
b10101000001110111110001111011101 &
b1000 $
#450
b11 6
b100000101111110010001101110000000110001111100101011011011000 !
b100000101111110010001101110000000110001111100101011011011000 )
b100000101111110010001101110000000110001111100101011011011000 5
b1000001011110111101101100000 4
b1001010111000100101011011011000 3
b1001101011110111011101101011100 2
b1000001011110111101101100000 ,
b1000001011110111101101100000 7
b1000001011110111101101100000 ;
b1000 >
0<
b10001 ?
b1001 =
b1000100101010010000111100010000 +
b1000100101010010000111100010000 J
b1000100101010010000111100010000 N
b1000 Q
0O
b10001 S
b1001 P
b1001010111000100101011011011000 -
b1001010111000100101011011011000 @
b1001010111000100101011011011000 D
b1000 G
0E
b10001 I
b1001 F
b1000110100101010110001001100 *
b1000110100101010110001001100 T
b1000110100101010110001001100 X
b1000 [
0Y
b10001 ]
b1001 Z
b110010011000 /
b110010011000 9
b110010011000 V
b110110000011001 .
b110110000011001 B
b110110000011001 L
b1010011001100100 :
b1010011001100100 M
b1010011001100100 1
b1010011001100100 8
b1010011001100100 K
b1011001101001100 C
b1011001101001100 W
b1011001101001100 0
b1011001101001100 A
b1011001101001100 U
b1100100110000110110000011001 #
b1100100110000110110000011001 (
b10100110011001001011001101001100 "
b10100110011001001011001101001100 '
b1100100110000110101000110011 &
b1001 $
#500
b11 6
b1010111100011001001111111100101000111000101101100011011110111 !
b1010111100011001001111111100101000111000101101100011011110111 )
b1010111100011001001111111100101000111000101101100011011110111 5
b10101111000101100101110110100 4
b1011101101110111100011011110111 3
b1011100010001001110100101011011 2
b10101111000101100101110110100 ,
b10101111000101100101110110100 7
b10101111000101100101110110100 ;
b1000 >
0<
b10001 ?
b1001 =
b100010101110111101101110100100 +
b100010101110111101101110100100 J
b100010101110111101101110100100 N
b1000 Q
0O
b10001 S
b1001 P
b1011101101110111100011011110111 -
b1011101101110111100011011110111 @
b1011101101110111100011011110111 D
b1000 G
0E
b10001 I
b1001 F
b111001100010010000110110110111 *
b111001100010010000110110110111 T
b111001100010010000110110110111 X
b1000 [
0Y
b10001 ]
b1001 Z
b101101011100101 /
b101101011100101 9
b101101011100101 V
b1001001010110101 .
b1001001010110101 B
b1001001010110101 L
b11110110100100 :
b11110110100100 M
b11110110100100 1
b11110110100100 8
b11110110100100 K
b1010001001111011 C
b1010001001111011 W
b1010001001111011 0
b1010001001111011 A
b1010001001111011 U
b1011010111001011001001010110101 #
b1011010111001011001001010110101 (
b111101101001001010001001111011 "
b111101101001001010001001111011 '
b1011010111001011001000111111001 &
b1010 $
#550
b11 6
b1101010011001000011101000111111111001110110100110001010111 !
b1101010011001000011101000111111111001110110100110001010111 )
b1101010011001000011101000111111111001110110100110001010111 5
b11010100101011010001010000 4
b11110000011010100110001010111 3
b1101101100000011110000100101110 2
b11010100101011010001010000 ,
b11010100101011010001010000 7
b11010100101011010001010000 ;
b1000 >
0<
b10001 ?
b1001 =
b110110101001000111100111 +
b110110101001000111100111 J
b110110101001000111100111 N
b1000 Q
b10001 S
b1001 P
b11110000011010100110001010111 -
b11110000011010100110001010111 @
b11110000011010100110001010111 D
b1000 G
0E
b10001 I
b1001 F
b1101100101001110100111101000111 *
b1101100101001110100111101000111 T
b1101100101001110100111101000111 X
b1000 [
0Y
b10001 ]
b1001 Z
b1100100110100110 /
b1100100110100110 9
b1100100110100110 V
b11011110010011 .
b11011110010011 B
b11011110010011 L
b10000111000 :
b10000111000 M
b10000111000 1
b10000111000 8
b10000111000 K
b1000101000001000 C
b1000101000001000 W
b1000101000001000 0
b1000101000001000 A
b1000101000001000 U
b11001001101001100011011110010011 #
b11001001101001100011011110010011 (
b100001110001000101000001000 "
b100001110001000101000001000 '
b11001001101001100011010010101111 &
b1011 $
#600
b11 6
b10011101100000111110110110110001011011000001110011101100000 !
b10011101100000111110110110110001011011000001110011101100000 )
b10011101100000111110110110110001011011000001110011101100000 5
b100111011000001011101000000 4
b11010000001110011101100000 3
b1000001011011000100000100000 2
b100111011000001011101000000 ,
b100111011000001011101000000 7
b100111011000001011101000000 ;
b1000 >
0<
b10001 ?
b1001 =
b100111100011011000001000000 +
b100111100011011000001000000 J
b100111100011011000001000000 N
b1000 Q
0O
b10001 S
b1001 P
b11010000001110011101100000 -
b11010000001110011101100000 @
b11010000001110011101100000 D
b1000 G
0E
b10001 I
b1001 F
b11001110111101011111100000 *
b11001110111101011111100000 T
b11001110111101011111100000 X
b1000 [
0Y
b10001 ]
b1001 Z
b10100000010000 /
b10100000010000 9
b10100000010000 V
b10100001010000 .
b10100001010000 B
b10100001010000 L
b1111101110100 :
b1111101110100 M
b1111101110100 1
b1111101110100 8
b1111101110100 K
b1010000111110 C
b1010000111110 W
b1010000111110 0
b1010000111110 A
b1010000111110 U
b101000000100000010100001010000 #
b101000000100000010100001010000 (
b11111011101000001010000111110 "
b11111011101000001010000111110 '
b101000000100000010011111010101 &
b1100 $
#650
b11 6
b110010011011001001100100101111011000111101111110011101100100 !
b110010011011001001100100101111011000111101111110011101100100 )
b110010011011001001100100101111011000111101111110011101100100 5
b1100100110100111111111101110 4
b1110001011000001110011101100100 3
b10100110010111010110011110010111 2
b1100100110100111111111101110 ,
b1100100110100111111111101110 7
b1100100110100111111111101110 ;
b1000 >
0<
b10001 ?
b1001 =
b1000111111110111101110111000 +
b1000111111110111101110111000 J
b1000111111110111101110111000 N
0O
b1000 Q
b10001 S
b1001 P
b1110001011000001110011101100100 -
b1110001011000001110011101100100 @
b1110001011000001110011101100100 D
b1000 G
0E
b10001 I
b1001 F
b10011101010111011110101111011111 *
b10011101010111011110101111011111 T
b10011101010111011110101111011111 X
b1000 [
0Y
b10001 ]
b1001 Z
b1101101000101011 /
b1101101000101011 9
b1101101000101011 V
b1001111110110100 .
b1001111110110100 B
b1001111110110100 L
b111011001010 :
b111011001010 M
b111011001010 1
b111011001010 8
b111011001010 K
b1011100000011101 C
b1011100000011101 W
b1011100000011101 0
b1011100000011101 A
b1011100000011101 U
b11011010001010111001111110110100 #
b11011010001010111001111110110100 (
b1110110010101011100000011101 "
b1110110010101011100000011101 '
b11011010001010111001110011101011 &
b1101 $
#700
b11 6
b101111000011100010110011110110010010110011111111010011000110000 !
b101111000011100010110011110110010010110011111111010011000110000 )
b101111000011100010110011110110010010110011111111010011000110000 5
b1011110000110111010110000110111 4
b1001100110100101010011000110000 3
b10101101101101010100100110101101 2
b1011110000110111010110000110111 ,
b1011110000110111010110000110111 7
b1011110000110111010110000110111 ;
b1000 >
0<
b10001 ?
b1001 =
b1000100011010100101001111010000 +
b1000100011010100101001111010000 J
b1000100011010100101001111010000 N
b1000 Q
0O
b10001 S
b1001 P
b1001100110100101010011000110000 -
b1001100110100101010011000110000 @
b1001100110100101010011000110000 D
b1000 G
0E
b10001 I
b1001 F
b1101001010010101111010111011101 *
b1101001010010101111010111011101 T
b1101001010010101111010111011101 X
b1000 [
0Y
b10001 ]
b1001 Z
b1011000000011001 /
b1011000000011001 9
b1011000000011001 V
b1000001101100000 .
b1000001101100000 B
b1000001101100000 L
b1000100011001111 :
b1000100011001111 M
b1000100011001111 1
b1000100011001111 8
b1000100011001111 K
b1001100100010001 C
b1001100100010001 W
b1001100100010001 0
b1001100100010001 A
b1001100100010001 U
b10110000000110011000001101100000 #
b10110000000110011000001101100000 (
b10001000110011111001100100010001 "
b10001000110011111001100100010001 '
b10110000000110011000000101110001 &
b1110 $
#750
b11 6
b1010101010100110011001111001111110001110101111010111011010110010 !
b1010101010100110011001111001111110001110101111010111011010110010 )
b1010101010100110011001111001111110001110101111010111011010110010 5
b10101010101001110101101010000000 4
b1011011110010010111011010110010 3
b100001101000111110011001011110100 2
b10101010101001110101101010000000 ,
b10101010101001110101101010000000 7
b10101010101001110101101010000000 ;
b1000 >
0<
b10001 ?
b1001 =
b10111000101011001011111000100000 +
b10111000101011001011111000100000 J
b10111000101011001011111000100000 N
b1000 Q
0O
b10001 S
b1001 P
b1011011110010010111011010110010 -
b1011011110010010111011010110010 @
b1011011110010010111011010110010 D
b1000 G
0E
b10001 I
b1001 F
b1010100011100100111010011010100 *
b1010100011100100111010011010100 T
b1010100011100100111010011010100 X
b1000 [
0Y
b10001 ]
b1001 Z
b1101000010011000 /
b1101000010011000 9
b1101000010011000 V
b1110000110100001 .
b1110000110100001 B
b1110000110100001 L
b1101000101110000 :
b1101000101110000 M
b1101000101110000 1
b1101000101110000 8
b1101000101110000 K
b110011110100010 C
b110011110100010 W
b110011110100010 0
b110011110100010 A
b110011110100010 U
b11010000100110001110000110100001 #
b11010000100110001110000110100001 (
b11010001011100000110011110100010 "
b11010001011100000110011110100010 '
b11010000100110001101111011100111 &
b1111 $
#800
b11 6
b1000001101000001110010000110011100001100111100001000011101111101 !
b1000001101000001110010000110011100001100111100001000011101111101 )
b1000001101000001110010000110011100001100111100001000011101111101 5
b10000011010000010111000111001001 4
b1110010001101000011101111101 3
b1010110100111011111111010101010 2
b10000011010000010111000111001001 ,
b10000011010000010111000111001001 7
b10000011010000010111000111001001 ;
b1000 >
0<
b10001 ?
b1001 =
b101001011111110000110101101111 +
b101001011111110000110101101111 J
b101001011111110000110101101111 N
b1000 Q
0O
b10001 S
b1001 P
b1110010001101000011101111101 -
b1110010001101000011101111101 @
b1110010001101000011101111101 D
b1000 G
0E
b10001 I
b1001 F
b101101000111101111000100111011 *
b101101000111101111000100111011 T
b101101000111101111000100111011 X
b1000 [
0Y
b10001 ]
b1001 Z
b1100001010100011 /
b1100001010100011 9
b1100001010100011 V
b11110110000101 .
b11110110000101 B
b11110110000101 L
b1010110010100011 :
b1010110010100011 M
b1010110010100011 1
b1010110010100011 8
b1010110010100011 K
b11101101011001 C
b11101101011001 W
b11101101011001 0
b11101101011001 A
b11101101011001 U
b11000010101000110011110110000101 #
b11000010101000110011110110000101 (
b10101100101000110011101101011001 "
b10101100101000110011101101011001 '
b11000010101000110011101011001101 &
b10000 $
