ABM-M1-Karatsuba-bitwise-32- single approx/radix4approx.v
`timescale 10ms / 1ms

module radix4approx(p,x,y);         //8 bit multiplier to give 16 bit product

parameter N = 16;   //size of muliplicant and multiplier
parameter K = N/2;  //

input   [N-1 : 0]   x,y;
output  [N+N-1:0]   p;

reg [2:0]   bits    [K:0];
reg   neg     [K:0];
reg   two     [K:0];
reg   zero     [K:0];

wire [N+1:0] x_new;
reg [N+1:0]       PP      [K:0]; //riyaj 
reg [N+N-1:0]   ACC     [K:0];
reg [N+N-1:0]   ANS;
reg mux;

integer i , j, t;
integer  m = 32;        //number of bits to approximate

assign x_new = {2'b0,x};

always@(*)

begin
    bits[0] = {y[1],y[0],1'b0};             //setting last bit -1 as 0

    for(i=1; i<K+1; i=i+1) begin
            if(i == K)
                bits[i] = {2'b0,y[2*i-1]};
            else
                bits[i] = {y[2*i+1], y[2*i], y[2*i-1]};
            //$display("%b", bits[i]);
            
        end


    for(i=0; i<K+1; i=i+1)
        begin                               //approximated 2A as A introduced error
            case(bits[i])

            
            3'b001, 3'b010:         
            begin
                neg[i] = 1'b0;
                two[i] = 1'b0;
                zero[i] = 1'b0;
            end

            3'b011:
            begin
                neg[i] = 1'b0;
                two[i] = 1'b1;
                zero[i] = 1'b0;
            end

            3'b101, 3'b110:         
            begin 
               neg[i] = 1'b1;
                two[i] = 1'b0;
                zero[i] = 1'b0;
            end

            3'b100:
            begin
                neg[i] = 1'b1;
                two[i] = 1'b1;
                zero[i] = 1'b0;
            end
         
            default: 
            begin
                neg[i] = 1'b0;
                two[i] = 1'b0;
                zero[i] = 1'b1;
            end

            endcase

            PP[i] = 0;
            PP[i][N+1] = neg[i];           //sign conservation

            for(t=0; t<N+1; t=t+1) begin
                if(t>=m) 
                begin
                    mux = (x_new[t] & ~two[i]) | (x_new[t-1] & two[i]);             
                    PP[i][t] = ~zero[i] & (neg[i] ^ mux);
                end

                else 
                begin
                    PP[i][t] = (~x_new[t] & neg[i]) | (x_new[t] & ~neg[i] & ~zero[i]);
                end
            end

            PP[i] = PP[i] + neg[i];

            ACC[i] = $signed(PP[i]);        //sign extension
            
            for(j=0; j<i; j=j+1)
                ACC[i] = {ACC[i],2'b00};        //shifting

        
        end

    ANS = ACC[0];

    for(i=1; i<K+1; i=i+1)
        ANS = ANS+ACC[i];
        
end


assign p = ANS;

endmodule

ABM-M1-Karatsuba-bitwise-32- single approx/radix4approx_tb.v
`timescale 10ms / 1ms
`include "radix4approx.v"

module radix4approx_tb();


reg  unsigned [15 : 0]   A,B;

wire unsigned [31:0]   P;

integer i, out, seed=7;

radix4approx uut(P,A,B);

initial begin
    $dumpfile("radix4approx.vcd");
    $dumpvars(0, radix4approx_tb);
    out = $fopen("radix4-approx-mult-result.csv");
    
        A = 0;
        B = 18;
        #1;
        $fwrite(out, "%d, %d, %d\n", A,B,P);
        #4;

    for(i=0; i<100; i=i+1)                       //10 test cases A and B: 1-100 
    begin
        A = $urandom(seed) %200 + 32000;
        B = $urandom(seed) %200;
        #1;
        $fwrite(out, "%d, %d, %d\n", A,B,P);
        #4;
    end

    for(i=0; i<100; i=i+1)                       //10 test cases A: 1-100 B: till 2^15
    begin
        A = $urandom(seed) %200;
        B = $urandom(seed) %32768;
        #1;
        $fwrite(out, "%d, %d, %d\n", A,B,P);
        #4;
    end

    for(i=0; i<100; i=i+1)                       //10 test cases B: 1-100 A: till 2^32
    begin
        A = $urandom(seed) %65500;
        B = $urandom(seed) %200 + 1024;
        #1;
        $fwrite(out, "%d, %d, %d\n", A,B,P);
        #4;
    end


    for(i=0; i<200; i=i+1)                       //50 cases : till 1024 A: 2^10 B: 2^20
    begin
        A = $urandom(seed) %1024;
        B = $urandom(seed) %65500;
        #1;
        $fwrite(out, "%d, %d, %d\n", A,B,P);
        #4;
    end

    for(i=0; i<500; i=i+1)                       //500 cases : till 32768 which is 2^15
    begin
        A = $urandom(seed) %65536;
        B = $urandom(seed) %32768;
        #1;
        $fwrite(out, "%d, %d, %d\n", A,B,P);
        #4;
    end
    $finish;
end
endmodule

ABM-M1-Karatsuba-bitwise-32- single approx/radix4approx.vcd
$date
	Sat Sep 18 15:03:09 2021
$end
$version
	Icarus Verilog
$end
$timescale
	1ms
$end
$scope module radix4approx_tb $end
$var wire 32 ! P [31:0] $end
$var reg 16 " A [15:0] $end
$var reg 16 # B [15:0] $end
$var integer 32 $ i [31:0] $end
$var integer 32 % out [31:0] $end
$var integer 32 & seed [31:0] $end
$scope module uut $end
$var wire 32 ' p [31:0] $end
$var wire 16 ( x [15:0] $end
$var wire 16 ) y [15:0] $end
$var wire 18 * x_new [17:0] $end
$var reg 32 + ANS [31:0] $end
$var reg 1 , mux $end
$var integer 32 - i [31:0] $end
$var integer 32 . j [31:0] $end
$var integer 32 / m [31:0] $end
$var integer 32 0 t [31:0] $end
$upscope $end
$upscope $end
$enddefinitions $end
#0
$dumpvars
b10001 0
b1000 /
b1000 .
b1001 -
0,
b111111111111111111 +
b0 *
b10010 )
b0 (
b111111111111111111 '
b111 &
b10 %
bx $
b10010 #
b0 "
b111111111111111111 !
$end
#50
b1010111111101001001100000 !
b1010111111101001001100000 '
b1010111111101001001100000 +
b1000 .
0,
b10001 0
b1001 -
b11000100 #
b11000100 )
b111110100101000 *
b111110100101000 "
b111110100101000 (
b11000110011011000100100011101101 &
b0 $
#100
b1010111000011101000010100 !
b1010111000011101000010100 '
b1010111000011101000010100 +
b1000 .
0,
b10001 0
b1001 -
b10011100 #
b10011100 )
b111110100010010 *
b111110100010010 "
b111110100010010 (
b10101110011011011111100111000011 &
b1 $
#150
b1001101100000010111001 !
b1001101100000010111001 '
b1001101100000010111001 +
b1000 .
0,
b10001 0
b1001 -
b1000111 #
b1000111 )
b111110101010011 *
b111110101010011 "
b111110101010011 (
b11001111110001011111000000001001 &
b10 $
#200
b1100100000110000110000100 !
b1100100000110000110000100 '
b1100100000110000110000100 +
b1000 .
0,
b10001 0
b1001 -
b10100100 #
b10100100 )
b111110110000101 *
b111110110000101 "
b111110110000101 (
b10011100001010010100111111 &
b11 $
#250
b1110001100000010110001 !
b1110001100000010110001 '
b1110001100000010110001 +
b1000 .
0,
b10001 0
b1001 -
b1001011 #
b1001011 )
b111110101110011 *
b111110101110011 "
b111110101110011 (
b1110111101000111011100101 &
b100 $
#300
b1000001011010001001101 !
b1000001011010001001101 '
b1000001011010001001101 +
b1000 .
0,
b10001 0
b1001 -
b11010 #
b11010 )
b111110100110110 *
b111110100110110 "
b111110100110110 (
b1101001110110111111001111011 &
b101 $
#350
b10101001001111011111011 !
b10101001001111011111011 '
b10101001001111011111011 +
b1000 .
0,
b10001 0
b1001 -
b100010 #
b100010 )
b111110100011001 *
b111110100011001 "
b111110100011001 (
b1111001000111010000000110000001 &
b110 $
#400
b111111011111001000101 !
b111111011111001000101 '
b111111011111001000101 +
b1000 .
0,
b10001 0
b1001 -
b1000001 #
b1000001 )
b111110100000101 *
b111110100000101 "
b111110100000101 (
b1100100101011111100000101110111 &
b111 $
#450
b1111101001111100000 !
b1111101001111100000 '
b1111101001111100000 +
b1000 .
0,
b10001 0
b1001 -
b10000 #
b10000 )
b111110100111110 *
b111110100111110 "
b111110100111110 (
b10101000001110111110001111011101 &
b1000 $
#500
b1010100110001110110101000 !
b1010100110001110110101000 '
b1010100110001110110101000 +
b1000 .
0,
b10001 0
b1001 -
b10001001 #
b10001001 )
b111110110011100 *
b111110110011100 "
b111110110011100 (
b1100100110000110101000110011 &
b1001 $
#550
b1010101010001010100001111 !
b1010101010001010100001111 '
b1010101010001010100001111 +
b1000 .
0,
b10001 0
b1001 -
b10001101 #
b10001101 )
b111110101001011 *
b111110101001011 "
b111110101001011 (
b1011010111001011001000111111001 &
b1010 $
#600
b11010100100000101111 !
b11010100100000101111 '
b11010100100000101111 +
b1000 .
0,
b10001 0
b1001 -
b10011 #
b10011 )
b111110100010000 *
b111110100010000 "
b111110100010000 (
b11001001101001100011010010101111 &
b1011 $
#650
b1010100101001001011000100 !
b1010100101001001011000100 '
b1010100101001001011000100 +
b1000 .
0,
b10001 0
b1001 -
b10001000 #
b10001000 )
b111110100110110 *
b111110100110110 "
b111110100110110 (
b101000000100000010011111010101 &
b1100 $
#700
b10011100011001000100 !
b10011100011001000100 '
b10011100011001000100 +
b1000 .
0,
b10001 0
b1001 -
b10100 #
b10100 )
b111110100011101 *
b111110100011101 "
b111110100011101 (
b11011010001010111001110011101011 &
b1101 $
#750
b10101111000010100110000 !
b10101111000010100110000 '
b10101111000010100110000 +
b1000 .
0,
b10001 0
b1001 -
b110000 #
b110000 )
b111110101110001 *
b111110101110001 "
b111110101110001 (
b10110000000110011000000101110001 &
b1110 $
#800
b1100011101110010111111010 !
b1100011101110010111111010 '
b1100011101110010111111010 +
b1000 .
0,
b10001 0
b1001 -
b10100001 #
b10100001 )
b111110101101010 *
b111110101101010 "
b111110101101010 (
b11010000100110001101111011100111 &
b1111 $
#850
b10100100101001000101 !
b10100100101001000101 '
b10100100101001000101 +
b1000 .
0,
b10001 0
b1001 -
b10101 #
b10101 )
b111110101110001 *
b111110101110001 "
b111110101110001 (
b11000010101000110011101011001101 &
b10000 $
#900
b1100110011111000111010101 !
b1100110011111000111010101 '
b1100110011111000111010101 +
b1000 .
0,
b10001 0
b1001 -
b10101111 #
b10101111 )
b111110110111010 *
b111110110111010 "
b111110110111010 (
b1011101101111111011010100011 &
b10001 $
#950
b100111110100100011100 !
b100111110100100011100 '
b100111110100100011100 +
b1000 .
0,
b10001 0
b1001 -
b1000 #
b1000 )
b111110100011000 *
b111110100011000 "
b111110100011000 (
b1001000001011101010111111101001 &
b10010 $
#1000
b111111101110110000000 !
b111111101110110000000 '
b111111101110110000000 +
b1000 .
0,
b10001 0
b1001 -
b1000001 #
b1000001 )
b111110110000000 *
b111110110000000 "
b111110110000000 (
b1000101010001010000000011111 &
b10011 $
#1050
b10110101001010011100001 !
b10110101001010011100001 '
b10110101001010011100001 +
b1000 .
0,
b10001 0
b1001 -
b101110 #
b101110 )
b111110110101110 *
b111110110101110 "
b111110110101110 (
b10001011011110001111110011000101 &
b10100 $
#1100
b111100010100101111110 !
b111100010100101111110 '
b111100010100101111110 +
b1000 .
0,
b10001 0
b1001 -
b11101 #
b11101 )
b111110100001010 *
b111110100001010 "
b111110100001010 (
b10001010100111000101011101011011 &
b10101 $
#1150
b1010101001110100111010001 !
b1010101001110100111010001 '
b1010101001110100111010001 +
b1000 .
0,
b10001 0
b1001 -
b10001101 #
b10001101 )
b111110100010101 *
b111110100010101 "
b111110100010101 (
b111110100101101111110101100001 &
b10110 $
#1200
b100000110001111100010100 !
b100000110001111100010100 '
b100000110001111100010100 +
b1000 .
0,
b10001 0
b1001 -
b1101000 #
b1101000 )
b111110110011110 *
b111110110011110 "
b111110110011110 (
b1010100010100100101100001010111 &
b10111 $
#1250
b1010100011011011100110111 !
b1010100011011011100110111 '
b1010100011011011100110111 +
b1000 .
0,
b10001 0
b1001 -
b10011111 #
b10011111 )
b111110100011001 *
b111110100011001 "
b111110100011001 (
b1010111110100010100110110111101 &
b11000 $
#1300
b1010011010110000001011101 !
b1010011010110000001011101 '
b1010011010110000001011101 +
b1000 .
0,
b10001 0
b1001 -
b10010110 #
b10010110 )
b111110100101010 *
b111110100101010 "
b111110100101010 (
b11101111010100111001111100010011 &
b11001 $
#1350
b1100100000111010000110000 !
b1100100000111010000110000 '
b1100100000111010000110000 +
b1000 .
0,
b10001 0
b1001 -
b10100100 #
b10100100 )
b111110110100000 *
b111110110100000 "
b111110110100000 (
b10100010010000000100100111011001 &
b11010 $
#1400
b1010001110001101011001110 !
b1010001110001101011001110 '
b1010001110001101011001110 +
b1000 .
0,
b10001 0
b1001 -
b10010001 #
b10010001 )
b111110110101110 *
b111110110101110 "
b111110110101110 (
b10111100111011101110011110001111 &
b11011 $
#1450
b1000010011111011100100 !
b1000010011111011100100 '
b1000010011111011100100 +
b1000 .
0,
b10001 0
b1001 -
b1000100 #
b1000100 )
b111110100101001 *
b111110100101001 "
b111110100101001 (
b10011110001010000000110110110101 &
b11100 $
#1500
b11011110110010010011000 !
b11011110110010010011000 '
b11011110110010010011000 +
b1000 .
0,
b10001 0
b1001 -
b1100001 #
b1100001 )
b111110100101000 *
b111110100101000 "
b111110100101000 (
b1001100111101001010110111001011 &
b11101 $
#1550
b1100100110100101000111111 !
b1100100110100101000111111 '
b1100100110100101000111111 +
b1000 .
0,
b10001 0
b1001 -
b10100010 #
b10100010 )
b111110101000101 *
b111110101000101 "
b111110101000101 (
b1101000101000111010101010001 &
b11110 $
#1600
b1011010111101001010011100 !
b1011010111101001010011100 '
b1011010111101001010011100 +
b1000 .
0,
b10001 0
b1001 -
b10111100 #
b10111100 )
b111110100001001 *
b111110100001001 "
b111110100001001 (
b10110110001100110010110111000111 &
b11111 $
#1650
b1010110000010000011000111 !
b1010110000010000011000111 '
b1010110000010000011000111 +
b1000 .
0,
b10001 0
b1001 -
b10001011 #
b10001011 )
b111110110100100 *
b111110110100100 "
b111110110100100 (
b1000101101101010001110010101101 &
b100000 $
#1700
b1010110110001011001101110 !
b1010110110001011001101110 '
b1010110110001011001101110 +
b1000 .
0,
b10001 0
b1001 -
b10011001 #
b10011001 )
b111110101111010 *
b111110101111010 "
b111110101111010 (
b1101100101100100110001110000011 &
b100001 $
#1750
b1101111001101000101 !
b1101111001101000101 '
b1101111001101000101 +
b1000 .
0,
b10001 0
b1001 -
b110 #
b110 )
b111110111000010 *
b111110111000010 "
b111110111000010 (
b101011011110010101111111001001 &
b100010 $
#1800
b1101001111110000100110001 !
b1101001111110000100110001 '
b1101001111110000100110001 +
b1000 .
0,
b10001 0
b1001 -
b10101011 #
b10101011 )
b111110110010011 *
b111110110010011 "
b111110110010011 (
b11010001101100000000101011111111 &
b100011 $
#1850
b1001001011100111100001 !
b1001001011100111100001 '
b1001001011100111100001 +
b1000 .
0,
b10001 0
b1001 -
b1000011 #
b1000011 )
b111110100001011 *
b111110100001011 "
b111110100001011 (
b1100101111011000101101010100101 &
b100100 $
#1900
b1000001100100100001001 !
b1000001100100100001001 '
b1000001100100100001001 +
b1000 .
0,
b10001 0
b1001 -
b11010 #
b11010 )
b111110110111011 *
b111110110111011 "
b111110110111011 (
b1111001010110111010000000111011 &
b100101 $
#1950
b11110100100001110110101 !
b11110100100001110110101 '
b11110100100001110110101 +
b1000 .
0,
b10001 0
b1001 -
b1101111 #
b1101111 )
b111110101011011 *
b111110101011011 "
b111110101011011 (
b110011110100001110100101000001 &
b100110 $
#2000
b1011000000100101101011000 !
b1011000000100101101011000 '
b1011000000100101101011000 +
b1000 .
0,
b10001 0
b1001 -
b11000100 #
b11000100 )
b111110111000110 *
b111110111000110 "
b111110111000110 (
b11100010010100100101111100110111 &
b100111 $
#2050
b1000010011001111110111 !
b1000010011001111110111 '
b1000010011001111110111 +
b1000 .
0,
b10001 0
b1001 -
b11011 #
b11011 )
b111110101110100 *
b111110101110100 "
b111110101110100 (
b11110101111111011010011110011101 &
b101000 $
#2100
b1011011110111110010110 !
b1011011110111110010110 '
b1011011110111110010110 +
b1000 .
0,
b10001 0
b1001 -
b111101 #
b111101 )
b111110110100010 *
b111110110100010 "
b111110110100010 (
b11010110110110100001111110011 &
b101001 $
#2150
b1001001110000010011101 !
b1001001110000010011101 '
b1001001110000010011101 +
b1000 .
0,
b10001 0
b1001 -
b1000011 #
b1000011 )
b111110110011111 *
b111110110011111 "
b111110110011111 (
b1001101111110001111000110111001 &
b101010 $
#2200
b11111100111111110011011 !
b11111100111111110011011 '
b11111100111111110011011 +
b1000 .
0,
b10001 0
b1001 -
b1110111 #
b1110111 )
b111110110100100 *
b111110110100100 "
b111110110100100 (
b10001111111000110000101001101111 &
b101011 $
#2250
b1010100101001001000111100 !
b1010100101001001000111100 '
b1010100101001001000111100 +
b1000 .
0,
b10001 0
b1001 -
b10001000 #
b10001000 )
b111110100110101 *
b111110100110101 "
b111110100110101 (
b1101100010101001110001110010101 &
b101100 $
#2300
b1010001000011010100110001 !
b1010001000011010100110001 '
b1010001000011010100110001 +
b1000 .
0,
b10001 0
b1001 -
b10000011 #
b10000011 )
b111110110100110 *
b111110110100110 "
b111110110100110 (
b1101110000010111010101011 &
b101101 $
#2350
b1011011110101000011111 !
b1011011110101000011111 '
b1011011110101000011111 +
b1000 .
0,
b10001 0
b1001 -
b111101 #
b111101 )
b111110110001011 *
b111110110001011 "
b111110110001011 (
b11101010110010110101100100110001 &
b101110 $
#2400
b1101001000111101100000111 !
b1101001000111101100000111 '
b1101001000111101100000111 +
b1000 .
0,
b10001 0
b1001 -
b10101101 #
b10101101 )
b111110100000011 *
b111110100000011 "
b111110100000011 (
b1011010100001101110110010100111 &
b101111 $
#2450
b11001010111110000101100 !
b11001010111110000101100 '
b11001010111110000101100 +
b1000 .
0,
b10001 0
b1001 -
b101100 #
b101100 )
b111110100000001 *
b111110100000001 "
b111110100000001 (
b1001110000110011110111010001101 &
b110000 $
#2500
b111100010110101000000 !
b111100010110101000000 '
b111100010110101000000 +
b1000 .
0,
b10001 0
b1001 -
b11101 #
b11101 )
b111110101010100 *
b111110101010100 "
b111110101010100 (
b11100010100101010100000001100011 &
b110001 $
#2550
b1011101011000110010011 !
b1011101011000110010011 '
b1011101011000110010011 +
b1000 .
0,
b10001 0
b1001 -
b1010111 #
b1010111 )
b111110110011100 *
b111110110011100 "
b111110110011100 (
b1011100111011111111110101001 &
b110010 $
#2600
b1100100000101000000101000 !
b1100100000101000000101000 '
b1100100000101000000101000 +
b1000 .
0,
b10001 0
b1001 -
b10100100 #
b10100100 )
b111110101010110 *
b111110101010110 "
b111110101010110 (
b1110001111101110010111011111 &
b110011 $
#2650
b1011011001101101111101011 !
b1011011001101101111101011 '
b1011011001101101111101011 +
b1000 .
0,
b10001 0
b1001 -
b10111101 #
b10111101 )
b111110111000111 *
b111110111000111 "
b111110111000111 (
b10101110101100001010100010000101 &
b110100 $
#2700
b1100100111010100001111011 !
b1100100111010100001111011 '
b1100100111010100001111011 +
b1000 .
0,
b10001 0
b1001 -
b10100011 #
b10100011 )
b111110100011001 *
b111110100011001 "
b111110100011001 (
b11100001101100010101100100011011 &
b110101 $
#2750
b10111001110110111111001 !
b10111001110110111111001 '
b10111001110110111111001 +
b1000 .
0,
b10001 0
b1001 -
b110011 #
b110011 )
b111110100100011 *
b111110100100011 "
b111110100100011 (
b1111001110000101100010100100001 &
b110110 $
#2800
b1111010010101001001100 !
b1111010010101001001100 '
b1111010010101001001100 +
b1000 .
0,
b10001 0
b1001 -
b1011100 #
b1011100 )
b111110110011100 *
b111110110011100 "
b111110110011100 (
b10100110011001111101011000010111 &
b110111 $
#2850
b100101010011100001101 !
b100101010011100001101 '
b100101010011100001101 +
b1000 .
0,
b10001 0
b1001 -
b11110 #
b11110 )
b111110100010010 *
b111110100010010 "
b111110100010010 (
b10011111001110001111000101111101 &
b111000 $
#2900
b111011100010001101100 !
b111011100010001101100 '
b111011100010001101100 +
b1000 .
0,
b10001 0
b1001 -
b11100 #
b11100 )
b111110110110100 *
b111110110110100 "
b111110110110100 (
b1101110011001110101100011010011 &
b111001 $
#2950
b1100100000011000100111000 !
b1100100000011000100111000 '
b1100100000011000100111000 +
b1000 .
0,
b10001 0
b1001 -
b10100100 #
b10100100 )
b111110100101010 *
b111110100101010 "
b111110100101010 (
b11101110000001111000100110011001 &
b111010 $
#3000
b10101001010110011101101 !
b10101001010110011101101 '
b10101001010110011101101 +
b1000 .
0,
b10001 0
b1001 -
b100010 #
b100010 )
b111110101011111 *
b111110101011111 "
b111110101011111 (
b10100001001110101001110101001111 &
b111011 $
#3050
b1100110000101001011001000 !
b1100110000101001011001000 '
b1100110000101001011001000 +
b1000 .
0,
b10001 0
b1001 -
b10110100 #
b10110100 )
b111110110011110 *
b111110110011110 "
b111110110011110 (
b10001110000011101010100101110101 &
b111100 $
#3100
b101100101100100100111 !
b101100101100100100111 '
b101100101100100100111 +
b1000 .
0,
b10001 0
b1001 -
b1101 #
b1101 )
b111110100000011 *
b111110100000011 "
b111110100000011 (
b10001110101011100001111110001011 &
b111101 $
#3150
b11000111001101000101100 !
b11000111001101000101100 '
b11000111001101000101100 +
b1000 .
0,
b10001 0
b1001 -
b101000 #
b101000 )
b111110110000001 *
b111110110000001 "
b111110110000001 (
b101000001101100010110100010001 &
b111110 $
#3200
b10101101011010000111 !
b10101101011010000111 '
b10101101011010000111 +
b1000 .
0,
b10001 0
b1001 -
b1110 #
b1110 )
b111110100001001 *
b111110100001001 "
b111110100001001 (
b11000011010011000001101110000111 &
b111111 $
#3250
b1010111111101001101100100 !
b1010111111101001101100100 '
b1010111111101001101100100 +
b1000 .
0,
b10001 0
b1001 -
b11000100 #
b11000100 )
b111110100101001 *
b111110100101001 "
b111110100101001 (
b10010110010010011011000001101101 &
b1000000 $
#3300
b1011000001001111000000110 !
b1011000001001111000000110 '
b1011000001001111000000110 +
b1000 .
0,
b10001 0
b1001 -
b11000101 #
b11000101 )
b111110110001110 *
b111110110001110 "
b111110110001110 (
b10011010100110001000110101000011 &
b1000001 $
#3350
b10100100000110111101 !
b10100100000110111101 '
b10100100000110111101 +
b1000 .
0,
b10001 0
b1001 -
b10101 #
b10101 )
b111110100001001 *
b111110100001001 "
b111110100001001 (
b11110110100101001000111110001001 &
b1000010 $
#3400
b11111100000011100001101 !
b11111100000011100001101 '
b11111100000011100001101 +
b1000 .
0,
b10001 0
b1001 -
b1110110 #
b1110110 )
b111110110111111 *
b111110110111111 "
b111110110111111 (
b1001011000011010011000010111111 &
b1000011 $
#3450
b10000011110011100110101 !
b10000011110011100110101 '
b10000011110011100110101 +
b1000 .
0,
b10001 0
b1001 -
b1111110 #
b1111110 )
b111110110001011 *
b111110110001011 "
b111110110001011 (
b10111111001111011110011001100101 &
b1000100 $
#3500
b11101101010010100001101 !
b11101101010010100001101 '
b11101101010010100001101 +
b1000 .
0,
b10001 0
b1001 -
b1100111 #
b1100111 )
b111110110111111 *
b111110110111111 "
b111110110111111 (
b1100111110101011000000111111011 &
b1000101 $
#3550
b1011011101111010001010101 !
b1011011101111010001010101 '
b1011011101111010001010101 +
b1000 .
0,
b10001 0
b1001 -
b10111010 #
b10111010 )
b111110100101111 *
b111110100101111 "
b111110100101111 (
b101101011001001001000100000001 &
b1000110 $
#3600
b1101000100001111110000100 !
b1101000100001111110000100 '
b1101000100001111110000100 +
b1000 .
0,
b10001 0
b1001 -
b10101000 #
b10101000 )
b111110100100011 *
b111110100100011 "
b111110100100011 (
b10010100010010101011110011110111 &
b1000111 $
#3650
b1100110011010001111100111 !
b1100110011010001111100111 '
b1100110011010001111100111 +
b1000 .
0,
b10001 0
b1001 -
b10101111 #
b10101111 )
b111110101001000 *
b111110101001000 "
b111110101001000 (
b101011111110110010101101011101 &
b1001000 $
#3700
b1010010111000011100011011 !
b1010010111000011100011011 '
b1010010111000011100011011 +
b1000 .
0,
b10001 0
b1001 -
b10010010 #
b10010010 )
b111110110011001 *
b111110110011001 "
b111110110011001 (
b11100101001011111101110110110011 &
b1001001 $
#3750
b1100100000101000000101000 !
b1100100000101000000101000 '
b1100100000101000000101000 +
b1000 .
0,
b10001 0
b1001 -
b10100100 #
b10100100 )
b111110101010110 *
b111110101010110 "
b111110101010110 (
b10001110011001000001000101111001 &
b1001010 $
#3800
b1100110011101010100011111 !
b1100110011101010100011111 '
b1100110011101010100011111 +
b1000 .
0,
b10001 0
b1001 -
b10101111 #
b10101111 )
b111110110010000 *
b111110110010000 "
b111110110010000 (
b101011101011011010000000101111 &
b1001011 $
#3850
b11100010110001010111110 !
b11100010110001010111110 '
b11100010110001010111110 +
b1000 .
0,
b10001 0
b1001 -
b1100101 #
b1100101 )
b111110101010110 *
b111110101010110 "
b111110101010110 (
b111010110011010101111101010101 &
b1001100 $
#3900
b1000010100111101011100 !
b1000010100111101011100 '
b1000010100111101011100 +
b1000 .
0,
b10001 0
b1001 -
b1000100 #
b1000100 )
b111110101100111 *
b111110101100111 "
b111110101100111 (
b100110000011101000000001101011 &
b1001101 $
#3950
b1101000100111100000111100 !
b1101000100111100000111100 '
b1101000100111100000111100 +
b1000 .
0,
b10001 0
b1001 -
b10101000 #
b10101000 )
b111110110101101 *
b111110110101101 "
b111110110101101 (
b10100000010011001111000011110001 &
b1001110 $
#4000
b1111001111001000111100 !
b1111001111001000111100 '
b1111001111001000111100 +
b1000 .
0,
b10001 0
b1001 -
b1011100 #
b1011100 )
b111110100010101 *
b111110100010101 "
b111110100010101 (
b1010010001110101011101001100111 &
b1001111 $
#4050
b10100000010101000110101 !
b10100000010101000110101 '
b10100000010101000110101 +
b1000 .
0,
b10001 0
b1001 -
b100001 #
b100001 )
b111110101000101 *
b111110101000101 "
b111110101000101 (
b10010100101111000110001001001101 &
b1010000 $
#4100
b11010101001010010011 !
b11010101001010010011 '
b11010101001010010011 +
b1000 .
0,
b10001 0
b1001 -
b10011 #
b10011 )
b111110110011100 *
b111110110011100 "
b111110110011100 (
b11011101111101000100101000100011 &
b1010001 $
#4150
b1100110000100000110000100 !
b1100110000100000110000100 '
b1100110000100000110000100 +
b1000 .
0,
b10001 0
b1001 -
b10110100 #
b10110100 )
b111110110000101 *
b111110110000101 "
b111110110000101 (
b1110110010101010000111101101001 &
b1010010 $
#4200
b11011111010111111000110 !
b11011111010111111000110 '
b11011111010111111000110 +
b1000 .
0,
b10001 0
b1001 -
b1100001 #
b1100001 )
b111110110110110 *
b111110110110110 "
b111110110110110 (
b11110000110100101110101110011111 &
b1010011 $
#4250
b1110000100011001001111 !
b1110000100011001001111 '
b1110000100011001001111 +
b1000 .
0,
b10001 0
b1001 -
b1001010 #
b1001010 )
b111110101111100 *
b111110101111100 "
b111110101111100 (
b101101000011000001010001000101 &
b1010100 $
#4300
b1010100101010011011110100 !
b1010100101010011011110100 '
b1010100101010011011110100 +
b1000 .
0,
b10001 0
b1001 -
b10001000 #
b10001000 )
b111110101001111 *
b111110101001111 "
b111110101001111 (
b1001100000000000001101011011011 &
b1010101 $
#4350
b1011100111110110010111 !
b1011100111110110010111 '
b1011100111110110010111 +
b1000 .
0,
b10001 0
b1001 -
b1010111 #
b1010111 )
b111110100001000 *
b111110100001000 "
b111110100001000 (
b1100111101011100100110011100001 &
b1010110 $
#4400
b1100111010110000110101101 !
b1100111010110000110101101 '
b1100111010110000110101101 +
b1000 .
0,
b10001 0
b1001 -
b10110111 #
b10110111 )
b111110100001010 *
b111110100001010 "
b111110100001010 (
b11111011101100110001001111010111 &
b1010111 $
#4450
b10110000000110001010100 !
b10110000000110001010100 '
b10110000000110001010100 +
b1000 .
0,
b10001 0
b1001 -
b110001 #
b110001 )
b111110110100100 *
b111110110100100 "
b111110110100100 (
b110000101111000101010100111101 &
b1011000 $
#4500
b1011010111100011111100 !
b1011010111100011111100 '
b1011010111100011111100 +
b1000 .
0,
b10001 0
b1001 -
b111100 #
b111100 )
b111110111000000 *
b111110111000000 "
b111110111000000 (
b10010110011011001101001010010011 &
b1011001 $
#4550
b10101101001101100111011 !
b10101101001101100111011 '
b10101101001101100111011 +
b1000 .
0,
b10001 0
b1001 -
b100110 #
b100110 )
b111110110000100 *
b111110110000100 "
b111110110000100 (
b10110111000001101000100101011001 &
b1011010 $
#4600
b1010011000001010110010111 !
b1010011000001010110010111 '
b1010011000001010110010111 +
b1000 .
0,
b10001 0
b1001 -
b10010011 #
b10010011 )
b111110110101101 *
b111110110101101 "
b111110110101101 (
b1000101111101000001001100001111 &
b1011011 $
#4650
b11100001110001010010000 !
b11100001110001010010000 '
b11100001110001010010000 +
b1000 .
0,
b10001 0
b1001 -
b1100100 #
b1100100 )
b111110101001000 *
b111110101001000 "
b111110101001000 (
b11100110000010010000010100110101 &
b1011100 $
#4700
b11111010011011100 !
b11111010011011100 '
b11111010011011100 +
b1000 .
0,
b10001 0
b1001 -
b100 #
b100 )
b111110100110111 *
b111110100110111 "
b111110100110111 (
b10010110000100010101000101001011 &
b1011101 $
#4750
b11111010111110000 !
b11111010111110000 '
b11111010111110000 +
b1000 .
0,
b10001 0
b1001 -
b111110101111100 *
b111110101111100 "
b111110101111100 (
b101010000001111010010011010001 &
b1011110 $
#4800
b11001100100111111111 !
b11001100100111111111 '
b11001100100111111111 +
b1000 .
0,
b10001 0
b1001 -
b10010 #
b10010 )
b111110100000000 *
b111110100000000 "
b111110100000000 (
b11000101000010101100100101000111 &
b1011111 $
#4850
b1100110011011001011110001 !
b1100110011011001011110001 '
b1100110011011001011110001 +
b1000 .
0,
b10001 0
b1001 -
b10101111 #
b10101111 )
b111110101011110 *
b111110101011110 "
b111110101011110 (
b1111011111010100000010000101101 &
b1100000 $
#4900
b10000000111110101011011 !
b10000000111110101011011 '
b10000000111110101011011 +
b1000 .
0,
b10001 0
b1001 -
b1011011 #
b1011011 )
b111110100110001 *
b111110100110001 "
b111110100110001 (
b10001111000000111011100000011 &
b1100001 $
#4950
b111110101100011 !
b111110101100011 '
b111110101100011 +
b1000 .
0,
b10001 0
b1001 -
b1 #
b1 )
b111110101100011 *
b111110101100011 "
b111110101100011 (
b10010000110101110111111101001001 &
b1100010 $
#5000
b1100011100011000110010000 !
b1100011100011000110010000 '
b1100011100011000110010000 +
b1000 .
0,
b10001 0
b1001 -
b10100000 #
b10100000 )
b111110100011010 *
b111110100011010 "
b111110100011010 (
b1000100010010000001011001111111 &
b1100011 $
#5050
b1000001000111111000001011100101 !
b1000001000111111000001011100101 '
b1000001000111111000001011100101 +
0,
b1000 .
b10001 0
b1001 -
b11010110010011 #
b11010110010011 )
b10000010 *
b10000010 "
b10000010 (
b11001001100100110011001000100101 &
b0 $
