ABM-M1-Karatsuba-bitwise-64/radix4approx34bit.v
`timescale 10ms / 1ms

module radix4approx34bit(p,x,y);         

parameter N = 34;   //size of muliplicant and multiplier
parameter K = N/2;  //

input   [N-1 : 0]   x,y;
output  [N+N-1:0]   p;

reg [2:0]   bits    [K:0];
reg   neg     [K:0];
reg   two     [K:0];
reg   zero     [K:0];

wire [N+1:0] x_new;
reg [N+1:0]       PP      [K:0]; //riyaj 
reg [N+N-1:0]   ACC     [K:0];
reg [N+N-1:0]   ANS;
reg mux;

integer i , j, t;
integer  m = 24;        //number of bits to approximate

assign x_new = {2'b0,x};

always@(*)

begin
    bits[0] = {y[1],y[0],1'b0};             //setting last bit -1 as 0

    for(i=1; i<K+1; i=i+1) begin
            if(i == K)
                bits[i] = {2'b0,y[2*i-1]};
            else
                bits[i] = {y[2*i+1], y[2*i], y[2*i-1]};
            //$display("%b", bits[i]);
            
        end


    for(i=0; i<K+1; i=i+1)
        begin                               //approximated 2A as A introduced error
            case(bits[i])

            
            3'b001, 3'b010:         
            begin
                neg[i] = 1'b0;
                two[i] = 1'b0;
                zero[i] = 1'b0;
            end

            3'b011:
            begin
                neg[i] = 1'b0;
                two[i] = 1'b1;
                zero[i] = 1'b0;
            end

            3'b101, 3'b110:         
            begin 
               neg[i] = 1'b1;
                two[i] = 1'b0;
                zero[i] = 1'b0;
            end

            3'b100:
            begin
                neg[i] = 1'b1;
                two[i] = 1'b1;
                zero[i] = 1'b0;
            end
         
            default: 
            begin
                neg[i] = 1'b0;
                two[i] = 1'b0;
                zero[i] = 1'b1;
            end

            endcase

            PP[i] = 0;
            PP[i][N+1] = neg[i];           //sign conservation

            for(t=0; t<N+1; t=t+1) begin
                if(t>=m) 
                begin
                    mux = (x_new[t] & ~two[i]) | (x_new[t-1] & two[i]);             
                    PP[i][t] = ~zero[i] & (neg[i] ^ mux);
                end

                else 
                begin
                    PP[i][t] = (~x_new[t] & neg[i]) | (x_new[t] & ~neg[i] & ~zero[i]);
                end
            end

            PP[i][0] = PP[i][0] | neg[i];

            ACC[i] = $signed(PP[i]);        //sign extension
            
            for(j=0; j<i; j=j+1)
                ACC[i] = {ACC[i],2'b00};        //shifting

        
        end

    ANS = ACC[0];

    for(i=1; i<K+1; i=i+1)
        ANS = ANS+ACC[i];
        
end


assign p = ANS;

endmodule

ABM-M1-Karatsuba-bitwise-64/adder8.v
`timescale 10ms / 1ms

module adder8(s,a,b);

input [31:0] a,b;

output [32:0] s;


assign s = a+b;

endmodule

ABM-M1-Karatsuba-bitwise-64/radix4approx.v
`timescale 10ms / 1ms

module radix4approx(p,x,y);         //8 bit multiplier to give 16 bit product

parameter N = 32;   //size of muliplicant and multiplier
parameter K = N/2;  //

input   [N-1 : 0]   x,y;
output  [N+N-1:0]   p;

reg [2:0]   bits    [K:0];
reg   neg     [K:0];
reg   two     [K:0];
reg   zero     [K:0];

wire [N+1:0] x_new;
reg [N+1:0]       PP      [K:0]; //riyaj 
reg [N+N-1:0]   ACC     [K:0];
reg [N+N-1:0]   ANS;
reg mux;

integer i , j, t;
integer  m = 24;        //number of bits to approximate

assign x_new = {2'b0,x};

always@(*)

begin
    bits[0] = {y[1],y[0],1'b0};             //setting last bit -1 as 0

    for(i=1; i<K+1; i=i+1) begin
            if(i == K)
                bits[i] = {2'b0,y[2*i-1]};
            else
                bits[i] = {y[2*i+1], y[2*i], y[2*i-1]};
            //$display("%b", bits[i]);
            
        end


    for(i=0; i<K+1; i=i+1)
        begin                               //approximated 2A as A introduced error
            case(bits[i])

            
            3'b001, 3'b010:         
            begin
                neg[i] = 1'b0;
                two[i] = 1'b0;
                zero[i] = 1'b0;
            end

            3'b011:
            begin
                neg[i] = 1'b0;
                two[i] = 1'b1;
                zero[i] = 1'b0;
            end

            3'b101, 3'b110:         
            begin 
               neg[i] = 1'b1;
                two[i] = 1'b0;
                zero[i] = 1'b0;
            end

            3'b100:
            begin
                neg[i] = 1'b1;
                two[i] = 1'b1;
                zero[i] = 1'b0;
            end
         
            default: 
            begin
                neg[i] = 1'b0;
                two[i] = 1'b0;
                zero[i] = 1'b1;
            end

            endcase

            PP[i] = 0;
            PP[i][N+1] = neg[i];           //sign conservation

            for(t=0; t<N+1; t=t+1) begin
                if(t>=m) 
                begin
                    mux = (x_new[t] & ~two[i]) | (x_new[t-1] & two[i]);             
                    PP[i][t] = ~zero[i] & (neg[i] ^ mux);
                end

                else 
                begin
                    PP[i][t] = (~x_new[t] & neg[i]) | (x_new[t] & ~neg[i] & ~zero[i]);
                end
            end

            PP[i][0] = PP[i][0] | neg[i];

            ACC[i] = $signed(PP[i]);        //sign extension
            
            for(j=0; j<i; j=j+1)
                ACC[i] = {ACC[i],2'b00};        //shifting

        
        end

    ANS = ACC[0];

    for(i=1; i<K+1; i=i+1)
        ANS = ANS+ACC[i];
        
end


assign p = ANS;

endmodule

ABM-M1-Karatsuba-bitwise-64/radix4acc.v
`timescale 10ms / 1ms

module radix4acc(p,x,y);         //8 bit multiplier to give 16 bit product

parameter N = 32;   //size of muliplicant and multiplier
parameter K = N/2;  //

input [N-1 : 0]   x,y;
output [N+N-1:0]   p;

reg [2:0]   bits    [K:0];
reg   neg     [K:0];
reg   two     [K:0];
reg   zero     [K:0];

wire [N+1:0] x_new;
reg [N+1:0]       PP      [K:0]; //riyaj 
reg [N+N-1:0]   ACC     [K:0];
reg [N+N-1:0]   ANS;
reg mux;

integer i , j, t;

assign x_new = {2'b0,x};

always@(*)

begin
    bits[0] = {y[1],y[0],1'b0};             //setting last bit -1 as 0
    //$display("%b", bits[0]);
    for(i=1; i<K+1; i=i+1) begin
        if(i == K)
            bits[i] = {2'b0,y[2*i-1]};
        else
            bits[i] = {y[2*i+1], y[2*i], y[2*i-1]};
        //$display("%b", bits[i]);
        
    end

    for(i=0; i<K+1; i=i+1)
        begin                                      //accurate cases
            case(bits[i])

            
            3'b001, 3'b010:         
            begin
                neg[i] = 1'b0;
                two[i] = 1'b0;
                zero[i] = 1'b0;
            end

            3'b011:
            begin
                neg[i] = 1'b0;
                two[i] = 1'b1;
                zero[i] = 1'b0;
            end

            3'b101, 3'b110:         
            begin 
               neg[i] = 1'b1;
                two[i] = 1'b0;
                zero[i] = 1'b0;
            end

            3'b100:
            begin
                neg[i] = 1'b1;
                two[i] = 1'b1;
                zero[i] = 1'b0;
            end
         
            default: 
            begin
                neg[i] = 1'b0;
                two[i] = 1'b0;
                zero[i] = 1'b1;
            end

            endcase
            
            //$display("%b %b %b", neg[i], two[i], zero[i]);
            
            PP[i] = 0;
            PP[i][N+1] = neg[i];           //sign conservation

            for(t=0; t<N+1; t=t+1) begin
                if(t==0) 
                    mux = (x_new[t] & ~two[i]) | (1'b0 & two[i]);
                
                else
                    mux = (x_new[t] & ~two[i]) | (x_new[t-1] & two[i]);

                
                PP[i][t] = ~zero[i] & (neg[i] ^ mux);       
            end

            PP[i] = PP[i] + neg[i];             //correction term added
            
            //$display("%b", PP[i]);

            ACC[i] = $signed(PP[i]);        //sign extension
            //$display("%b", ACC[i]);

            for(j=0; j<i; j=j+1)
                ACC[i] = {ACC[i],2'b00};        //shifting

        
        end

    ANS = ACC[0];

    for(i=1; i<K+1; i=i+1)
        ANS = ANS+ACC[i];
        
    
end


assign p = ANS;

endmodule

ABM-M1-Karatsuba-bitwise-64/karatsuba64.v
`timescale 10ms/1ms
`include "radix4acc.v"
`include "radix4approx.v"
`include "radix4approx34bit.v"
`include "adder8.v"

module karatsuba64(P,A,B);


parameter N = 64;   //size of muliplicant and multiplier
parameter K = N/2;  //

input   [N-1 : 0]   A,B;
output  [N+N-1:0]   P;

wire [K-1:0] AH, AL, BH, BL;

wire reg    [N-1:0]     M1, M2;
wire reg    [K:0]       S1, S2;
wire reg    [33:0]       c,d;
wire reg    [67:0]      M3;

reg [67:0] M4, M5, M6;

reg     [67:0]   A1, A2, A3;


reg [N+N-1:0]   ACC     [2:0];
reg [N+N-1:0] ANS;
integer i;


assign AH = A[N-1:K];
assign AL = A[K-1:0];

assign BH = B[N-1:K];
assign BL = B[K-1:0];



radix4acc ACC1(.p(M1), .x(AH), .y(BH));
radix4approx APP1(.p(M2), .x(AL), .y(BL));


adder8 ADD1(.s(S1), .a(AH), .b(AL));
adder8 ADD2(.s(S2), .a(BH), .b(BL));

assign c = (S1);
assign d = (S2);

radix4approx34bit APP2(.p(M3), .x(c), .y(d));


always@(*)
begin
    
    M4 = $signed(M1);
    M5 = $signed(M2);
    
    M6 = M3 - M4 - M5;

    ACC[0] = $signed(M6);
    ACC[0] = {ACC[0], {32{1'b0}}};

    ACC[1] = $signed(M2);
    
    ACC[2] = $signed(M1);
    ACC[2] = {ACC[2], {64{1'b0}}};

    ANS = ACC[0];
    for(i=1; i<3; i=i+1)
        ANS = ANS+ACC[i];
end

assign P = ANS;

endmodule

ABM-M1-Karatsuba-bitwise-64/karatsuba64_tb.v
`timescale 10ms / 1ms
`include "karatsuba64.v"

module karatsuba64_tb();

reg unsigned [63:0] A,B;
wire unsigned [127:0] P;
integer i, out, seed=7;


karatsuba64 uut(P,A,B);


initial begin
    $dumpfile("karatsuba64.vcd");
    $dumpvars(0, karatsuba64_tb);
    out = $fopen("karatsuba_output.csv");
    
    for(i=0; i<500; i=i+1)
    begin
        A = {2{$urandom(seed)}};
        B = {2{$urandom(seed)}};
        #1;
        $fwrite(out, "%d, %d, %d\n", A,B,P);
        #4;
    end
    
    $finish;
end




endmodule

ABM-M1-Karatsuba-bitwise-64/karatsuba64.vcd
$date
	Fri Jul  9 14:03:04 2021
$end
$version
	Icarus Verilog
$end
$timescale
	1ms
$end
$scope module karatsuba64_tb $end
$var wire 128 ! P [127:0] $end
$var reg 64 " A [63:0] $end
$var reg 64 # B [63:0] $end
$var integer 32 $ i [31:0] $end
$var integer 32 % out [31:0] $end
$var integer 32 & seed [31:0] $end
$scope module uut $end
$var wire 64 ' A [63:0] $end
$var wire 64 ( B [63:0] $end
$var wire 128 ) P [127:0] $end
$var wire 34 * d [33:0] $end
$var wire 34 + c [33:0] $end
$var wire 33 , S2 [32:0] $end
$var wire 33 - S1 [32:0] $end
$var wire 68 . M3 [67:0] $end
$var wire 64 / M2 [63:0] $end
$var wire 64 0 M1 [63:0] $end
$var wire 32 1 BL [31:0] $end
$var wire 32 2 BH [31:0] $end
$var wire 32 3 AL [31:0] $end
$var wire 32 4 AH [31:0] $end
$var reg 128 5 ANS [127:0] $end
$var reg 68 6 M4 [67:0] $end
$var reg 68 7 M5 [67:0] $end
$var reg 68 8 M6 [67:0] $end
$var integer 32 9 i [31:0] $end
$scope module ACC1 $end
$var wire 64 : p [63:0] $end
$var wire 32 ; x [31:0] $end
$var wire 32 < y [31:0] $end
$var wire 34 = x_new [33:0] $end
$var reg 64 > ANS [63:0] $end
$var reg 1 ? mux $end
$var integer 32 @ i [31:0] $end
$var integer 32 A j [31:0] $end
$var integer 32 B t [31:0] $end
$upscope $end
$scope module ADD1 $end
$var wire 32 C a [31:0] $end
$var wire 32 D b [31:0] $end
$var wire 33 E s [32:0] $end
$upscope $end
$scope module ADD2 $end
$var wire 32 F a [31:0] $end
$var wire 32 G b [31:0] $end
$var wire 33 H s [32:0] $end
$upscope $end
$scope module APP1 $end
$var wire 64 I p [63:0] $end
$var wire 32 J x [31:0] $end
$var wire 32 K y [31:0] $end
$var wire 34 L x_new [33:0] $end
$var reg 64 M ANS [63:0] $end
$var reg 1 N mux $end
$var integer 32 O i [31:0] $end
$var integer 32 P j [31:0] $end
$var integer 32 Q m [31:0] $end
$var integer 32 R t [31:0] $end
$upscope $end
$scope module APP2 $end
$var wire 68 S p [67:0] $end
$var wire 34 T x [33:0] $end
$var wire 34 U y [33:0] $end
$var wire 36 V x_new [35:0] $end
$var reg 68 W ANS [67:0] $end
$var reg 1 X mux $end
$var integer 32 Y i [31:0] $end
$var integer 32 Z j [31:0] $end
$var integer 32 [ m [31:0] $end
$var integer 32 \ t [31:0] $end
$upscope $end
$upscope $end
$upscope $end
$enddefinitions $end
#0
$dumpvars
b100011 \
b11000 [
b10001 Z
b10010 Y
0X
b1011110100000000000000010111111110001110111011111100 W
b11101100010000000000 V
b110001100110110001001011100011000 U
b11101100010000000000 T
b1011110100000000000000010111111110001110111011111100 S
b100001 R
b11000 Q
b10000 P
b10001 O
0N
b101101000001110110011000110100001000001001110111100 M
b1110110001000000000 L
b11000110011011000100101110001100 K
b1110110001000000000 J
b101101000001110110011000110100001000001001110111100 I
b110001100110110001001011100011000 H
b11000110011011000100101110001100 G
b11000110011011000100101110001100 F
b11101100010000000000 E
b1110110001000000000 D
b1110110001000000000 C
b100001 B
b10000 A
b10001 @
0?
b101101110001110101110000101101111111001100000000000 >
b1110110001000000000 =
b11000110011011000100101110001100 <
b1110110001000000000 ;
b101101110001110101110000101101111111001100000000000 :
b11 9
b11101100010011111001011101101010100001101000000 8
b101101000001110110011000110100001000001001110111100 7
b101101110001110101110000101101111111001100000000000 6
b1011011100011101011100001011100000000001110001001111100101110111010111001000010110011000110100001000001001110111100 5
b1110110001000000000 4
b1110110001000000000 3
b11000110011011000100101110001100 2
b11000110011011000100101110001100 1
b101101110001110101110000101101111111001100000000000 0
b101101000001110110011000110100001000001001110111100 /
b1011110100000000000000010111111110001110111011111100 .
b11101100010000000000 -
b110001100110110001001011100011000 ,
b11101100010000000000 +
b110001100110110001001011100011000 *
b1011011100011101011100001011100000000001110001001111100101110111010111001000010110011000110100001000001001110111100 )
b1100011001101100010010111000110011000110011011000100101110001100 (
b111011000100000000000000000000001110110001000000000 '
b11000110011011000100100011101101 &
b10 %
b0 $
b1100011001101100010010111000110011000110011011000100101110001100 #
b111011000100000000000000000000001110110001000000000 "
b1011011100011101011100001011100000000001110001001111100101110111010111001000010110011000110100001000001001110111100 !
$end
#50
b11 9
b1110110000110111110011101111010011000110001111010011110111101011111101111110001111000011001011010110010011111001101111110110100 !
b1110110000110111110011101111010011000110001111010011110111101011111101111110001111000011001011010110010011111001101111110110100 )
b1110110000110111110011101111010011000110001111010011110111101011111101111110001111000011001011010110010011111001101111110110100 5
b1110110000111100101001001001110110000101110101011011100011100000 8
b111011000011100001010001011011010110010011111001101111110110100 7
b111011000011011111001110111100101110110111000011111101001011000 6
b111011000011011111001110111100101110110111000011111101001011000 0
b111011000011011111001110111100101110110111000011111101001011000 :
b111011000011011111001110111100101110110111000011111101001011000 >
b10000 A
0?
b100001 B
b10001 @
b11101100001110100101101001100110110101111001101001001001011101100 .
b11101100001110100101101001100110110101111001101001001001011101100 S
b11101100001110100101101001100110110101111001101001001001011101100 W
b10001 Z
0X
b100011 \
b10010 Y
b111011000011100001010001011011010110010011111001101111110110100 /
b111011000011100001010001011011010110010011111001101111110110100 I
b111011000011100001010001011011010110010011111001101111110110100 M
b10000 P
0N
b100001 R
b10001 O
b10101110011011011111101101011100 2
b10101110011011011111101101011100 <
b10101110011011011111101101011100 F
b101011100110110111111011010111000 *
b101011100110110111111011010111000 U
b101011100110110111111011010111000 ,
b101011100110110111111011010111000 H
b10101110011011011111101101011100 1
b10101110011011011111101101011100 G
b10101110011011011111101101011100 K
b10101101010101110111000101011010 =
b10101101010101110111000101011010 4
b10101101010101110111000101011010 ;
b10101101010101110111000101011010 C
b101011010101011101110001010110100 V
b101011010101011101110001010110100 +
b101011010101011101110001010110100 T
b101011010101011101110001010110100 -
b101011010101011101110001010110100 E
b10101101010101110111000101011010 L
b10101101010101110111000101011010 3
b10101101010101110111000101011010 D
b10101101010101110111000101011010 J
b1010111001101101111110110101110010101110011011011111101101011100 #
b1010111001101101111110110101110010101110011011011111101101011100 (
b1010110101010111011100010101101010101101010101110111000101011010 "
b1010110101010111011100010101101010101101010101110111000101011010 '
b10101110011011011111100111000011 &
b1 $
#100
b11 9
b110001111011000110101111100001110000100101110101111111000110000101010000101011100010000000110101011100100110100101101001110101 !
b110001111011000110101111100001110000100101110101111111000110000101010000101011100010000000110101011100100110100101101001110101 )
b110001111011000110101111100001110000100101110101111111000110000101010000101011100010000000110101011100100110100101101001110101 5
b110001111010100000110111011001100100010001111110001101110101111 8
b11000111101100011011000101111001011100100110100101101001110101 7
b11000111101100011010111110000101011110100010010110001101100101 6
b11000111101100011010111110000101011110100010010110001101100101 0
b11000111101100011010111110000101011110100010010110001101100101 :
b11000111101100011010111110000101011110100010010110001101100101 >
b10000 A
0?
b100001 B
b10001 @
b1100011110101100111100111111001011011101011000101101100110001001 .
b1100011110101100111100111111001011011101011000101101100110001001 S
b1100011110101100111100111111001011011101011000101101100110001001 W
b10001 Z
0X
b100011 \
b10010 Y
b11000111101100011011000101111001011100100110100101101001110101 /
b11000111101100011011000101111001011100100110100101101001110101 I
b11000111101100011011000101111001011100100110100101101001110101 M
b10000 P
0N
b100001 R
b10001 O
b11001111110001011111001110011111 2
b11001111110001011111001110011111 <
b11001111110001011111001110011111 F
b110011111100010111110011100111110 *
b110011111100010111110011100111110 U
b110011111100010111110011100111110 ,
b110011111100010111110011100111110 H
b11001111110001011111001110011111 1
b11001111110001011111001110011111 G
b11001111110001011111001110011111 K
b111101100000101110101001111011 =
b111101100000101110101001111011 4
b111101100000101110101001111011 ;
b111101100000101110101001111011 C
b1111011000001011101010011110110 V
b1111011000001011101010011110110 +
b1111011000001011101010011110110 T
b1111011000001011101010011110110 -
b1111011000001011101010011110110 E
b111101100000101110101001111011 L
b111101100000101110101001111011 3
b111101100000101110101001111011 D
b111101100000101110101001111011 J
b1100111111000101111100111001111111001111110001011111001110011111 #
b1100111111000101111100111001111111001111110001011111001110011111 (
b11110110000010111010100111101100111101100000101110101001111011 "
b11110110000010111010100111101100111101100000101110101001111011 '
b11001111110001011111000000001001 &
b10 $
#150
b11 9
b111001110010010001111000011101101011011111001101001110110011101101111111010110110100001111111101100010001110000111110100 !
b111001110010010001111000011101101011011111001101001110110011101101111111010110110100001111111101100010001110000111110100 )
b111001110010010001111000011101101011011111001101001110110011101101111111010110110100001111111101100010001110000111110100 5
b111001110100001000100011100111010100110000110101011001100 8
b11100110111100000111011111111101100010001110000111110100 7
b11100111001001000111100001110100111010010100100011110100 6
b11100111001001000111100001110100111010010100100011110100 0
b11100111001001000111100001110100111010010100100011110100 :
b11100111001001000111100001110100111010010100100011110100 >
b10000 A
0?
b100001 B
b10001 @
b1110011100100110010011011110101101000010101001010110110100 .
b1110011100100110010011011110101101000010101001010110110100 S
b1110011100100110010011011110101101000010101001010110110100 W
b10001 Z
0X
b100011 \
b10010 Y
b11100110111100000111011111111101100010001110000111110100 /
b11100110111100000111011111111101100010001110000111110100 I
b11100110111100000111011111111101100010001110000111110100 M
b10000 P
0N
b100001 R
b10001 O
b10011100001010011000000100 2
b10011100001010011000000100 <
b10011100001010011000000100 F
b100111000010100110000001000 *
b100111000010100110000001000 U
b100111000010100110000001000 ,
b100111000010100110000001000 H
b10011100001010011000000100 1
b10011100001010011000000100 G
b10011100001010011000000100 K
b1011110101110101010111010111101 =
b1011110101110101010111010111101 4
b1011110101110101010111010111101 ;
b1011110101110101010111010111101 C
b10111101011101010101110101111010 V
b10111101011101010101110101111010 +
b10111101011101010101110101111010 T
b10111101011101010101110101111010 -
b10111101011101010101110101111010 E
b1011110101110101010111010111101 L
b1011110101110101010111010111101 3
b1011110101110101010111010111101 D
b1011110101110101010111010111101 J
b1001110000101001100000010000000010011100001010011000000100 #
b1001110000101001100000010000000010011100001010011000000100 (
b101111010111010101011101011110101011110101110101010111010111101 "
b101111010111010101011101011110101011110101110101010111010111101 '
b10011100001010010100111111 &
b11 $
#200
b11 9
b100110001111111001111011010100111110111000011011111001011110001011011100000110010110111100000111101101010000100111101001 !
b100110001111111001111011010100111110111000011011111001011110001011011100000110010110111100000111101101010000100111101001 )
b100110001111111001111011010100111110111000011011111001011110001011011100000110010110111100000111101101010000100111101001 5
b100110001110100011111110011100010010000101110111111111111 8
b10011001001010010111000000000111101101010000100111101001 7
b10011000111111100111101101010010101111000100100111101001 6
b10011000111111100111101101010010101111000100100111101001 0
b10011000111111100111101101010010101111000100100111101001 :
b10011000111111100111101101010010101111000100100111101001 >
b10000 A
0?
b100001 B
b10001 @
b1001100011111110011110100000111100101101000100001111010001 .
b1001100011111110011110100000111100101101000100001111010001 S
b1001100011111110011110100000111100101101000100001111010001 W
b10001 Z
0X
b100011 \
b10010 Y
b10011001001010010111000000000111101101010000100111101001 /
b10011001001010010111000000000111101101010000100111101001 I
b10011001001010010111000000000111101101010000100111101001 M
b10000 P
0N
b100001 R
b10001 O
b1110111101001000000000011 2
b1110111101001000000000011 <
b1110111101001000000000011 F
b11101111010010000000000110 *
b11101111010010000000000110 U
b11101111010010000000000110 ,
b11101111010010000000000110 H
b1110111101001000000000011 1
b1110111101001000000000011 G
b1110111101001000000000011 K
b1010001110101111000100010100011 =
b1010001110101111000100010100011 4
b1010001110101111000100010100011 ;
b1010001110101111000100010100011 C
b10100011101011110001000101000110 V
b10100011101011110001000101000110 +
b10100011101011110001000101000110 T
b10100011101011110001000101000110 -
b10100011101011110001000101000110 E
b1010001110101111000100010100011 L
b1010001110101111000100010100011 3
b1010001110101111000100010100011 D
b1010001110101111000100010100011 J
b111011110100100000000001100000001110111101001000000000011 #
b111011110100100000000001100000001110111101001000000000011 (
b101000111010111100010001010001101010001110101111000100010100011 "
b101000111010111100010001010001101010001110101111000100010100011 '
b1110111101000111011100101 &
b100 $
#250
b11 9
b100101110010001000001111010111100010110101011000000111000111110000001001010001100000010100110100010100010111111011111001101 !
b100101110010001000001111010111100010110101011000000111000111110000001001010001100000010100110100010100010111111011111001101 )
b100101110010001000001111010111100010110101011000000111000111110000001001010001100000010100110100010100010111111011111001101 5
b100101110110000011100110011111011011100100010001111110010111 8
b10010111001000100001001001010100010100010111111011111001101 7
b10010111001000100000111101011100111111101001011001001111100 6
b10010111001000100000111101011100111111101001011001001111100 0
b10010111001000100000111101011100111111101001011001001111100 :
b10010111001000100000111101011100111111101001011001001111100 >
b10000 A
0?
b100001 B
b10001 @
b1001011101000001011110111010101100110000100011100100111100000 .
b1001011101000001011110111010101100110000100011100100111100000 S
b1001011101000001011110111010101100110000100011100100111100000 W
b10001 Z
0X
b100011 \
b10010 Y
b10010111001000100001001001010100010100010111111011111001101 /
b10010111001000100001001001010100010100010111111011111001101 I
b10010111001000100001001001010100010100010111111011111001101 M
b10000 P
0N
b100001 R
b10001 O
b1101001110111000000000011010 2
b1101001110111000000000011010 <
b1101001110111000000000011010 F
b11010011101110000000000110100 *
b11010011101110000000000110100 U
b11010011101110000000000110100 ,
b11010011101110000000000110100 H
b1101001110111000000000011010 1
b1101001110111000000000011010 G
b1101001110111000000000011010 K
b1011011010111110001000010110110 =
b1011011010111110001000010110110 4
b1011011010111110001000010110110 ;
b1011011010111110001000010110110 C
b10110110101111100010000101101100 V
b10110110101111100010000101101100 +
b10110110101111100010000101101100 T
b10110110101111100010000101101100 -
b10110110101111100010000101101100 E
b1011011010111110001000010110110 L
b1011011010111110001000010110110 3
b1011011010111110001000010110110 D
b1011011010111110001000010110110 J
b110100111011100000000001101000001101001110111000000000011010 #
b110100111011100000000001101000001101001110111000000000011010 (
b101101101011111000100001011011001011011010111110001000010110110 "
b101101101011111000100001011011001011011010111110001000010110110 '
b1101001110110111111001111011 &
b101 $
#300
b11 9
b1101100000010010111110000101100011010101001101011010101110100010111001000110111111110111101010010010011001111100000000011011 !
b1101100000010010111110000101100011010101001101011010101110100010111001000110111111110111101010010010011001111100000000011011 )
b1101100000010010111110000101100011010101001101011010101110100010111001000110111111110111101010010010011001111100000000011011 5
b1101011100111001000101101100000100000101010100111110010011011 8
b110110011100100000101101111110010010011001111100000000011011 7
b110110000001001011111000010101110010011011000011011111100010 6
b110110000001001011111000010101110010011011000011011111100010 0
b110110000001001011111000010101110010011011000011011111100010 :
b110110000001001011111000010101110010011011000011011111100010 >
b10000 A
0?
b100001 B
b10001 @
b11011000000100110101010011110100100101011111100111010010011000 .
b11011000000100110101010011110100100101011111100111010010011000 S
b11011000000100110101010011110100100101011111100111010010011000 W
b10001 Z
0X
b100011 \
b10010 Y
b110110011100100000101101111110010010011001111100000000011011 /
b110110011100100000101101111110010010011001111100000000011011 I
b110110011100100000101101111110010010011001111100000000011011 M
b10000 P
0N
b100001 R
b10001 O
b1111001000111010000001011110010 2
b1111001000111010000001011110010 <
b1111001000111010000001011110010 F
b11110010001110100000010111100100 *
b11110010001110100000010111100100 U
b11110010001110100000010111100100 ,
b11110010001110100000010111100100 H
b1111001000111010000001011110010 1
b1111001000111010000001011110010 G
b1111001000111010000001011110010 K
b11100100010111000100000111001 =
b11100100010111000100000111001 4
b11100100010111000100000111001 ;
b11100100010111000100000111001 C
b111001000101110001000001110010 V
b111001000101110001000001110010 +
b111001000101110001000001110010 T
b111001000101110001000001110010 -
b111001000101110001000001110010 E
b11100100010111000100000111001 L
b11100100010111000100000111001 3
b11100100010111000100000111001 D
b11100100010111000100000111001 J
b111100100011101000000101111001001111001000111010000001011110010 #
b111100100011101000000101111001001111001000111010000001011110010 (
b1110010001011100010000011100100011100100010111000100000111001 "
b1110010001011100010000011100100011100100010111000100000111001 '
b1111001000111010000000110000001 &
b110 $
#350
b11 9
b101110101110100101010111100010001010010111101110010010100010111010100011111011001100111110010001011011010011001011000111001001 !
b101110101110100101010111100010001010010111101110010010100010111010100011111011001100111110010001011011010011001011000111001001 )
b101110101110100101010111100010001010010111101110010010100010111010100011111011001100111110010001011011010011001011000111001001 5
b101110101101001111011000111011001111010001101111010001010001111 8
b10111011000011100100010101010101011011010011001011000111001001 7
b10111010111010010101011110000111001100000100011010011000010101 6
b10111010111010010101011110000111001100000100011010011000010101 0
b10111010111010010101011110000111001100000100011010011000010101 :
b10111010111010010101011110000111001100000100011010011000010101 >
b10000 A
0?
b100001 B
b10001 @
b1011101011100111110100111010110110100001100101011111101001101101 .
b1011101011100111110100111010110110100001100101011111101001101101 S
b1011101011100111110100111010110110100001100101011111101001101101 W
b10001 Z
0X
b100011 \
b10010 Y
b10111011000011100100010101010101011011010011001011000111001001 /
b10111011000011100100010101010101011011010011001011000111001001 I
b10111011000011100100010101010101011011010011001011000111001001 M
b10000 P
0N
b100001 R
b10001 O
b1100100101011111100001011001001 2
b1100100101011111100001011001001 <
b1100100101011111100001011001001 F
b11001001010111111000010110010010 *
b11001001010111111000010110010010 U
b11001001010111111000010110010010 ,
b11001001010111111000010110010010 H
b1100100101011111100001011001001 1
b1100100101011111100001011001001 G
b1100100101011111100001011001001 K
b1110110110011101100001011101101 =
b1110110110011101100001011101101 4
b1110110110011101100001011101101 ;
b1110110110011101100001011101101 C
b11101101100111011000010111011010 V
b11101101100111011000010111011010 +
b11101101100111011000010111011010 T
b11101101100111011000010111011010 -
b11101101100111011000010111011010 E
b1110110110011101100001011101101 L
b1110110110011101100001011101101 3
b1110110110011101100001011101101 D
b1110110110011101100001011101101 J
b110010010101111110000101100100101100100101011111100001011001001 #
b110010010101111110000101100100101100100101011111100001011001001 (
b111011011001110110000101110110101110110110011101100001011101101 "
b111011011001110110000101110110101110110110011101100001011101101 '
b1100100101011111100000101110111 &
b111 $
#400
b11 9
b110011111011111011100011001001001110000010110001010100110100110001111000000010111001011101101101110011110100101101011101100000 !
b110011111011111011100011001001001110000010110001010100110100110001111000000010111001011101101101110011110100101101011101100000 )
b110011111011111011100011001001001110000010110001010100110100110001111000000010111001011101101101110011110100101101011101100000 5
b110011111011111010011010111001011101010000100110000110100110000 8
b11001111101111110110001010101101110011110100101101011101100000 7
b11001111101111101110001100100011010000010011010000011101100000 6
b11001111101111101110001100100011010000010011010000011101100000 0
b11001111101111101110001100100011010000010011010000011101100000 :
b11001111101111101110001100100011010000010011010000011101100000 >
b10000 A
0?
b100001 B
b10001 @
b1100111110111110110111101110011100101110001100101110101111110000 .
b1100111110111110110111101110011100101110001100101110101111110000 S
b1100111110111110110111101110011100101110001100101110101111110000 W
b10001 Z
0X
b100011 \
b10010 Y
b11001111101111110110001010101101110011110100101101011101100000 /
b11001111101111110110001010101101110011110100101101011101100000 I
b11001111101111110110001010101101110011110100101101011101100000 M
b10000 P
0N
b100001 R
b10001 O
b10101000001110111110010101010000 2
b10101000001110111110010101010000 <
b10101000001110111110010101010000 F
b101010000011101111100101010100000 *
b101010000011101111100101010100000 U
b101010000011101111100101010100000 ,
b101010000011101111100101010100000 H
b10101000001110111110010101010000 1
b10101000001110111110010101010000 G
b10101000001110111110010101010000 K
b1001111000001111111100010011110 =
b1001111000001111111100010011110 4
b1001111000001111111100010011110 ;
b1001111000001111111100010011110 C
b10011110000011111111000100111100 V
b10011110000011111111000100111100 +
b10011110000011111111000100111100 T
b10011110000011111111000100111100 -
b10011110000011111111000100111100 E
b1001111000001111111100010011110 L
b1001111000001111111100010011110 3
b1001111000001111111100010011110 D
b1001111000001111111100010011110 J
b1010100000111011111001010101000010101000001110111110010101010000 #
b1010100000111011111001010101000010101000001110111110010101010000 (
b100111100000111111110001001111001001111000001111111100010011110 "
b100111100000111111110001001111001001111000001111111100010011110 '
b10101000001110111110001111011101 &
b1000 $
