ABM-M1-Karatsuba-bitwise-64/radix4approx34bit.v
`timescale 10ms / 1ms

module radix4approx34bit(p,x,y);         

parameter N = 34;   //size of muliplicant and multiplier
parameter K = N/2;  //

input   [N-1 : 0]   x,y;
output  [N+N-1:0]   p;

reg [2:0]   bits    [K:0];
reg   neg     [K:0];
reg   two     [K:0];
reg   zero     [K:0];

wire [N+1:0] x_new;
reg [N+1:0]       PP      [K:0]; //riyaj 
reg [N+N-1:0]   ACC     [K:0];
reg [N+N-1:0]   ANS;
reg mux;

integer i , j, t;
integer  m = 24;        //number of bits to approximate

assign x_new = {2'b0,x};

always@(*)

begin
    bits[0] = {y[1],y[0],1'b0};             //setting last bit -1 as 0

    for(i=1; i<K+1; i=i+1) begin
            if(i == K)
                bits[i] = {2'b0,y[2*i-1]};
            else
                bits[i] = {y[2*i+1], y[2*i], y[2*i-1]};
            //$display("%b", bits[i]);
            
        end


    for(i=0; i<K+1; i=i+1)
        begin                               //approximated 2A as A introduced error
            case(bits[i])

            
            3'b001, 3'b010:         
            begin
                neg[i] = 1'b0;
                two[i] = 1'b0;
                zero[i] = 1'b0;
            end

            3'b011:
            begin
                neg[i] = 1'b0;
                two[i] = 1'b1;
                zero[i] = 1'b0;
            end

            3'b101, 3'b110:         
            begin 
               neg[i] = 1'b1;
                two[i] = 1'b0;
                zero[i] = 1'b0;
            end

            3'b100:
            begin
                neg[i] = 1'b1;
                two[i] = 1'b1;
                zero[i] = 1'b0;
            end
         
            default: 
            begin
                neg[i] = 1'b0;
                two[i] = 1'b0;
                zero[i] = 1'b1;
            end

            endcase

            PP[i] = 0;
            PP[i][N+1] = neg[i];           //sign conservation

            for(t=0; t<N+1; t=t+1) begin
                if(t>=m) 
                begin
                    mux = (x_new[t] & ~two[i]) | (x_new[t-1] & two[i]);             
                    PP[i][t] = ~zero[i] & (neg[i] ^ mux);
                end

                else 
                begin
                    PP[i][t] = (~x_new[t] & neg[i]) | (x_new[t] & ~neg[i] & ~zero[i]);
                end
            end

            PP[i][0] = PP[i][0] | neg[i];

            ACC[i] = $signed(PP[i]);        //sign extension
            
            for(j=0; j<i; j=j+1)
                ACC[i] = {ACC[i],2'b00};        //shifting

        
        end

    ANS = ACC[0];

    for(i=1; i<K+1; i=i+1)
        ANS = ANS+ACC[i];
        
end


assign p = ANS;

endmodule

ABM-M1-Karatsuba-bitwise-64/radix4approx34bit_tb.v
`timescale 10ms / 1ms
`include "radix4approx34bit.v"

module radix4approx34bit_tb();


reg  unsigned [33 : 0]   x,y;

wire unsigned [67:0]   p;

integer i, out, seed=7;

radix4approx34bit uut(p,x,y);

initial begin
    $dumpfile("radix4approx34bit.vcd");
    $dumpvars(0, radix4approx34bit_tb);
    out = $fopen("radix4-approx-34bit-mult-result.csv");
    

    for(i=0; i<50; i=i+1)
        begin
        x = $urandom(seed);
        y = $urandom(seed);


        #1;
        $fwrite(out, "%d, %d, %d\n", x,y,p);
        #4;
    end
    $finish;
end
endmodule

ABM-M1-Karatsuba-bitwise-64/radix4approx34bit.vcd
$date
	Fri Jul  9 13:56:18 2021
$end
$version
	Icarus Verilog
$end
$timescale
	1ms
$end
$scope module radix4approx34bit_tb $end
$var wire 68 ! p [67:0] $end
$var reg 34 " x [33:0] $end
$var reg 34 # y [33:0] $end
$var integer 32 $ i [31:0] $end
$var integer 32 % out [31:0] $end
$var integer 32 & seed [31:0] $end
$scope module uut $end
$var wire 68 ' p [67:0] $end
$var wire 34 ( x [33:0] $end
$var wire 34 ) y [33:0] $end
$var wire 36 * x_new [35:0] $end
$var reg 68 + ANS [67:0] $end
$var reg 1 , mux $end
$var integer 32 - i [31:0] $end
$var integer 32 . j [31:0] $end
$var integer 32 / m [31:0] $end
$var integer 32 0 t [31:0] $end
$upscope $end
$upscope $end
$enddefinitions $end
#0
$dumpvars
b100011 0
b11000 /
b10001 .
b10010 -
0,
b101101000001110110011000110100001000001001110111100 +
b1110110001000000000 *
b11000110011011000100101110001100 )
b1110110001000000000 (
b101101000001110110011000110100001000001001110111100 '
b11000110011011000100100011101101 &
b10 %
b0 $
b11000110011011000100101110001100 #
b1110110001000000000 "
b101101000001110110011000110100001000001001110111100 !
$end
#50
b111011000011100001010001011011010110010011111001101111110110100 !
b111011000011100001010001011011010110010011111001101111110110100 '
b111011000011100001010001011011010110010011111001101111110110100 +
b10001 .
0,
b100011 0
b10010 -
b10101110011011011111101101011100 #
b10101110011011011111101101011100 )
b10101101010101110111000101011010 *
b10101101010101110111000101011010 "
b10101101010101110111000101011010 (
b10101110011011011111100111000011 &
b1 $
#100
b11000111101100011011000101111001011100100110100101101001110101 !
b11000111101100011011000101111001011100100110100101101001110101 '
b11000111101100011011000101111001011100100110100101101001110101 +
b10001 .
0,
b100011 0
b10010 -
b11001111110001011111001110011111 #
b11001111110001011111001110011111 )
b111101100000101110101001111011 *
b111101100000101110101001111011 "
b111101100000101110101001111011 (
b11001111110001011111000000001001 &
b10 $
#150
b11100110111100000111011111111101100010001110000111110100 !
b11100110111100000111011111111101100010001110000111110100 '
b11100110111100000111011111111101100010001110000111110100 +
b10001 .
0,
b100011 0
b10010 -
b10011100001010011000000100 #
b10011100001010011000000100 )
b1011110101110101010111010111101 *
b1011110101110101010111010111101 "
b1011110101110101010111010111101 (
b10011100001010010100111111 &
b11 $
#200
b10011001001010010111000000000111101101010000100111101001 !
b10011001001010010111000000000111101101010000100111101001 '
b10011001001010010111000000000111101101010000100111101001 +
b10001 .
0,
b100011 0
b10010 -
b1110111101001000000000011 #
b1110111101001000000000011 )
b1010001110101111000100010100011 *
b1010001110101111000100010100011 "
b1010001110101111000100010100011 (
b1110111101000111011100101 &
b100 $
#250
b10010111001000100001001001010100010100010111111011111001101 !
b10010111001000100001001001010100010100010111111011111001101 '
b10010111001000100001001001010100010100010111111011111001101 +
b10001 .
0,
b100011 0
b10010 -
b1101001110111000000000011010 #
b1101001110111000000000011010 )
b1011011010111110001000010110110 *
b1011011010111110001000010110110 "
b1011011010111110001000010110110 (
b1101001110110111111001111011 &
b101 $
#300
b110110011100100000101101111110010010011001111100000000011011 !
b110110011100100000101101111110010010011001111100000000011011 '
b110110011100100000101101111110010010011001111100000000011011 +
b10001 .
0,
b100011 0
b10010 -
b1111001000111010000001011110010 #
b1111001000111010000001011110010 )
b11100100010111000100000111001 *
b11100100010111000100000111001 "
b11100100010111000100000111001 (
b1111001000111010000000110000001 &
b110 $
#350
b10111011000011100100010101010101011011010011001011000111001001 !
b10111011000011100100010101010101011011010011001011000111001001 '
b10111011000011100100010101010101011011010011001011000111001001 +
b10001 .
0,
b100011 0
b10010 -
b1100100101011111100001011001001 #
b1100100101011111100001011001001 )
b1110110110011101100001011101101 *
b1110110110011101100001011101101 "
b1110110110011101100001011101101 (
b1100100101011111100000101110111 &
b111 $
#400
b11001111101111110110001010101101110011110100101101011101100000 !
b11001111101111110110001010101101110011110100101101011101100000 '
b11001111101111110110001010101101110011110100101101011101100000 +
b10001 .
0,
b100011 0
b10010 -
b10101000001110111110010101010000 #
b10101000001110111110010101010000 )
b1001111000001111111100010011110 *
b1001111000001111111100010011110 "
b1001111000001111111100010011110 (
b10101000001110111110001111011101 &
b1000 $
#450
b100000101111110111101100111111110110001110100001011011011000 !
b100000101111110111101100111111110110001110100001011011011000 '
b100000101111110111101100111111110110001110100001011011011000 +
b10001 .
0,
b100011 0
b10010 -
b1100100110000110110000011001 #
b1100100110000110110000011001 )
b10100110011001001011001101001100 *
b10100110011001001011001101001100 "
b10100110011001001011001101001100 (
b1100100110000110101000110011 &
b1001 $
#500
b1010111101000110110010001111100001101111010111100011011110111 !
b1010111101000110110010001111100001101111010111100011011110111 '
b1010111101000110110010001111100001101111010111100011011110111 +
b10001 .
0,
b100011 0
b10010 -
b1011010111001011001001010110101 #
b1011010111001011001001010110101 )
b111101101001001010001001111011 *
b111101101001001010001001111011 "
b111101101001001010001001111011 (
b1011010111001011001000111111001 &
b1010 $
#550
b1101010011110011100111000001011101011000000100110001010111 !
b1101010011110011100111000001011101011000000100110001010111 '
b1101010011110011100111000001011101011000000100110001010111 +
b10001 .
0,
b100011 0
b10010 -
b11001001101001100011011110010011 #
b11001001101001100011011110010011 )
b100001110001000101000001000 *
b100001110001000101000001000 "
b100001110001000101000001000 (
b11001001101001100011010010101111 &
b1011 $
#600
b10011101101111011111011000110011111101000001110011101100000 !
b10011101101111011111011000110011111101000001110011101100000 '
b10011101101111011111011000110011111101000001110011101100000 +
b10001 .
0,
b100011 0
b10010 -
b101000000100000010100001010000 #
b101000000100000010100001010000 )
b11111011101000001010000111110 *
b11111011101000001010000111110 "
b11111011101000001010000111110 (
b101000000100000010011111010101 &
b1100 $
#650
b110010011110010001010011110000111101010001111110011101100100 !
b110010011110010001010011110000111101010001111110011101100100 '
b110010011110010001010011110000111101010001111110011101100100 +
b10001 .
0,
b100011 0
b10010 -
b11011010001010111001111110110100 #
b11011010001010111001111110110100 )
b1110110010101011100000011101 *
b1110110010101011100000011101 "
b1110110010101011100000011101 (
b11011010001010111001110011101011 &
b1101 $
#700
b101111000011100010111100010000001010101010100001010011000110000 !
b101111000011100010111100010000001010101010100001010011000110000 '
b101111000011100010111100010000001010101010100001010011000110000 +
b10001 .
0,
b100011 0
b10010 -
b10110000000110011000001101100000 #
b10110000000110011000001101100000 )
b10001000110011111001100100010001 *
b10001000110011111001100100010001 "
b10001000110011111001100100010001 (
b10110000000110011000000101110001 &
b1110 $
#750
b1010101010101000011111100110010000010100101100110111011010110010 !
b1010101010101000011111100110010000010100101100110111011010110010 '
b1010101010101000011111100110010000010100101100110111011010110010 +
b10001 .
0,
b100011 0
b10010 -
b11010000100110001110000110100001 #
b11010000100110001110000110100001 )
b11010001011100000110011110100010 *
b11010001011100000110011110100010 "
b11010001011100000110011110100010 (
b11010000100110001101111011100111 &
b1111 $
#800
b1000001101000001110000101001100011001100110000001000011101111101 !
b1000001101000001110000101001100011001100110000001000011101111101 '
b1000001101000001110000101001100011001100110000001000011101111101 +
b10001 .
0,
b100011 0
b10010 -
b11000010101000110011110110000101 #
b11000010101000110011110110000101 )
b10101100101000110011101101011001 *
b10101100101000110011101101011001 "
b10101100101000110011101101011001 (
b11000010101000110011101011001101 &
b10000 $
#850
b10001110110100010010010110110011100100010111000001001100101 !
b10001110110100010010010110110011100100010111000001001100101 '
b10001110110100010010010110110011100100010111000001001100101 +
b10001 .
0,
b100011 0
b10010 -
b1011101101111111100000010111 #
b1011101101111111100000010111 )
b1100001011111111000000011000010 *
b1100001011111111000000011000010 "
b1100001011111111000000011000010 (
b1011101101111111011010100011 &
b10001 $
#900
b11000111000100010101110110000111001000100101000100110111000000 !
b11000111000100010101110110000111001000100101000100110111000000 '
b11000111000100010101110110000111001000100101000100110111000000 +
b10001 .
0,
b100011 0
b10010 -
b1001000001011101011000010010000 #
b1001000001011101011000010010000 )
b10110000011110011100100101100000 *
b10110000011110011100100101100000 "
b10110000011110011100100101100000 (
b1001000001011101010111111101001 &
b10010 $
#950
b11101110011110100110110011001100000010000010110100000111000 !
b11101110011110100110110011001100000010000010110100000111000 '
b11101110011110100110110011001100000010000010110100000111000 +
b10001 .
0,
b100011 0
b10010 -
b1000101010001010001000010001 #
b1000101010001010001000010001 )
b11011100001110101011010110111000 *
b11011100001110101011010110111000 "
b11011100001110101011010110111000 (
b1000101010001010000000011111 &
b10011 $
#1000
b1000100011101011100100011000011110110010111001110100110011001 !
b1000100011101011100100011000011110110010111001110100110011001 '
b1000100011101011100100011000011110110010111001110100110011001 +
b10001 .
0,
b100011 0
b10010 -
b10001011011110001111111100010110 #
b10001011011110001111111100010110 )
b11111010010001100110000111110 *
b11111010010001100110000111110 "
b11111010010001100110000111110 (
b10001011011110001111110011000101 &
b10100 $
#1050
b111000110001101000000010101010011010101000101111011010001001010 !
b111000110001101000000010101010011010101000101111011010001001010 '
b111000110001101000000010101010011010101000101111011010001001010 +
b10001 .
0,
b100011 0
b10010 -
b10001010100111000101100100010101 #
b10001010100111000101100100010101 )
b11010001011111010110110110100010 *
b11010001011111010110110110100010 "
b11010001011111010110110110100010 (
b10001010100111000101011101011011 &
b10101 $
#1100
b1000101011011000010011011110101000011110100011101100010011001 !
b1000101011011000010011011110101000011110100011101100010011001 '
b1000101011011000010011011110101000011110100011101100010011001 +
b10001 .
0,
b100011 0
b10010 -
b111110100101101111111001111101 #
b111110100101101111111001111101 )
b1000110111111001001010010001101 *
b1000110111111001001010010001101 "
b1000110111111001001010010001101 (
b111110100101101111110101100001 &
b10110 $
#1150
b100000110011001001000111000000100001011100001111000001000010100 !
b100000110011001001000111000000100001011100001111000001000010100 '
b100000110011001001000111000000100001011100001111000001000010100 +
b10001 .
0,
b100011 0
b10010 -
b1010100010100100101101010101000 #
b1010100010100100101101010101000 )
b11000111001001111101010110001110 *
b11000111001001111101010110001110 "
b11000111001001111101010110001110 (
b1010100010100100101100001010111 &
b10111 $
#1200
b10001100010000010011011100011111000010101010110010100010111 !
b10001100010000010011011100011111000010101010110010100010111 '
b10001100010000010011011100011111000010101010110010100010111 +
b10001 .
0,
b100011 0
b10010 -
b1010111110100010100111010101111 #
b1010111110100010100111010101111 )
b1100110001000010101000011001 *
b1100110001000010101000011001 "
b1100110001000010101000011001 (
b1010111110100010100110110111101 &
b11000 $
#1250
b11110100001010001101101001000100110101111001011011111011011101 !
b11110100001010001101101001000100110101111001011011111011011101 '
b11110100001010001101101001000100110101111001011011111011011101 +
b10001 .
0,
b100011 0
b10010 -
b11101111010100111010000111011110 #
b11101111010100111010000111011110 )
b1000001010010101101101010000010 *
b1000001010010101101101010000010 "
b1000001010010101101101010000010 (
b11101111010100111001111100010011 &
b11001 $
#1300
b101001110111101101101001101010010111010011101111000000100100000 !
b101001110111101101101001101010010111010011101111000000100100000 '
b101001110111101101101001101010010111010011101111000000100100000 +
b10001 .
0,
b100011 0
b10010 -
b10100010010000000100101101000100 #
b10100010010000000100101101000100 )
b10000100000111010101101100001000 *
b10000100000111010101101100001000 "
b10000100000111010101101100001000 (
b10100010010000000100100111011001 &
b11010 $
#1350
b101101011010101101010110001001001001010010111000110110010011010 !
b101101011010101101010110001001001001010010111000110110010011010 '
b101101011010101101010110001001001001010010111000110110010011010 +
b10001 .
0,
b100011 0
b10010 -
b10111100111011101110100101111001 #
b10111100111011101110100101111001 )
b1111011000101000010100011110110 *
b1111011000101000010100011110110 "
b1111011000101000010100011110110 (
b10111100111011101110011110001111 &
b11011 $
#1400
b11010000110110001011010001111010011100001011011100011010011100 !
b11010000110110001011010001111010011100001011011100011010011100 '
b11010000110110001011010001111010011100001011011100011010011100 +
b10001 .
0,
b100011 0
b10010 -
b10011110001010000000111100111100 #
b10011110001010000000111100111100 )
b1010100101000001011001010101001 *
b1010100101000001011001010101001 "
b1010100101000001011001010101001 (
b10011110001010000000110110110101 &
b11100 $
#1450
b11100010101000011010100111111010111011000011011010011111010100 !
b11100010101000011010100111111010111011000011011010011111010100 '
b11100010101000011010100111111010111011000011011010011111010100 +
b10001 .
0,
b100011 0
b10010 -
b1001100111101001010111010011001 #
b1001100111101001010111010011001 )
b10111100011110100010110101111000 *
b10111100011110100010110101111000 "
b10111100011110100010110101111000 (
b1001100111101001010110111001011 &
b11101 $
#1500
b100110001000000110001001101011100111001101101011001100000111 !
b100110001000000110001001101011100111001101101011001100000111 '
b100110001000000110001001101011100111001101101011001100000111 +
b10001 .
0,
b100011 0
b10010 -
b1101000101000111011000011010 #
b1101000101000111011000011010 )
b10111010100011010111110101110101 *
b10111010100011010111110101110101 "
b10111010100011010111110101110101 (
b1101000101000111010101010001 &
b11110 $
#1550
b1011000011111010001111000001011011101110001100010101010001101100 !
b1011000011111010001111000001011011101110001100010101010001101100 '
b1011000011111010001111000001011011101110001100010101010001101100 +
b10001 .
0,
b100011 0
b10010 -
b10110110001100110010111101101100 #
b10110110001100110010111101101100 )
b11111000101010000001000111110001 *
b11111000101010000001000111110001 "
b11111000101010000001000111110001 (
b10110110001100110010110111000111 &
b11111 $
#1600
b10111101100110111100101001010010110101110010101000011010101111 !
b10111101100110111100101001010010110101110010101000011010101111 '
b10111101100110111100101001010010110101110010101000011010101111 +
b10001 .
0,
b100011 0
b10010 -
b1000101101101010001111010001011 #
b1000101101101010001111010001011 )
b10101110000101011100010101011100 *
b10101110000101011100010101011100 "
b10101110000101011100010101011100 (
b1000101101101010001110010101101 &
b100000 $
#1650
b111000001010010010010100010101000111010100010100110010010110 !
b111000001010010010010100010101000111010100010100110010010110 '
b111000001010010010010100010101000111010100010100110010010110 +
b10001 .
0,
b100011 0
b10010 -
b1101100101100100110010011011001 #
b1101100101100100110010011011001 )
b100001001010011100000001000010 *
b100001001010011100000001000010 "
b100001001010011100000001000010 (
b1101100101100100110001110000011 &
b100001 $
#1700
b1010101001100001110100110011100101101101101111010100100001101 !
b1010101001100001110100110011100101101101101111010100100001101 '
b1010101001100001110100110011100101101101101111010100100001101 +
b10001 .
0,
b100011 0
b10010 -
b101011011110010110000001010110 #
b101011011110010110000001010110 )
b1111101011010100101100011111010 *
b1111101011010100101100011111010 "
b1111101011010100101100011111010 (
b101011011110010101111111001001 &
b100010 $
#1750
b100100110010111001101111110110000011100000010010111111100101001 !
b100100110010111001101111110110000011100000010010111111100101001 '
b100100110010111001101111110110000011100000010010111111100101001 +
b10001 .
0,
b100011 0
b10010 -
b11010001101100000000110110100011 #
b11010001101100000000110110100011 )
b1011001110101111110101010110011 *
b1011001110101111110101010110011 "
b1011001110101111110101010110011 (
b11010001101100000000101011111111 &
b100011 $
#1800
b101101101111001010010110011101110111111001000011000010111111001 !
b101101101111001010010110011101110111111001000011000010111111001 '
b101101101111001010010110011101110111111001000011000010111111001 +
b10001 .
0,
b100011 0
b10010 -
b1100101111011000101110011001011 #
b1100101111011000101110011001011 )
b11100101100001101100001111001011 *
b11100101100001101100001111001011 "
b11100101100001101100001111001011 (
b1100101111011000101101010100101 &
b100100 $
#1850
b111011001100101110010110000001011000011010000100011011110101001 !
b111011001100101110010110000001011000011010000100011011110101001 '
b111011001100101110010110000001011000011010000100011011110101001 +
b10001 .
0,
b100011 0
b10010 -
b1111001010110111010001011110010 #
b1111001010110111010001011110010 )
b11111001100000111111100111110011 *
b11111001100000111111100111110011 "
b11111001100000111111100111110011 (
b1111001010110111010000000111011 &
b100101 $
#1900
b1011111010100110011001011111011000101111011101101011111010001 !
b1011111010100110011001011111011000101111011101101011111010001 '
b1011111010100110011001011111011000101111011101101011111010001 +
b10001 .
0,
b100011 0
b10010 -
b110011110100001110101001100111 #
b110011110100001110101001100111 )
b1110101101111010101000011101011 *
b1110101101111010101000011101011 "
b1110101101111010101000011101011 (
b110011110100001110100101000001 &
b100110 $
#1950
b1100000110000110100111100111001000000101000111010001011000 !
b1100000110000110100111100111001000000101000111010001011000 '
b1100000110000110100111100111001000000101000111010001011000 +
b10001 .
0,
b100011 0
b10010 -
b11100010010100100110000111000100 #
b11100010010100100110000111000100 )
b11011001000001100000000110 *
b11011001000001100000000110 "
b11011001000001100000000110 (
b11100010010100100101111100110111 &
b100111 $
#2000
b1100001000011101000101000000011111011011100110001001001011000111 !
b1100001000011101000101000000011111011011100110001001001011000111 '
b1100001000011101000101000000011111011011100110001001001011000111 +
b10001 .
0,
b100011 0
b10010 -
b11110101111111011010100111101011 #
b11110101111111011010100111101011 )
b11001010000000110000110110010100 *
b11001010000000110000110110010100 "
b11001010000000110000110110010100 (
b11110101111111011010011110011101 &
b101000 $
#2050
b110111110110100101001001110000110111010011010011100100000010 !
b110111110110100101001001110000110111010011010011100100000010 '
b110111110110100101001001110000110111010011010011100100000010 +
b10001 .
0,
b100011 0
b10010 -
b11010110110110100010000110101 #
b11010110110110100010000110101 )
b10000101001111110011001100001010 *
b10000101001111110011001100001010 "
b10000101001111110011001100001010 (
b11010110110110100001111110011 &
b101001 $
#2100
b100011010101000010101011100111010100111100000011111001100100101 !
b100011010101000010101011100111010100111100000011111001100100101 '
b100011010101000010101011100111010100111100000011111001100100101 +
b10001 .
0,
b100011 0
b10010 -
b1001101111110001111001010011011 #
b1001101111110001111001010011011 )
b11100111111110111100001111001111 *
b11100111111110111100001111001111 "
b11100111111110111100001111001111 (
b1001101111110001111000110111001 &
b101010 $
#2150
b1110100111100101110101100000101011001000100010000010110011 !
b1110100111100101110101100000101011001000100010000010110011 '
b1110100111100101110101100000101011001000100010000010110011 +
b10001 .
0,
b100011 0
b10010 -
b10001111111000110000110100011111 #
b10001111111000110000110100011111 )
b110010110001111100000001100 *
b110010110001111100000001100 "
b110010110001111100000001100 (
b10001111111000110000101001101111 &
b101011 $
#2200
b101010111011101010001100010010101001010010001011010111010111100 !
b101010111011101010001100010010101001010010001011010111010111100 '
b101010111011101010001100010010101001010010001011010111010111100 +
b10001 .
0,
b100011 0
b10010 -
b1101100010101001110010011011000 #
b1101100010101001110010011011000 )
b11001010110001011111111110010101 *
b11001010110001011111111110010101 "
b11001010110001011111111110010101 (
b1101100010101001110001110010101 &
b101100 $
#2250
b110100001111010110111111010010101010110001000010110110001 !
b110100001111010110111111010010101010110001000010110110001 '
b110100001111010110111111010010101010110001000010110110001 +
b10001 .
0,
b100011 0
b10010 -
b1101110000011000000000011 #
b1101110000011000000000011 )
b11110011000111011101000111100110 *
b11110011000111011101000111100110 "
b11110011000111011101000111100110 (
b1101110000010111010101011 &
b101101 $
#2300
b1101011000101110111101100101110101001001010100111111101110001111 !
b1101011000101110111101100101110101001001010100111111101110001111 '
b1101011000101110111101100101110101001001010100111111101110001111 +
b10001 .
0,
b100011 0
b10010 -
b11101010110010110101101111010101 #
b11101010110010110101101111010101 )
b11101001100001110000111111010011 *
b11101001100001110000111111010011 "
b11101001100001110000111111010011 (
b11101010110010110101100100110001 &
b101110 $
#2350
b11111011010000110010111110100101100111111010000111011011111111 !
b11111011010000110010111110100101100111111010000111011011111111 '
b11111011010000110010111110100101100111111010000111011011111111 +
b10001 .
0,
b100011 0
b10010 -
b1011010100001101110111010110101 #
b1011010100001101110111010110101 )
b10110001100011101110101101100011 *
b10110001100011101110101101100011 "
b10110001100011101110101101100011 (
b1011010100001101110110010100111 &
b101111 $
#2400
b1010011110110011100101011010110010101110111110100010100101100 !
b1010011110110011100101011010110010101110111110100010100101100 '
b1010011110110011100101011010110010101110111110100010100101100 +
b10001 .
0,
b100011 0
b10010 -
b1001110000110011111000010011100 #
b1001110000110011111000010011100 )
b1000100101101101111111010001001 *
b1000100101101101111111010001001 "
b1000100101101101111111010001001 (
b1001110000110011110111010001101 &
b110000 $
#2450
b1011001100110010010011100010001110110100101010011110001010100100 !
b1011001100110010010011100010001110110100101010011110001010100100 '
b1011001100110010010011100010001110110100101010011110001010100100 +
b10001 .
0,
b100011 0
b10010 -
b11100010100101010100001111000101 #
b11100010100101010100001111000101 )
b11001010011011100011000110010100 *
b11001010011011100011000110010100 "
b11001010011011100011000110010100 (
b11100010100101010100000001100011 &
b110001 $
#2500
b110010 $
