ABM-M3-Karatsuba-bitwise-32-double approx/radix4approx18bit.v
`timescale 10ms / 1ms

module radix4approx18bit(p,x,y);         

parameter N = 18;   //size of muliplicant and multiplier
parameter K = N/2;  //

input   [N-1 : 0]   x,y;
output  [N+N-1:0]   p;

reg [2:0]   bits    [K:0];
reg   neg     [K:0];
reg   two     [K:0];
reg   zero     [K:0];

wire [N+1:0] x_new;
reg [N+1:0]       PP      [K:0]; //riyaj 
reg [N+N-1:0]   ACC     [K:0];
reg [N+N-1:0]   ANS;
reg mux;
reg ord = 0;

integer i , j, t, b;
integer  m = 8;        //number of bits to approximate
integer d = 8;

assign x_new = {2'b0,x};


always@(*)

begin
    bits[0] = {y[1],y[0],1'b0};             //setting last bit -1 as 0

    for(i=1; i<K+1; i=i+1) begin
            if(i == K)
                bits[i] = {2'b0,y[2*i-1]};
            else
                bits[i] = {y[2*i+1], y[2*i], y[2*i-1]};
            //$display("%b", bits[i]);
            
        end


    for(i=0; i<K+1; i=i+1)
        begin                               //approximated 2A as A introduced error
            case(bits[i])

            
            3'b001, 3'b010:         
            begin
                neg[i] = 1'b0;
                two[i] = 1'b0;
                zero[i] = 1'b0;
            end

            3'b011:
            begin
                neg[i] = 1'b0;
                two[i] = 1'b1;
                zero[i] = 1'b0;
            end

            3'b101, 3'b110:         
            begin 
               neg[i] = 1'b1;
                two[i] = 1'b0;
                zero[i] = 1'b0;
            end

            3'b100:
            begin
                neg[i] = 1'b1;
                two[i] = 1'b1;
                zero[i] = 1'b0;
            end
         
            default: 
            begin
                neg[i] = 1'b0;
                two[i] = 1'b0;
                zero[i] = 1'b1;
            end

            endcase

            PP[i] = 0;
            PP[i][N+1] = neg[i];           //sign conservation

            for(t=0; t<N+1; t=t+1) begin
                if(t>=m) 
                begin
                    mux = (x_new[t] & ~two[i]) | (x_new[t-1] & two[i]);             
                    PP[i][t] = ~zero[i] & (neg[i] ^ mux);
                end

                else 
                begin
                    for(b=0; b<d;b=b+1) begin
                        ord = ord | x_new[b];
                    end
                    PP[i][t] = ord & ~zero[i];
                    d = d-2;
                    
                end
            end

            PP[i][0] = PP[i][0] | neg[i];

            ACC[i] = $signed(PP[i]);        //sign extension
            
            for(j=0; j<i; j=j+1)
                ACC[i] = {ACC[i],2'b00};        //shifting

        
        end

    ANS = ACC[0];

    for(i=1; i<K+1; i=i+1)
        ANS = ANS+ACC[i];
        
end


assign p = ANS;

endmodule

ABM-M1-Karatsuba-bitwise-32/adder8.v
`timescale 10ms / 1ms

module adder8(s,a,b);

input [15:0] a,b;

output [16:0] s;


assign s = a+b;

endmodule

ABM-M3-Karatsuba-bitwise-32-double approx/radix4approx.v
`timescale 10ms / 1ms

module radix4approx(p,x,y);         

parameter N = 16;   //size of muliplicant and multiplier
parameter K = N/2;  //

input   [N-1 : 0]   x,y;
output  [N+N-1:0]   p;

reg [2:0]   bits    [K:0];
reg   neg     [K:0];
reg   two     [K:0];
reg   zero     [K:0];

wire [N+1:0] x_new;
reg [N+1:0]       PP      [K:0]; //riyaj 
reg [N+N-1:0]   ACC     [K:0];
reg [N+N-1:0]   ANS;
reg mux;
reg ord = 0;

integer i , j, t=0, b;
integer  m = 8;        //number of bits to approximate
integer d = 8;

assign x_new = {2'b0,x};


always@(*)

begin
    bits[0] = {y[1],y[0],1'b0};             //setting last bit -1 as 0

    for(i=1; i<K+1; i=i+1) begin
            if(i == K)
                bits[i] = {2'b0,y[2*i-1]};
            else
                bits[i] = {y[2*i+1], y[2*i], y[2*i-1]};
            //$display("%b", bits[i]);
            
        end


    for(i=0; i<K+1; i=i+1)
        begin                               //approximated 2A as A introduced error
            case(bits[i])

            
            3'b001, 3'b010:         
            begin
                neg[i] = 1'b0;
                two[i] = 1'b0;
                zero[i] = 1'b0;
            end

            3'b011:
            begin
                neg[i] = 1'b0;
                two[i] = 1'b1;
                zero[i] = 1'b0;
            end

            3'b101, 3'b110:         
            begin 
               neg[i] = 1'b1;
                two[i] = 1'b0;
                zero[i] = 1'b0;
            end

            3'b100:
            begin
                neg[i] = 1'b1;
                two[i] = 1'b1;
                zero[i] = 1'b0;
            end
         
            default: 
            begin
                neg[i] = 1'b0;
                two[i] = 1'b0;
                zero[i] = 1'b1;
            end

            endcase

            PP[i] = 0;
            PP[i][N+1] = neg[i];           //sign conservation

            for(t=0; t<N+1; t=t+1) begin
                if(t>=m) 
                begin
                    mux = (x_new[t] & ~two[i]) | (x_new[t-1] & two[i]);             
                    PP[i][t] = ~zero[i] & (neg[i] ^ mux);
                end

                else 
                begin
                    for(b=0; b<d;b=b+1) begin                   //M3 appproximation
                        ord = ord | x_new[b];
                    end
                    PP[i][t] = ord & ~zero[i];
                    d = d-2;
                    
                end

            end

            PP[i][0] = PP[i][0] | neg[i];

            ACC[i] = $signed(PP[i]);        //sign extension
            
            for(j=0; j<i; j=j+1)
                ACC[i] = {ACC[i],2'b00};        //shifting

        
        end

    ANS = ACC[0];

    for(i=1; i<K+1; i=i+1)
        ANS = ANS+ACC[i];
        
end


assign p = ANS;

endmodule

ABM-M1-WT-bitwise-32/radix4acc.v
`timescale 10ms / 1ms

module radix4acc(p,x,y);        

parameter N = 16;   //size of muliplicant and multiplier
parameter K = N/2;  //

input [N-1 : 0]   x,y;
output [N+N-1:0]   p;

reg [2:0]   bits    [K:0];
reg   neg     [K:0];
reg   two     [K:0];
reg   zero     [K:0];

wire [N+1:0] x_new;
reg [N+1:0]       PP      [K:0]; 
reg [N+N-1:0]   ACC     [K:0];
reg [N+N-1:0]   ANS;
reg mux;

integer i , j, t;

assign x_new = {2'b0,x};

always@(*)

begin
    bits[0] = {y[1],y[0],1'b0};             //setting last bit -1 as 0
    //$display("%b", bits[0]);
    for(i=1; i<K+1; i=i+1) begin
        if(i == K)
            bits[i] = {2'b0,y[2*i-1]};
        else
            bits[i] = {y[2*i+1], y[2*i], y[2*i-1]};
        //$display("%b", bits[i]);
        
    end

    for(i=0; i<K+1; i=i+1)
        begin                                      //accurate cases
            case(bits[i])

            
            3'b001, 3'b010:         
            begin
                neg[i] = 1'b0;
                two[i] = 1'b0;
                zero[i] = 1'b0;
            end

            3'b011:
            begin
                neg[i] = 1'b0;
                two[i] = 1'b1;
                zero[i] = 1'b0;
            end

            3'b101, 3'b110:         
            begin 
               neg[i] = 1'b1;
                two[i] = 1'b0;
                zero[i] = 1'b0;
            end

            3'b100:
            begin
                neg[i] = 1'b1;
                two[i] = 1'b1;
                zero[i] = 1'b0;
            end
         
            default: 
            begin
                neg[i] = 1'b0;
                two[i] = 1'b0;
                zero[i] = 1'b1;
            end

            endcase
            
            //$display("%b %b %b", neg[i], two[i], zero[i]);
            
            PP[i] = 0;
            PP[i][N+1] = neg[i];           //sign conservation

            for(t=0; t<N+1; t=t+1) begin
                if(t==0) 
                    mux = (x_new[t] & ~two[i]) | (1'b0 & two[i]);
                
                else
                    mux = (x_new[t] & ~two[i]) | (x_new[t-1] & two[i]);

                
                PP[i][t] = ~zero[i] & (neg[i] ^ mux);       
            end

            PP[i] = PP[i] + neg[i];             //correction term added
            
            //$display("%b", PP[i]);

            ACC[i] = $signed(PP[i]);        //sign extension
            //$display("%b", ACC[i]);

            for(j=0; j<i; j=j+1)
                ACC[i] = {ACC[i],2'b00};        //shifting

        
        end

    ANS = ACC[0];

    for(i=1; i<K+1; i=i+1)
        ANS = ANS+ACC[i];
        
    
end


assign p = ANS;

endmodule

ABM-M1-Karatsuba-bitwise-32- double approx/karatsuba32.v
`timescale 10ms/1ms
`include "radix4acc.v"
`include "radix4approx.v"
`include "radix4approx18bit.v"
`include "adder8.v"

module karatsuba32(P,A,B);


parameter N = 32;   //size of muliplicant and multiplier
parameter K = N/2;  //

input   [N-1 : 0]   A,B;
output  [N+N-1:0]   P;

wire [K-1:0] AH, AL, BH, BL;

wire reg    [N-1:0]     M1, M2;
wire reg    [K:0]       S1, S2;
wire reg    [17:0]       c,d;
wire reg    [35:0]      M3;

reg [35:0] M4, M5, M6;

reg     [35:0]   A1, A2, A3;


reg [N+N-1:0]   ACC     [2:0];
reg [N+N-1:0] ANS;
integer i;


assign AH = A[N-1:K];
assign AL = A[K-1:0];

assign BH = B[N-1:K];
assign BL = B[K-1:0];



radix4acc ACC1(.p(M1), .x(AH), .y(BH));
radix4approx APP1(.p(M2), .x(AL), .y(BL));      //approx1


adder8 ADD1(.s(S1), .a(AH), .b(AL));
adder8 ADD2(.s(S2), .a(BH), .b(BL));

assign c = (S1);
assign d = (S2);

radix4approx18bit APP2(.p(M3), .x(c), .y(d));       //approx2



always@(*)                  //, AL, BH, BL, M1, M2, S1, S2, M3
begin
    /*$display("AH= %b",AH);
    $display("AL= %b",AL);    
    $display("BH= %b", BH);    
    $display("BL= %b",BL);    
    $display("M1= %b",M1);    
    $display("M2= %b",M2);    
    $display("S1= %b",S1);
    $display("S2= %b",S2);    
    $display("M3= %b",M3);    
    $display("---------");
    $display("---------");
    $display("---------");
    $display("---------");
    */

    M4 = (M1);
    M5 = (M2);
    
    if(M3 > (M4+M5))
        M6 = M3 - M4 - M5;
    else
        M6 = (M4+M5) - M3;


    ACC[0] = (M6);
    ACC[0] = {ACC[0], {16{1'b0}}};
    //$display("ACC[0]= %d",ACC[0]);    

    ACC[1] = (M2);
    //$display("ACC[1]= %d",ACC[1]);    
    
    ACC[2] = (M1);
    ACC[2] = {ACC[2], {32{1'b0}}};
    //$display("ACC[2]= %d",ACC[2]);    

    ANS = ACC[0];
    for(i=1; i<3; i=i+1)
        ANS = ANS+ACC[i];
end

assign P = ANS;

endmodule

ABM-M1-Karatsuba-bitwise-32- double approx/karatsuba32_tb.v
`timescale 10ms / 1ms
`include "karatsuba32.v"

module karatsuba32_tb();

reg unsigned [31:0] A,B;
wire unsigned [63:0] P;
integer i, out, seed=7;


karatsuba32 uut(P,A,B);


initial begin
    $dumpfile("karatsuba32.vcd");
    $dumpvars(0, karatsuba32_tb);
    out = $fopen("results16.csv");
  
/*    
        A = 58;
        B = 84607;
        #1;
        $fwrite(out, "%d, %d, %d\n", A,B,P);
        #4;

        A = 73066;
        B = 615406;
        #1;
        $fwrite(out, "%d, %d, %d\n", A,B,P);
        #4;

        A = 10;
        B = 96224;
        #1;
        $fwrite(out, "%d, %d, %d\n", A,B,P);
        #4;

        A = 12;
        B = 94209;
        #1;
        $fwrite(out, "%d, %d, %d\n", A,B,P);
        #4;

        A = 20;
        B = 95679;
        #1;
        $fwrite(out, "%d, %d, %d\n", A,B,P);
        #4;
    */

    
    for(i=0; i<100; i=i+1)                       //10 test cases A and B: 1-100 
    begin
        A = $urandom(seed) %200 + 65536;
        B = $urandom(seed) %200;
        #1;
        $fwrite(out, "%d, %d, %d\n", A,B,P);
        #4;
    end

    for(i=0; i<100; i=i+1)                       //10 test cases A: 1-100 B: till 2^15
    begin
        A = $urandom(seed) %200;
        B = $urandom(seed) %32768 + 65536;
        #1;
        $fwrite(out, "%d, %d, %d\n", A,B,P);
        #4;
    end

    for(i=0; i<100; i=i+1)                       //10 test cases B: 1-100 A: till 2^32
    begin
        A = $urandom(seed) %4294967295;
        B = $urandom(seed) %200 + 65535;
        #1;
        $fwrite(out, "%d, %d, %d\n", A,B,P);
        #4;
    end

    
    for(i=0; i<200; i=i+1)                       //50 cases : till 1024 A: 2^10 B: 2^20
    begin
        A = $urandom(seed) %1024;
        B = $urandom(seed) %1048576;
        #1;
        $fwrite(out, "%d, %d, %d\n", A,B,P);
        #4;
    end

    for(i=0; i<500; i=i+1)                       //500 cases : till 32768 which is 2^15
    begin
        A = $urandom(seed) %65536 + 65536;
        B = $urandom(seed) %32768;
        #1;
        $fwrite(out, "%d, %d, %d\n", A,B,P);
        #4;
    end

    for(i=0; i<500; i=i+1)                       //500 cases : till 2^20
    begin
        A = $urandom(seed) %1048576;
        B = $urandom(seed) %1048576;
        #1;
        $fwrite(out, "%d, %d, %d\n", A,B,P);
        #4;
    end

    for(i=0; i<500; i=i+1)                       //50 cases : till 1024 A: 2^32 B: 2^20
    begin
        A = $urandom(seed) %4294967295;
        B = $urandom(seed) %1048576;
        #1;
        $fwrite(out, "%d, %d, %d\n", A,B,P);
        #4;
    end

    for(i=0; i<500; i=i+1)                          //50 cases till 2^32
    begin
        A = $urandom(seed) %4294967295;
        B = $urandom(seed) %4294967295;
        #1;
        $fwrite(out, "%d, %d, %d\n", A,B,P);
        #4;
    end
    
    
    $finish;
end

endmodule

ABM-M3-Karatsuba-bitwise-32-double approx/karatsuba32.vcd
$date
	Tue Sep 14 01:04:58 2021
$end
$version
	Icarus Verilog
$end
$timescale
	1ms
$end
$scope module karatsuba32_tb $end
$var wire 64 ! P [63:0] $end
$var reg 32 " A [31:0] $end
$var reg 32 # B [31:0] $end
$var integer 32 $ i [31:0] $end
$var integer 32 % out [31:0] $end
$var integer 32 & seed [31:0] $end
$scope module uut $end
$var wire 32 ' A [31:0] $end
$var wire 32 ( B [31:0] $end
$var wire 64 ) P [63:0] $end
$var wire 18 * d [17:0] $end
$var wire 18 + c [17:0] $end
$var wire 17 , S2 [16:0] $end
$var wire 17 - S1 [16:0] $end
$var wire 36 . M3 [35:0] $end
$var wire 32 / M2 [31:0] $end
$var wire 32 0 M1 [31:0] $end
$var wire 16 1 BL [15:0] $end
$var wire 16 2 BH [15:0] $end
$var wire 16 3 AL [15:0] $end
$var wire 16 4 AH [15:0] $end
$var reg 64 5 ANS [63:0] $end
$var reg 36 6 M4 [35:0] $end
$var reg 36 7 M5 [35:0] $end
$var reg 36 8 M6 [35:0] $end
$var integer 32 9 i [31:0] $end
$scope module ACC1 $end
$var wire 32 : p [31:0] $end
$var wire 16 ; x [15:0] $end
$var wire 16 < y [15:0] $end
$var wire 18 = x_new [17:0] $end
$var reg 32 > ANS [31:0] $end
$var reg 1 ? mux $end
$var integer 32 @ i [31:0] $end
$var integer 32 A j [31:0] $end
$var integer 32 B t [31:0] $end
$upscope $end
$scope module ADD1 $end
$var wire 16 C a [15:0] $end
$var wire 16 D b [15:0] $end
$var wire 17 E s [16:0] $end
$upscope $end
$scope module ADD2 $end
$var wire 16 F a [15:0] $end
$var wire 16 G b [15:0] $end
$var wire 17 H s [16:0] $end
$upscope $end
$scope module APP1 $end
$var wire 32 I p [31:0] $end
$var wire 16 J x [15:0] $end
$var wire 16 K y [15:0] $end
$var wire 18 L x_new [17:0] $end
$var reg 32 M ANS [31:0] $end
$var reg 1 N mux $end
$var reg 1 O ord $end
$var integer 32 P b [31:0] $end
$var integer 32 Q d [31:0] $end
$var integer 32 R i [31:0] $end
$var integer 32 S j [31:0] $end
$var integer 32 T m [31:0] $end
$var integer 32 U t [31:0] $end
$upscope $end
$scope module APP2 $end
$var wire 36 V p [35:0] $end
$var wire 18 W x [17:0] $end
$var wire 18 X y [17:0] $end
$var wire 20 Y x_new [19:0] $end
$var reg 36 Z ANS [35:0] $end
$var reg 1 [ mux $end
$var reg 1 \ ord $end
$var integer 32 ] b [31:0] $end
$var integer 32 ^ d [31:0] $end
$var integer 32 _ i [31:0] $end
$var integer 32 ` j [31:0] $end
$var integer 32 a m [31:0] $end
$var integer 32 b t [31:0] $end
$upscope $end
$upscope $end
$upscope $end
$enddefinitions $end
#0
$dumpvars
b10011 b
b1000 a
b1001 `
b1010 _
b11111111111111111111111011001000 ^
b0 ]
x\
0[
bx Z
b110001000000111 Y
b10001000111111000 X
b110001000000111 W
bx V
b10001 U
b1001101100 T
b1000 S
b1001 R
b11111111111111111111110110100100 Q
b0 P
xO
xN
bx M
b110001000000000 L
b100101110001100 K
b110001000000000 J
bx I
b10001000111111000 H
b100101110001100 G
b1100011001101100 F
b110001000000111 E
b110001000000000 D
b111 C
b10001 B
b1000 A
b1001 @
0?
b1010110110011110100 >
b111 =
b1100011001101100 <
b111 ;
b1010110110011110100 :
b11 9
bx 8
bx 7
b1010110110011110100 6
bx 5
b111 4
b110001000000000 3
b1100011001101100 2
b100101110001100 1
b1010110110011110100 0
bx /
bx .
b110001000000111 -
b10001000111111000 ,
b110001000000111 +
b10001000111111000 *
bx )
b11000110011011000100101110001100 (
b1110110001000000000 '
b11000110011011000100100011101101 &
b10 %
b0 $
b11000110011011000100101110001100 #
b1110110001000000000 "
bx !
$end
#50
b11 9
bx !
bx )
bx 5
b1110110000110101111000000001011 6
b1110110000110101111000000001011 0
b1110110000110101111000000001011 :
b1110110000110101111000000001011 >
b1000 A
0?
b10001 B
b1001 @
bx .
bx V
bx Z
b1001 `
0[
b11111111111111111111111000101000 ^
b10011 b
b1010 _
bx /
bx I
bx M
b1000 S
b1110011110 T
b11111111111111111111110001110010 Q
b10001 U
b1001 R
b1010111001101101 2
b1010111001101101 <
b1010111001101101 F
b11010100111001001 *
b11010100111001001 X
b11010100111001001 ,
b11010100111001001 H
b1111101101011100 1
b1111101101011100 G
b1111101101011100 K
b1010110101010111 =
b1010110101010111 4
b1010110101010111 ;
b1010110101010111 C
b10001111010110001 Y
b10001111010110001 +
b10001111010110001 W
b10001111010110001 -
b10001111010110001 E
b111000101011010 L
b111000101011010 3
b111000101011010 D
b111000101011010 J
b10101110011011011111101101011100 #
b10101110011011011111101101011100 (
b10101101010101110111000101011010 "
b10101101010101110111000101011010 '
b10101110011011011111100111000011 &
b1 $
#100
b11 9
bx !
bx )
bx 5
b110001111010110111001100001010 6
b110001111010110111001100001010 0
b110001111010110111001100001010 :
b110001111010110111001100001010 >
b1000 A
0?
b10001 B
b1001 @
bx .
bx V
bx Z
b1001 `
0[
b11111111111111111111110110001000 ^
b10011 b
b1010 _
bx /
bx I
bx M
b1000 S
b10011010000 T
b11111111111111111111101101000000 Q
b10001 U
b1001 R
b1100111111000101 2
b1100111111000101 <
b1100111111000101 F
b11100001101100100 *
b11100001101100100 X
b11100001101100100 ,
b11100001101100100 H
b1111001110011111 1
b1111001110011111 G
b1111001110011111 K
b11110110000010 =
b11110110000010 4
b11110110000010 ;
b11110110000010 C
b10010011111111101 Y
b10010011111111101 +
b10010011111111101 W
b10010011111111101 -
b10010011111111101 E
b1110101001111011 L
b1110101001111011 3
b1110101001111011 D
b1110101001111011 J
b11001111110001011111001110011111 #
b11001111110001011111001110011111 (
b111101100000101110101001111011 "
b111101100000101110101001111011 '
b11001111110001011111000000001001 &
b10 $
#150
b11 9
bx !
bx )
bx 5
b111001101110010101100000 6
b111001101110010101100000 0
b111001101110010101100000 :
b111001101110010101100000 >
b1000 A
0?
b10001 B
b1001 @
bx .
bx V
bx Z
b1001 `
0[
b11111111111111111111110011101000 ^
b10011 b
b1010 _
bx /
bx I
bx M
b1000 S
b11000000010 T
b11111111111111111111101000001110 Q
b10001 U
b1001 R
b1001110000 2
b1001110000 <
b1001110000 F
b1010100001110100 *
b1010100001110100 X
b1010100001110100 ,
b1010100001110100 H
b1010011000000100 1
b1010011000000100 G
b1010011000000100 K
b101111010111010 =
b101111010111010 4
b101111010111010 ;
b101111010111010 C
b10000110101110111 Y
b10000110101110111 +
b10000110101110111 W
b10000110101110111 -
b10000110101110111 E
b1010111010111101 L
b1010111010111101 3
b1010111010111101 D
b1010111010111101 J
b10011100001010011000000100 #
b10011100001010011000000100 (
b1011110101110101010111010111101 "
b1011110101110101010111010111101 '
b10011100001010010100111111 &
b11 $
#200
b11 9
bx !
bx )
bx 5
b100110001100111101110010 6
b100110001100111101110010 0
b100110001100111101110010 :
b100110001100111101110010 >
b1000 A
0?
b10001 B
b1001 @
bx .
bx V
bx Z
b1001 `
0[
b11111111111111111111110001001000 ^
b10011 b
b1010 _
bx /
bx I
bx M
b1000 S
b11100110100 T
b11111111111111111111100011011100 Q
b10001 U
b1001 R
b111011110 2
b111011110 <
b111011110 F
b1001000111100001 *
b1001000111100001 X
b1001000111100001 ,
b1001000111100001 H
b1001000000000011 1
b1001000000000011 G
b1001000000000011 K
b101000111010111 =
b101000111010111 4
b101000111010111 ;
b101000111010111 C
b1101101001111010 Y
b1101101001111010 +
b1101101001111010 W
b1101101001111010 -
b1101101001111010 E
b1000100010100011 L
b1000100010100011 3
b1000100010100011 D
b1000100010100011 J
b1110111101001000000000011 #
b1110111101001000000000011 (
b1010001110101111000100010100011 "
b1010001110101111000100010100011 '
b1110111101000111011100101 &
b100 $
#250
b11 9
bx !
bx )
bx 5
b100101110001110000111100101 6
b100101110001110000111100101 0
b100101110001110000111100101 :
b100101110001110000111100101 >
b1000 A
0?
b10001 B
b1001 @
bx .
bx V
bx Z
b1001 `
0[
b11111111111111111111101110101000 ^
b10011 b
b1010 _
bx /
bx I
bx M
b1000 S
b100001100110 T
b11111111111111111111011110101010 Q
b10001 U
b1001 R
b110100111011 2
b110100111011 <
b110100111011 F
b1000110101010101 *
b1000110101010101 X
b1000110101010101 ,
b1000110101010101 H
b1000000000011010 1
b1000000000011010 G
b1000000000011010 K
b101101101011111 =
b101101101011111 4
b101101101011111 ;
b101101101011111 C
b110110000010101 Y
b110110000010101 +
b110110000010101 W
b110110000010101 -
b110110000010101 E
b1000010110110 L
b1000010110110 3
b1000010110110 D
b1000010110110 J
b1101001110111000000000011010 #
b1101001110111000000000011010 (
b1011011010111110001000010110110 "
b1011011010111110001000010110110 '
b1101001110110111111001111011 &
b101 $
#300
b11 9
bx !
bx )
bx 5
b1101100000001110111010111111 6
b1101100000001110111010111111 0
b1101100000001110111010111111 :
b1101100000001110111010111111 >
b1000 A
0?
b10001 B
b1001 @
bx .
bx V
bx Z
b1001 `
0[
b11111111111111111111101100001000 ^
b10011 b
b1010 _
bx /
bx I
bx M
b1000 S
b100110011000 T
b11111111111111111111011001111000 Q
b10001 U
b1001 R
b111100100011101 2
b111100100011101 <
b111100100011101 F
b111110000001111 *
b111110000001111 X
b111110000001111 ,
b111110000001111 H
b1011110010 1
b1011110010 G
b1011110010 K
b1110010001011 =
b1110010001011 4
b1110010001011 ;
b1110010001011 C
b1010010011000100 Y
b1010010011000100 +
b1010010011000100 W
b1010010011000100 -
b1010010011000100 E
b1000100000111001 L
b1000100000111001 3
b1000100000111001 D
b1000100000111001 J
b1111001000111010000001011110010 #
b1111001000111010000001011110010 (
b11100100010111000100000111001 "
b11100100010111000100000111001 '
b1111001000111010000000110000001 &
b110 $
#350
b11 9
bx !
bx )
bx 5
b101110101110011010111011010010 6
b101110101110011010111011010010 0
b101110101110011010111011010010 :
b101110101110011010111011010010 >
b1000 A
0?
b10001 B
b1001 @
bx .
bx V
bx Z
b1001 `
0[
b11111111111111111111101001101000 ^
b10011 b
b1010 _
bx /
bx I
bx M
b1000 S
b101011001010 T
b11111111111111111111010101000110 Q
b10001 U
b1001 R
b110010010101111 2
b110010010101111 <
b110010010101111 F
b10010011101111000 *
b10010011101111000 X
b10010011101111000 ,
b10010011101111000 H
b1100001011001001 1
b1100001011001001 G
b1100001011001001 K
b111011011001110 =
b111011011001110 4
b111011011001110 ;
b111011011001110 C
b10011100110111011 Y
b10011100110111011 +
b10011100110111011 W
b10011100110111011 -
b10011100110111011 E
b1100001011101101 L
b1100001011101101 3
b1100001011101101 D
b1100001011101101 J
b1100100101011111100001011001001 #
b1100100101011111100001011001001 (
b1110110110011101100001011101101 "
b1110110110011101100001011101101 '
b1100100101011111100000101110111 &
b111 $
#400
b11 9
bx !
bx )
bx 5
b110011111011101100111010011101 6
b110011111011101100111010011101 0
b110011111011101100111010011101 :
b110011111011101100111010011101 >
b1000 A
0?
b10001 B
b1001 @
bx .
bx V
bx Z
b1001 `
0[
b11111111111111111111100111001000 ^
b10011 b
b1010 _
bx /
bx I
bx M
b1000 S
b101111111100 T
b11111111111111111111010000010100 Q
b10001 U
b1001 R
b1010100000111011 2
b1010100000111011 <
b1010100000111011 F
b11000110110001011 *
b11000110110001011 X
b11000110110001011 ,
b11000110110001011 H
b1110010101010000 1
b1110010101010000 G
b1110010101010000 K
b100111100000111 =
b100111100000111 4
b100111100000111 ;
b100111100000111 C
b10100011110100101 Y
b10100011110100101 +
b10100011110100101 W
b10100011110100101 -
b10100011110100101 E
b1111100010011110 L
b1111100010011110 3
b1111100010011110 D
b1111100010011110 J
b10101000001110111110010101010000 #
b10101000001110111110010101010000 (
b1001111000001111111100010011110 "
b1001111000001111111100010011110 '
b10101000001110111110001111011101 &
b1000 $
#450
b11 9
bx !
bx )
bx 5
b1000001011110111101101100000 6
b1000001011110111101101100000 0
b1000001011110111101101100000 :
b1000001011110111101101100000 >
b1000 A
0?
b10001 B
b1001 @
bx .
bx V
bx Z
b1001 `
0[
b11111111111111111111100100101000 ^
b10011 b
b1010 _
bx /
bx I
bx M
b1000 S
b110100101110 T
b11111111111111111111001011100010 Q
b10001 U
b1001 R
b110010011000 2
b110010011000 <
b110010011000 F
b111100010110001 *
b111100010110001 X
b111100010110001 ,
b111100010110001 H
b110110000011001 1
b110110000011001 G
b110110000011001 K
b1010011001100100 =
b1010011001100100 4
b1010011001100100 ;
b1010011001100100 C
b10101100110110000 Y
b10101100110110000 +
b10101100110110000 W
b10101100110110000 -
b10101100110110000 E
b1011001101001100 L
b1011001101001100 3
b1011001101001100 D
b1011001101001100 J
b1100100110000110110000011001 #
b1100100110000110110000011001 (
b10100110011001001011001101001100 "
b10100110011001001011001101001100 '
b1100100110000110101000110011 &
b1001 $
#500
b11 9
bx !
bx )
bx 5
b10101111000101100101110110100 6
b10101111000101100101110110100 0
b10101111000101100101110110100 :
b10101111000101100101110110100 >
b1000 A
0?
b10001 B
b1001 @
bx .
bx V
bx Z
b1001 `
0[
b11111111111111111111100010001000 ^
b10011 b
b1010 _
bx /
bx I
bx M
b1000 S
b111001100000 T
b11111111111111111111000110110000 Q
b10001 U
b1001 R
b101101011100101 2
b101101011100101 <
b101101011100101 F
b1110110110011010 *
b1110110110011010 X
b1110110110011010 ,
b1110110110011010 H
b1001001010110101 1
b1001001010110101 G
b1001001010110101 K
b11110110100100 =
b11110110100100 4
b11110110100100 ;
b11110110100100 C
b1110000000011111 Y
b1110000000011111 +
b1110000000011111 W
b1110000000011111 -
b1110000000011111 E
b1010001001111011 L
b1010001001111011 3
b1010001001111011 D
b1010001001111011 J
b1011010111001011001001010110101 #
b1011010111001011001001010110101 (
b111101101001001010001001111011 "
b111101101001001010001001111011 '
b1011010111001011001000111111001 &
b1010 $
#550
b11 9
bx !
bx )
bx 5
b11010100101011010001010000 6
b11010100101011010001010000 0
b11010100101011010001010000 :
b11010100101011010001010000 >
b1000 A
0?
b10001 B
b1001 @
bx .
bx V
bx Z
b1001 `
0[
b11111111111111111111011111101000 ^
b10011 b
b1010 _
bx /
bx I
bx M
b1000 S
b111110010010 T
b11111111111111111111000001111110 Q
b10001 U
b1001 R
b1100100110100110 2
b1100100110100110 <
b1100100110100110 F
b10000000100111001 *
b10000000100111001 X
b10000000100111001 ,
b10000000100111001 H
b11011110010011 1
b11011110010011 G
b11011110010011 K
b10000111000 =
b10000111000 4
b10000111000 ;
b10000111000 C
b1000111001000000 Y
b1000111001000000 +
b1000111001000000 W
b1000111001000000 -
b1000111001000000 E
b1000101000001000 L
b1000101000001000 3
b1000101000001000 D
b1000101000001000 J
b11001001101001100011011110010011 #
b11001001101001100011011110010011 (
b100001110001000101000001000 "
b100001110001000101000001000 '
b11001001101001100011010010101111 &
b1011 $
#600
b11 9
bx !
bx )
bx 5
b100111011000001011101000000 6
b100111011000001011101000000 0
b100111011000001011101000000 :
b100111011000001011101000000 >
b1000 A
0?
b10001 B
b1001 @
bx .
bx V
bx Z
b1001 `
0[
b11111111111111111111011101001000 ^
b10011 b
b1010 _
bx /
bx I
bx M
b1000 S
b1000011000100 T
b11111111111111111110111101001100 Q
b10001 U
b1001 R
b10100000010000 2
b10100000010000 <
b10100000010000 F
b101000001100000 *
b101000001100000 X
b101000001100000 ,
b101000001100000 H
b10100001010000 1
b10100001010000 G
b10100001010000 K
b1111101110100 =
b1111101110100 4
b1111101110100 ;
b1111101110100 C
b11001110110010 Y
b11001110110010 +
b11001110110010 W
b11001110110010 -
b11001110110010 E
b1010000111110 L
b1010000111110 3
b1010000111110 D
b1010000111110 J
b101000000100000010100001010000 #
b101000000100000010100001010000 (
b11111011101000001010000111110 "
b11111011101000001010000111110 '
b101000000100000010011111010101 &
b1100 $
#650
b11 9
bx !
bx )
bx 5
b1100100110100111111111101110 6
b1100100110100111111111101110 0
b1100100110100111111111101110 :
b1100100110100111111111101110 >
b1000 A
0?
b10001 B
b1001 @
bx .
bx V
bx Z
b1001 `
0[
b11111111111111111111011010101000 ^
b10011 b
b1010 _
bx /
bx I
bx M
b1000 S
b1000111110110 T
b11111111111111111110111000011010 Q
b10001 U
b1001 R
b1101101000101011 2
b1101101000101011 <
b1101101000101011 F
b10111100111011111 *
b10111100111011111 X
b10111100111011111 ,
b10111100111011111 H
b1001111110110100 1
b1001111110110100 G
b1001111110110100 K
b111011001010 =
b111011001010 4
b111011001010 ;
b111011001010 C
b1100011011100111 Y
b1100011011100111 +
b1100011011100111 W
b1100011011100111 -
b1100011011100111 E
b1011100000011101 L
b1011100000011101 3
b1011100000011101 D
b1011100000011101 J
b11011010001010111001111110110100 #
b11011010001010111001111110110100 (
b1110110010101011100000011101 "
b1110110010101011100000011101 '
b11011010001010111001110011101011 &
b1101 $
