ABM-M3-Karatsuba-bitwise-32-double approx/radix4approx18bit.v
`timescale 10ms / 1ms

module radix4approx18bit(p,x,y);         

parameter N = 18;   //size of muliplicant and multiplier
parameter K = N/2;  //

input   [N-1 : 0]   x,y;
output  [N+N-1:0]   p;

reg [2:0]   bits    [K:0];
reg   neg     [K:0];
reg   two     [K:0];
reg   zero     [K:0];

wire [N+1:0] x_new;
reg [N+1:0]       PP      [K:0]; //riyaj 
reg [N+N-1:0]   ACC     [K:0];
reg [N+N-1:0]   ANS;
reg mux;
reg ord = 0;

integer i , j, t, b;
integer  m = 8;        //number of bits to approximate
integer d = 8;

assign x_new = {2'b0,x};


always@(*)

begin
    bits[0] = {y[1],y[0],1'b0};             //setting last bit -1 as 0

    for(i=1; i<K+1; i=i+1) begin
            if(i == K)
                bits[i] = {2'b0,y[2*i-1]};
            else
                bits[i] = {y[2*i+1], y[2*i], y[2*i-1]};
            //$display("%b", bits[i]);
            
        end


    for(i=0; i<K+1; i=i+1)
        begin                               //approximated 2A as A introduced error
            case(bits[i])

            
            3'b001, 3'b010:         
            begin
                neg[i] = 1'b0;
                two[i] = 1'b0;
                zero[i] = 1'b0;
            end

            3'b011:
            begin
                neg[i] = 1'b0;
                two[i] = 1'b1;
                zero[i] = 1'b0;
            end

            3'b101, 3'b110:         
            begin 
               neg[i] = 1'b1;
                two[i] = 1'b0;
                zero[i] = 1'b0;
            end

            3'b100:
            begin
                neg[i] = 1'b1;
                two[i] = 1'b1;
                zero[i] = 1'b0;
            end
         
            default: 
            begin
                neg[i] = 1'b0;
                two[i] = 1'b0;
                zero[i] = 1'b1;
            end

            endcase

            PP[i] = 0;
            PP[i][N+1] = neg[i];           //sign conservation

            for(t=0; t<N+1; t=t+1) begin
                if(t>=m) 
                begin
                    mux = (x_new[t] & ~two[i]) | (x_new[t-1] & two[i]);             
                    PP[i][t] = ~zero[i] & (neg[i] ^ mux);
                end

                else 
                begin
                    for(b=0; b<d;b=b+1) begin
                        ord = ord | x_new[b];
                    end
                    PP[i][t] = ord & ~zero[i];
                    d = d-2;
                    
                end
            end

            PP[i][0] = PP[i][0] | neg[i];

            ACC[i] = $signed(PP[i]);        //sign extension
            
            for(j=0; j<i; j=j+1)
                ACC[i] = {ACC[i],2'b00};        //shifting

        
        end

    ANS = ACC[0];

    for(i=1; i<K+1; i=i+1)
        ANS = ANS+ACC[i];
        
end


assign p = ANS;

endmodule

ABM-M3-Karatsuba-bitwise-32-double approx/radix4approx18bit_tb.v
`timescale 10ms / 1ms
`include "radix4approx18bit.v"

module radix4approx18bit_tb();


reg  unsigned [17 : 0]   x,y;

wire unsigned [35:0]   p;

integer i, out, seed=7;

radix4approx18bit uut(p,x,y);

initial begin
    $dumpfile("radix4approx18bit.vcd");
    $dumpvars(0, radix4approx18bit_tb);
    out = $fopen("radix4-approx-18bit-mult-result.csv");
    

    for(i=0; i<50; i=i+1)
        begin
        x = $urandom(seed) %262143;
        y = $urandom(seed) %262143;


        #1;
        $fwrite(out, "%d, %d, %d\n", x,y,p);
        #4;
    end
    $finish;
end
endmodule

ABM-M3-Karatsuba-bitwise-32-double approx/radix4approx18bit.vcd
$date
	Tue Sep  7 15:11:55 2021
$end
$version
	Icarus Verilog
$end
$timescale
	1ms
$end
$scope module radix4approx18bit_tb $end
$var wire 36 ! p [35:0] $end
$var reg 18 " x [17:0] $end
$var reg 18 # y [17:0] $end
$var integer 32 $ i [31:0] $end
$var integer 32 % out [31:0] $end
$var integer 32 & seed [31:0] $end
$scope module uut $end
$var wire 36 ' p [35:0] $end
$var wire 18 ( x [17:0] $end
$var wire 18 ) y [17:0] $end
$var wire 20 * x_new [19:0] $end
$var reg 36 + ANS [35:0] $end
$var reg 1 , mux $end
$var reg 1 - ord $end
$var integer 32 . b [31:0] $end
$var integer 32 / d [31:0] $end
$var integer 32 0 i [31:0] $end
$var integer 32 1 j [31:0] $end
$var integer 32 2 m [31:0] $end
$var integer 32 3 t [31:0] $end
$upscope $end
$upscope $end
$enddefinitions $end
#0
$dumpvars
b10011 3
b1000 2
b1001 1
b1010 0
b11111111111111111111111101101000 /
b0 .
1-
0,
b110100111100111101110110010101011 +
b110110001000000001 *
b111110100100111 )
b110110001000000001 (
b110100111100111101110110010101011 '
b11000110011011000100100011101101 &
b10 %
b0 $
b111110100100111 #
b110110001000000001 "
b110100111100111101110110010101011 !
$end
#50
b11111000111110101100011011011101011 !
b11111000111110101100011011011101011 '
b11111000111110101100011011011101011 +
b1001 1
0,
b11111111111111111111111011001000 /
b10011 3
b1010 0
b100010011011110111 #
b100010011011110111 )
b111001110010101111 *
b111001110010101111 "
b111001110010101111 (
b10101110011011011111100111000011 &
b1 $
#100
b11001101010110011011000101110110000 !
b11001101010110011011000101110110000 '
b11001101010110011011000101110110000 +
b1001 1
0,
b11111111111111111111111000101000 /
b10011 3
b1010 0
b100010011110010000 #
b100010011110010000 )
b101111100111011011 *
b101111100111011011 "
b101111100111011011 (
b11001111110001011111000000001001 &
b10 $
#150
b111001111001000100110101010110000 !
b111001111001000100110101010110000 '
b111001111001000100110101010110000 +
b1001 1
0,
b11111111111111111111110110001000 /
b10011 3
b1010 0
b1010011010100000 #
b1010011010100000 )
b101100011001101011 *
b101100011001101011 "
b101100011001101011 (
b10011100001010010100111111 &
b11 $
#200
b100101001000000100111100000110111011 !
b100101001000000100111100000110111011 '
b100101001000000100111100000110111011 +
b1001 1
0,
b11111111111111111111110011101000 /
b10011 3
b1010 0
b101001000001111010 #
b101001000001111010 )
b111001110100011000 *
b111001110100011000 "
b111001110100011000 (
b1110111101000111011100101 &
b100 $
#250
b101100010110111111010000111010101100 !
b101100010110111111010000111010101100 '
b101100010110111111010000111010101100 +
b1001 1
0,
b11111111111111111111110001001000 /
b10011 3
b1010 0
b111000001101101000 #
b111000001101101000 )
b110010011110001101 *
b110010011110001101 "
b110010011110001101 (
b1101001110110111111001111011 &
b101 $
#300
b10000000110011110011100011010111011 !
b10000000110011110011100011010111011 '
b10000000110011110011100011010111011 +
b1001 1
0,
b11111111111111111111101110101000 /
b10011 3
b1010 0
b10010000100111001 #
b10010000100111001 )
b111000111101011011 *
b111000111101011011 "
b111000111101011011 (
b1111001000111010000000110000001 &
b110 $
#350
b101100011100011110010010111111101100 !
b101100011100011110010010111111101100 '
b101100011100011110010010111111101100 +
b1001 1
0,
b11111111111111111111101100001000 /
b10011 3
b1010 0
b111101101111110100 #
b111101101111110100 )
b101110000010100000 *
b101110000010100000 "
b101110000010100000 (
b1100100101011111100000101110111 &
b111 $
#400
b110010001011001010101111 !
b110010001011001010101111 '
b110010001011001010101111 +
b1001 1
0,
b11111111111111111111101001101000 /
b10011 3
b1010 0
b111101011111 #
b111101011111 )
b110001100000 *
b110001100000 "
b110001100000 (
b10101000001110111110001111011101 &
b1000 $
#450
b1100000000110100001001010111111 !
b1100000000110100001001010111111 '
b1100000000110100001001010111111 +
b1001 1
0,
b11111111111111111111100111001000 /
b10011 3
b1010 0
b110111100111111 #
b110111100111111 )
b1101110011100101 *
b1101110011100101 "
b1101110011100101 (
b1100100110000110101000110011 &
b1001 $
#500
b100101000001000010011011110101111 !
b100101000001000010011011110101111 '
b100101000001000010011011110101111 +
b1001 1
0,
b11111111111111111111100100101000 /
b10011 3
b1010 0
b11010100101101110 #
b11010100101101110 )
b1011000111100100 *
b1011000111100100 "
b1011000111100100 (
b1011010111001011001000111111001 &
b1010 $
#550
b101010011110001110111111011111100 !
b101010011110001110111111011111100 '
b101010011110001110111111011111100 +
b1001 1
0,
b11111111111111111111100010001000 /
b10011 3
b1010 0
b100110100111111100 #
b100110100111111100 )
b1000101100010110 *
b1000101100010110 "
b1000101100010110 (
b11001001101001100011010010101111 &
b1011 $
#600
b101110001010010111010101100 !
b101110001010010111010101100 '
b101110001010010111010101100 +
b1001 1
0,
b11111111111111111111011111101000 /
b10011 3
b1010 0
b11001001010100 #
b11001001010100 )
b1110000011011 *
b1110000011011 "
b1110000011011 (
b101000000100000010011111010101 &
b1100 $
#650
b101001111110000011100011001110111111 !
b101001111110000011100011001110111111 '
b101001111110000011100011001110111111 +
b1001 1
0,
b11111111111111111111011101001000 /
b10011 3
b1010 0
b111101011000111110 #
b111101011000111110 )
b101011101111001111 *
b101011101111001111 "
b101011101111001111 (
b11011010001010111001110011101011 &
b1101 $
#700
b11001001010010100000111010010101011 !
b11001001010010100000111010010101011 '
b11001001010010100000111010010101011 +
b1001 1
0,
b11111111111111111111011010101000 /
b10011 3
b1010 0
b11010111101100110 #
b11010111101100110 )
b111011101101000100 *
b111011101101000100 "
b111011101101000100 (
b10110000000110011000000101110001 &
b1110 $
#750
b10101001010001000110111110111011 !
b10101001010001000110111110111011 '
b10101001010001000110111110111011 +
b1001 1
0,
b11111111111111111111011000001000 /
b10011 3
b1010 0
b10001010111000111 #
b10001010111000111 )
b1001101111111110 *
b1001101111111110 "
b1001101111111110 (
b11010000100110001101111011100111 &
b1111 $
#800
b101110101100111001101101110110101011 !
b101110101100111001101101110110101011 '
b101110101100111001101101110110101011 +
b1001 1
0,
b11111111111111111111010101101000 /
b10011 3
b1010 0
b110110111000101101 #
b110110111000101101 )
b110110011010000001 *
b110110011010000001 "
b110110011010000001 (
b11000010101000110011101011001101 &
b10000 $
#850
b111001010110000011010110001011111100 !
b111001010110000011010110001011111100 '
b111001010110000011010110001011111100 +
b1001 1
0,
b11111111111111111111010011001000 /
b10011 3
b1010 0
b111111101100000100 #
b111111101100000100 )
b111001100100100001 *
b111001100100100001 "
b111001100100100001 (
b1011101101111111011010100011 &
b10001 $
#900
b10101101010110110000010000110101011 !
b10101101010110110000010000110101011 '
b10101101010110110000010000110101011 +
b1001 1
0,
b11111111111111111111010000101000 /
b10011 3
b1010 0
b101100001010011011 #
b101100001010011011 )
b11111010101111110 *
b11111010101111110 "
b11111010101111110 (
b1001000001011101010111111101001 &
b10010 $
#950
b111100000110011110100111110111011 !
b111100000110011110100111110111011 '
b111100000110011110100111110111011 +
b1001 1
0,
b11111111111111111111001110001000 /
b10011 3
b1010 0
b1010010000111011 #
b1010010000111011 )
b101110110011000110 *
b101110110011000110 "
b101110110011000110 (
b1000101010001010000000011111 &
b10011 $
#1000
b11110001010111011100001011101100 !
b11110001010111011100001011101100 '
b11110001010111011100001011101100 +
b1001 1
0,
b11111111111111111111001011101000 /
b10011 3
b1010 0
b10010000111110100 #
b10010000111110100 )
b1101010000010000 *
b1101010000010000 "
b1101010000010000 (
b10001011011110001111110011000101 &
b10100 $
#1050
b11001010010010001011001110111100 !
b11001010010010001011001110111100 '
b11001010010010001011001110111100 +
b1001 1
0,
b11111111111111111111001001001000 /
b10011 3
b1010 0
b111101110111100 #
b111101110111100 )
b11010001000000001 *
b11010001000000001 "
b11010001000000001 (
b10001010100111000101011101011011 &
b10101 $
#1100
b111111111001101010011111010101011 !
b111111111001101010011111010101011 '
b111111111001101010011111010101011 +
b1001 1
0,
b11111111111111111111000110101000 /
b10011 3
b1010 0
b110000111000100010 #
b110000111000100010 )
b1010011001001100 *
b1010011001001100 "
b1010011001001100 (
b111110100101101111110101100001 &
b10110 $
#1150
b10101010010001101001110111100 !
b10101010010001101001110111100 '
b10101010010001101001110111100 +
b1001 1
0,
b11111111111111111111000100001000 /
b10011 3
b1010 0
b100110111110111100 #
b100110111110111100 )
b11101011000 *
b11101011000 "
b11101011000 (
b1010100010100100101100001010111 &
b10111 $
#1200
b111111111101000101010110101011 !
b111111111101000101010110101011 '
b111111111101000101010110101011 +
b1001 1
0,
b11111111111111111111000001101000 /
b10011 3
b1010 0
b10110010010100011 #
b10110010010100011 )
b10110101001010 *
b10110101001010 "
b10110101001010 (
b1010111110100010100110110111101 &
b11000 $
#1250
b101101001000001001100110000110101011 !
b101101001000001001100110000110101011 '
b101101001000001001100110000110101011 +
b1001 1
0,
b11111111111111111110111111001000 /
b10011 3
b1010 0
b111101110110110010 #
b111101110110110010 )
b101110101011010100 *
b101110101011010100 "
b101110101011010100 (
b11101111010100111001111100010011 &
b11001 $
#1300
b10101100001100100110111110101100 !
b10101100001100100110111110101100 '
b10101100001100100110111110101100 +
b1001 1
0,
b11111111111111111110111100101000 /
b10011 3
b1010 0
b111001111010100 #
b111001111010100 )
b10111110000001111 *
b10111110000001111 "
b10111110000001111 (
b10100010010000000100100111011001 &
b11010 $
#1350
b11011111111100011101101010101100 !
b11011111111100011101101010101100 '
b11011111111100011101101010101100 +
b1001 1
0,
b11111111111111111110111010001000 /
b10011 3
b1010 0
b110001100010110100 #
b110001100010110100 )
b100011110111011 *
b100011110111011 "
b100011110111011 (
b10111100111011101110011110001111 &
b11011 $
#1400
b101010110110111001101110111011 !
b101010110110111001101110111011 '
b101010110110111001101110111011 +
b1001 1
0,
b11111111111111111110110111101000 /
b10011 3
b1010 0
b11011011000110 #
b11011011000110 )
b1100011111010001 *
b1100011111010001 "
b1100011111010001 (
b10011110001010000000110110110101 &
b11100 $
#1450
b111001010010101011011110110101011 !
b111001010010101011011110110101011 '
b111001010010101011011110110101011 +
b1001 1
0,
b11111111111111111110110101001000 /
b10011 3
b1010 0
b1100000111010110 #
b1100000111010110 )
b100101110010010110 *
b100101110010010110 "
b100101110010010110 (
b1001100111101001010110111001011 &
b11101 $
#1500
b11001011001010111101111010101111 !
b11001011001010111101111010101111 '
b11001011001010111101111010101111 +
b1001 1
0,
b11111111111111111110110010101000 /
b10011 3
b1010 0
b111100101011111 #
b111100101011111 )
b11010110000011000 *
b11010110000011000 "
b11010110000011000 (
b1101000101000111010101010001 &
b11110 $
#1550
b100010001010110010010101011111100 !
b100010001010110010010101011111100 '
b100010001010110010010101011111100 +
b1001 1
0,
b11111111111111111110110000001000 /
b10011 3
b1010 0
b110101110011111000 #
b110101110011111000 )
b101000000011011 *
b101000000011011 "
b101000000011011 (
b10110110001100110010110111000111 &
b11111 $
#1600
b1001001110001011110010101111111100 !
b1001001110001011110010101111111100 '
b1001001110001011110010101111111100 +
b1001 1
0,
b11111111111111111110101101101000 /
b10011 3
b1010 0
b10010111111111000 #
b10010111111111000 )
b11111000011100001 *
b11111000011100001 "
b11111000011100001 (
b1000101101101010001110010101101 &
b100000 $
#1650
b10001110111110000111010110011111011 !
b10001110111110000111010110011111011 '
b10001110111110000111010110011111011 +
b1001 1
0,
b11111111111111111110101011001000 /
b10011 3
b1010 0
b101000000000000101 #
b101000000000000101 )
b11100100010001100 *
b11100100010001100 "
b11100100010001100 (
b1101100101100100110001110000011 &
b100001 $
#1700
b1110000001111001110100111010101100 !
b1110000001111001110100111010101100 '
b1110000001111001110100111010101100 +
b1001 1
0,
b11111111111111111110101000101000 /
b10011 3
b1010 0
b10110101100110100 #
b10110101100110100 )
b100111100001010100 *
b100111100001010100 "
b100111100001010100 (
b101011011110010101111111001001 &
b100010 $
#1750
b100001011101100111101111 !
b100001011101100111101111 '
b100001011101100111101111 +
b1001 1
0,
b11111111111111111110100110001000 /
b10011 3
b1010 0
b100001000001111 #
b100001000001111 )
b100101001 *
b100101001 "
b100101001 (
b11010001101100000000101011111111 &
b100011 $
#1800
b101100001101100110001110010111011 !
b101100001101100110001110010111011 '
b101100001101100110001110010111011 +
b1001 1
0,
b11111111111111111110100011101000 /
b10011 3
b1010 0
b111011001000110 #
b111011001000110 )
b101111110100101100 *
b101111110100101100 "
b101111110100101100 (
b1100101111011000101101010100101 &
b100100 $
#1850
b11010110010001001100111010101100 !
b11010110010001001100111010101100 '
b11010110010001001100111010101100 +
b1001 1
0,
b11111111111111111110100001001000 /
b10011 3
b1010 0
b111100000101001000 #
b111100000101001000 )
b11100001010100 *
b11100001010100 "
b11100001010100 (
b1111001010110111010000000111011 &
b100101 $
#1900
b101100010101001110101010010101011 !
b101100010101001110101010010101011 '
b101100010101001110101010010101011 +
b1001 1
0,
b11111111111111111110011110101000 /
b10011 3
b1010 0
b1111011101011011 #
b1111011101011011 )
b10110111001011010 *
b10110111001011010 "
b10110111001011010 (
b110011110100001110100101000001 &
b100110 $
#1950
b1000010010100100100011010101100 !
b1000010010100100100011010101100 '
b1000010010100100100011010101100 +
b1001 1
0,
b11111111111111111110011100001000 /
b10011 3
b1010 0
b101001101001011000 #
b101001101001011000 )
b1100011011111 *
b1100011011111 "
b1100011011111 (
b11100010010100100101111100110111 &
b100111 $
#2000
b11000110001000110111010101010101011 !
b11000110001000110111010101010101011 '
b11000110001000110111010101010101011 +
b1001 1
0,
b11111111111111111110011001101000 /
b10011 3
b1010 0
b11110011101101010 #
b11110011101101010 )
b110100000000010100 *
b110100000000010100 "
b110100000000010100 (
b11110101111111011010011110011101 &
b101000 $
#2050
b101011111001101000001100011011101011 !
b101011111001101000001100011011101011 '
b101011111001101000001100011011101011 +
b1001 1
0,
b11111111111111111110010111001000 /
b10011 3
b1010 0
b110100101011101011 #
b110100101011101011 )
b110101010001011001 *
b110101010001011001 "
b110101010001011001 (
b11010110110110100001111110011 &
b101001 $
#2100
b10000010110010101111100110011101011 !
b10000010110010101111100110011101011 '
b10000010110010101111100110011101011 +
b1001 1
0,
b11111111111111111110010100101000 /
b10011 3
b1010 0
b10000011000011001 #
b10000011000011001 )
b111111110111001101 *
b111111110111001101 "
b111111110111001101 (
b1001101111110001111000110111001 &
b101010 $
#2150
b1100011110111110110010010111101011 !
b1100011110111110110010010111101011 '
b1100011110111110110010010111101011 +
b1001 1
0,
b11111111111111111110010010001000 /
b10011 3
b1010 0
b110011000100010111 #
b110011000100010111 )
b1111100110100010 *
b1111100110100010 "
b1111100110100010 (
b10001111111000110000101001101111 &
b101011 $
#2200
b1000110010110101010100101011101011 !
b1000110010110101010100101011101011 '
b1000110010110101010100101011101011 +
b1001 1
0,
b11111111111111111110001111101000 /
b10011 3
b1010 0
b1111111111101101 #
b1111111111101101 )
b100011001001000110 *
b100011001001000110 "
b100011001001000110 (
b1101100010101001110001110010101 &
b101100 $
#2250
b1100011110010000101111010101111 !
b1100011110010000101111010101111 '
b1100011110010000101111010101111 +
b1001 1
0,
b11111111111111111110001101001000 /
b10011 3
b1010 0
b11000001110001 #
b11000001110001 )
b100000111010101101 *
b100000111010101101 "
b100000111010101101 (
b1101110000010111010101011 &
b101101 $
#2300
b101111010001001001111011010010111011 !
b101111010001001001111011010010111011 '
b101111010001001001111011010010111011 +
b1001 1
0,
b11111111111111111110001010101000 /
b10011 3
b1010 0
b111001011010000111 #
b111001011010000111 )
b110100101000110100 *
b110100101000110100 "
b110100101000110100 (
b11101010110010110101100100110001 &
b101110 $
#2350
b100101011001011111010000101110101011 !
b100101011001011111010000101110101011 '
b100101011001011111010000101110101011 +
b1001 1
0,
b11111111111111111110001000001000 /
b10011 3
b1010 0
b110000010101010110 #
b110000010101010110 )
b110001011111000110 *
b110001011111000110 "
b110001011111000110 (
b1011010100001101110110010100111 &
b101111 $
#2400
b11000101101101000110010110010101011 !
b11000101101101000110010110010101011 '
b11000101101101000110010110010101011 +
b1001 1
0,
b11111111111111111110000101101000 /
b10011 3
b1010 0
b100000010000100010 #
b100000010000100010 )
b110000111110110110 *
b110000111110110110 "
b110000111110110110 (
b1001110000110011110111010001101 &
b110000 $
#2450
b1110001110101011000110001110101011 !
b1110001110101011000110001110101011 '
b1110001110101011000110001110101011 +
b1001 1
0,
b11111111111111111110000011001000 /
b10011 3
b1010 0
b10111110001101010 #
b10111110001101010 )
b100110010000101111 *
b100110010000101111 "
b100110010000101111 (
b11100010100101010100000001100011 &
b110001 $
#2500
b110010 $
