ABM-M1-Karatsuba-bitwise-32- double approx/radix4approx18bit.v
`timescale 10ms / 1ms

module radix4approx18bit(p,x,y);         

parameter N = 18;   //size of muliplicant and multiplier
parameter K = N/2;  //

input   [N-1 : 0]   x,y;
output  [N+N-1:0]   p;

reg [2:0]   bits    [K:0];
reg   neg     [K:0];
reg   two     [K:0];
reg   zero     [K:0];

wire [N+1:0] x_new;
reg [N+1:0]       PP      [K:0]; //riyaj 
reg [N+N-1:0]   ACC     [K:0];
reg [N+N-1:0]   ANS;
reg mux;

integer i , j, t;
integer  m = 12;        //number of bits to approximate

assign x_new = {2'b0,x};

always@(*)

begin
    bits[0] = {y[1],y[0],1'b0};             //setting last bit -1 as 0

    for(i=1; i<K+1; i=i+1) begin
            if(i == K)
                bits[i] = {2'b0,y[2*i-1]};
            else
                bits[i] = {y[2*i+1], y[2*i], y[2*i-1]};
            //$display("%b", bits[i]);
            
        end


    for(i=0; i<K+1; i=i+1)
        begin                               //approximated 2A as A introduced error
            case(bits[i])

            
            3'b001, 3'b010:         
            begin
                neg[i] = 1'b0;
                two[i] = 1'b0;
                zero[i] = 1'b0;
            end

            3'b011:
            begin
                neg[i] = 1'b0;
                two[i] = 1'b1;
                zero[i] = 1'b0;
            end

            3'b101, 3'b110:         
            begin 
               neg[i] = 1'b1;
                two[i] = 1'b0;
                zero[i] = 1'b0;
            end

            3'b100:
            begin
                neg[i] = 1'b1;
                two[i] = 1'b1;
                zero[i] = 1'b0;
            end
         
            default: 
            begin
                neg[i] = 1'b0;
                two[i] = 1'b0;
                zero[i] = 1'b1;
            end

            endcase

            PP[i] = 0;
            PP[i][N+1] = neg[i];           //sign conservation

            for(t=0; t<N+1; t=t+1) begin
                if(t>=m) 
                begin
                    mux = (x_new[t] & ~two[i]) | (x_new[t-1] & two[i]);             
                    PP[i][t] = ~zero[i] & (neg[i] ^ mux);
                end

                else 
                begin
                    PP[i][t] = (~x_new[t] & neg[i]) | (x_new[t] & ~neg[i] & ~zero[i]);
                end
            end

            PP[i][0] = PP[i][0] | neg[i];

            ACC[i] = $signed(PP[i]);        //sign extension
            
            for(j=0; j<i; j=j+1)
                ACC[i] = {ACC[i],2'b00};        //shifting

        
        end

    ANS = ACC[0];

    for(i=1; i<K+1; i=i+1)
        ANS = ANS+ACC[i];
        
end


assign p = ANS;

endmodule

ABM-M1-Karatsuba-bitwise-32/adder8.v
`timescale 10ms / 1ms

module adder8(s,a,b);

input [15:0] a,b;

output [16:0] s;


assign s = a+b;

endmodule

ABM-M1-Karatsuba-bitwise-32- double approx/radix4approx.v
`timescale 10ms / 1ms

module radix4approx(p,x,y);         //8 bit multiplier to give 16 bit product

parameter N = 16;   //size of muliplicant and multiplier
parameter K = N/2;  //

input   [N-1 : 0]   x,y;
output  [N+N-1:0]   p;

reg [2:0]   bits    [K:0];
reg   neg     [K:0];
reg   two     [K:0];
reg   zero     [K:0];

wire [N+1:0] x_new;
reg [N+1:0]       PP      [K:0]; //riyaj 
reg [N+N-1:0]   ACC     [K:0];
reg [N+N-1:0]   ANS;
reg mux;

integer i , j, t;
integer  m = 8;        //number of bits to approximate

assign x_new = {2'b0,x};

always@(*)

begin
    bits[0] = {y[1],y[0],1'b0};             //setting last bit -1 as 0

    for(i=1; i<K+1; i=i+1) begin
            if(i == K)
                bits[i] = {2'b0,y[2*i-1]};
            else
                bits[i] = {y[2*i+1], y[2*i], y[2*i-1]};
            //$display("%b", bits[i]);
            
        end


    for(i=0; i<K+1; i=i+1)
        begin                               //approximated 2A as A introduced error
            case(bits[i])

            
            3'b001, 3'b010:         
            begin
                neg[i] = 1'b0;
                two[i] = 1'b0;
                zero[i] = 1'b0;
            end

            3'b011:
            begin
                neg[i] = 1'b0;
                two[i] = 1'b1;
                zero[i] = 1'b0;
            end

            3'b101, 3'b110:         
            begin 
               neg[i] = 1'b1;
                two[i] = 1'b0;
                zero[i] = 1'b0;
            end

            3'b100:
            begin
                neg[i] = 1'b1;
                two[i] = 1'b1;
                zero[i] = 1'b0;
            end
         
            default: 
            begin
                neg[i] = 1'b0;
                two[i] = 1'b0;
                zero[i] = 1'b1;
            end

            endcase

            PP[i] = 0;
            PP[i][N+1] = neg[i];           //sign conservation

            for(t=0; t<N+1; t=t+1) begin
                if(t>=m) 
                begin
                    mux = (x_new[t] & ~two[i]) | (x_new[t-1] & two[i]);             
                    PP[i][t] = ~zero[i] & (neg[i] ^ mux);
                end

                else 
                begin
                    PP[i][t] = (~x_new[t] & neg[i]) | (x_new[t] & ~neg[i] & ~zero[i]);
                end
            end

            PP[i][0] = PP[i][0] | neg[i];

            ACC[i] = $signed(PP[i]);        //sign extension
            
            for(j=0; j<i; j=j+1)
                ACC[i] = {ACC[i],2'b00};        //shifting

        
        end

    ANS = ACC[0];

    for(i=1; i<K+1; i=i+1)
        ANS = ANS+ACC[i];
        
end


assign p = ANS;

endmodule

ABM-M1-WT-bitwise-32/radix4acc.v
`timescale 10ms / 1ms

module radix4acc(p,x,y);        

parameter N = 16;   //size of muliplicant and multiplier
parameter K = N/2;  //

input [N-1 : 0]   x,y;
output [N+N-1:0]   p;

reg [2:0]   bits    [K:0];
reg   neg     [K:0];
reg   two     [K:0];
reg   zero     [K:0];

wire [N+1:0] x_new;
reg [N+1:0]       PP      [K:0]; 
reg [N+N-1:0]   ACC     [K:0];
reg [N+N-1:0]   ANS;
reg mux;

integer i , j, t;

assign x_new = {2'b0,x};

always@(*)

begin
    bits[0] = {y[1],y[0],1'b0};             //setting last bit -1 as 0
    //$display("%b", bits[0]);
    for(i=1; i<K+1; i=i+1) begin
        if(i == K)
            bits[i] = {2'b0,y[2*i-1]};
        else
            bits[i] = {y[2*i+1], y[2*i], y[2*i-1]};
        //$display("%b", bits[i]);
        
    end

    for(i=0; i<K+1; i=i+1)
        begin                                      //accurate cases
            case(bits[i])

            
            3'b001, 3'b010:         
            begin
                neg[i] = 1'b0;
                two[i] = 1'b0;
                zero[i] = 1'b0;
            end

            3'b011:
            begin
                neg[i] = 1'b0;
                two[i] = 1'b1;
                zero[i] = 1'b0;
            end

            3'b101, 3'b110:         
            begin 
               neg[i] = 1'b1;
                two[i] = 1'b0;
                zero[i] = 1'b0;
            end

            3'b100:
            begin
                neg[i] = 1'b1;
                two[i] = 1'b1;
                zero[i] = 1'b0;
            end
         
            default: 
            begin
                neg[i] = 1'b0;
                two[i] = 1'b0;
                zero[i] = 1'b1;
            end

            endcase
            
            //$display("%b %b %b", neg[i], two[i], zero[i]);
            
            PP[i] = 0;
            PP[i][N+1] = neg[i];           //sign conservation

            for(t=0; t<N+1; t=t+1) begin
                if(t==0) 
                    mux = (x_new[t] & ~two[i]) | (1'b0 & two[i]);
                
                else
                    mux = (x_new[t] & ~two[i]) | (x_new[t-1] & two[i]);

                
                PP[i][t] = ~zero[i] & (neg[i] ^ mux);       
            end

            PP[i] = PP[i] + neg[i];             //correction term added
            
            //$display("%b", PP[i]);

            ACC[i] = $signed(PP[i]);        //sign extension
            //$display("%b", ACC[i]);

            for(j=0; j<i; j=j+1)
                ACC[i] = {ACC[i],2'b00};        //shifting

        
        end

    ANS = ACC[0];

    for(i=1; i<K+1; i=i+1)
        ANS = ANS+ACC[i];
        
    
end


assign p = ANS;

endmodule

ABM-M1-Karatsuba-bitwise-32- double approx/karatsuba32.v
`timescale 10ms/1ms
`include "radix4acc.v"
`include "radix4approx.v"
`include "radix4approx18bit.v"
`include "adder8.v"

module karatsuba32(P,A,B);


parameter N = 32;   //size of muliplicant and multiplier
parameter K = N/2;  //

input   [N-1 : 0]   A,B;
output  [N+N-1:0]   P;

wire [K-1:0] AH, AL, BH, BL;

wire reg    [N-1:0]     M1, M2;
wire reg    [K:0]       S1, S2;
wire reg    [17:0]       c,d;
wire reg    [35:0]      M3;

reg [35:0] M4, M5, M6;

reg     [35:0]   A1, A2, A3;


reg [N+N-1:0]   ACC     [2:0];
reg [N+N-1:0] ANS;
integer i;


assign AH = A[N-1:K];
assign AL = A[K-1:0];

assign BH = B[N-1:K];
assign BL = B[K-1:0];



radix4acc ACC1(.p(M1), .x(AH), .y(BH));
radix4approx APP1(.p(M2), .x(AL), .y(BL));      //approx1


adder8 ADD1(.s(S1), .a(AH), .b(AL));
adder8 ADD2(.s(S2), .a(BH), .b(BL));

assign c = (S1);
assign d = (S2);

radix4approx18bit APP2(.p(M3), .x(c), .y(d));       //approx2


always@(*)
begin
    
    M4 = $signed(M1);
    M5 = $signed(M2);
    
    M6 = M3 - M4 - M5;

    ACC[0] = $signed(M6);
    ACC[0] = {ACC[0], {16{1'b0}}};

    ACC[1] = $signed(M2);
    
    ACC[2] = $signed(M1);
    ACC[2] = {ACC[2], {32{1'b0}}};

    ANS = ACC[0];
    for(i=1; i<3; i=i+1)
        ANS = ANS+ACC[i];
end

assign P = ANS;

endmodule

ABM-M1-Karatsuba-bitwise-32- double approx/karatsuba32_tb.v
`timescale 10ms / 1ms
`include "karatsuba32.v"

module karatsuba32_tb();

reg unsigned [31:0] A,B;
wire unsigned [63:0] P;
integer i, out, seed=7;


karatsuba32 uut(P,A,B);


initial begin
    $dumpfile("karatsuba32.vcd");
    $dumpvars(0, karatsuba32_tb);
    out = $fopen("results16.csv");
  
/*    
        A = 58;
        B = 84607;
        #1;
        $fwrite(out, "%d, %d, %d\n", A,B,P);
        #4;

        A = 73066;
        B = 615406;
        #1;
        $fwrite(out, "%d, %d, %d\n", A,B,P);
        #4;

        A = 10;
        B = 96224;
        #1;
        $fwrite(out, "%d, %d, %d\n", A,B,P);
        #4;

        A = 12;
        B = 94209;
        #1;
        $fwrite(out, "%d, %d, %d\n", A,B,P);
        #4;

        A = 20;
        B = 95679;
        #1;
        $fwrite(out, "%d, %d, %d\n", A,B,P);
        #4;
    */

    
    for(i=0; i<100; i=i+1)                       //10 test cases A and B: 1-100 
    begin
        A = $urandom(seed) %200 + 65536;
        B = $urandom(seed) %200;
        #1;
        $fwrite(out, "%d, %d, %d\n", A,B,P);
        #4;
    end

    for(i=0; i<100; i=i+1)                       //10 test cases A: 1-100 B: till 2^15
    begin
        A = $urandom(seed) %200;
        B = $urandom(seed) %32768 + 65536;
        #1;
        $fwrite(out, "%d, %d, %d\n", A,B,P);
        #4;
    end

    for(i=0; i<100; i=i+1)                       //10 test cases B: 1-100 A: till 2^32
    begin
        A = $urandom(seed) %4294967295;
        B = $urandom(seed) %200 + 65535;
        #1;
        $fwrite(out, "%d, %d, %d\n", A,B,P);
        #4;
    end

    
    for(i=0; i<200; i=i+1)                       //50 cases : till 1024 A: 2^10 B: 2^20
    begin
        A = $urandom(seed) %1024;
        B = $urandom(seed) %1048576;
        #1;
        $fwrite(out, "%d, %d, %d\n", A,B,P);
        #4;
    end

    for(i=0; i<500; i=i+1)                       //500 cases : till 32768 which is 2^15
    begin
        A = $urandom(seed) %65536 + 65536;
        B = $urandom(seed) %32768;
        #1;
        $fwrite(out, "%d, %d, %d\n", A,B,P);
        #4;
    end

    for(i=0; i<500; i=i+1)                       //500 cases : till 2^20
    begin
        A = $urandom(seed) %1048576;
        B = $urandom(seed) %1048576;
        #1;
        $fwrite(out, "%d, %d, %d\n", A,B,P);
        #4;
    end

    for(i=0; i<500; i=i+1)                       //50 cases : till 1024 A: 2^32 B: 2^20
    begin
        A = $urandom(seed) %4294967295;
        B = $urandom(seed) %1048576;
        #1;
        $fwrite(out, "%d, %d, %d\n", A,B,P);
        #4;
    end

    for(i=0; i<500; i=i+1)                          //50 cases till 2^32
    begin
        A = $urandom(seed) %4294967295;
        B = $urandom(seed) %4294967295;
        #1;
        $fwrite(out, "%d, %d, %d\n", A,B,P);
        #4;
    end
    
    
    $finish;
end

endmodule

ABM-M1-Karatsuba-bitwise-32- double approx/karatsuba32.vcd
$date
	Tue Sep  7 15:30:46 2021
$end
$version
	Icarus Verilog
$end
$timescale
	1ms
$end
$scope module karatsuba32_tb $end
$var wire 64 ! P [63:0] $end
$var reg 32 " A [31:0] $end
$var reg 32 # B [31:0] $end
$var integer 32 $ i [31:0] $end
$var integer 32 % out [31:0] $end
$var integer 32 & seed [31:0] $end
$scope module uut $end
$var wire 32 ' A [31:0] $end
$var wire 32 ( B [31:0] $end
$var wire 64 ) P [63:0] $end
$var wire 18 * d [17:0] $end
$var wire 18 + c [17:0] $end
$var wire 17 , S2 [16:0] $end
$var wire 17 - S1 [16:0] $end
$var wire 36 . M3 [35:0] $end
$var wire 32 / M2 [31:0] $end
$var wire 32 0 M1 [31:0] $end
$var wire 16 1 BL [15:0] $end
$var wire 16 2 BH [15:0] $end
$var wire 16 3 AL [15:0] $end
$var wire 16 4 AH [15:0] $end
$var reg 64 5 ANS [63:0] $end
$var reg 36 6 M4 [35:0] $end
$var reg 36 7 M5 [35:0] $end
$var reg 36 8 M6 [35:0] $end
$var integer 32 9 i [31:0] $end
$scope module ACC1 $end
$var wire 32 : p [31:0] $end
$var wire 16 ; x [15:0] $end
$var wire 16 < y [15:0] $end
$var wire 18 = x_new [17:0] $end
$var reg 32 > ANS [31:0] $end
$var reg 1 ? mux $end
$var integer 32 @ i [31:0] $end
$var integer 32 A j [31:0] $end
$var integer 32 B t [31:0] $end
$upscope $end
$scope module ADD1 $end
$var wire 16 C a [15:0] $end
$var wire 16 D b [15:0] $end
$var wire 17 E s [16:0] $end
$upscope $end
$scope module ADD2 $end
$var wire 16 F a [15:0] $end
$var wire 16 G b [15:0] $end
$var wire 17 H s [16:0] $end
$upscope $end
$scope module APP1 $end
$var wire 32 I p [31:0] $end
$var wire 16 J x [15:0] $end
$var wire 16 K y [15:0] $end
$var wire 18 L x_new [17:0] $end
$var reg 32 M ANS [31:0] $end
$var reg 1 N mux $end
$var integer 32 O i [31:0] $end
$var integer 32 P j [31:0] $end
$var integer 32 Q m [31:0] $end
$var integer 32 R t [31:0] $end
$upscope $end
$scope module APP2 $end
$var wire 36 S p [35:0] $end
$var wire 18 T x [17:0] $end
$var wire 18 U y [17:0] $end
$var wire 20 V x_new [19:0] $end
$var reg 36 W ANS [35:0] $end
$var reg 1 X mux $end
$var integer 32 Y i [31:0] $end
$var integer 32 Z j [31:0] $end
$var integer 32 [ m [31:0] $end
$var integer 32 \ t [31:0] $end
$upscope $end
$upscope $end
$upscope $end
$enddefinitions $end
#0
$dumpvars
b10011 \
b1000 [
b1001 Z
b1010 Y
0X
b1101000111010000110011011100100 W
b110001000000111 V
b10001000111111000 U
b110001000000111 T
b1101000111010000110011011100100 S
b10001 R
b1000 Q
b1000 P
b1001 O
0N
b11100111010111001001110111100 M
b110001000000000 L
b100101110001100 K
b110001000000000 J
b11100111010111001001110111100 I
b10001000111111000 H
b100101110001100 G
b1100011001101100 F
b110001000000111 E
b110001000000000 D
b111 C
b10001 B
b1000 A
b1001 @
0?
b1010110110011110100 >
b111 =
b1100011001101100 <
b111 ;
b1010110110011110100 :
b11 9
b1001011111101110110011000110100 8
b11100111010111001001110111100 7
b1010110110011110100 6
b101101110001110101110000011000111111001001110111100 5
b111 4
b110001000000000 3
b1100011001101100 2
b100101110001100 1
b1010110110011110100 0
b11100111010111001001110111100 /
b1101000111010000110011011100100 .
b110001000000111 -
b10001000111111000 ,
b110001000000111 +
b10001000111111000 *
b101101110001110101110000011000111111001001110111100 )
b11000110011011000100101110001100 (
b1110110001000000000 '
b11000110011011000100100011101101 &
b10 %
b0 $
b11000110011011000100101110001100 #
b1110110001000000000 "
b101101110001110101110000011000111111001001110111100 !
$end
#50
b11 9
b111011000011011111001111100011110010011010010011110111110110100 !
b111011000011011111001111100011110010011010010011110111110110100 )
b111011000011011111001111100011110010011010010011110111110110100 5
b11110111101111000010001111111110 8
b1101111010010111110111110110100 7
b1110110000110101111000000001011 6
b1110110000110101111000000001011 0
b1110110000110101111000000001011 :
b1110110000110101111000000001011 >
b1000 A
0?
b10001 B
b1001 @
b111011101001000110000001110111101 .
b111011101001000110000001110111101 S
b111011101001000110000001110111101 W
b1001 Z
0X
b10011 \
b1010 Y
b1101111010010111110111110110100 /
b1101111010010111110111110110100 I
b1101111010010111110111110110100 M
b1000 P
0N
b10001 R
b1001 O
b1010111001101101 2
b1010111001101101 <
b1010111001101101 F
b11010100111001001 *
b11010100111001001 U
b11010100111001001 ,
b11010100111001001 H
b1111101101011100 1
b1111101101011100 G
b1111101101011100 K
b1010110101010111 =
b1010110101010111 4
b1010110101010111 ;
b1010110101010111 C
b10001111010110001 V
b10001111010110001 +
b10001111010110001 T
b10001111010110001 -
b10001111010110001 E
b111000101011010 L
b111000101011010 3
b111000101011010 D
b111000101011010 J
b10101110011011011111101101011100 #
b10101110011011011111101101011100 (
b10101101010101110111000101011010 "
b10101101010101110111000101011010 '
b10101110011011011111100111000011 &
b1 $
#100
b11 9
b11000111101101011010111110001101001000000010010111101001110101 !
b11000111101101011010111110001101001000000010010111101001110101 )
b11000111101101011010111110001101001000000010010111101001110101 5
b111111000110110010110100011100101 8
b111111011111001001000111101001110101 7
b110001111010110111001100001010 6
b110001111010110111001100001010 0
b110001111010110111001100001010 :
b110001111010110111001100001010 >
b1000 A
0?
b10001 B
b1001 @
b1000001001111010010101011001100100 .
b1000001001111010010101011001100100 S
b1000001001111010010101011001100100 W
b1001 Z
0X
b10011 \
b1010 Y
b11011111001001000111101001110101 /
b11011111001001000111101001110101 I
b11011111001001000111101001110101 M
b1000 P
0N
b10001 R
b1001 O
b1100111111000101 2
b1100111111000101 <
b1100111111000101 F
b11100001101100100 *
b11100001101100100 U
b11100001101100100 ,
b11100001101100100 H
b1111001110011111 1
b1111001110011111 G
b1111001110011111 K
b11110110000010 =
b11110110000010 4
b11110110000010 ;
b11110110000010 C
b10010011111111101 V
b10010011111111101 +
b10010011111111101 T
b10010011111111101 -
b10010011111111101 E
b1110101001111011 L
b1110101001111011 3
b1110101001111011 D
b1110101001111011 J
b11001111110001011111001110011111 #
b11001111110001011111001110011111 (
b111101100000101110101001111011 "
b111101100000101110101001111011 '
b11001111110001011111000000001001 &
b10 $
#150
b11 9
b11100111001001000111110110011010001001011110000111110100 !
b11100111001001000111110110011010001001011110000111110100 )
b11100111001001000111110110011010001001011110000111110100 5
b111111000111010010100011011000 8
b1110001010011011110000111110100 7
b111001101110010101100000 6
b111001101110010101100000 0
b111001101110010101100000 :
b111001101110010101100000 >
b1000 A
0?
b10001 B
b1001 @
b10110001010100011111000000101100 .
b10110001010100011111000000101100 S
b10110001010100011111000000101100 W
b1001 Z
0X
b10011 \
b1010 Y
b1110001010011011110000111110100 /
b1110001010011011110000111110100 I
b1110001010011011110000111110100 M
b1000 P
0N
b10001 R
b1001 O
b1001110000 2
b1001110000 <
b1001110000 F
b1010100001110100 *
b1010100001110100 U
b1010100001110100 ,
b1010100001110100 H
b1010011000000100 1
b1010011000000100 G
b1010011000000100 K
b101111010111010 =
b101111010111010 4
b101111010111010 ;
b101111010111010 C
b10000110101110111 V
b10000110101110111 +
b10000110101110111 T
b10000110101110111 -
b10000110101110111 E
b1010111010111101 L
b1010111010111101 3
b1010111010111101 D
b1010111010111101 J
b10011100001010011000000100 #
b10011100001010011000000100 (
b1011110101110101010111010111101 "
b1011110101110101010111010111101 '
b10011100001010010100111111 &
b11 $
#200
b11 9
b10011000111111101011000001100000001101010000100111101001 !
b10011000111111101011000001100000001101010000100111101001 )
b10011000111111101011000001100000001101010000100111101001 5
b101111001111100001001101101111 8
b1001100110001100000100111101001 7
b100110001100111101110010 6
b100110001100111101110010 0
b100110001100111101110010 :
b100110001100111101110010 >
b1000 A
0?
b10001 B
b1001 @
b1111100100111001110110011001010 .
b1111100100111001110110011001010 S
b1111100100111001110110011001010 W
b1001 Z
0X
b10011 \
b1010 Y
b1001100110001100000100111101001 /
b1001100110001100000100111101001 I
b1001100110001100000100111101001 M
b1000 P
0N
b10001 R
b1001 O
b111011110 2
b111011110 <
b111011110 F
b1001000111100001 *
b1001000111100001 U
b1001000111100001 ,
b1001000111100001 H
b1001000000000011 1
b1001000000000011 G
b1001000000000011 K
b101000111010111 =
b101000111010111 4
b101000111010111 ;
b101000111010111 C
b1101101001111010 V
b1101101001111010 +
b1101101001111010 T
b1101101001111010 -
b1101101001111010 E
b1000100010100011 L
b1000100010100011 3
b1000100010100011 D
b1000100010100011 J
b1110111101001000000000011 #
b1110111101001000000000011 (
b1010001110101111000100010100011 "
b1010001110101111000100010100011 '
b1110111101000111011100101 &
b100 $
#250
b11 9
b10010111001000100001001001011100011100100001111011011001101 !
b10010111001000100001001001011100011100100001111011011001101 )
b10010111001000100001001001011100011100100001111011011001101 5
b101110101011011101101101000111 8
b1000010010011111011011001101 7
b100101110001110000111100101 6
b100101110001110000111100101 0
b100101110001110000111100101 :
b100101110001110000111100101 >
b1000 A
0?
b10001 B
b1001 @
b111011101100001011001111111001 .
b111011101100001011001111111001 S
b111011101100001011001111111001 W
b1001 Z
0X
b10011 \
b1010 Y
b1000010010011111011011001101 /
b1000010010011111011011001101 I
b1000010010011111011011001101 M
b1000 P
0N
b10001 R
b1001 O
b110100111011 2
b110100111011 <
b110100111011 F
b1000110101010101 *
b1000110101010101 U
b1000110101010101 ,
b1000110101010101 H
b1000000000011010 1
b1000000000011010 G
b1000000000011010 K
b101101101011111 =
b101101101011111 4
b101101101011111 ;
b101101101011111 C
b110110000010101 V
b110110000010101 +
b110110000010101 T
b110110000010101 -
b110110000010101 E
b1000010110110 L
b1000010110110 3
b1000010110110 D
b1000010110110 J
b1101001110111000000000011010 #
b1101001110111000000000011010 (
b1011011010111110001000010110110 "
b1011011010111110001000010110110 '
b1101001110110111111001111011 &
b101 $
#300
b11 9
b110110000001001011111001010001101110001100100011100000011011 !
b110110000001001011111001010001101110001100100011100000011011 )
b110110000001001011111001010001101110001100100011100000011011 5
b1000000110101010110110010100001 8
b1100100010011100000011011 7
b1101100000001110111010111111 6
b1101100000001110111010111111 0
b1101100000001110111010111111 :
b1101100000001110111010111111 >
b1000 A
0?
b10001 B
b1001 @
b1001111111001111001001101111011 .
b1001111111001111001001101111011 S
b1001111111001111001001101111011 W
b1001 Z
0X
b10011 \
b1010 Y
b1100100010011100000011011 /
b1100100010011100000011011 I
b1100100010011100000011011 M
b1000 P
0N
b10001 R
b1001 O
b111100100011101 2
b111100100011101 <
b111100100011101 F
b111110000001111 *
b111110000001111 U
b111110000001111 ,
b111110000001111 H
b1011110010 1
b1011110010 G
b1011110010 K
b1110010001011 =
b1110010001011 4
b1110010001011 ;
b1110010001011 C
b1010010011000100 V
b1010010011000100 +
b1010010011000100 T
b1010010011000100 -
b1010010011000100 E
b1000100000111001 L
b1000100000111001 3
b1000100000111001 D
b1000100000111001 J
b1111001000111010000001011110010 #
b1111001000111010000001011110010 (
b11100100010111000100000111001 "
b11100100010111000100000111001 '
b1111001000111010000000110000001 &
b110 $
#350
b11 9
b10111010111011010101011101110110100000100010011010010111001001 !
b10111010111011010101011101110110100000100010011010010111001001 )
b10111010111011010101011101110110100000100010011010010111001001 5
b110100111000011000000110000111001 8
b111110010100010100001010010111001001 7
b101110101110011010111011010010 6
b101110101110011010111011010010 0
b101110101110011010111011010010 :
b101110101110011010111011010010 >
b1000 A
0?
b10001 B
b1001 @
b101101010000101100110000011010100 .
b101101010000101100110000011010100 S
b101101010000101100110000011010100 W
b1001 Z
0X
b10011 \
b1010 Y
b10010100010100001010010111001001 /
b10010100010100001010010111001001 I
b10010100010100001010010111001001 M
b1000 P
0N
b10001 R
b1001 O
b110010010101111 2
b110010010101111 <
b110010010101111 F
b10010011101111000 *
b10010011101111000 U
b10010011101111000 ,
b10010011101111000 H
b1100001011001001 1
b1100001011001001 G
b1100001011001001 K
b111011011001110 =
b111011011001110 4
b111011011001110 ;
b111011011001110 C
b10011100110111011 V
b10011100110111011 +
b10011100110111011 T
b10011100110111011 -
b10011100110111011 E
b1100001011101101 L
b1100001011101101 3
b1100001011101101 D
b1100001011101101 J
b1100100101011111100001011001001 #
b1100100101011111100001011001001 (
b1110110110011101100001011101101 "
b1110110110011101100001011101101 '
b1100100101011111100000101110111 &
b111 $
#400
b11 9
b11001111110000101110010001001010000100100001101101011101100000 !
b11001111110000101110010001001010000100100001101101011101100000 )
b11001111110000101110010001001010000100100001101101011101100000 5
b111101010011101011010010111011010 8
b111111011110101011001101011101100000 7
b110011111011101100111010011101 6
b110011111011101100111010011101 0
b110011111011101100111010011101 :
b110011111011101100111010011101 >
b1000 A
0?
b10001 B
b1001 @
b111111101000100010100101111010111 .
b111111101000100010100101111010111 S
b111111101000100010100101111010111 W
b1001 Z
0X
b10011 \
b1010 Y
b11011110101011001101011101100000 /
b11011110101011001101011101100000 I
b11011110101011001101011101100000 M
b1000 P
0N
b10001 R
b1001 O
b1010100000111011 2
b1010100000111011 <
b1010100000111011 F
b11000110110001011 *
b11000110110001011 U
b11000110110001011 ,
b11000110110001011 H
b1110010101010000 1
b1110010101010000 G
b1110010101010000 K
b100111100000111 =
b100111100000111 4
b100111100000111 ;
b100111100000111 C
b10100011110100101 V
b10100011110100101 +
b10100011110100101 T
b10100011110100101 -
b10100011110100101 E
b1111100010011110 L
b1111100010011110 3
b1111100010011110 D
b1111100010011110 J
b10101000001110111110010101010000 #
b10101000001110111110010101010000 (
b1001111000001111111100010011110 "
b1001111000001111111100010011110 '
b10101000001110111110001111011101 &
b1000 $
#450
b11 9
b100000101111110010101001101010010011110010100111101011011000 !
b100000101111110010101001101010010011110010100111101011011000 )
b100000101111110010101001101010010011110010100111101011011000 5
b1001111001110100100100000101000 8
b1001011101000100111101011011000 7
b1000001011110111101101100000 6
b1000001011110111101101100000 0
b1000001011110111101101100000 :
b1000001011110111101101100000 >
b1000 A
0?
b10001 B
b1001 @
b10100011000011000011111001100000 .
b10100011000011000011111001100000 S
b10100011000011000011111001100000 W
b1001 Z
0X
b10011 \
b1010 Y
b1001011101000100111101011011000 /
b1001011101000100111101011011000 I
b1001011101000100111101011011000 M
b1000 P
0N
b10001 R
b1001 O
b110010011000 2
b110010011000 <
b110010011000 F
b111100010110001 *
b111100010110001 U
b111100010110001 ,
b111100010110001 H
b110110000011001 1
b110110000011001 G
b110110000011001 K
b1010011001100100 =
b1010011001100100 4
b1010011001100100 ;
b1010011001100100 C
b10101100110110000 V
b10101100110110000 +
b10101100110110000 T
b10101100110110000 -
b10101100110110000 E
b1011001101001100 L
b1011001101001100 3
b1011001101001100 D
b1011001101001100 J
b1100100110000110110000011001 #
b1100100110000110110000011001 (
b10100110011001001011001101001100 "
b10100110011001001011001101001100 '
b1100100110000110101000110011 &
b1001 $
#500
b11 9
b1010111100011001010001001100100110111001001011100011011110111 !
b1010111100011001010001001100100110111001001011100011011110111 )
b1010111100011001010001001100100110111001001011100011011110111 5
b1011100111001001101100111101010 8
b1011101001110111100011011110111 7
b10101111000101100101110110100 6
b10101111000101100101110110100 0
b10101111000101100101110110100 :
b10101111000101100101110110100 >
b1000 A
0?
b10001 B
b1001 @
b11010000000000110110110010010101 .
b11010000000000110110110010010101 S
b11010000000000110110110010010101 W
b1001 Z
0X
b10011 \
b1010 Y
b1011101001110111100011011110111 /
b1011101001110111100011011110111 I
b1011101001110111100011011110111 M
b1000 P
0N
b10001 R
b1001 O
b101101011100101 2
b101101011100101 <
b101101011100101 F
b1110110110011010 *
b1110110110011010 U
b1110110110011010 ,
b1110110110011010 H
b1001001010110101 1
b1001001010110101 G
b1001001010110101 K
b11110110100100 =
b11110110100100 4
b11110110100100 ;
b11110110100100 C
b1110000000011111 V
b1110000000011111 +
b1110000000011111 T
b1110000000011111 -
b1110000000011111 E
b1010001001111011 L
b1010001001111011 3
b1010001001111011 D
b1010001001111011 J
b1011010111001011001001010110101 #
b1011010111001011001001010110101 (
b111101101001001010001001111011 "
b111101101001001010001001111011 '
b1011010111001011001000111111001 &
b1010 $
#550
b11 9
b1101010011001000011111010010001010100010111100110001010111 !
b1101010011001000011111010010001010100010111100110001010111 )
b1101010011001000011111010010001010100010111100110001010111 5
b1101101101001000110110010010101 8
b11101111101101100110001010111 7
b11010100101011010001010000 6
b11010100101011010001010000 0
b11010100101011010001010000 :
b11010100101011010001010000 >
b1000 A
0?
b10001 B
b1001 @
b10001110111011011110110100111100 .
b10001110111011011110110100111100 S
b10001110111011011110110100111100 W
b1001 Z
0X
b10011 \
b1010 Y
b11101111101101100110001010111 /
b11101111101101100110001010111 I
b11101111101101100110001010111 M
b1000 P
0N
b10001 R
b1001 O
b1100100110100110 2
b1100100110100110 <
b1100100110100110 F
b10000000100111001 *
b10000000100111001 U
b10000000100111001 ,
b10000000100111001 H
b11011110010011 1
b11011110010011 G
b11011110010011 K
b10000111000 =
b10000111000 4
b10000111000 ;
b10000111000 C
b1000111001000000 V
b1000111001000000 +
b1000111001000000 T
b1000111001000000 -
b1000111001000000 E
b1000101000001000 L
b1000101000001000 3
b1000101000001000 D
b1000101000001000 J
b11001001101001100011011110010011 #
b11001001101001100011011110010011 (
b100001110001000101000001000 "
b100001110001000101000001000 '
b11001001101001100011010010101111 &
b1011 $
