ABM-M1-Karatsuba-bitwise-32- double approx/radix4approx18bit.v
`timescale 10ms / 1ms

module radix4approx18bit(p,x,y);         

parameter N = 18;   //size of muliplicant and multiplier
parameter K = N/2;  //

input   [N-1 : 0]   x,y;
output  [N+N-1:0]   p;

reg [2:0]   bits    [K:0];
reg   neg     [K:0];
reg   two     [K:0];
reg   zero     [K:0];

wire [N+1:0] x_new;
reg [N+1:0]       PP      [K:0]; //riyaj 
reg [N+N-1:0]   ACC     [K:0];
reg [N+N-1:0]   ANS;
reg mux;

integer i , j, t;
integer  m = 16;        //number of bits to approximate

assign x_new = {2'b0,x};

always@(*)

begin
    //$display("---Middle mult------");
    
    //$display("X= %b",x);
    //$display("X New= %b",x_new);
    //$display("Y= %b",y);
    
    //$display("------");
    
    bits[0] = {y[1],y[0],1'b0};             //setting last bit -1 as 0
    /*$display("Bits(0)= %b",bits[0]);
    $display("------");
    */
    for(i=1; i<K+1; i=i+1) begin
            if(i == K)
                bits[i] = {2'b0,y[2*i-1]};
            else
                bits[i] = {y[2*i+1], y[2*i], y[2*i-1]};
            //$display("%b", bits[i]);

            //$display("Bits(%d)= %b",i,bits[i]);
            //$display("------");
            
        end

    //$display("Bits= %b",bits);    
    /*$display("BH= %b", BH);    
    $display("BL= %b",BL);    
    $display("M1= %b",M1);    
    $display("M2= %b",M2);    
    $display("S1= %b",S1);
    $display("S2= %b",S2);    
    $display("M3= %b",M3);    
    $display("---------");
    */

    for(i=0; i<K+1; i=i+1)
        begin                               //approximated 2A as A introduced error
            case(bits[i])

            
            3'b001, 3'b010:         
            begin
                neg[i] = 1'b0;
                two[i] = 1'b0;
                zero[i] = 1'b0;
            end

            3'b011:
            begin
                neg[i] = 1'b0;
                two[i] = 1'b1;
                zero[i] = 1'b0;
            end

            3'b101, 3'b110:         
            begin 
               neg[i] = 1'b1;
                two[i] = 1'b0;
                zero[i] = 1'b0;
            end

            3'b100:
            begin
                neg[i] = 1'b1;
                two[i] = 1'b1;
                zero[i] = 1'b0;
            end
         
            default: 
            begin
                neg[i] = 1'b0;
                two[i] = 1'b0;
                zero[i] = 1'b1;
            end

            endcase

            PP[i] = 0;
            PP[i][N+1] = neg[i];           //sign conservation

            for(t=0; t<N+1; t=t+1) begin
                if(t>=m) 
                begin
                    mux = (x_new[t] & ~two[i]) | (x_new[t-1] & two[i]);             
                    PP[i][t] = ~zero[i] & (neg[i] ^ mux);
                end

                else 
                begin
                    PP[i][t] = (~x_new[t] & neg[i]) | (x_new[t] & ~neg[i] & ~zero[i]);
                end

                
            end

            //$display("PP before (%d)= %b",i,PP[i]);
            //$display("------");


            //add neg[i]    
            PP[i] = PP[i] + neg[i];

            //$display("middle mult PP after (%d)= %b",i,PP[i]);
            //$display("------");

            ACC[i] = $signed(PP[i]);        //sign extension
            
            for(j=0; j<i; j=j+1)
                ACC[i] = {ACC[i],2'b00};        //shifting

            //$display("ACC(%d)= %b",i,ACC[i]);
            //$display("------");
        end

    ANS = ACC[0];
    //$display("ANS(0)= %b",ANS[0]);
    //$display("------");

    for(i=1; i<K+1; i=i+1)
    begin
        ANS = ANS+ACC[i];
        //$display("ANS(%d)= %b",i,ANS[i]);
        //$display("------");
    end
       
        
end


assign p = ANS;


endmodule

ABM-M1-Karatsuba-bitwise-32/adder8.v
`timescale 10ms / 1ms

module adder8(s,a,b);

input [15:0] a,b;

output [16:0] s;


assign s = a+b;

endmodule

ABM-M1-Karatsuba-bitwise-32- double approx/radix4approx.v
`timescale 10ms / 1ms

module radix4approx(p,x,y);         //8 bit multiplier to give 16 bit product

parameter N = 16;   //size of muliplicant and multiplier
parameter K = N/2;  //

input   [N-1 : 0]   x,y;
output  [N+N-1:0]   p;

reg [2:0]   bits    [K:0];
reg   neg     [K:0];
reg   two     [K:0];
reg   zero     [K:0];

wire [N+1:0] x_new;
reg [N+1:0]       PP      [K:0]; //riyaj 
reg [N+N-1:0]   ACC     [K:0];
reg [N+N-1:0]   ANS;
reg mux;

integer i , j, t;
integer  m = 16;        //number of bits to approximate

assign x_new = {2'b0,x};

always@(*)

begin
    /*
    $display("---LSB mult------");
    
    $display("X= %b",x);
    $display("X New= %b",x_new);
    $display("Y= %b",y);
    
    $display("------");
    
    */

    bits[0] = {y[1],y[0],1'b0};             //setting last bit -1 as 0

    for(i=1; i<K+1; i=i+1) begin
            if(i == K)
                bits[i] = {2'b0,y[2*i-1]};
            else
                bits[i] = {y[2*i+1], y[2*i], y[2*i-1]};
            //$display("%b", bits[i]);
            
        end


    for(i=0; i<K+1; i=i+1)
        begin                               //approximated 2A as A introduced error
            case(bits[i])

            
            3'b001, 3'b010:         
            begin
                neg[i] = 1'b0;
                two[i] = 1'b0;
                zero[i] = 1'b0;
            end

            3'b011:
            begin
                neg[i] = 1'b0;
                two[i] = 1'b1;
                zero[i] = 1'b0;
            end

            3'b101, 3'b110:         
            begin 
               neg[i] = 1'b1;
                two[i] = 1'b0;
                zero[i] = 1'b0;
            end

            3'b100:
            begin
                neg[i] = 1'b1;
                two[i] = 1'b1;
                zero[i] = 1'b0;
            end
         
            default: 
            begin
                neg[i] = 1'b0;
                two[i] = 1'b0;
                zero[i] = 1'b1;
            end

            endcase

            PP[i] = 0;
            PP[i][N+1] = neg[i];           //sign conservation

            for(t=0; t<N+1; t=t+1) begin
                if(t>=m) 
                begin
                    mux = (x_new[t] & ~two[i]) | (x_new[t-1] & two[i]);             
                    PP[i][t] = ~zero[i] & (neg[i] ^ mux);
                end

                else 
                begin
                    PP[i][t] = (~x_new[t] & neg[i]) | (x_new[t] & ~neg[i] & ~zero[i]);
                end
            end

            PP[i] = PP[i] + neg[i];
            //$display("LSB mult PP after (%d)= %b",i,PP[i]);
            //$display("------");


            ACC[i] = $signed(PP[i]);        //sign extension
            
            for(j=0; j<i; j=j+1)
                ACC[i] = {ACC[i],2'b00};        //shifting

        
        end

    ANS = ACC[0];

    for(i=1; i<K+1; i=i+1)
        ANS = ANS+ACC[i];
        
end


assign p = ANS;

endmodule

ABM-M1-WT-bitwise-32/radix4acc.v
`timescale 10ms / 1ms

module radix4acc(p,x,y);        

parameter N = 16;   //size of muliplicant and multiplier
parameter K = N/2;  //

input [N-1 : 0]   x,y;
output [N+N-1:0]   p;

reg [2:0]   bits    [K:0];
reg   neg     [K:0];
reg   two     [K:0];
reg   zero     [K:0];

wire [N+1:0] x_new;
reg [N+1:0]       PP      [K:0]; 
reg [N+N-1:0]   ACC     [K:0];
reg [N+N-1:0]   ANS;
reg mux;

integer i , j, t;

assign x_new = {2'b0,x};

always@(*)

begin
    bits[0] = {y[1],y[0],1'b0};             //setting last bit -1 as 0
    //$display("%b", bits[0]);
    for(i=1; i<K+1; i=i+1) begin
        if(i == K)
            bits[i] = {2'b0,y[2*i-1]};
        else
            bits[i] = {y[2*i+1], y[2*i], y[2*i-1]};
        //$display("%b", bits[i]);
        
    end

    for(i=0; i<K+1; i=i+1)
        begin                                      //accurate cases
            case(bits[i])

            
            3'b001, 3'b010:         
            begin
                neg[i] = 1'b0;
                two[i] = 1'b0;
                zero[i] = 1'b0;
            end

            3'b011:
            begin
                neg[i] = 1'b0;
                two[i] = 1'b1;
                zero[i] = 1'b0;
            end

            3'b101, 3'b110:         
            begin 
               neg[i] = 1'b1;
                two[i] = 1'b0;
                zero[i] = 1'b0;
            end

            3'b100:
            begin
                neg[i] = 1'b1;
                two[i] = 1'b1;
                zero[i] = 1'b0;
            end
         
            default: 
            begin
                neg[i] = 1'b0;
                two[i] = 1'b0;
                zero[i] = 1'b1;
            end

            endcase
            
            //$display("%b %b %b", neg[i], two[i], zero[i]);
            
            PP[i] = 0;
            PP[i][N+1] = neg[i];           //sign conservation

            for(t=0; t<N+1; t=t+1) begin
                if(t==0) 
                    mux = (x_new[t] & ~two[i]) | (1'b0 & two[i]);
                
                else
                    mux = (x_new[t] & ~two[i]) | (x_new[t-1] & two[i]);

                
                PP[i][t] = ~zero[i] & (neg[i] ^ mux);       
            end

            PP[i] = PP[i] + neg[i];             //correction term added
            
            //$display("%b", PP[i]);

            ACC[i] = $signed(PP[i]);        //sign extension
            //$display("%b", ACC[i]);

            for(j=0; j<i; j=j+1)
                ACC[i] = {ACC[i],2'b00};        //shifting

        
        end

    ANS = ACC[0];

    for(i=1; i<K+1; i=i+1)
        ANS = ANS+ACC[i];
        
    
end


assign p = ANS;

endmodule

ABM-M1-Karatsuba-bitwise-32- double approx/karatsuba32.v
`timescale 10ms/1ms
`include "radix4acc.v"
`include "radix4approx.v"
`include "radix4approx18bit.v"
`include "adder8.v"

module karatsuba32(P,A,B);


parameter N = 32;   //size of muliplicant and multiplier
parameter K = N/2;  //

input   [N-1 : 0]   A,B;
output  [N+N-1:0]   P;

wire [K-1:0] AH, AL, BH, BL;

wire reg    [N-1:0]     M1, M2;
wire reg    [K:0]       S1, S2;
wire reg    [17:0]       c,d;
wire reg    [35:0]      M3;

reg [35:0] M4, M5, M6;

reg     [35:0]   A1, A2, A3;


reg [N+N-1:0]   ACC     [2:0];
reg [N+N-1:0] ANS;
integer i;


assign AH = A[N-1:K];
assign AL = A[K-1:0];

assign BH = B[N-1:K];
assign BL = B[K-1:0];



radix4acc ACC1(.p(M1), .x(AH), .y(BH));
radix4approx APP1(.p(M2), .x(AL), .y(BL));      //approx1


adder8 ADD1(.s(S1), .a(AH), .b(AL));
adder8 ADD2(.s(S2), .a(BH), .b(BL));

assign c = (S1);
assign d = (S2);

radix4approx18bit APP2(.p(M3), .x(c), .y(d));       //approx2



always@(*)                  //, AL, BH, BL, M1, M2, S1, S2, M3
begin
    /*$display("AH= %b",AH);
    $display("AL= %b",AL);    
    $display("BH= %b", BH);    
    $display("BL= %b",BL);    
    $display("M1= %b",M1);    
    $display("M2= %b",M2);    
    $display("S1= %b",S1);
    $display("S2= %b",S2);    
    $display("M3= %b",M3);    
    $display("---------");
    $display("---------");
    $display("---------");
    $display("---------");
    */

    M4 = (M1);
    M5 = (M2);
    
    if(M3 > (M4+M5))
        M6 = M3 - M4 - M5;
    else
        M6 = (M4+M5) - M3;


    ACC[0] = (M6);
    ACC[0] = {ACC[0], {16{1'b0}}};
    //$display("ACC[0]= %d",ACC[0]);    

    ACC[1] = (M2);
    //$display("ACC[1]= %d",ACC[1]);    
    
    ACC[2] = (M1);
    ACC[2] = {ACC[2], {32{1'b0}}};
    //$display("ACC[2]= %d",ACC[2]);    

    ANS = ACC[0];
    for(i=1; i<3; i=i+1)
        ANS = ANS+ACC[i];
end

assign P = ANS;

endmodule

ABM-M1-Karatsuba-bitwise-32- double approx/karatsuba32_tb.v
`timescale 10ms / 1ms
`include "karatsuba32.v"

module karatsuba32_tb();

reg unsigned [31:0] A,B;
wire unsigned [63:0] P;
integer i, out, seed=7;


karatsuba32 uut(P,A,B);


initial begin
    $dumpfile("karatsuba32.vcd");
    $dumpvars(0, karatsuba32_tb);
    out = $fopen("results16.csv");
  
/*    
        A = 58;
        B = 84607;
        #1;
        $fwrite(out, "%d, %d, %d\n", A,B,P);
        #4;

        A = 73066;
        B = 615406;
        #1;
        $fwrite(out, "%d, %d, %d\n", A,B,P);
        #4;

        A = 10;
        B = 96224;
        #1;
        $fwrite(out, "%d, %d, %d\n", A,B,P);
        #4;

        A = 12;
        B = 94209;
        #1;
        $fwrite(out, "%d, %d, %d\n", A,B,P);
        #4;

        A = 20;
        B = 95679;
        #1;
        $fwrite(out, "%d, %d, %d\n", A,B,P);
        #4;
    */

    
    for(i=0; i<100; i=i+1)                       //10 test cases A and B: 1-100 
    begin
        A = $urandom(seed) %200 + 65536;
        B = $urandom(seed) %200;
        #1;
        $fwrite(out, "%d, %d, %d\n", A,B,P);
        #4;
    end

    for(i=0; i<100; i=i+1)                       //10 test cases A: 1-100 B: till 2^15
    begin
        A = $urandom(seed) %200;
        B = $urandom(seed) %32768 + 65536;
        #1;
        $fwrite(out, "%d, %d, %d\n", A,B,P);
        #4;
    end

    for(i=0; i<100; i=i+1)                       //10 test cases B: 1-100 A: till 2^32
    begin
        A = $urandom(seed) %4294967295;
        B = $urandom(seed) %200 + 65535;
        #1;
        $fwrite(out, "%d, %d, %d\n", A,B,P);
        #4;
    end

    
    for(i=0; i<200; i=i+1)                       //50 cases : till 1024 A: 2^10 B: 2^20
    begin
        A = $urandom(seed) %1024;
        B = $urandom(seed) %1048576;
        #1;
        $fwrite(out, "%d, %d, %d\n", A,B,P);
        #4;
    end

    for(i=0; i<500; i=i+1)                       //500 cases : till 32768 which is 2^15
    begin
        A = $urandom(seed) %65536 + 65536;
        B = $urandom(seed) %32768;
        #1;
        $fwrite(out, "%d, %d, %d\n", A,B,P);
        #4;
    end

    for(i=0; i<500; i=i+1)                       //500 cases : till 2^20
    begin
        A = $urandom(seed) %1048576;
        B = $urandom(seed) %1048576;
        #1;
        $fwrite(out, "%d, %d, %d\n", A,B,P);
        #4;
    end

    for(i=0; i<500; i=i+1)                       //50 cases : till 1024 A: 2^32 B: 2^20
    begin
        A = $urandom(seed) %4294967295;
        B = $urandom(seed) %1048576;
        #1;
        $fwrite(out, "%d, %d, %d\n", A,B,P);
        #4;
    end

    for(i=0; i<500; i=i+1)                          //50 cases till 2^32
    begin
        A = $urandom(seed) %4294967295;
        B = $urandom(seed) %4294967295;
        #1;
        $fwrite(out, "%d, %d, %d\n", A,B,P);
        #4;
    end
    
    
    $finish;
end

endmodule

ABM-M1-Karatsuba-bitwise-32- double approx/karatsuba32.vcd
$date
	Tue Sep 21 22:13:41 2021
$end
$version
	Icarus Verilog
$end
$timescale
	1ms
$end
$scope module karatsuba32_tb $end
$var wire 64 ! P [63:0] $end
$var reg 32 " A [31:0] $end
$var reg 32 # B [31:0] $end
$var integer 32 $ i [31:0] $end
$var integer 32 % out [31:0] $end
$var integer 32 & seed [31:0] $end
$scope module uut $end
$var wire 32 ' A [31:0] $end
$var wire 32 ( B [31:0] $end
$var wire 64 ) P [63:0] $end
$var wire 18 * d [17:0] $end
$var wire 18 + c [17:0] $end
$var wire 17 , S2 [16:0] $end
$var wire 17 - S1 [16:0] $end
$var wire 36 . M3 [35:0] $end
$var wire 32 / M2 [31:0] $end
$var wire 32 0 M1 [31:0] $end
$var wire 16 1 BL [15:0] $end
$var wire 16 2 BH [15:0] $end
$var wire 16 3 AL [15:0] $end
$var wire 16 4 AH [15:0] $end
$var reg 64 5 ANS [63:0] $end
$var reg 36 6 M4 [35:0] $end
$var reg 36 7 M5 [35:0] $end
$var reg 36 8 M6 [35:0] $end
$var integer 32 9 i [31:0] $end
$scope module ACC1 $end
$var wire 32 : p [31:0] $end
$var wire 16 ; x [15:0] $end
$var wire 16 < y [15:0] $end
$var wire 18 = x_new [17:0] $end
$var reg 32 > ANS [31:0] $end
$var reg 1 ? mux $end
$var integer 32 @ i [31:0] $end
$var integer 32 A j [31:0] $end
$var integer 32 B t [31:0] $end
$upscope $end
$scope module ADD1 $end
$var wire 16 C a [15:0] $end
$var wire 16 D b [15:0] $end
$var wire 17 E s [16:0] $end
$upscope $end
$scope module ADD2 $end
$var wire 16 F a [15:0] $end
$var wire 16 G b [15:0] $end
$var wire 17 H s [16:0] $end
$upscope $end
$scope module APP1 $end
$var wire 32 I p [31:0] $end
$var wire 16 J x [15:0] $end
$var wire 16 K y [15:0] $end
$var wire 18 L x_new [17:0] $end
$var reg 32 M ANS [31:0] $end
$var reg 1 N mux $end
$var integer 32 O i [31:0] $end
$var integer 32 P j [31:0] $end
$var integer 32 Q m [31:0] $end
$var integer 32 R t [31:0] $end
$upscope $end
$scope module APP2 $end
$var wire 36 S p [35:0] $end
$var wire 18 T x [17:0] $end
$var wire 18 U y [17:0] $end
$var wire 20 V x_new [19:0] $end
$var reg 36 W ANS [35:0] $end
$var reg 1 X mux $end
$var integer 32 Y i [31:0] $end
$var integer 32 Z j [31:0] $end
$var integer 32 [ m [31:0] $end
$var integer 32 \ t [31:0] $end
$upscope $end
$upscope $end
$upscope $end
$enddefinitions $end
#0
$dumpvars
b10011 \
b10000 [
b1001 Z
b1010 Y
0X
b1111101100100 W
b101001 V
b11000100 U
b101001 T
b1111101100100 S
b10001 R
b10000 Q
b1000 P
b1001 O
0N
b100000000001111010100000 M
b101000 L
b11000100 K
b101000 J
b100000000001111010100000 I
b11000100 H
b11000100 G
b0 F
b101001 E
b101000 D
b1 C
b10001 B
b1000 A
b1001 @
0?
b0 >
b1 =
b0 <
b1 ;
b0 :
b11 9
b11111111111111100111100 8
b100000000001111010100000 7
b0 6
b111111111111111101111000001111010100000 5
b1 4
b101000 3
b0 2
b11000100 1
b0 0
b100000000001111010100000 /
b1111101100100 .
b101001 -
b11000100 ,
b101001 +
b11000100 *
b111111111111111101111000001111010100000 )
b11000100 (
b10000000000101000 '
b11000110011011000100100011101101 &
b10 %
b0 $
b11000100 #
b10000000000101000 "
b111111111111111101111000001111010100000 !
$end
#50
b11 9
b1000011111111111101111000000111001011000 !
b1000011111111111101111000000111001011000 )
b1000011111111111101111000000111001011000 5
b100001111111111100110100 8
b100010000000111001011000 7
b111100100100 .
b111100100100 S
b111100100100 W
b1001 Z
b10011 \
b1010 Y
b100010000000111001011000 /
b100010000000111001011000 I
b100010000000111001011000 M
b1000 P
b10001 R
b1001 O
b10011100 *
b10011100 U
b10011100 ,
b10011100 H
b10011100 1
b10011100 G
b10011100 K
b10011 V
b10011 +
b10011 T
b10011 -
b10011 E
b10010 L
b10010 3
b10010 D
b10010 J
b10011100 #
b10011100 (
b10000000000010010 "
b10000000000010010 '
b10101110011011011111100111000011 &
b1 $
#100
b11 9
b111111111101111110001010110111001 !
b111111111101111110001010110111001 )
b111111111101111110001010110111001 5
b11111111110111101 8
b100001010110111001 7
b1010111111100 .
b1010111111100 S
b1010111111100 W
b1001 Z
b10011 \
b1010 Y
b100001010110111001 /
b100001010110111001 I
b100001010110111001 M
b1000 P
b10001 R
b1001 O
b1000111 *
b1000111 U
b1000111 ,
b1000111 H
b1000111 1
b1000111 G
b1000111 K
b1010100 V
b1010100 +
b1010100 T
b1010100 -
b1010100 E
b1010011 L
b1010011 3
b1010011 D
b1010011 J
b1000111 #
b1000111 (
b10000000001010011 "
b10000000001010011 '
b11001111110001011111000000001001 &
b10 $
#150
b11 9
b1001111111111111111011000101110110000100 !
b1001111111111111111011000101110110000100 )
b1001111111111111111011000101110110000100 5
b100111111111111101001100 8
b101000000101110110000100 7
b101111000111000 .
b101111000111000 S
b101111000111000 W
b1001 Z
b10011 \
b1010 Y
b101000000101110110000100 /
b101000000101110110000100 I
b101000000101110110000100 M
b1000 P
b10001 R
b1001 O
b10100100 *
b10100100 U
b10100100 ,
b10100100 H
b10100100 1
b10100100 G
b10100100 K
b10000110 V
b10000110 +
b10000110 T
b10000110 -
b10000110 E
b10000101 L
b10000101 3
b10000101 D
b10000101 J
b10100100 #
b10100100 (
b10000000010000101 "
b10000000010000101 '
b10011100001010010100111111 &
b11 $
#200
b11 9
b100111111111101111110010000110110001 !
b100111111111101111110010000110110001 )
b100111111111101111110010000110110001 5
b10011111111110110101 8
b10100010000110110001 7
b10000111111100 .
b10000111111100 S
b10000111111100 W
b1001 Z
b10011 \
b1010 Y
b10100010000110110001 /
b10100010000110110001 I
b10100010000110110001 M
b1000 P
b10001 R
b1001 O
b1001011 *
b1001011 U
b1001011 ,
b1001011 H
b1001011 1
b1001011 G
b1001011 K
b1110100 V
b1110100 +
b1110100 T
b1110100 -
b1110100 E
b1110011 L
b1110011 3
b1110011 D
b1110011 J
b1001011 #
b1001011 (
b10000000001110011 "
b10000000001110011 '
b1110111101000111011100101 &
b100 $
#250
b11 9
b100111111111111111110000001001010010 !
b100111111111111111110000001001010010 )
b100111111111111111110000001001010010 5
b10011111111111110101 8
b10100000001001010010 7
b1001011101 .
b1001011101 S
b1001011101 W
b1001 Z
b10011 \
b1010 Y
b10100000001001010010 /
b10100000001001010010 I
b10100000001001010010 M
b1000 P
b10001 R
b1001 O
b11010 *
b11010 U
b11010 ,
b11010 H
b11010 1
b11010 G
b11010 K
b110111 V
b110111 +
b110111 T
b110111 -
b110111 E
b110110 L
b110110 3
b110110 D
b110110 J
b11010 #
b11010 (
b10000000000110110 "
b10000000000110110 '
b1101001110110111111001111011 &
b101 $
#300
b11 9
b10000111111111111011110000010011111011 !
b10000111111111111011110000010011111011 )
b10000111111111111011110000010011111011 5
b1000011111111111001101 8
b1000100000010011111011 7
b10100101110 .
b10100101110 S
b10100101110 W
b1001 Z
b10011 \
b1010 Y
b1000100000010011111011 /
b1000100000010011111011 I
b1000100000010011111011 M
b1000 P
b10001 R
b1001 O
b100010 *
b100010 U
b100010 ,
b100010 H
b100010 1
b100010 G
b100010 K
b11010 V
b11010 +
b11010 T
b11010 -
b11010 E
b11001 L
b11001 3
b11001 D
b11001 J
b100010 #
b100010 (
b10000000000011001 "
b10000000000011001 '
b1111001000111010000000110000001 &
b110 $
#350
b11 9
b10000010000000101000101 !
b10000010000000101000101 )
b10000010000000101000101 5
b1000001 8
b101000101 7
b110000110 .
b110000110 S
b110000110 W
b1001 Z
b10011 \
b1010 Y
b101000101 /
b101000101 I
b101000101 M
b1000 P
b10001 R
b1001 O
b1000001 *
b1000001 U
b1000001 ,
b1000001 H
b1000001 1
b1000001 G
b1000001 K
b110 V
b110 +
b110 T
b110 -
b110 E
b101 L
b101 3
b101 D
b101 J
b1000001 #
b1000001 (
b10000000000000101 "
b10000000000000101 '
b1100100101011111100000101110111 &
b111 $
#400
b11 9
b100000000001111100000 !
b100000000001111100000 )
b100000000001111100000 5
b10000 8
b1111100000 7
b1111110000 .
b1111110000 S
b1111110000 W
b1001 Z
b10011 \
b1010 Y
b1111100000 /
b1111100000 I
b1111100000 M
b1000 P
b10001 R
b1001 O
b10000 *
b10000 U
b10000 ,
b10000 H
b10000 1
b10000 G
b10000 K
b111111 V
b111111 +
b111111 T
b111111 -
b111111 E
b111110 L
b111110 3
b111110 D
b111110 J
b10000 #
b10000 (
b10000000000111110 "
b10000000000111110 '
b10101000001110111110001111011101 &
b1000 $
#450
b11 9
b1000011111111111101110110111110011101100 !
b1000011111111111101110110111110011101100 )
b1000011111111111101110110111110011101100 5
b100001111111111100110011 8
b100010000111110011101100 7
b111110110111001 .
b111110110111001 S
b111110110111001 W
b1001 Z
b10011 \
b1010 Y
b100010000111110011101100 /
b100010000111110011101100 I
b100010000111110011101100 M
b1000 P
b10001 R
b1001 O
b10001001 *
b10001001 U
b10001001 ,
b10001001 H
b10001001 1
b10001001 G
b10001001 K
b10011101 V
b10011101 +
b10011101 T
b10011101 -
b10011101 E
b10011100 L
b10011100 3
b10011100 D
b10011100 J
b10001001 #
b10001001 (
b10000000010011100 "
b10000000010011100 '
b1100100110000110101000110011 &
b1001 $
#500
b11 9
b1000011111111111101110110011110000001111 !
b1000011111111111101110110011110000001111 )
b1000011111111111101110110011110000001111 5
b100010000011110000001111 7
b11110011011100 .
b11110011011100 S
b11110011011100 W
b1001 Z
b10011 \
b1010 Y
b100010000011110000001111 /
b100010000011110000001111 I
b100010000011110000001111 M
b1000 P
b10001 R
b1001 O
b10001101 *
b10001101 U
b10001101 ,
b10001101 H
b10001101 1
b10001101 G
b10001101 K
b1001100 V
b1001100 +
b1001100 T
b1001100 -
b1001100 E
b1001011 L
b1001011 3
b1001011 D
b1001011 J
b10001101 #
b10001101 (
b10000000001001011 "
b10000000001001011 '
b1011010111001011001000111111001 &
b1010 $
#550
b11 9
b111111111111011110000000100110000 !
b111111111111011110000000100110000 )
b111111111111011110000000100110000 5
b11111111111101101 8
b100000000100110000 7
b101000011 .
b101000011 S
b101000011 W
b1001 Z
b10011 \
b1010 Y
b100000000100110000 /
b100000000100110000 I
b100000000100110000 M
b1000 P
b10001 R
b1001 O
b10011 *
b10011 U
b10011 ,
b10011 H
b10011 1
b10011 G
b10011 K
b10001 V
b10001 +
b10001 T
b10001 -
b10001 E
b10000 L
b10000 3
b10000 D
b10000 J
b10011 #
b10011 (
b10000000000010000 "
b10000000000010000 '
b11001001101001100011010010101111 &
b1011 $
#600
b11 9
b1000011111111111101111000010101100001000 !
b1000011111111111101111000010101100001000 )
b1000011111111111101111000010101100001000 5
b100001111111111100110100 8
b100010000010101100001000 7
b10101111010100 .
b10101111010100 S
b10101111010100 W
b1001 Z
b10011 \
b1010 Y
b100010000010101100001000 /
b100010000010101100001000 I
b100010000010101100001000 M
b1000 P
b10001 R
b1001 O
b10001000 *
b10001000 U
b10001000 ,
b10001000 H
b10001000 1
b10001000 G
b10001000 K
b110111 V
b110111 +
b110111 T
b110111 -
b110111 E
b110110 L
b110110 3
b110110 D
b110110 J
b10001000 #
b10001000 (
b10000000000110110 "
b10000000000110110 '
b101000000100000010011111010101 &
b1100 $
#650
b11 9
b101000000001001000100 !
b101000000001001000100 )
b101000000001001000100 5
b10100 8
b1001000100 7
b1001011000 .
b1001011000 S
b1001011000 W
b1001 Z
b10011 \
b1010 Y
b1001000100 /
b1001000100 I
b1001000100 M
b1000 P
b10001 R
b1001 O
b10100 *
b10100 U
b10100 ,
b10100 H
b10100 1
b10100 G
b10100 K
b11110 V
b11110 +
b11110 T
b11110 -
b11110 E
b11101 L
b11101 3
b11101 D
b11101 J
b10100 #
b10100 (
b10000000000011101 "
b10000000000011101 '
b11011010001010111001110011101011 &
b1101 $
#700
b11 9
b1111111111111111100000001010100110000 !
b1111111111111111100000001010100110000 )
b1111111111111111100000001010100110000 5
b111111111111111010000 8
b1000000001010100110000 7
b1010101100000 .
b1010101100000 S
b1010101100000 W
b1001 Z
b10011 \
b1010 Y
b1000000001010100110000 /
b1000000001010100110000 I
b1000000001010100110000 M
b1000 P
b10001 R
b1001 O
b110000 *
b110000 U
b110000 ,
b110000 H
b110000 1
b110000 G
b110000 K
b1110010 V
b1110010 +
b1110010 T
b1110010 -
b1110010 E
b1110001 L
b1110001 3
b1110001 D
b1110001 J
b110000 #
b110000 (
b10000000001110001 "
b10000000001110001 '
b10110000000110011000000101110001 &
b1110 $
#750
b11 9
b1001111111111111111011110100100101001010 !
b1001111111111111111011110100100101001010 )
b1001111111111111111011110100100101001010 5
b100111111111111101001111 8
b101000000100100101001010 7
b100100111111011 .
b100100111111011 S
b100100111111011 W
b1001 Z
b10011 \
b1010 Y
b101000000100100101001010 /
b101000000100100101001010 I
b101000000100100101001010 M
b1000 P
b10001 R
b1001 O
b10100001 *
b10100001 U
b10100001 ,
b10100001 H
b10100001 1
b10100001 G
b10100001 K
b1101011 V
b1101011 +
b1101011 T
b1101011 -
b1101011 E
b1101010 L
b1101010 3
b1101010 D
b1101010 J
b10100001 #
b10100001 (
b10000000001101010 "
b10000000001101010 '
b11010000100110001101111011100111 &
b1111 $
#800
b11 9
b101010000100101000101 !
b101010000100101000101 )
b101010000100101000101 5
b10101 8
b100101000101 7
b100101011010 .
b100101011010 S
b100101011010 W
b1001 Z
b10011 \
b1010 Y
b100101000101 /
b100101000101 I
b100101000101 M
b1000 P
b10001 R
b1001 O
b10101 *
b10101 U
b10101 ,
b10101 H
b10101 1
b10101 G
b10101 K
b1110010 V
b1110010 +
b1110010 T
b1110010 -
b1110010 E
b1110001 L
b1110001 3
b1110001 D
b1110001 J
b10101 #
b10101 (
b10000000001110001 "
b10000000001110001 '
b11000010101000110011101011001101 &
b10000 $
#850
b11 9
b1010000111111111111100110111111100100110 !
b1010000111111111111100110111111100100110 )
b1010000111111111111100110111111100100110 5
b101000011111111101010001 8
b101000100111111100100110 7
b111111111010101 .
b111111111010101 S
b111111111010101 W
b1001 Z
b10011 \
b1010 Y
b101000100111111100100110 /
b101000100111111100100110 I
b101000100111111100100110 M
b1000 P
b10001 R
b1001 O
b10101111 *
b10101111 U
b10101111 ,
b10101111 H
b10101111 1
b10101111 G
b10101111 K
b10111011 V
b10111011 +
b10111011 T
b10111011 -
b10111011 E
b10111010 L
b10111010 3
b10111010 D
b10111010 J
b10101111 #
b10101111 (
b10000000010111010 "
b10000000010111010 '
b1011101101111111011010100011 &
b10001 $
#900
b11 9
b11111111111111111000000000100100000 !
b11111111111111111000000000100100000 )
b11111111111111111000000000100100000 5
b1111111111111110100 8
b10000000000100100000 7
b100101100 .
b100101100 S
b100101100 W
b1001 Z
b10011 \
b1010 Y
b10000000000100100000 /
b10000000000100100000 I
b10000000000100100000 M
b1000 P
b10001 R
b1001 O
b1000 *
b1000 U
b1000 ,
b1000 H
b1000 1
b1000 G
b1000 K
b11001 V
b11001 +
b11001 T
b11001 -
b11001 E
b11000 L
b11000 3
b11000 D
b11000 J
b1000 #
b1000 (
b10000000000011000 "
b10000000000011000 '
b1001000001011101010111111101001 &
b10010 $
#950
b11 9
b10000010010000010000000 !
b10000010010000010000000 )
b10000010010000010000000 5
b1000001 8
b10000010000000 7
b10000011000001 .
b10000011000001 S
b10000011000001 W
b1001 Z
b10011 \
b1010 Y
b10000010000000 /
b10000010000000 I
b10000010000000 M
b1000 P
b10001 R
b1001 O
b1000001 *
b1000001 U
b1000001 ,
b1000001 H
b1000001 1
b1000001 G
b1000001 K
b10000001 V
b10000001 +
b10000001 T
b10000001 -
b10000001 E
b10000000 L
b10000000 3
b10000000 D
b10000000 J
b1000001 #
b1000001 (
b10000000010000000 "
b10000000010000000 '
b1000101010001010000000011111 &
b10011 $
