unsigned/karatsuba/radix4approx10bit.v
`timescale 10ms / 1ms

module radix4approx10bit(p,x,y);         //8 bit multiplier to give 32 bit product

parameter N = 10;   //size of muliplicant and multiplier
parameter K = N/2;  //

input   [N-1 : 0]   x,y;
output  [N+N-1:0]   p;

reg [2:0]   bits    [K-1:0];
reg   neg     [K-1:0];
reg   two     [K-1:0];
reg   zero     [K-1:0];


reg [N:0]       PP      [K-1:0];
reg [N+N-1:0]   ACC     [K-1:0];
reg [N+N-1:0]   ANS;
reg mux;

integer i , j, t,m = 8;

always@(*)

begin
    bits[0] = {y[1],y[0],1'b0};             //setting last bit -1 as 0

    for(i=1; i<K; i=i+1)
        bits[i] = {y[2*i+1], y[2*i], y[2*i-1]};


    for(i=0; i<K; i=i+1)
        begin
            case(bits[i])

            
            3'b001, 3'b010:         
            begin
                neg[i] = 1'b0;
                two[i] = 1'b0;
                zero[i] = 1'b0;
            end

            3'b011:
            begin
                neg[i] = 1'b0;
                two[i] = 1'b1;
                zero[i] = 1'b0;
            end

            3'b101, 3'b110:         
            begin 
               neg[i] = 1'b1;
                two[i] = 1'b0;
                zero[i] = 1'b0;
            end

            3'b100:
            begin
                neg[i] = 1'b1;
                two[i] = 1'b1;
                zero[i] = 1'b0;
            end
         
            default: 
            begin
                neg[i] = 1'b0;
                two[i] = 1'b0;
                zero[i] = 1'b1;
            end

            endcase
            
            PP[i] = 0;
            PP[i][N] = x[N-1]^neg[i];           //sign conservation

            for(t=0; t<N; t=t+1) begin
                if(t>=m) 
                begin
                    mux = (x[t] & ~two[i]) | (x[t-1] & two[i]);             
                    PP[i][t] = ~zero[i] & (neg[i] ^ mux);
                end

                else 
                begin
                    PP[i][t] = (~x[t] & neg[i]) | (x[t] & ~neg[i] & ~zero[i]);
                end
            end

            PP[i][0] = PP[i][0] | neg[i];

            ACC[i] = $signed(PP[i]);        //sign extension
            
            for(j=0; j<i; j=j+1)
                ACC[i] = {ACC[i],2'b00};        //shifting

        
        end

    ANS = ACC[0];

    for(i=1; i<K; i=i+1)
        ANS = ANS+ACC[i];

    //ANS[9:2] = 1'b1;            //hybrid approximation          //doesnt make much difference
    //ANS = {ANS[N+N-1],ANS[N+N-3:0],1'b0};
    
end


assign p = ANS;

endmodule

unsigned/karatsuba/adder8.v
`timescale 10ms / 1ms

module adder8(s,a,b);

input [7:0] a,b;

output [8:0] s;


assign s = a+b;

endmodule

unsigned/WT/radix4approx.v
`timescale 10ms / 1ms

module radix4approx(p,x,y);         //16 bit multiplier to give 32 bit product

parameter N = 8;   //size of muliplicant and multiplier
parameter K = N/2;  //

input   [N-1 : 0]   x,y;
output  [N+N-1:0]   p;

reg [2:0]   bits    [K-1:0];
reg   neg     [K-1:0];
reg   two     [K-1:0];
reg   zero     [K-1:0];


reg [N:0]       PP      [K-1:0];
reg [N+N-1:0]   ACC     [K-1:0];
reg [N+N-1:0]   ANS;
reg mux;

integer i , j, t,m=6;

wire [N:0] xbar;
assign xbar = {~x[N-1], ~x} + 1'b1;         //2's complement retaining the sign bit

always@(*)

begin
    bits[0] = {y[1],y[0],1'b0};             //setting last bit -1 as 0

    for(i=1; i<K; i=i+1)
        bits[i] = {y[2*i+1], y[2*i], y[2*i-1]};


    for(i=0; i<K; i=i+1)
        begin                               //approximated 2A as A introduced error
            case(bits[i])

            
            3'b001, 3'b010:         
            begin
                neg[i] = 1'b0;
                two[i] = 1'b0;
                zero[i] = 1'b0;
            end

            3'b011:
            begin
                neg[i] = 1'b0;
                two[i] = 1'b1;
                zero[i] = 1'b0;
            end

            3'b101, 3'b110:         
            begin 
               neg[i] = 1'b1;
                two[i] = 1'b0;
                zero[i] = 1'b0;
            end

            3'b100:
            begin
                neg[i] = 1'b1;
                two[i] = 1'b1;
                zero[i] = 1'b0;
            end
         
            default: 
            begin
                neg[i] = 1'b0;
                two[i] = 1'b0;
                zero[i] = 1'b1;
            end

            endcase

            PP[i] = 0;
            PP[i][N] = x[N-1]^neg[i];           //sign conservation

            for(t=0; t<N; t=t+1) begin
                if(t>=m) 
                begin
                    mux = (x[t] & ~two[i]) | (x[t-1] & two[i]);             
                    PP[i][t] = ~zero[i] & (neg[i] ^ mux);
                end

                else 
                begin
                    PP[i][t] = (~x[t] & neg[i]) | (x[t] & ~neg[i] & ~zero[i]);
                end
            end

            PP[i][0] = PP[i][0] | neg[i];

            ACC[i] = $signed(PP[i]);        //sign extension
            
            for(j=0; j<i; j=j+1)
                ACC[i] = {ACC[i],2'b00};        //shifting

        
        end

    ANS = ACC[0];

    for(i=1; i<K; i=i+1)
        ANS = ANS+ACC[i];
        
end


assign p = ANS;

endmodule

unsigned/karatsuba/radix4acc.v
`timescale 10ms / 1ms

module radix4acc(p,x,y);         //8 bit multiplier to give 32 bit product

parameter N = 8;   //size of muliplicant and multiplier
parameter K = N/2;  //

input   [N-1 : 0]   x,y;
output  [N+N-1:0]   p;

reg [2:0]   bits    [K-1:0];
reg   neg     [K-1:0];
reg   two     [K-1:0];
reg   zero     [K-1:0];


reg [N:0]       PP      [K-1:0];
reg [N+N-1:0]   ACC     [K-1:0];
reg [N+N-1:0]   ANS;
reg mux;

integer i , j, t;

wire [N:0] xbar;
assign xbar = {~x[N-1], ~x} + 1'b1;         //2's complement retaining the sign bit

always@(*)

begin
    bits[0] = {y[1],y[0],1'b0};             //setting last bit -1 as 0

    for(i=1; i<K; i=i+1)
        bits[i] = {y[2*i+1], y[2*i], y[2*i-1]};


    for(i=0; i<K; i=i+1)
        begin                                      //accurate cases
            case(bits[i])

            
            3'b001, 3'b010:         
            begin
                neg[i] = 1'b0;
                two[i] = 1'b0;
                zero[i] = 1'b0;
            end

            3'b011:
            begin
                neg[i] = 1'b0;
                two[i] = 1'b1;
                zero[i] = 1'b0;
            end

            3'b101, 3'b110:         
            begin 
               neg[i] = 1'b1;
                two[i] = 1'b0;
                zero[i] = 1'b0;
            end

            3'b100:
            begin
                neg[i] = 1'b1;
                two[i] = 1'b1;
                zero[i] = 1'b0;
            end
         
            default: 
            begin
                neg[i] = 1'b0;
                two[i] = 1'b0;
                zero[i] = 1'b1;
            end

            endcase

            PP[i] = 0;
            PP[i][N] = x[N-1]^neg[i];           //sign conservation

            for(t=0; t<N; t=t+1) begin
                if(t==0) 
                    mux = (x[t] & ~two[i]) | (1'b0 & two[i]);
                
                else
                    mux = (x[t] & ~two[i]) | (x[t-1] & two[i]);

                
                PP[i][t] = ~zero[i] & (neg[i] ^ mux);       
            end

            PP[i] = PP[i] + neg[i];             //correction term added
            

            ACC[i] = $signed(PP[i]);        //sign extension
            
            for(j=0; j<i; j=j+1)
                ACC[i] = {ACC[i],2'b00};        //shifting

        
        end

    ANS = ACC[0];

    for(i=1; i<K; i=i+1)
        ANS = ANS+ACC[i];
    
        
end


assign p = ANS;

endmodule

ABM-M1-Karatsuba-overall-16/karatsuba16.v
`timescale 10ms/1ms
`include "radix4acc.v"
`include "radix4approx.v"
`include "radix4approx10bit.v"
`include "adder8.v"

module karatsuba16(P,A,B);


parameter N = 16;   //size of muliplicant and multiplier
parameter K = N/2;  //

input   [N-1 : 0]   A,B;
output  [N+N-1:0]   P;

wire [K-1:0] AH, AL, BH, BL;

wire reg    [N-1:0]     M1, M2;
wire reg    [K:0]       S1, S2;
wire reg    [9:0]       c,d;
wire reg    [19:0]      M3;

reg [19:0] M4, M5, M6;

reg     [19:0]   A1, A2, A3;


reg [N+N-1:0]   ACC     [2:0];
reg [N+N-1:0] ANS;
integer i;


assign AH = A[N-1:K];
assign AL = A[K-1:0];

assign BH = B[N-1:K];
assign BL = B[K-1:0];



radix4acc ACC1(.p(M1), .x(AH), .y(BH));
radix4approx APP1(.p(M2), .x(AL), .y(BL));


adder8 ADD1(.s(S1), .a(AH), .b(AL));
adder8 ADD2(.s(S2), .a(BH), .b(BL));

assign c = $signed(S1);
assign d = $signed(S2);

radix4approx10bit APP2(.p(M3), .x(c), .y(d));


always@(*)
begin
    
    M4 = $signed(M1);
    M5 = $signed(M2);
    
    M6 = M3 - M4 - M5;

    ACC[0] = $signed(M6);
    ACC[0] = {ACC[0], {8{1'b0}}};

    ACC[1] = $signed(M2);
    
    ACC[2] = $signed(M1);
    ACC[2] = {ACC[2], {16{1'b0}}};

    ANS = ACC[0];
    for(i=1; i<3; i=i+1)
        ANS = ANS+ACC[i];
end

assign P = ANS;

endmodule

unsigned/karatsuba/karatsuba16_tb.v
`timescale 10ms / 1ms
`include "karatsuba16.v"

module karatsuba16_tb();

reg signed [15:0] A,B;
wire signed [31:0] P;
integer i, out, seed=7;


karatsuba16 uut(P,A,B);


initial begin
    $dumpfile("karatsuba16.vcd");
    $dumpvars(0, karatsuba16_tb);
    out = $fopen("karatsuba_output.csv");
    
    for(i=0; i<500; i=i+1)
    begin
        A = $random(seed) %32767;
        B = $random(seed) %32767;
        #1;
        $fwrite(out, "%d, %d, %d\n", A,B,P);
        #4;
    end
    
    $finish;
end




endmodule

unsigned/karatsuba/karatsuba16.vcd
$date
	Sat Jun 26 00:15:29 2021
$end
$version
	Icarus Verilog
$end
$timescale
	1ms
$end
$scope module karatsuba16_tb $end
$var wire 32 ! P [31:0] $end
$var reg 16 " A [15:0] $end
$var reg 16 # B [15:0] $end
$var integer 32 $ i [31:0] $end
$var integer 32 % out [31:0] $end
$var integer 32 & seed [31:0] $end
$scope module uut $end
$var wire 16 ' A [15:0] $end
$var wire 16 ( B [15:0] $end
$var wire 32 ) P [31:0] $end
$var wire 10 * d [9:0] $end
$var wire 10 + c [9:0] $end
$var wire 9 , S2 [8:0] $end
$var wire 9 - S1 [8:0] $end
$var wire 20 . M3 [19:0] $end
$var wire 16 / M2 [15:0] $end
$var wire 16 0 M1 [15:0] $end
$var wire 8 1 BL [7:0] $end
$var wire 8 2 BH [7:0] $end
$var wire 8 3 AL [7:0] $end
$var wire 8 4 AH [7:0] $end
$var reg 32 5 ANS [31:0] $end
$var reg 20 6 M4 [19:0] $end
$var reg 20 7 M5 [19:0] $end
$var reg 20 8 M6 [19:0] $end
$var integer 32 9 i [31:0] $end
$scope module ACC1 $end
$var wire 16 : p [15:0] $end
$var wire 8 ; x [7:0] $end
$var wire 8 < y [7:0] $end
$var wire 9 = xbar [8:0] $end
$var reg 16 > ANS [15:0] $end
$var reg 1 ? mux $end
$var integer 32 @ i [31:0] $end
$var integer 32 A j [31:0] $end
$var integer 32 B t [31:0] $end
$upscope $end
$scope module ADD1 $end
$var wire 8 C a [7:0] $end
$var wire 8 D b [7:0] $end
$var wire 9 E s [8:0] $end
$upscope $end
$scope module ADD2 $end
$var wire 8 F a [7:0] $end
$var wire 8 G b [7:0] $end
$var wire 9 H s [8:0] $end
$upscope $end
$scope module APP1 $end
$var wire 16 I p [15:0] $end
$var wire 8 J x [7:0] $end
$var wire 8 K y [7:0] $end
$var wire 9 L xbar [8:0] $end
$var reg 16 M ANS [15:0] $end
$var reg 1 N mux $end
$var integer 32 O i [31:0] $end
$var integer 32 P j [31:0] $end
$var integer 32 Q m [31:0] $end
$var integer 32 R t [31:0] $end
$upscope $end
$scope module APP2 $end
$var wire 20 S p [19:0] $end
$var wire 10 T x [9:0] $end
$var wire 10 U y [9:0] $end
$var reg 20 V ANS [19:0] $end
$var reg 1 W mux $end
$var integer 32 X i [31:0] $end
$var integer 32 Y j [31:0] $end
$var integer 32 Z m [31:0] $end
$var integer 32 [ t [31:0] $end
$upscope $end
$upscope $end
$upscope $end
$enddefinitions $end
#0
$dumpvars
b1010 [
b1000 Z
b100 Y
b101 X
0W
b1011000001110011 V
b10111101 U
b11101111 T
b1011000001110011 S
b1000 R
b110 Q
b11 P
b100 O
0N
b1010110001 M
b111110011 L
b1100101 K
b1101 J
b1010110001 I
b10111101 H
b1100101 G
b1011000 F
b11101111 E
b1101 D
b11100010 C
b1000 B
b11 A
b100 @
1?
b1111010010110000 >
b11110 =
b1011000 <
b11100010 ;
b1111010010110000 :
b11 9
b1011100100010010 8
b1010110001 7
b11111111010010110000 6
b11110101011010010001010010110001 5
b11100010 4
b1101 3
b1011000 2
b1100101 1
b1111010010110000 0
b1010110001 /
b1011000001110011 .
b11101111 -
b10111101 ,
b11101111 +
b10111101 *
b11110101011010010001010010110001 )
b101100001100101 (
b1110001000001101 '
b11000110011011000100100011101101 &
b10 %
b0 $
b101100001100101 #
b1110001000001101 "
b11110101011010010001010010110001 !
$end
#50
b11 9
b11010010010001101011000011100 !
b11010010010001101011000011100 )
b11010010010001101011000011100 5
b10100011010100 8
b1000011100 7
b1101000100000 6
b110110100 =
b1101000100000 0
b1101000100000 :
b1101000100000 >
b11 A
0?
b1000 B
b100 @
b100010100010000 .
b100010100010000 S
b100010100010000 V
b100 Y
b1010 [
b101 X
b111110111 L
b1000011100 /
b1000011100 I
b1000011100 M
b11 P
b1000 R
b100 O
b10010000 *
b10010000 U
b10010000 ,
b10010000 H
b111000 1
b111000 G
b111000 K
b1001100 4
b1001100 ;
b1001100 C
b1010101 +
b1010101 T
b1010101 -
b1010101 E
b1001 3
b1001 D
b1001 J
b101100000111000 #
b101100000111000 (
b100110000001001 "
b100110000001001 '
b10101110011011011111100111000011 &
b1 $
#100
b11 9
b10111001111000011101100011101100 !
b10111001111000011101100011101100 )
b10111001111000011101100011101100 5
b10111110001011110000 8
b11111110100011101100 7
b11111011110111111111 6
b11011 =
b1011110111111111 0
b1011110111111111 :
b1011110111111111 >
b11 A
1?
b1000 B
b100 @
b10111000100111011011 .
b10111000100111011011 S
b10111000100111011011 V
b100 Y
1W
b1010 [
b101 X
b10000000 L
b1110100011101100 /
b1110100011101100 I
b1110100011101100 M
b11 P
1N
b1000 R
b100 O
b10011 2
b10011 <
b10011 F
b111111 *
b111111 U
b111111 ,
b111111 H
b101100 1
b101100 G
b101100 K
b11100101 4
b11100101 ;
b11100101 C
b1101100101 +
b1101100101 T
b101100101 -
b101100101 E
b10000000 3
b10000000 D
b10000000 J
b1001100101100 #
b1001100101100 (
b1110010110000000 "
b1110010110000000 '
b11001111110001011111000000001001 &
b10 $
#150
b11 9
b11000100111010101010011000 !
b11000100111010101010011000 )
b11000100111010101010011000 5
b11000101101110110001 8
b11111111100110011000 7
b11010111000 6
b10100 =
b11010111000 0
b11010111000 :
b11010111000 >
b11 A
1?
b1000 B
b100 @
b11000101110000000001 .
b11000101110000000001 S
b11000101110000000001 V
b100 Y
1W
b1010 [
b101 X
b111001110 L
b1111100110011000 /
b1111100110011000 I
b1111100110011000 M
b11 P
0N
b1000 R
b100 O
b10101010 2
b10101010 <
b10101010 F
b1110001110 *
b1110001110 U
b110001110 ,
b110001110 H
b11100100 1
b11100100 G
b11100100 K
b11101100 4
b11101100 ;
b11101100 C
b1100011110 +
b1100011110 T
b100011110 -
b100011110 E
b110010 3
b110010 D
b110010 J
b1010101011100100 #
b1010101011100100 (
b1110110000110010 "
b1110110000110010 '
b10011100001010010100111111 &
b11 $
#200
b11 9
b100011000001111001001011101101 !
b100011000001111001001011101101 )
b100011000001111001001011101101 5
b11110100001110101000 8
b11111110101011101101 7
b10001111000100 6
b1010100 =
b10001111000100 0
b10001111000100 :
b10001111000100 >
b11 A
0?
b1000 B
b100 @
b11110101001001011001 .
b11110101001001011001 S
b11110101001001011001 V
b100 Y
0W
b1010 [
b101 X
b110101110 L
b1110101011101101 /
b1110101011101101 I
b1110101011101101 M
b11 P
0N
b1000 R
b100 O
b10010011 2
b10010011 <
b10010011 F
b1101010010 *
b1101010010 U
b101010010 ,
b101010010 H
b10111111 1
b10111111 G
b10111111 K
b10101100 4
b10101100 ;
b10101100 C
b11111110 +
b11111110 T
b11111110 -
b11111110 E
b1010010 3
b1010010 D
b1010010 J
b1001001110111111 #
b1001001110111111 (
b1010110001010010 "
b1010110001010010 '
b1110111101000111011100101 &
b100 $
#250
b11 9
b10111011110011111110100000000 !
b10111011110011111110100000000 )
b10111011110011111110100000000 5
b1100010000110011 8
b11111100101000000000 7
b1011010110110 6
b111001 =
b1011010110110 0
b1011010110110 :
b1011010110110 >
b11 A
1?
b1000 B
b100 @
b1010010011101001 .
b1010010011101001 S
b1010010011101001 V
b100 Y
1W
b1010 [
b101 X
b110001100 L
b1100101000000000 /
b1100101000000000 I
b1100101000000000 M
b11 P
1N
b1000 R
b100 O
b10011010 2
b10011010 <
b10011010 F
b1100101010 *
b1100101010 U
b100101010 ,
b100101010 H
b10010000 1
b10010000 G
b10010000 K
b11000111 4
b11000111 ;
b11000111 C
b1100111011 +
b1100111011 T
b100111011 -
b100111011 E
b1110100 3
b1110100 D
b1110100 J
b1001101010010000 #
b1001101010010000 (
b1100011101110100 "
b1100011101110100 '
b1101001110110111111001111011 &
b101 $
#300
b11 9
b11000011101001011100010010010100 !
b11000011101001011100010010010100 )
b11000011101001011100010010010100 5
b1111000010110111 8
b110110010100 7
b11111100001010110101 6
b111111 =
b1100001010110101 0
b1100001010110101 :
b1100001010110101 >
b11 A
1?
b1000 B
b100 @
b1100000100000000 .
b1100000100000000 S
b1100000100000000 V
1W
b100 Y
b1010 [
b101 X
b110110001 L
b110110010100 /
b110110010100 I
b110110010100 M
b11 P
0N
b1000 R
b100 O
b11110101 2
b11110101 <
b11110101 F
b1100100001 *
b1100100001 U
b100100001 ,
b100100001 H
b101100 1
b101100 G
b101100 K
b11000001 4
b11000001 ;
b11000001 C
b1100010000 +
b1100010000 T
b100010000 -
b100010000 E
b1001111 3
b1001111 D
b1001111 J
b1111010100101100 #
b1111010100101100 (
b1100000101001111 "
b1100000101001111 '
b1111001000111010000000110000001 &
b110 $
#350
b11 9
b100010101000111111010101101111 !
b100010101000111111010101101111 )
b100010101000111111010101101111 5
b11110110010000001000 8
b11111110110101101111 7
b10001101000000 6
b1010000 =
b10001101000000 0
b10001101000000 :
b10001101000000 >
b11 A
0?
b1000 B
b100 @
b11110111010010110111 .
b11110111010010110111 S
b11110111010010110111 V
b100 Y
b1010 [
b101 X
b1110101 L
b1110110101101111 /
b1110110101101111 I
b1110110101101111 M
b11 P
1N
b1000 R
b100 O
b10001100 2
b10001100 <
b10001100 F
b10110101 *
b10110101 U
b10110101 ,
b10110101 H
b101001 1
b101001 G
b101001 K
b10110000 4
b10110000 ;
b10110000 C
b1100111011 +
b1100111011 T
b100111011 -
b100111011 E
b10001011 3
b10001011 D
b10001011 J
b1000110000101001 #
b1000110000101001 (
b1011000010001011 "
b1011000010001011 '
b1100100101011111100000101110111 &
b111 $
#400
b11 9
b11101000000110011100111001100100 !
b11101000000110011100111001100100 )
b11101000000110011100111001100100 5
b11100000101110111110 8
b1000001100100 7
b11111110101000001110 6
b1101010 =
b1110101000001110 0
b1110101000001110 :
b1110101000001110 >
b11 A
1?
b1000 B
b100 @
b11100000011000110000 .
b11100000011000110000 S
b11100000011000110000 V
b100 Y
b1010 [
b101 X
b1010010 L
b1000001100100 /
b1000001100100 I
b1000001100100 M
b11 P
1N
b1000 R
b100 O
b110101 2
b110101 <
b110101 F
b11111101 *
b11111101 U
b11111101 ,
b11111101 H
b11001000 1
b11001000 G
b11001000 K
b10010110 4
b10010110 ;
b10010110 C
b1101000100 +
b1101000100 T
b101000100 -
b101000100 E
b10101110 3
b10101110 D
b10101110 J
b11010111001000 #
b11010111001000 (
b1001011010101110 "
b1001011010101110 '
b10101000001110111110001111011101 &
b1000 $
#450
b11 9
b10101111010110011010 !
b10101111010110011010 )
b10101111010110011010 5
b101011101111 8
b11010011010 7
b0 6
b0 =
b0 0
b0 :
b0 >
b11 A
0?
b1000 B
b100 @
b1000110001001 .
b1000110001001 S
b1000110001001 V
b100 Y
0W
b1010 [
b101 X
b111101010 L
b11010011010 /
b11010011010 I
b11010011010 M
b11 P
0N
b1000 R
b100 O
b10000101 2
b10000101 <
b10000101 F
b11001110 *
b11001110 U
b11001110 ,
b11001110 H
b1001001 1
b1001001 G
b1001001 K
b0 4
b0 ;
b0 C
b10110 +
b10110 T
b10110 -
b10110 E
b10110 3
b10110 D
b10110 J
b1000010101001001 #
b1000010101001001 (
b10110 "
b10110 '
b1100100110000110101000110011 &
b1001 $
#500
b11 9
b10100111110010110110111000000 !
b10100111110010110110111000000 )
b10100111110010110110111000000 5
b101000101100100 8
b100111000000 7
b1010010101000 6
b1100011 =
b1010010101000 0
b1010010101000 :
b1010010101000 >
b11 A
1?
b1000 B
b100 @
b110111111001100 .
b110111111001100 S
b110111111001100 V
b100 Y
1W
b1010 [
b101 X
b111100 L
b100111000000 /
b100111000000 I
b100111000000 M
b11 P
1N
b1000 R
b100 O
b11001000 2
b11001000 <
b11001000 F
b1101001000 *
b1101001000 U
b101001000 ,
b101001000 H
b10000000 1
b10000000 G
b10000000 K
b10011101 4
b10011101 ;
b10011101 C
b1101100001 +
b1101100001 T
b101100001 -
b101100001 E
b11000100 3
b11000100 D
b11000100 J
b1100100010000000 #
b1100100010000000 (
b1001110111000100 "
b1001110111000100 '
b1011010111001011001000111111001 &
b1010 $
#550
b11 9
b11100001001011111110010101110000 !
b11100001001011111110010101110000 )
b11100001001011111110010101110000 5
b1111101111110101 8
b11111111000001110000 7
b11111110000000110100 6
b1101110 =
b1110000000110100 0
b1110000000110100 :
b1110000000110100 >
b11 A
1?
b1000 B
b100 @
b1100110010011001 .
b1100110010011001 S
b1100110010011001 V
b100 Y
1W
b1010 [
b101 X
b110001000 L
b1111000001110000 /
b1111000001110000 I
b1111000001110000 M
b11 P
0N
b1000 R
b100 O
b1001010 2
b1001010 <
b1001010 F
b1100101010 *
b1100101010 U
b100101010 ,
b100101010 H
b11100000 1
b11100000 G
b11100000 K
b10010010 4
b10010010 ;
b10010010 C
b1100001010 +
b1100001010 T
b100001010 -
b100001010 E
b1111000 3
b1111000 D
b1111000 J
b100101011100000 #
b100101011100000 (
b1001001001111000 "
b1001001001111000 '
b11001001101001100011010010101111 &
b1011 $
#600
b11 9
b10110000000011010011101011001011 !
b10110000000011010011101011001011 )
b10110000000011010011101011001011 5
b11111010010100100100 8
b1011011001011 7
b11111011000001101000 6
b101101 =
b1011000001101000 0
b1011000001101000 :
b1011000001101000 >
b11 A
1?
b1000 B
b100 @
b11110110110001010111 .
b11110110110001010111 S
b11110110110001010111 V
b100 Y
0W
b1010 [
b101 X
b111011011 L
b1011011001011 /
b1011011001011 I
b1011011001011 M
0N
b11 P
b1000 R
b100 O
b11111000 2
b11111000 <
b11111000 F
b1101100111 *
b1101100111 U
b101100111 ,
b101100111 H
b1101111 1
b1101111 G
b1101111 K
b11010011 4
b11010011 ;
b11010011 C
b11111000 +
b11111000 T
b11111000 -
b11111000 E
b100101 3
b100101 D
b100101 J
b1111100001101111 #
b1111100001101111 (
b1101001100100101 "
b1101001100100101 '
b101000000100000010011111010101 &
b1100 $
#650
b11 9
b11101101000011001001101101001100 !
b11101101000011001001101101001100 )
b11101101000011001001101101001100 5
b11000010100011100000 8
b11111011101101001100 7
b11111111000011100100 6
b101011 =
b1111000011100100 0
b1111000011100100 :
b1111000011100100 >
b11 A
1?
b1000 B
b100 @
b10111101010100010000 .
b10111101010100010000 S
b10111101010100010000 V
b100 Y
1W
b1010 [
b101 X
b1001111 L
b1011101101001100 /
b1011101101001100 I
b1011101101001100 M
b11 P
1N
b1000 R
b100 O
b1010100 2
b1010100 <
b1010100 F
b1100000 *
b1100000 U
b1100000 ,
b1100000 H
b1100 1
b1100 G
b1100 K
b11010101 4
b11010101 ;
b11010101 C
b1110000110 +
b1110000110 T
b110000110 -
b110000110 E
b10110001 3
b10110001 D
b10110001 J
b101010000001100 #
b101010000001100 (
b1101010110110001 "
b1101010110110001 '
b11011010001010111001110011101011 &
b1101 $
#700
b11 9
b10000111000011110110111001111 !
b10000111000011110110111001111 )
b10000111000011110110111001111 5
b1010001111010000 8
b1110111001111 7
b1000000111110 6
b111010110 =
b1000000111110 0
b1000000111110 :
b1000000111110 >
b11 A
0?
b1000 B
b100 @
b1101000111011101 .
b1101000111011101 S
b1101000111011101 V
b100 Y
0W
b1010 [
b101 X
b1010000 L
b1110111001111 /
b1110111001111 I
b1110111001111 M
b11 P
0N
b1000 R
b100 O
b1100011 2
b1100011 <
b1100011 F
b11110110 *
b11110110 U
b11110110 ,
b11110110 H
b10010011 1
b10010011 G
b10010011 K
b101010 4
b101010 ;
b101010 C
b11011010 +
b11011010 T
b11011010 -
b11011010 E
b10110000 3
b10110000 D
b10110000 J
b110001110010011 #
b110001110010011 (
b10101010110000 "
b10101010110000 '
b10110000000110011000000101110001 &
b1110 $
#750
b11 9
b11101111011100100010000 !
b11101111011100100010000 )
b11101111011100100010000 5
b110001110100101 8
b1010000010000 7
b10100 6
b111110110 =
b10100 0
b10100 :
b10100 >
b11 A
0?
b1000 B
b100 @
b111011111001001 .
b111011111001001 S
b111011111001001 V
b100 Y
0W
b1010 [
b101 X
b1111100 L
b1010000010000 /
b1010000010000 I
b1010000010000 M
b11 P
1N
b1000 R
b100 O
b10 2
b10 <
b10 F
b11010110 *
b11010110 U
b11010110 ,
b11010110 H
b11010100 1
b11010100 G
b11010100 K
b1010 4
b1010 ;
b1010 C
b10001110 +
b10001110 T
b10001110 -
b10001110 E
b10000100 3
b10000100 D
b10000100 J
b1011010100 #
b1011010100 (
b101010000100 "
b101010000100 '
b11010000100110001101111011100111 &
b1111 $
#800
b11 9
b100011001010011100100111100 !
b100011001010011100100111100 )
b100011001010011100100111100 5
b11110011110100100111 8
b1001000111100 7
b10100101000 6
b111101100 =
b10100101000 0
b10100101000 :
b10100101000 >
b11 A
0?
b1000 B
b100 @
b11110101010010001011 .
b11110101010010001011 S
b11110101010010001011 V
b100 Y
0W
b1010 [
b101 X
b1100000 L
b1001000111100 /
b1001000111100 I
b1001000111100 M
b11 P
1N
b1000 R
b100 O
b1000010 2
b1000010 <
b1000010 F
b1100001110 *
b1100001110 U
b100001110 ,
b100001110 H
b11001100 1
b11001100 G
b11001100 K
b10100 4
b10100 ;
b10100 C
b10110100 +
b10110100 T
b10110100 -
b10110100 E
b10100000 3
b10100000 D
b10100000 J
b100001011001100 #
b100001011001100 (
b1010010100000 "
b1010010100000 '
b11000010101000110011101011001101 &
b10000 $
#850
b11 9
b10110001110001011001001000011 !
b10110001110001011001001000011 )
b10110001110001011001001000011 5
b11110100101110100100 8
b111001000011 7
b1011011101101 6
b111101 =
b1011011101101 0
b1011011101101 :
b1011011101101 >
b11 A
1?
b1000 B
b100 @
b11110111000011010100 .
b11110111000011010100 S
b11110111000011010100 V
b100 Y
1W
b1010 [
b101 X
b111111 L
b111001000011 /
b111001000011 I
b111001000011 M
b11 P
1N
b1000 R
b100 O
b10001111 2
b10001111 <
b10001111 F
b1100010101 *
b1100010101 U
b100010101 ,
b100010101 H
b10000110 1
b10000110 G
b10000110 K
b11000011 4
b11000011 ;
b11000011 C
b1110000100 +
b1110000100 T
b110000100 -
b110000100 E
b11000001 3
b11000001 D
b11000001 J
b1000111110000110 #
b1000111110000110 (
b1100001111000001 "
b1100001111000001 '
b1011101101111111011010100011 &
b10001 $
#900
b11 9
b11110101011001111001101110110000 !
b11110101011001111001101110110000 )
b11110101011001111001101110110000 5
b11111110011110100010 8
b11111111100110110000 7
b11111111010110000000 6
b111010110 =
b1111010110000000 0
b1111010110000000 :
b1111010110000000 >
b11 A
0?
b1000 B
b100 @
b11111101011011010010 .
b11111101011011010010 S
b11111101011011010010 V
b100 Y
0W
b1010 [
b101 X
b110101100 L
b1111100110110000 /
b1111100110110000 I
b1111100110110000 M
b11 P
0N
b1000 R
b100 O
b11000000 2
b11000000 <
b11000000 F
b1110101101 *
b1110101101 U
b110101101 ,
b110101101 H
b11101101 1
b11101101 G
b11101101 K
b101010 4
b101010 ;
b101010 C
b1111110 +
b1111110 T
b1111110 -
b1111110 E
b1010100 3
b1010100 D
b1010100 J
b1100000011101101 #
b1100000011101101 (
b10101001010100 "
b10101001010100 '
b1001000001011101010111111101001 &
b10010 $
#950
b11 9
b11011110011001011001110010111110 !
b11011110011001011001110010111110 )
b11011110011001011001110010111110 5
b11110111101110001000 8
b1010010111110 7
b11111101111011101010 6
b110010010 =
b1101111011101010 0
b1101111011101010 :
b1101111011101010 >
b11 A
0?
b1000 B
b100 @
b11110110111100110000 .
b11110110111100110000 S
b11110110111100110000 V
b100 Y
b1010 [
b101 X
b111010010 L
b1010010111110 /
b1010010111110 I
b1010010111110 M
0N
b11 P
b1000 R
b100 O
b10110011 2
b10110011 <
b10110011 F
b1100010100 *
b1100010100 U
b100010100 ,
b100010100 H
b1100001 1
b1100001 G
b1100001 K
b1101110 4
b1101110 ;
b1101110 C
b10011100 +
b10011100 T
b10011100 -
b10011100 E
b101110 3
b101110 D
b101110 J
b1011001101100001 #
b1011001101100001 (
b110111000101110 "
b110111000101110 '
b1000101010001010000000011111 &
b10011 $
#1000
b11 9
b10110001001111110110010010110100 !
b10110001001111110110010010110100 )
b10110001001111110110010010110100 5
b10110110001110100111 8
b11111011110110110100 7
b11111011010111011100 6
b1110110 =
b1011010111011100 0
b1011010111011100 :
b1011010111011100 >
b11 A
1?
b1000 B
b100 @
b10101101011100110111 .
b10101101011100110111 S
b10101101011100110111 V
b100 Y
1W
b1010 [
b101 X
b110001 L
b1011110110110100 /
b1011110110110100 I
b1011110110110100 M
b11 P
1N
b1000 R
b100 O
b10110 2
b10110 <
b10110 F
b11110 *
b11110 U
b11110 ,
b11110 H
b1000 1
b1000 G
b1000 K
b10001010 4
b10001010 ;
b10001010 C
b1101011001 +
b1101011001 T
b101011001 -
b101011001 E
b11001111 3
b11001111 D
b11001111 J
b1011000001000 #
b1011000001000 (
b1000101011001111 "
b1000101011001111 '
b10001011011110001111110011000101 &
b10100 $
